Workbook
Name \0: #REF!
Name \0: #REF!
Name \0: #REF!
Name \A: #REF!
Name \A: #REF!
Name \A: #REF!
Name \b: #REF!
Name \b: #REF!
Name \b: #REF!
Name \c: #REF!
Name \c: #REF!
Name \c: #REF!
Name \F: #REF!
Name \F: #REF!
Name \G: #REF!
Name \G: #REF!
Name \h: #REF!
Name \h: #REF!
Name \L: #REF!
Name \L: #REF!
Name \n: #REF!
Name \n: #REF!
Name \O: #REF!
Name \O: #REF!
Name \P: #REF!
Name \P: #REF!
Name \Q: #REF!
Name \Q: #REF!
Name \R: #REF!
Name \R: #REF!
Name \s: #REF!
Name \s: #REF!
Name \t: #REF!
Name \t: #REF!
Name \V: #REF!
Name \V: #REF!
Name \w: #REF!
Name \w: #REF!
Name \x: #N/A
Name \y: #REF!
Name \y: #REF!
Name \z: #N/A
Name _________________________________mm1: #REF!
Name _________________________________mm1: QQP!_________________________________mm1
Name _________________________________mm1: #REF!
Name ________________________________mm1: #REF!
Name ________________________________mm1: QQP!________________________________mm1
Name ________________________________mm1: #REF!
Name _______________________________mm1: #REF!
Name _______________________________mm1: QQP!_______________________________mm1
Name _______________________________mm1: #REF!
Name ______________________________mm1: #REF!
Name ______________________________mm1: QQP!______________________________mm1
Name ______________________________mm1: #REF!
Name _____________________________mm1: #REF!
Name _____________________________mm1: QQP!_____________________________mm1
Name _____________________________mm1: #REF!
Name ____________________________mm1: #REF!
Name ____________________________mm1: QQP!____________________________mm1
Name ____________________________mm1: #REF!

Sheet APR
C1: ANÁLISE DE RISCO | R1: PRO-009-25
R2: DATA: | S2: 45701
B4: 1ª ETAPA - ANÁLISE PRELIMINAR DE RISCO
B5: Nome do Contrato: | C5: CSS00206 - RDC 4598275 - CONTRATAÇÃO DE SERVIÇO PARA MONTAGEM E SERVIÇOS ELETROMECÂNICOS - SUBSTITUIÇÃO DA TALHA ELÉTRICA 161-TL-01 | M5: Dono do Risco: | O5: WELLINGTON DE SOUZA | Q5: Cliente: | R5: ALUMAR
B6: Missão do Contrato: | C6: CSS00206 - RDC 4598275 - CONTRATAÇÃO DE SERVIÇO PARA MONTAGEM E SERVIÇOS ELETROMECÂNICOS - SUBSTITUIÇÃO DA TALHA ELÉTRICA 161-TL-01 | M6: Prazo (dias): | N6: 0 | O6: Prazo pgto (dd): | P6: 0 | Q6: Local: | R6: SÃO LUÍS (MA)
B7: ESTIMATIVA FINANCEIRAS
B8: Valor Estimado | C8: =R8*T8 -> 733060.98 | D8: Nr. De Pessoas | F8: Custo M.obra | G8: =CHECK!I126 -> 224123.35 | I8: Custo Equipam. | J8: =CHECK!I127 -> 197996.86 | M8: Custo Consumiveis | N8: =CHECK!I128 -> 25222.816 | O8: Outros | P8: =CHECK!I129 -> 47224.356 | Q8: Custo Total | R8: =G8+J8+N8+P8 -> 494567.39 | S8: K | T8: =CHECK!I151 -> 1.4822267
B9: OBSERVAÇÕES
B10: 1 - A OBRA OCORRERÁ NA ÁREA DO PRÉDIO 161Z 2 - O ESCOPO SERÁ IMPRETERIVELMENTE A TROCA DA TALHA ELÉTRICA, COM AQUISIÇÃO DE CABOS E ACESSÓRIOS 3 - A MOBILIZAÇÃO OCORRERÁ COM A EQUIPE COMPOSTA POR ENGENHEIRO ELETRICISTA, ELETRICISTA DE FORÇA E CONTROLE E AUXILIAR.
B12: 2ª ETAPA - ANÁLISE DE RISCO
B14: Riscos a Verificar
C17: Criterio de Avaliação do Nivel do Risco | AF17: Nota | AG17: Probabilidade | AH17: NR | AI17: NR
C18: Probabilidade do Risco Acontecer | E18: NR | G18: Nota | AF18: 1 | AG18: QUASE CERTO | AH18: Risco Alto | AI18: Alto | AK18: GRÁFICO | AQ18: VERMELHO | AT18: AMARELO | AW18: VERDE
C19: QUASE CERTO | E19: Alto | G19: 1 a 2,5 | AF19: 2 | AG19: QUASE CERTO | AH19: Risco Alto | AI19: Alto | AK19: =B26 -> Tipo de Riscos | AL19: Nivel | AM19: Vermelho | AN19: Amarelo | AO19: Verde | AQ19: =AK19 -> Tipo de Riscos | AR19: =" " | AT19: =AK19 -> Tipo de Riscos | AU19: =" " | AW19: =AK19 -> Tipo de Riscos | AX19: =" "
C20: MUITO PROVÁVEL | E20: Alto | G20: 2,6 a 4,9 | AF20: 2.5 | AG20: QUASE CERTO | AH20: Risco Alto | AI20: Alto | AJ20: 1 | AK20: =B27 -> 1-FINANCEIRO (Fluxo de caixa) | AL20: =F27 -> 8.6 | AM20: =IF(AL20<=4.9,AL20,"") | AN20: =IF(AND(AL20>4.9,AL20<=8.5),AL20,"") | AO20: =IF(AL20>=8.6,AL20,"") -> 8.6 | AQ20: =AK20 -> 1-FINANCEIRO (Fluxo de caixa) | AR20: =AM20 | AT20: =AK20 -> 1-FINANCEIRO (Fluxo de caixa) | AU20: =AN20 | AW20: =AK20 -> 1-FINANCEIRO (Fluxo de caixa) | AX20: =AO20 -> 8.6
C21: PROVÁVEL | E21: Médio | G21: 5 a 7,4 | AF21: 2.6 | AG21: MUITO PROVÁVEL | AH21: Risco Alto | AI21: Alto | AJ21: 2 | AK21: =B29 -> 2-CALOTE (SERASA) | AL21: =F29 -> 8.6 | AM21: =IF(AL21<=4.9,AL21,"") | AN21: =IF(AND(AL21>4.9,AL21<=8.5),AL21,"") | AO21: =IF(AL21>=8.6,AL21,"") -> 8.6 | AQ21: =AK21 -> 2-CALOTE (SERASA) | AR21: =AM21 | AT21: =AK21 -> 2-CALOTE (SERASA) | AU21: =AN21 | AW21: =AK21 -> 2-CALOTE (SERASA) | AX21: =AO21 -> 8.6
C22: POUCO PROVÁVEL | E22: Médio | G22: 7,5 a 8,5 | AF22: 3 | AG22: MUITO PROVÁVEL | AH22: Risco Alto | AI22: Alto | AJ22: 3 | AK22: =B31 -> 3-NIVEL DE COMPLEXIDADE | AL22: =F31 -> 7 | AM22: =IF(AL22<=4.9,AL22,"") | AN22: =IF(AND(AL22>4.9,AL22<=8.5),AL22,"") -> 7 | AO22: =IF(AL22>=8.6,AL22,"") | AQ22: =AK22 -> 3-NIVEL DE COMPLEXIDADE | AR22: =AM22 | AT22: =AK22 -> 3-NIVEL DE COMPLEXIDADE | AU22: =AN22 -> 7 | AW22: =AK22 -> 3-NIVEL DE COMPLEXIDADE | AX22: =AO22
C23: IMPROVÁVEL | E23: Baixo | G23: 8,6 a 9,3 | AF23: 4 | AG23: MUITO PROVÁVEL | AH23: Risco Alto | AI23: Alto | AJ23: 4 | AK23: =B33 -> 4-CAPACIDADE TÉCNICA | AL23: =F33 -> 7 | AM23: =IF(AL23<=4.9,AL23,"") | AN23: =IF(AND(AL23>4.9,AL23<=8.5),AL23,"") -> 7 | AO23: =IF(AL23>=8.6,AL23,"") | AQ23: =AK23 -> 4-CAPACIDADE TÉCNICA | AR23: =AM23 | AT23: =AK23 -> 4-CAPACIDADE TÉCNICA | AU23: =AN23 -> 7 | AW23: =AK23 -> 4-CAPACIDADE TÉCNICA | AX23: =AO23
C24: RARO | E24: Baixo | G24: 9,4 a 10 | AF24: 4.9 | AG24: MUITO PROVÁVEL | AH24: Risco Alto | AI24: Alto | AJ24: 5 | AK24: =B35 -> 5-SSMA | AL24: =F35 -> 8.9 | AM24: =IF(AL24<=4.9,AL24,"") | AN24: =IF(AND(AL24>4.9,AL24<=8.5),AL24,"") | AO24: =IF(AL24>=8.6,AL24,"") -> 8.9 | AQ24: =AK24 -> 5-SSMA | AR24: =AM24 | AT24: =AK24 -> 5-SSMA | AU24: =AN24 | AW24: =AK24 -> 5-SSMA | AX24: =AO24 -> 8.9
B25: Quanto maior a probabilidade do risco, menor a Nota atribuída e vice versa. | AF25: 5 | AG25: PROVÁVEL | AH25: Risco Médio | AI25: Médio | AJ25: 6 | AK25: =B37 -> 6-RISCO DE NÃO ACONTECER | AL25: =F37 -> 8.6 | AM25: =IF(AL25<=4.9,AL25,"") | AN25: =IF(AND(AL25>4.9,AL25<=8.5),AL25,"") | AO25: =IF(AL25>=8.6,AL25,"") -> 8.6 | AQ25: =AK25 -> 6-RISCO DE NÃO ACONTECER | AR25: =AM25 | AT25: =AK25 -> 6-RISCO DE NÃO ACONTECER | AU25: =AN25 | AW25: =AK25 -> 6-RISCO DE NÃO ACONTECER | AX25: =AO25 -> 8.6
B26: Tipo de Riscos | D26: Peso da Consequencia | E26: Nivel de Risco | I26: Yeld | AF26: 6 | AG26: PROVÁVEL | AH26: Risco Médio | AI26: Médio | AJ26: 7 | AK26: =B39 -> 7-DISPONIBILIDADE DE RECURSOS (Mercado) | AL26: =F39 -> 8.9 | AM26: =IF(AL26<=4.9,AL26,"") | AN26: =IF(AND(AL26>4.9,AL26<=8.5),AL26,"") | AO26: =IF(AL26>=8.6,AL26,"") -> 8.9 | AQ26: =AK26 -> 7-DISPONIBILIDADE DE RECURSOS (Mercado) | AR26: =AM26 | AT26: =AK26 -> 7-DISPONIBILIDADE DE RECURSOS (Mercado) | AU26: =AN26 | AW26: =AK26 -> 7-DISPONIBILIDADE DE RECURSOS (Mercado) | AX26: =AO26 -> 8.9
B27: 1-FINANCEIRO (Fluxo de caixa) | D27: 2.5 | F27: 8.6 | H27: =VLOOKUP(F27,$AF$18:$AI$36,3,TRUE) -> Risco Baixo | M27: Observações gerais a serem contempladas na APR | AF27: 7 | AG27: PROVÁVEL | AH27: Risco Médio | AI27: Médio | AJ27: 8 | AK27: =B41 -> 8-COMPETITIVIDADE (Concorrentes) | AL27: =F41 -> 9 | AM27: =IF(AL27<=4.9,AL27,"") | AN27: =IF(AND(AL27>4.9,AL27<=8.5),AL27,"") | AO27: =IF(AL27>=8.6,AL27,"") -> 9 | AQ27: =AK27 -> 8-COMPETITIVIDADE (Concorrentes) | AR27: =AM27 | AT27: =AK27 -> 8-COMPETITIVIDADE (Concorrentes) | AU27: =AN27 | AW27: =AK27 -> 8-COMPETITIVIDADE (Concorrentes) | AX27: =AO27 -> 9
AF28: 7.4 | AG28: PROVÁVEL | AH28: Risco Médio | AI28: Médio | AJ28: 9 | AK28: =B43 -> 9-HH PARADO/EQUIPAMENTO | AL28: =F43 -> 8.4 | AM28: =IF(AL28<=4.9,AL28,"") | AN28: =IF(AND(AL28>4.9,AL28<=8.5),AL28,"") -> 8.4 | AO28: =IF(AL28>=8.6,AL28,"") | AQ28: =AK28 -> 9-HH PARADO/EQUIPAMENTO | AR28: =AM28 | AT28: =AK28 -> 9-HH PARADO/EQUIPAMENTO | AU28: =AN28 -> 8.4 | AW28: =AK28 -> 9-HH PARADO/EQUIPAMENTO | AX28: =AO28
B29: 2-CALOTE (SERASA) | D29: 2 | F29: 8.6 | H29: =VLOOKUP(F29,$AF$18:$AI$36,3,TRUE) -> Risco Baixo | I29: =ROUND((D27*F27+D29*F29+D31*F31+D33*F33+D35*F35+D37*F37+D41*F41+D43*F43+D45*F45+D47*F47+D39*F39+D51*F51+D53*F53+D49*F49)/D56,1) -> 8.3 | AF29: 7.5 | AG29: POUCO PROVÁVEL | AH29: Risco Médio | AI29: Médio | AJ29: 10 | AK29: =B45 -> 10-LOGISTICA | AL29: =F45 -> 7 | AM29: =IF(AL29<=4.9,AL29,"") | AN29: =IF(AND(AL29>4.9,AL29<=8.5),AL29,"") -> 7 | AO29: =IF(AL29>=8.6,AL29,"") | AQ29: =AK29 -> 10-LOGISTICA | AR29: =AM29 | AT29: =AK29 -> 10-LOGISTICA | AU29: =AN29 -> 7 | AW29: =AK29 -> 10-LOGISTICA | AX29: =AO29
AF30: 8 | AG30: POUCO PROVÁVEL | AH30: Risco Médio | AI30: Médio | AJ30: 11 | AK30: =B47 -> 11-NOTIFICAÇÕES E MULTAS | AL30: =F47 -> 8 | AM30: =IF(AL30<=4.9,AL30,"") | AN30: =IF(AND(AL30>4.9,AL30<=8.5),AL30,"") -> 8 | AO30: =IF(AL30>=8.6,AL30,"") | AQ30: =AK30 -> 11-NOTIFICAÇÕES E MULTAS | AR30: =AM30 | AT30: =AK30 -> 11-NOTIFICAÇÕES E MULTAS | AU30: =AN30 -> 8 | AW30: =AK30 -> 11-NOTIFICAÇÕES E MULTAS | AX30: =AO30
B31: 3-NIVEL DE COMPLEXIDADE | D31: 0.5 | F31: 7 | H31: =VLOOKUP(F31,$AF$18:$AI$36,3,TRUE) -> Risco Médio | AF31: 8.5 | AG31: POUCO PROVÁVEL | AH31: Risco Médio | AI31: Médio | AJ31: 12 | AK31: =B49 -> 12-PRAZO DE ELABORAÇÃO PROPOSTA | AL31: =F49 -> 8 | AM31: =IF(AL31<=4.9,AL31,"") | AN31: =IF(AND(AL31>4.9,AL31<=8.5),AL31,"") -> 8 | AO31: =IF(AL31>=8.6,AL31,"") | AQ31: =AK31 -> 12-PRAZO DE ELABORAÇÃO PROPOSTA | AR31: =AM31 | AT31: =AK31 -> 12-PRAZO DE ELABORAÇÃO PROPOSTA | AU31: =AN31 -> 8 | AW31: =AK31 -> 12-PRAZO DE ELABORAÇÃO PROPOSTA | AX31: =AO31
AF32: 8.6 | AG32: IMPROVÁVEL | AH32: Risco Baixo | AI32: Baixo | AJ32: 13 | AK32: =B51 -> 13-PRAZO DE EXECUÇÃO | AL32: =F51 -> 8.6 | AM32: =IF(AL32<=4.9,AL32,"") | AN32: =IF(AND(AL32>4.9,AL32<=8.5),AL32,"") | AO32: =IF(AL32>=8.6,AL32,"") -> 8.6 | AQ32: =AK32 -> 13-PRAZO DE EXECUÇÃO | AR32: =AM32 | AT32: =AK32 -> 13-PRAZO DE EXECUÇÃO | AU32: =AN32 | AW32: =AK32 -> 13-PRAZO DE EXECUÇÃO | AX32: =AO32 -> 8.6
B33: 4-CAPACIDADE TÉCNICA | D33: 0.5 | F33: 7 | H33: =VLOOKUP(F33,$AF$18:$AI$36,3,TRUE) -> Risco Médio | AF33: 9 | AG33: IMPROVÁVEL | AH33: Risco Baixo | AI33: Baixo | AJ33: 14 | AK33: =B53 -> 14-LEILÃO | AL33: =F53 -> 8.6 | AM33: =IF(AL33<=4.9,AL33,"") | AN33: =IF(AND(AL33>4.9,AL33<=8.5),AL33,"") | AO33: =IF(AL33>=8.6,AL33,"") -> 8.6 | AQ33: =AK33 -> 14-LEILÃO | AR33: =AM33 | AT33: =AK33 -> 14-LEILÃO | AU33: =AN33 | AW33: =AK33 -> 14-LEILÃO | AX33: =AO33 -> 8.6
AF34: 9.3 | AG34: IMPROVÁVEL | AH34: Risco Baixo | AI34: Baixo
B35: 5-SSMA | D35: 0.5 | F35: 8.9 | H35: =VLOOKUP(F35,$AF$18:$AI$36,3,TRUE) -> Risco Baixo | AF35: 9.4 | AG35: RARO | AH35: Risco Baixo | AI35: Baixo
AF36: 10 | AG36: RARO | AH36: Risco Baixo | AI36: Baixo
B37: 6-RISCO DE NÃO ACONTECER | D37: 0.3 | F37: 8.6 | H37: =VLOOKUP(F37,$AF$18:$AI$36,3,TRUE) -> Risco Baixo
B39: 7-DISPONIBILIDADE DE RECURSOS (Mercado) | D39: 0.5 | F39: 8.9 | H39: =VLOOKUP(F39,$AF$18:$AI$36,3,TRUE) -> Risco Baixo
B41: 8-COMPETITIVIDADE (Concorrentes) | D41: 0.5 | F41: 9 | H41: =VLOOKUP(F41,$AF$18:$AI$36,3,TRUE) -> Risco Baixo | I41: Nível de Risco:
B43: 9-HH PARADO/EQUIPAMENTO | D43: 0.5 | F43: 8.4 | H43: =VLOOKUP(F43,$AF$18:$AI$36,3,TRUE) -> Risco Médio | I43: =VLOOKUP(I29,AF18:AI36,4,TRUE) -> Médio
B45: 10-LOGISTICA | D45: 0.5 | F45: 7 | H45: =VLOOKUP(F45,$AF$18:$AI$36,3,TRUE) -> Risco Médio
B47: 11-NOTIFICAÇÕES E MULTAS | D47: 0.5 | F47: 8 | H47: =VLOOKUP(F47,$AF$18:$AI$36,3,TRUE) -> Risco Médio
B49: 12-PRAZO DE ELABORAÇÃO PROPOSTA | D49: 0.5 | F49: 8 | H49: =VLOOKUP(F49,$AF$18:$AI$36,3,TRUE) -> Risco Médio
B51: 13-PRAZO DE EXECUÇÃO | D51: 0.5 | F51: 8.6 | H51: =VLOOKUP(F51,$AF$18:$AI$36,3,TRUE) -> Risco Baixo
B53: 14-LEILÃO | D53: 0.2 | F53: 8.6 | H53: =VLOOKUP(F53,$AF$18:$AI$36,3,TRUE) -> Risco Baixo
D56: =SUM(D27:D55) -> 10
B57: Nota 1 - Os Níveis de Risco considerados Médios e Altos (amarelo e vermelho) deverão ser contemplados na ARC (Análise de Risco do Contrato).
B58: Nota 2 - Yeld é o indicador qualitativo da oportunidade do contrato no que diz respeito ao risco, varia entre 1 e 10.
B59: Nota 3 - Yeld menor ou igual a 5, o processo será declinado, para Yeld > 5 e < 8,5, deverá ser elaborada Análise de Risco do Contrato com ações para mitigar os riscos | Q59: APROVADO
Q60: (Fazer a APR)
D62: Comercial | J62: Dono do Risco | Q62: REPROVADO
B63: Trabalhar esse formulário junto com a APR | Q63: (Declinar do Processo)
B64: Este formulario deve ser utilizado como ferramenta de decisão de continuidade em processos de contratação. | R64: Rev. 03 | S64: 14 | T64: 11 | U64: 23
R65: Marcio Lopes

Sheet CHECK
B1: =QQP!G55 -> 733060.91
G2: CHECK
B5: A - Mão de Obra + Encargos
B6: Cód. | C6: Discriminação | D6: Unid | E6: P.Unit | G6: Quant | H6: F.utiliz | I6: Custo
B7: ='CPU 1 '!B7 -> P01 | C7: ='CPU 1 '!C7 -> Técnico SSMA | D7: ='CPU 1 '!D7 -> hh | E7: ='CPU 1 '!E7 -> 30.027273 | I7: ='CPU 1 '!DS7 -> 17472.87 | J7: =I7/$I$130 -> 0.035329604
B8: ='CPU 1 '!B8 -> P02 | C8: ='CPU 1 '!C8 -> Eletricista de força e controle | D8: ='CPU 1 '!D8 -> hh | E8: ='CPU 1 '!E8 -> 35.63937 | I8: ='CPU 1 '!DS8 -> 17459.727 | J8: =I8/$I$130 -> 0.03530303
B9: ='CPU 1 '!B9 -> P03 | C9: ='CPU 1 '!C9 -> Ajudante de elétrica | D9: ='CPU 1 '!D9 -> hh | E9: ='CPU 1 '!E9 -> 21.211866 | I9: ='CPU 1 '!DS9 -> 15482.541 | J9: =I9/$I$130 -> 0.03130522
B10: ='CPU 1 '!B10 -> P04 | C10: ='CPU 1 '!C10 -> Engenheiro eletricista | D10: ='CPU 1 '!D10 -> hh | E10: ='CPU 1 '!E10 -> 122.13093 | I10: ='CPU 1 '!DS10 -> 36706.45 | J10: =I10/$I$130 -> 0.07421931
B11: ='CPU 1 '!B11 -> P05 | C11: ='CPU 1 '!C11 -> Engenheiro mecânico - Especialista em estruturas metálicas | D11: ='CPU 1 '!D11 -> hh | E11: ='CPU 1 '!E11 -> 122.13093 | I11: ='CPU 1 '!DS11 -> 19803.53 | J11: =I11/$I$130 -> 0.040042126
B12: ='CPU 1 '!B12 -> P06 | C12: ='CPU 1 '!C12 -> Projetista (Cadista) | D12: ='CPU 1 '!D12 -> hh | E12: ='CPU 1 '!E12 -> 28.525909 | I12: ='CPU 1 '!DS12 -> 5253.0462 | J12: =I12/$I$130 -> 0.010621497
B13: ='CPU 1 '!B13 -> P07 | C13: ='CPU 1 '!C13 -> Alpinista industrial (Montador de andaime) | D13: ='CPU 1 '!D13 -> hh | E13: ='CPU 1 '!E13 -> 34.667187 | I13: ='CPU 1 '!DS13 -> 13728.206 | J13: =I13/$I$130 -> 0.027758009
B14: ='CPU 1 '!B14 -> P08 | C14: ='CPU 1 '!C14 -> Encarregado de elétrica ou andaimes | D14: ='CPU 1 '!D14 -> hh | E14: ='CPU 1 '!E14 -> 42.538636 | I14: ='CPU 1 '!DS14 -> 24189.17 | J14: =I14/$I$130 -> 0.048909756
B15: ='CPU 1 '!B15 -> P09 | C15: ='CPU 1 '!C15 -> Montador de estruturas metálicas | D15: ='CPU 1 '!D15 -> hh | E15: ='CPU 1 '!E15 -> 30.14538 | I15: ='CPU 1 '!DS15 -> 11937.57 | J15: =I15/$I$130 -> 0.024137399
B16: ='CPU 1 '!B16 -> P10 | C16: ='CPU 1 '!C16 -> Topógrafo | D16: ='CPU 1 '!D16 -> hh | E16: ='CPU 1 '!E16 -> 31.028182 | I16: ='CPU 1 '!DS16 -> 4468.0582 | J16: =I16/$I$130 -> 0.0090342758
B17: ='CPU 1 '!B17 -> P11 | C17: ='CPU 1 '!C17 -> Auxiliar de topografia | D17: ='CPU 1 '!D17 -> hh | E17: ='CPU 1 '!E17 -> 16.515 | I17: ='CPU 1 '!DS17 -> 2378.16 | J17: =I17/$I$130 -> 0.0048085662
B18: ='CPU 1 '!B18 -> P12 | C18: ='CPU 1 '!C18 -> Sinaleiro de rigger | D18: ='CPU 1 '!D18 -> hh | E18: ='CPU 1 '!E18 -> 21.88788 | I18: ='CPU 1 '!DS18 -> 10418.631 | J18: =I18/$I$130 -> 0.02106615
... B20: ='CPU 1 '!B20 -> P14 | C20: ='CPU 1 '!C20 -> Supervisor de obras | D20: ='CPU 1 '!D20 -> hh | E20: ='CPU 1 '!E20 -> 52.047273 | I20: ='CPU 1 '!DS20 -> 29596.161 | J20: =I20/$I$130 -> 0.059842525
B21: A - Custo Total de Mão de Obra: | G21: =SUM(G7:G12) -> 0 | H21: =SUM(H7:H12) -> 0 | I21: =SUM(I7:I20) -> 224123.35
B22: B – Equipamentos e Ferramentas
B23: Cód. | C23: Discriminação | D23: Unid | E23: P.Unit | G23: Quant | H23: F.utiliz | I23: Custo
B24: ='CPU 1 '!B24 -> E01 | C24: ='CPU 1 '!C24 -> Conteiner escritório | D24: ='CPU 1 '!D24 -> Vb/mês | E24: ='CPU 1 '!E24 -> 1700 | I24: ='CPU 1 '!DS24 -> 2240.9091 | J24: =I24/$I$130 -> 0.0045310491
B25: ='CPU 1 '!B25 -> E02 | C25: ='CPU 1 '!C25 -> Banheiro químico | D25: ='CPU 1 '!D25 -> Vb/mês | E25: ='CPU 1 '!E25 -> 1200 | I25: ='CPU 1 '!DS25 -> 1581.8182 | J25: =I25/$I$130 -> 0.0031983876
B26: ='CPU 1 '!B26 -> E03 | C26: ='CPU 1 '!C26 -> Tenda lonada 6 x 6 m, piramidal - AQUISIÇÃO | D26: ='CPU 1 '!D26 -> Vb | E26: ='CPU 1 '!E26 -> 4500 | I26: ='CPU 1 '!DS26 -> 4500 | J26: =I26/$I$130 -> 0.0090988612
B27: ='CPU 1 '!B27 -> E04 | C27: ='CPU 1 '!C27 -> Mobiliário (Cadeiras e mesas plásticas) | D27: ='CPU 1 '!D27 -> Vb | E27: ='CPU 1 '!E27 -> 852.46 | I27: ='CPU 1 '!DS27 -> 852.46 | J27: =I27/$I$130 -> 0.0017236478
B28: ='CPU 1 '!B28 -> E05 | C28: ='CPU 1 '!C28 -> Veículo de Locação - Fiat Ducato Minibus Luxo 2025 - 16 lugares | D28: ='CPU 1 '!D28 -> Vb/mês | E28: ='CPU 1 '!E28 -> 15852.96 | I28: ='CPU 1 '!DS28 -> 16985.541 | J28: =I28/$I$130 -> 0.03434424
B29: ='CPU 1 '!B29 -> E06 | C29: ='CPU 1 '!C29 -> Nível DSZ automático com bolha | D29: ='CPU 1 '!D29 -> Vb/Mês | E29: ='CPU 1 '!E29 -> 275 | I29: ='CPU 1 '!DS29 -> 125 | J29: =I29/$I$130 -> 0.00025274614
B30: ='CPU 1 '!B30 -> E07 | C30: ='CPU 1 '!C30 -> Estação total Kit GD2i-8 | D30: ='CPU 1 '!D30 -> Vb/Mês | E30: ='CPU 1 '!E30 -> 1250 | I30: ='CPU 1 '!DS30 -> 568.18182 | J30: =I30/$I$130 -> 0.0011488461
B31: ='CPU 1 '!B31 -> E08 | C31: ='CPU 1 '!C31 -> Receptor GNSS RTKCHC i50 | D31: ='CPU 1 '!D31 -> Vb/Mês | E31: ='CPU 1 '!E31 -> 1750 | I31: ='CPU 1 '!DS31 -> 795.45455 | J31: =I31/$I$130 -> 0.0016083846
B32: ='CPU 1 '!B32 -> E09 | C32: ='CPU 1 '!C32 -> Guindaste c/operador 30 ton | D32: ='CPU 1 '!D32 -> Diária | E32: ='CPU 1 '!E32 -> 7852.5 | I32: ='CPU 1 '!DS32 -> 117787.5 | J32: =I32/$I$130 -> 0.23816269
B33: ='CPU 1 '!B33 -> E10 | C33: ='CPU 1 '!C33 -> Plano de rigging | D33: ='CPU 1 '!D33 -> Vb | E33: ='CPU 1 '!E33 -> 15000 | I33: ='CPU 1 '!DS33 -> 45000 | J33: =I33/$I$130 -> 0.090988612
B34: ='CPU 1 '!B34 -> E11 | C34: ='CPU 1 '!C34 -> Linha de vida | D34: ='CPU 1 '!D34 -> Vb | E34: ='CPU 1 '!E34 -> 2520 | I34: ='CPU 1 '!DS34 -> 7560 | J34: =I34/$I$130 -> 0.015286087
B35: ='CPU 1 '!B35 -> E12 | C35: ='CPU 1 '!C35 -> 0 | D35: ='CPU 1 '!D35 -> 0 | E35: ='CPU 1 '!E35 -> 0 | I35: ='CPU 1 '!DS35 -> 0 | J35: =I35/$I$130 -> 0
... B77: ='CPU 1 '!B77 -> E54 | C77: ='CPU 1 '!C77 -> 0 | D77: ='CPU 1 '!D77 -> 0 | E77: ='CPU 1 '!E77 -> 0 | I77: ='CPU 1 '!DS77 -> 0 | J77: =I77/$I$130 -> 0
B78: B - Custo Total de Equipamentos e Ferramentas: | E78: =SUM(#REF!) -> #REF! | I78: =SUM(I24:I77) -> 197996.86
B79: C – Materiais
B80: Cód. | C80: Discriminação | D80: Unid | E80: P.Unit | G80: Quant | H80: F.utiliz | I80: Custo
B81: ='CPU 1 '!B81 -> M01 | C81: ='CPU 1 '!C81 -> Cabo múltiplo de energia (tetrapolar), condutores flexíveis de cobre (classe 5), classe de tensão de 0.6/1kV, isolamento de PVC 70ºC - Seção 1x4/c # 10.0mm². | D81: ='CPU 1 '!D81 -> M | E81: ='CPU 1 '!E81 -> 45.2 | I81: ='CPU 1 '!DS81 -> 4746 | J81: =I81/$I$130 -> 0.0095962656
B82: ='CPU 1 '!B82 -> M02 | C82: ='CPU 1 '!C82 -> Chave seccionadora 30A TYPE 3R/4/12 CLAS S H 600V, NCM:8536.50.90 CF:5102 MR:ROCKWELL | D82: ='CPU 1 '!D82 -> UND | E82: ='CPU 1 '!E82 -> 230.22 | I82: ='CPU 1 '!DS82 -> 230.22 | J82: =I82/$I$130 -> 0.00046549774
B83: ='CPU 1 '!B83 -> M03 | C83: ='CPU 1 '!C83 -> Terminal olhal de cobre à compressão #10mm² com furo M8, TM-10-8 da Intelli ou similar. | D83: ='CPU 1 '!D83 -> UND | E83: ='CPU 1 '!E83 -> 5.66 | I83: ='CPU 1 '!DS83 -> 45.28 | J83: =I83/$I$130 -> 9.1554763e-05
B84: ='CPU 1 '!B84 -> M04 | C84: ='CPU 1 '!C84 -> Fusível NH Sitor Ultra Rápido Gr 32A 1000V 100Ka T-0, Indicador Frontal 3NE4 101 da Siemens ou similar | D84: ='CPU 1 '!D84 -> UND | E84: ='CPU 1 '!E84 -> 84.66 | I84: ='CPU 1 '!DS84 -> 507.96 | J84: =I84/$I$130 -> 0.0010270794
B85: ='CPU 1 '!B85 -> M05 | C85: ='CPU 1 '!C85 -> Base para Fusível NH Sitor Ultra Rápido Gr 32A 1000V 100Ka, T-0 tipo: 3NH3 230- 0RC da Siemens ou similar | D85: ='CPU 1 '!D85 -> UND | E85: ='CPU 1 '!E85 -> 64.33 | I85: ='CPU 1 '!DS85 -> 385.98 | J85: =I85/$I$130 -> 0.00078043965
B86: ='CPU 1 '!B86 -> M06 | C86: ='CPU 1 '!C86 -> Miscelâneas | D86: ='CPU 1 '!D86 -> Vb | E86: ='CPU 1 '!E86 -> 5600 | I86: ='CPU 1 '!DS86 -> 4200 | J86: =I86/$I$130 -> 0.0084922704
B87: ='CPU 1 '!B87 -> M07 | C87: ='CPU 1 '!C87 -> Água mineral | D87: ='CPU 1 '!D87 -> L | E87: ='CPU 1 '!E87 -> 1 | I87: ='CPU 1 '!DS87 -> 0 | J87: =I87/$I$130 -> 0
B88: ='CPU 1 '!B88 -> M08 | C88: ='CPU 1 '!C88 -> Gelo branco seco | D88: ='CPU 1 '!D88 -> Pct | E88: ='CPU 1 '!E88 -> 7 | I88: ='CPU 1 '!DS88 -> 0 | J88: =I88/$I$130 -> 0
B89: ='CPU 1 '!B89 -> M09 | C89: ='CPU 1 '!C89 -> Garrafa térmica 12 L | D89: ='CPU 1 '!D89 -> und | E89: ='CPU 1 '!E89 -> 140 | I89: ='CPU 1 '!DS89 -> 0 | J89: =I89/$I$130 -> 0
B90: ='CPU 1 '!B90 -> M11 | C90: ='CPU 1 '!C90 -> Estaca de madeira | D90: ='CPU 1 '!D90 -> und | E90: ='CPU 1 '!E90 -> 5 | I90: ='CPU 1 '!DS90 -> 125 | J90: =I90/$I$130 -> 0.00025274614
B91: ='CPU 1 '!B91 -> M12 | C91: ='CPU 1 '!C91 -> Piquete de madeira | D91: ='CPU 1 '!D91 -> und | E91: ='CPU 1 '!E91 -> 3.5 | I91: ='CPU 1 '!DS91 -> 52.5 | J91: =I91/$I$130 -> 0.00010615338
B92: ='CPU 1 '!B92 -> M13 | C92: ='CPU 1 '!C92 -> Tinta - 18L | D92: ='CPU 1 '!D92 -> und | E92: ='CPU 1 '!E92 -> 260 | I92: ='CPU 1 '!DS92 -> 260 | J92: =I92/$I$130 -> 0.00052571198
... B99: ='CPU 1 '!B99 -> M20 | C99: ='CPU 1 '!C99 -> 0 | D99: ='CPU 1 '!D99 -> 0 | E99: ='CPU 1 '!E99 -> 0 | I99: ='CPU 1 '!DS99 -> 0 | J99: =I99/$I$130 -> 0
B100: C - Custo Total de Materiais: | E100: =SUM(#REF!) -> #REF! | I100: =SUM(I81:I99) -> 25222.816
B101: D – Outros
B102: Cód. | C102: Discriminação | D102: Unid | E102: P.Unit | G102: Quant | H102: F.utiliz | I102: Custo
B103: ='CPU 1 '!B103 -> O01 | C103: ='CPU 1 '!C103 -> ART | D103: ='CPU 1 '!D103 -> Vb | E103: ='CPU 1 '!E103 -> 271.52 | I103: ='CPU 1 '!DS103 -> 271.52 | J103: =I103/$I$130 -> 0.00054900506
B104: ='CPU 1 '!B104 -> O02 | C104: ='CPU 1 '!C104 -> Exames médicos | D104: ='CPU 1 '!D104 -> Vb | E104: ='CPU 1 '!E104 -> 456 | I104: ='CPU 1 '!DS104 -> 5016 | J104: =I104/$I$130 -> 0.010142197
B105: ='CPU 1 '!B105 -> O03 | C105: ='CPU 1 '!C105 -> Treinamentos | D105: ='CPU 1 '!D105 -> Vb | E105: ='CPU 1 '!E105 -> 426 | I105: ='CPU 1 '!DS105 -> 4686 | J105: =I105/$I$130 -> 0.0094749474
B106: ='CPU 1 '!B106 -> O04 | C106: ='CPU 1 '!C106 -> Plano de saúde | D106: ='CPU 1 '!D106 -> Vb/mês | E106: ='CPU 1 '!E106 -> 254.1 | I106: ='CPU 1 '!DS106 -> 7459.0911 | J106: =I106/$I$130 -> 0.015082052
B107: ='CPU 1 '!B107 -> O05 | C107: ='CPU 1 '!C107 -> Cesta básica | D107: ='CPU 1 '!D107 -> Vb/mês | E107: ='CPU 1 '!E107 -> 326.13 | I107: ='CPU 1 '!DS107 -> 9573.5276 | J107: =I107/$I$130 -> 0.019357378
B108: ='CPU 1 '!B108 -> O06 | C108: ='CPU 1 '!C108 -> Seguro profissional | D108: ='CPU 1 '!D108 -> Vb/mês | E108: ='CPU 1 '!E108 -> 12.55 | I108: ='CPU 1 '!DS108 -> 368.40454 | J108: =I108/$I$130 -> 0.00074490261
B109: ='CPU 1 '!B109 -> O07 | C109: ='CPU 1 '!C109 -> Alimentação - Café da manhã | D109: ='CPU 1 '!D109 -> Vb/mês | E109: ='CPU 1 '!E109 -> 121 | I109: ='CPU 1 '!DS109 -> 3551.9481 | J109: =I109/$I$130 -> 0.0071819295
B110: ='CPU 1 '!B110 -> O08 | C110: ='CPU 1 '!C110 -> Alimentação - Almoço | D110: ='CPU 1 '!D110 -> Vb/mês | E110: ='CPU 1 '!E110 -> 440 | I110: ='CPU 1 '!DS110 -> 12916.175 | J110: =I110/$I$130 -> 0.026116107
B111: ='CPU 1 '!B111 -> O09 | C111: ='CPU 1 '!C111 -> Ferramentas para mão de obra | D111: ='CPU 1 '!D111 -> Vb/mês | E111: ='CPU 1 '!E111 -> 115.2 | I111: ='CPU 1 '!DS111 -> 3381.6895 | J111: =I111/$I$130 -> 0.0068376718
B112: ='CPU 1 '!B112 -> O10 | C112: ='CPU 1 '!C112 -> Combustível G/D | D112: ='CPU 1 '!D112 -> L | E112: ='CPU 1 '!E112 -> 6.8 | I112: ='CPU 1 '!DS112 -> 0 | J112: =I112/$I$130 -> 0
B113: ='CPU 1 '!B113 -> O11 | C113: ='CPU 1 '!C113 -> Água mineral | D113: ='CPU 1 '!D113 -> L | E113: ='CPU 1 '!E113 -> 1.05 | I113: ='CPU 1 '!DS113 -> 0 | J113: =I113/$I$130 -> 0
B114: ='CPU 1 '!B114 -> O12 | C114: ='CPU 1 '!C114 -> Gelo seco | D114: ='CPU 1 '!D114 -> pct | E114: ='CPU 1 '!E114 -> 25.6 | I114: ='CPU 1 '!DS114 -> 0 | J114: =I114/$I$130 -> 0
... B122: ='CPU 1 '!B122 -> O20 | C122: ='CPU 1 '!C122 -> 0 | D122: ='CPU 1 '!D122 -> 0 | E122: ='CPU 1 '!E122 -> 0 | I122: ='CPU 1 '!DS122 -> 0 | J122: =I122/$I$130 -> 0
B123: D - Custo Total de Outros: | E123: =SUM(#REF!) -> #REF! | I123: =SUM(I103:I122) -> 47224.356
B125: Item | C125: CUSTOS | H125: % | I125: $
B126: A | C126: Mão de Obra | H126: =I126/I130 -> 0.4531705 | I126: =I21 -> 224123.35
B127: B | C127: Equipamentos | H127: =I127/I130 -> 0.40034355 | I127: =I78 -> 197996.86
B128: C | C128: Materiais | H128: =I128/I130 -> 0.050999756 | I128: =I100 -> 25222.816
B129: D | C129: Outros | H129: =I129/I130 -> 0.095486191 | I129: =I123 -> 47224.356
C130: Subtotal: | E130: =SUM(E126:E129) -> 0 | H130: =SUM(H126:H129) -> 1 | I130: =SUM(I126:I129) -> 494567.39
B132: Item | C132: BDI | E132: Taxa | I132: $
B133: 1 | C133: Administração Local | E133: ='BDI-TRIBUTOS'!D8 -> 0.02 | I133: =I130*$E$133 -> 9891.3477
B134: 2 | C134: Administração Central | E134: ='BDI-TRIBUTOS'!D6 -> 0.02 | I134: =I130*$E$134 -> 9891.3477
B135: 3 | C135: Custo financ. capital giro | E135: ='BDI-TRIBUTOS'!D10 -> 0.035 | I135: =I130*$E$135 -> 17309.859
B136: 4 | C136: Risco do empreendimento | E136: ='BDI-TRIBUTOS'!D12 -> 0.02 | I136: =I130*$E$136 -> 9891.3477
B137: 5 | C137: Outros | E137: ='BDI-TRIBUTOS'!D14 -> 0.01 | I137: =I130*$E$137 -> 4945.6739
B138: 6 | C138: Lucro | E138: ='BDI-TRIBUTOS'!D4 -> 0.1 | I138: =I150*$E$138 -> 73306.098
C139: Subtotal: | E139: =SUM(E133:E138) -> 0.205 | H139: =SUM(I133:I137)+I130 -> 546496.96 | I139: =SUM(I133:I138) -> 125235.67
G140: =I139/I130 -> 0.25322267
B141: Item | C141: TRIBUTOS | E141: Taxa | I141: $
B142: 1 | C142: ISS | E142: ='BDI-TRIBUTOS'!D20 -> 0.05 | I142: =$I$150*E142 -> 36653.049
B143: 2 | C143: COFINS | E143: ='BDI-TRIBUTOS'!D21 -> 0.03 | I143: =$I$150*E143 -> 21991.829
B144: 3 | C144: PIS | E144: ='BDI-TRIBUTOS'!D22 -> 0.0065 | I144: =$I$150*E144 -> 4764.8964
B145: 4 | C145: CSLL | E145: ='BDI-TRIBUTOS'!D23 -> 0.018 | I145: =$I$150*E145 -> 13195.098
B146: 5 | C146: IRPJ | E146: ='BDI-TRIBUTOS'!D24 -> 0.03 | I146: =$I$150*E146 -> 21991.829
B147: 6 | C147: IRPJ Adicional 10% | E147: ='BDI-TRIBUTOS'!D25 -> 0.02 | I147: =$I$150*E147 -> 14661.22
B148: 7 | C148: Simples Nacional | E148: ='BDI-TRIBUTOS'!D26 -> 0
C149: Subtotal | E149: =SUM(E142:E148) -> 0.1545 | I149: =I150*$E$149 -> 113257.92
C150: PREÇO | I150: =H139/(1-$E$149-$E$138) -> 733060.98
I151: =I150/I130 -> 1.4822267

Sheet QQP
C1: PROJETA CONSULTORIA E SERVIÇOS LTDA | E1: PRO-009-25 | H1: =G55 -> 733060.91 | K1: MOBILIZAÇÃO | L1: =SUM(G14) -> 9351.77 | M1: =L1/$H$1 -> 0.012757153 | N1: 0.1 | O1: =$H$1*N1 -> 73306.091 | P1: =L1-O1 -> -63954.321 | Q1: =$H$2*N1 -> 0 | R1: =L1-Q1 -> 9351.77
C2: PROPOSTA COMERCIAL | E2: CLIENTE: | F2: ALUMAR | K2: FORNECIMENTO DE MATERIAL | L2: =SUM(G23:G28) -> 14818.19 | M2: =L2/$H$1 -> 0.020214132 | N2: 0.1 | O2: =$H$1*N2 -> 73306.091 | P2: =L2-O2 -> -58487.901 | Q2: =$H$2*N2 -> 0 | R2: =L2-Q2 -> 14818.19
C3: PLANILHA DE QUANTIDADES E PREÇOS | E3: REV. 1 | F3: DATA: | G3: 45763 | K3: DESMONTAGEM | L3: =SUM(G30:G35) -> 192526.45 | M3: =L3/$H$1 -> 0.26263363 | N3: 0.2 | O3: =$H$1*N3 -> 146612.18 | P3: =L3-O3 -> 45914.268 | Q3: =$H$2*N3 -> 0 | R3: =L3-Q3 -> 192526.45
B4: OBJETO: | C4: CSS00206 - RDC 4598275 - CONTRATAÇÃO DE SERVIÇO PARA MONTAGEM E SERVIÇOS ELETROMECÂNICOS - SUBSTITUIÇÃO DA TALHA ELÉTRICA 161-TL-01 | K4: MONTAGEM | L4: =SUM(G37:G42) -> 178353.04 | M4: =L4/$H$1 -> 0.24329907 | N4: 0.3 | O4: =$H$1*N4 -> 219918.27 | P4: =L4-O4 -> -41565.233 | Q4: =$H$2*N4 -> 0 | R4: =L4-Q4 -> 178353.04
P5: =L5-O5 -> 0 | R5: =L5-Q5 -> 0
B6: ITEM | C6: DESCRIÇÃO | D6: UNID. | E6: QUANT. | F6: P.UNITARIO | G6: P.TOTAL | K6: COMISSIONAMENTO | L6: =SUM(G19) -> 7903.57 | M6: =L6/$H$1 -> 0.010781601 | N6: 0.1 | O6: =$H$1*N6 -> 73306.091 | P6: =L6-O6 -> -65402.521 | Q6: =$H$2*N6 -> 0 | R6: =L6-Q6 -> 7903.57
A7: CPU 1 | B7: 1 | C7: GERAL | G7: =SUM(G8:G12) -> 215280.63 | K7: DATA BOOK E ENTREGA FINAL E DESMOBILIZAÇÃO | L7: =G12 -> 13167.76 | M7: =L7/$H$1 -> 0.017962709 | N7: 0.1 | O7: =$H$1*N7 -> 73306.091 | P7: =L7-O7 -> -60138.331 | Q7: =$H$2*N7 -> 0 | R7: =L7-Q7 -> 13167.76
B8: 1.1 | C8: Mobilização | D8: VB | E8: 1 | F8: =_xlfn.XLOOKUP(B8,'CPU 1 '!$F$1:$FU$1,'CPU 1 '!$F$150:$FU$150) -> 106622.07 | G8: =F8*E8 -> 106622.07 | H8: =G8/$G$55 -> 0.14544776 | N8: DIVISÃO | O8: IDEAL | Q8: MELHOR CENÁRIO
B9: 1.2 | C9: Desmobilização | D9: VB | E9: 1 | F9: =_xlfn.XLOOKUP(B9,'CPU 1 '!$F$1:$FU$1,'CPU 1 '!$F$150:$FU$150) -> 51826.93 | G9: =F9*E9 -> 51826.93 | H9: =G9/$G$55 -> 0.07069935
B10: 1.3 | C10: Canteiro de Obras | D10: VB | E10: 1 | F10: =_xlfn.XLOOKUP(B10,'CPU 1 '!$F$1:$FU$1,'CPU 1 '!$F$150:$FU$150) -> 17990.88 | G10: =F10*E10 -> 17990.88 | H10: =G10/$G$55 -> 0.024542135
B11: 1.4 | C11: Comissionamento e Start Up | D11: VB | E11: 1 | F11: =_xlfn.XLOOKUP(B11,'CPU 1 '!$F$1:$FU$1,'CPU 1 '!$F$150:$FU$150) -> 25672.99 | G11: =F11*E11 -> 25672.99 | H11: =G11/$G$55 -> 0.035021633
B12: 1.5 | C12: Databook | D12: VB | E12: 1 | F12: =_xlfn.XLOOKUP(B12,'CPU 1 '!$F$1:$FU$1,'CPU 1 '!$F$150:$FU$150) -> 13167.76 | G12: =F12*E12 -> 13167.76 | H12: =G12/$G$55 -> 0.017962709
A13: CPU 2 | B13: 2 | C13: ENGENHARIA/DOCUMENTOS | G13: =SUM(G14:G20) -> 63094.74 | K13: DATA BOOK E ENTREGA FINAL E DESMOBILIZAÇÃO | L13: =G20 -> 12924.69 | M13: =L13/$H$1 -> 0.017631127 | N13: 0.1 | O13: =$H$1*N13 -> 73306.091 | P13: =L13-O13 -> -60381.401 | Q13: =$H$2*N13 -> 0 | R13: =L13-Q13 -> 12924.69
B14: 2.1 | C14: Levantamento de Campo | D14: VB | E14: 1 | F14: =_xlfn.XLOOKUP(B14,'CPU 1 '!$F$1:$FU$1,'CPU 1 '!$F$150:$FU$150) -> 9351.77 | G14: =F14*E14 -> 9351.77 | H14: =G14/$G$55 -> 0.012757153 | L14: =SUM(E8:E12,E14:E20,E23:E28,E30:E35,E37:E42,E45:E48,E50:E51,E53:E54) -> 352 | N14: DIVISÃO | O14: IDEAL | Q14: MELHOR CENÁRIO
B15: 2.2 | C15: Topografia | D15: VB | E15: 1 | F15: =_xlfn.XLOOKUP(B15,'CPU 1 '!$F$1:$FU$1,'CPU 1 '!$F$150:$FU$150) -> 9204 | G15: =F15*E15 -> 9204 | H15: =G15/$G$55 -> 0.012555573 | L15: 0.028195865
B16: 2.3 | C16: Lista de Desenhos e Documentos (LDD) | D16: VB | E16: 1 | F16: =_xlfn.XLOOKUP(B16,'CPU 1 '!$F$1:$FU$1,'CPU 1 '!$F$150:$FU$150) -> 7903.57 | G16: =F16*E16 -> 7903.57 | H16: =G16/$G$55 -> 0.010781601
B17: 2.4 | C17: Memorial de Cálculo | D17: VB | E17: 1 | F17: =_xlfn.XLOOKUP(B17,'CPU 1 '!$F$1:$FU$1,'CPU 1 '!$F$150:$FU$150) -> 7903.57 | G17: =F17*E17 -> 7903.57 | H17: =G17/$G$55 -> 0.010781601
B18: 2.5 | C18: Especificação Técnica dos Perfis | D18: VB | E18: 1 | F18: =_xlfn.XLOOKUP(B18,'CPU 1 '!$F$1:$FU$1,'CPU 1 '!$F$150:$FU$150) -> 7903.57 | G18: =F18*E18 -> 7903.57 | H18: =G18/$G$55 -> 0.010781601
B19: 2.6 | C19: Planilha de Quantidades (PQ) | D19: VB | E19: 1 | F19: =_xlfn.XLOOKUP(B19,'CPU 1 '!$F$1:$FU$1,'CPU 1 '!$F$150:$FU$150) -> 7903.57 | G19: =F19*E19 -> 7903.57 | H19: =G19/$G$55 -> 0.010781601
B20: 2.7 | C20: As-Built | D20: VB | E20: 1 | F20: =_xlfn.XLOOKUP(B20,'CPU 1 '!$F$1:$FU$1,'CPU 1 '!$F$150:$FU$150) -> 12924.69 | G20: =F20*E20 -> 12924.69 | H20: =G20/$G$55 -> 0.017631127
A21: CPU 3 | B21: 3 | C21: ELÉTRICA | G21: =SUM(G22,G29,G36) -> 385697.68
B22: 3.1 | C22: FORNECIMENTO | G22: =SUM(G23:G28) -> 14818.19
B23: 3.1.1 | C23: Cabo múltiplo de energia (tetrapolar), condutores flexíveis de cobre (classe 5), classe de tensão de 0.6/1kV, isolamento de PVC 70ºC, nas cores preto, vermelho e azul e verde, condutor flexível de cobre nú, capa externa de PVC na cor laranja, retardante à chama, imune a radiação ultravioleta, Seção 1x4/c # 10.0mm². | D23: M | E23: 100 | F23: =_xlfn.XLOOKUP(B23,'CPU 1 '!$F$1:$FU$1,'CPU 1 '!$F$150:$FU$150) -> 76.97 | G23: =F23*E23 -> 7697 | H23: =G23/$G$55 -> 0.01049981
B24: 3.1.2 | C24: Chave seccionadora 30A TYPE 3R/4/12 CLAS S H 600V, NCM:8536.50.90 CF:5102 MR:ROCKWELL | D24: UND | E24: 1 | F24: =_xlfn.XLOOKUP(B24,'CPU 1 '!$F$1:$FU$1,'CPU 1 '!$F$150:$FU$150) -> 1003.78 | G24: =F24*E24 -> 1003.78 | H24: =G24/$G$55 -> 0.0013692996
B25: 3.1.3 | C25: Terminal olhal de cobre à compressão #10mm² com furo M8, TM-10-8 da Intelli ou similar. | D25: UND | E25: 8 | F25: =_xlfn.XLOOKUP(B25,'CPU 1 '!$F$1:$FU$1,'CPU 1 '!$F$150:$FU$150) -> 91.21 | G25: =F25*E25 -> 729.68 | H25: =G25/$G$55 -> 0.00099538795
B26: 3.1.4 | C26: Fusível NH Sitor Ultra Rápido Gr 32A 1000V 100Ka T-0, Indicador Frontal 3NE4 101 da Siemens ou similar | D26: UND | E26: 6 | F26: =_xlfn.XLOOKUP(B26,'CPU 1 '!$F$1:$FU$1,'CPU 1 '!$F$150:$FU$150) -> 235.91 | G26: =F26*E26 -> 1415.46 | H26: =G26/$G$55 -> 0.00193089
B27: 3.1.5 | C27: Base para Fusível NH Sitor Ultra Rápido Gr 32A 1000V 100Ka, T-0 tipo: 3NH3 230- 0RC da Siemens ou similar | D27: UND | E27: 6 | F27: =_xlfn.XLOOKUP(B27,'CPU 1 '!$F$1:$FU$1,'CPU 1 '!$F$150:$FU$150) -> 205.77 | G27: =F27*E27 -> 1234.62 | H27: =G27/$G$55 -> 0.0016841984
B28: 3.1.6 | C28: Miscelâneas | D28: VB | E28: 1 | F28: =_xlfn.XLOOKUP(B28,'CPU 1 '!$F$1:$FU$1,'CPU 1 '!$F$150:$FU$150) -> 2737.65 | G28: =F28*E28 -> 2737.65 | H28: =G28/$G$55 -> 0.0037345464
A29: CPU 4 | B29: 3.2 | C29: SERVIÇO (DESMONTAGEM) | G29: =SUM(G30:G35) -> 192526.45
B30: 3.2.1 | C30: Desmontagem do Cabo de Alimentação do Quadro de Distribuição QD-161T-11 até a Chave Seccionadora 440V no Campo | D30: M | E30: 100 | F30: =_xlfn.XLOOKUP(B30,'CPU 1 '!$F$1:$FU$1,'CPU 1 '!$F$150:$FU$150) -> 25.93 | G30: =F30*E30 -> 2593 | H30: =G30/$G$55 -> 0.0035372231
B31: 3.2.2 | C31: Desmontagem da Caixa da Chave Seccionadora 440V no Campo | D31: UND | E31: 1 | F31: =_xlfn.XLOOKUP(B31,'CPU 1 '!$F$1:$FU$1,'CPU 1 '!$F$150:$FU$150) -> 865.19 | G31: =F31*E31 -> 865.19 | H31: =G31/$G$55 -> 0.001180243
B32: 3.2.3 | C32: Desmontagem da Cortina de Cabos Existente com Trole no Campo | D32: UND | E32: 1 | F32: =_xlfn.XLOOKUP(B32,'CPU 1 '!$F$1:$FU$1,'CPU 1 '!$F$150:$FU$150) -> 59715.97 | G32: =F32*E32 -> 59715.97 | H32: =G32/$G$55 -> 0.08146113
B33: 3.2.4 | C33: Desmontagem da Talha Elétrica 1 Tonelada no Campo | D33: UND | E33: 1 | F33: =_xlfn.XLOOKUP(B33,'CPU 1 '!$F$1:$FU$1,'CPU 1 '!$F$150:$FU$150) -> 125689.24 | G33: =F33*E33 -> 125689.24 | H33: =G33/$G$55 -> 0.17145811
B34: 3.2.5 | C34: Desmontagem dos Componentes Internos do Quadro de distribuição QD-161T-11 | D34: UND | E34: 1 | F34: =_xlfn.XLOOKUP(B34,'CPU 1 '!$F$1:$FU$1,'CPU 1 '!$F$150:$FU$150) -> 2088.13 | G34: =F34*E34 -> 2088.13 | H34: =G34/$G$55 -> 0.0028485082
B35: 3.2.6 | C35: Desmontagem do Suporte Existente da Chave Seccionadora no Campo | D35: UND | E35: 1 | F35: =_xlfn.XLOOKUP(B35,'CPU 1 '!$F$1:$FU$1,'CPU 1 '!$F$150:$FU$150) -> 1574.92 | G35: =F35*E35 -> 1574.92 | H35: =G35/$G$55 -> 0.0021484163
A36: CPU 5 | B36: 3.3 | C36: SERVIÇO (MONTAGEM) | G36: =SUM(G37:G42) -> 178353.04
B37: 3.3.1 | C37: Montagem dos Componentes Internos do Quadro de distribuição QD-161T-11 | D37: UND | E37: 1 | F37: =_xlfn.XLOOKUP(B37,'CPU 1 '!$F$1:$FU$1,'CPU 1 '!$F$150:$FU$150) -> 2259.2 | G37: =F37*E37 -> 2259.2 | H37: =G37/$G$55 -> 0.0030818721
B38: 3.3.2 | C38: Montagem do Cabo de Alimentação do Quadro de Distribuição QD-161T-11 até a Chave Seccionadora 440V no Campo | D38: M | E38: 100 | F38: =_xlfn.XLOOKUP(B38,'CPU 1 '!$F$1:$FU$1,'CPU 1 '!$F$150:$FU$150) -> 291.74 | G38: =F38*E38 -> 29174 | H38: =G38/$G$55 -> 0.039797512
B39: 3.3.3 | C39: Montagem do Suporte Existente da Chave Seccionadora no Campo | D39: UND | E39: 1 | F39: =_xlfn.XLOOKUP(B39,'CPU 1 '!$F$1:$FU$1,'CPU 1 '!$F$150:$FU$150) -> 1090.21 | G39: =F39*E39 -> 1090.21 | H39: =G39/$G$55 -> 0.0014872025
B40: 3.3.4 | C40: Montagem da Caixa da Chave Seccionadora no Campo | D40: UND | E40: 1 | F40: =_xlfn.XLOOKUP(B40,'CPU 1 '!$F$1:$FU$1,'CPU 1 '!$F$150:$FU$150) -> 805.1 | G40: =F40*E40 -> 805.1 | H40: =G40/$G$55 -> 0.0010982716
B41: 3.3.5 | C41: Montagem da Talha Elétrica 1 Tonelada do Tipo CTX– Konecranes | D41: UND | E41: 1 | F41: =_xlfn.XLOOKUP(B41,'CPU 1 '!$F$1:$FU$1,'CPU 1 '!$F$150:$FU$150) -> 134773.34 | G41: =F41*E41 -> 134773.34 | H41: =G41/$G$55 -> 0.18385013
B42: 3.3.6 | C42: Montagem da Cortina de Cabos Completo Tipo Festoon com Troles Arrastador | D42: UND | E42: 1 | F42: =_xlfn.XLOOKUP(B42,'CPU 1 '!$F$1:$FU$1,'CPU 1 '!$F$150:$FU$150) -> 10251.19 | G42: =F42*E42 -> 10251.19 | H42: =G42/$G$55 -> 0.01398409
A43: CPU 4 | B43: 4 | C43: ESTRUTURAS METÁLICAS | G43: =SUM(G44,G49,G52) -> 68987.86
B44: 4.1 | C44: FORNECIMENTO | G44: =SUM(G45:G48) -> 28495.55 | K44: VEÍCULO | L44: ='CPU 1 '!E28 -> 15852.96
B45: 4.1.1 | C45: Fornecimento de perfis metálicos leve (< 25kg/m) | D45: VB | E45: 1 | F45: =_xlfn.XLOOKUP(B45,'CPU 1 '!$F$1:$FU$1,'CPU 1 '!$F$150:$FU$150) -> 6506.18 | G45: =F45*E45 -> 6506.18 | H45: =G45/$G$55 -> 0.0088753607
B46: 4.1.2 | C46: Fornecimento de perfis metálicos médio (> 25kg/m < 80kg/m) | D46: VB | E46: 1 | F46: =_xlfn.XLOOKUP(B46,'CPU 1 '!$F$1:$FU$1,'CPU 1 '!$F$150:$FU$150) -> 10951.44 | G46: =F46*E46 -> 10951.44 | H46: =G46/$G$55 -> 0.014939332
B47: 4.1.3 | C47: Fornecimento de perfis metálicos médio pesado (> 80kg/m) | D47: VB | E47: 1 | F47: =_xlfn.XLOOKUP(B47,'CPU 1 '!$F$1:$FU$1,'CPU 1 '!$F$150:$FU$150) -> 6225.16 | G47: =F47*E47 -> 6225.16 | H47: =G47/$G$55 -> 0.0084920092
B48: 4.1.4 | C48: Miscelâneas | D48: VB | E48: 1 | F48: =_xlfn.XLOOKUP(B48,'CPU 1 '!$F$1:$FU$1,'CPU 1 '!$F$150:$FU$150) -> 4812.77 | G48: =F48*E48 -> 4812.77 | H48: =G48/$G$55 -> 0.0065653071
B49: 4.2 | C49: SERVIÇO (DESMONTAGEM) | G49: =SUM(G50:G51) -> 12842.25
B50: 4.2.1 | C50: Desmontagem da monovia existente | D50: VB | E50: 1 | F50: =_xlfn.XLOOKUP(B50,'CPU 1 '!$F$1:$FU$1,'CPU 1 '!$F$150:$FU$150) -> 7243.78 | G50: =F50*E50 -> 7243.78 | H50: =G50/$G$55 -> 0.0098815527
B51: 4.2.2 | C51: Desmontagem das estruturas transversais de apoio | D51: VB | E51: 1 | F51: =_xlfn.XLOOKUP(B51,'CPU 1 '!$F$1:$FU$1,'CPU 1 '!$F$150:$FU$150) -> 5598.47 | G51: =F51*E51 -> 5598.47 | H51: =G51/$G$55 -> 0.0076371144
B52: 4.3 | C52: SERVIÇO (MONTAGEM) | G52: =SUM(G53:G54) -> 27650.06
B53: 4.3.1 | C53: Montagem da monovia existente | D53: VB | E53: 1 | F53: =_xlfn.XLOOKUP(B53,'CPU 1 '!$F$1:$FU$1,'CPU 1 '!$F$150:$FU$150) -> 17115.65 | G53: =F53*E53 -> 17115.65 | H53: =G53/$G$55 -> 0.023348196
B54: 4.3.2 | C54: Montagem das estruturas transversais de apoio | D54: VB | E54: 1 | F54: =_xlfn.XLOOKUP(B54,'CPU 1 '!$F$1:$FU$1,'CPU 1 '!$F$150:$FU$150) -> 10534.41 | G54: =F54*E54 -> 10534.41 | H54: =G54/$G$55 -> 0.014370443
B55: TOTAL GERAL | G55: =SUM(G7,G13,G21,G43) -> 733060.91
B56: NOTA: 1 - A base de cáculo para retenção do INSS pela contratante é somente sobre a parcela mão de obra que corresponde a XX% dos custos, por se tratar de um serviço que inclui equipamentos e materiais conforme IN 971/2009; 2 - A presente proposta prever a dedução de valor de material, para apuração da base de cálculo do INSS conforme instrução normativa de cada municipio; 3 - INSS e o ISS deverão ser sobre a parcela de mão de obra.
B57: PREMISSAS:
B65: LISTA DE DESVIOS:

Sheet CPU  1 
B1: =QQP!G55 -> 733060.91 | D1: CPU | E1: 1 | F1: =QQP!B8 -> 1.1 | G1: =H150 -> 106622.07 | I1: =QQP!B9 -> 1.2 | J1: =K150 -> 51826.933 | L1: =QQP!B10 -> 1.3 | M1: =N150 -> 17990.882 | O1: =QQP!B11 -> 1.4 | P1: =Q150 -> 25672.987 | R1: =QQP!B12 -> 1.5 | S1: =T150 -> 13167.762 | U1: =QQP!B14 -> 2.1 | V1: =W150 -> 9351.772 | X1: =QQP!B15 -> 2.2 | Y1: =Z150 -> 9204.0035 | AA1: =QQP!B16 -> 2.3 | AB1: =AC150 -> 7903.5663 | AD1: =QQP!B17 -> 2.4 | AE1: =AF150 -> 7903.5663 | AG1: =QQP!B18 -> 2.5 | AH1: =AI150 -> 7903.5663 | AJ1: =QQP!B19 -> 2.6 | AK1: =AL150 -> 7903.5663 | AM1: =QQP!B20 -> 2.7 | AN1: =AO150 -> 12924.693 | AP1: =QQP!B23 -> 3.1.1 | AQ1: =AR150 -> 76.971853 | AS1: =QQP!B24 -> 3.1.2 | AT1: =AU150 -> 1003.7757 | AV1: =QQP!B25 -> 3.1.3 | AW1: =AX150 -> 91.206582 | AY1: =QQP!B26 -> 3.1.4 | AZ1: =BA150 -> 235.90822 | BB1: =QQP!B27 -> 3.1.5 | BC1: =BD150 -> 205.77455 | BE1: =QQP!B28 -> 3.1.6 | BF1: =BG150 -> 2737.6548 | BH1: =QQP!B30 -> 3.2.1 | BI1: =BJ150 -> 25.92554 | BK1: =QQP!B31 -> 3.2.2 | BL1: =BM150 -> 865.18917 | BN1: =QQP!B32 -> 3.2.3 | BO1: =BP150 -> 59715.973 | BQ1: =QQP!B33 -> 3.2.4 | BR1: =BS150 -> 125689.24 | BT1: =QQP!B34 -> 3.2.5 | BU1: =BV150 -> 2088.1275 | BW1: =QQP!B35 -> 3.2.6 | BX1: =BY150 -> 1574.9151 | BZ1: =QQP!B37 -> 3.3.1 | CA1: =CB150 -> 2259.1983 | CC1: =QQP!B38 -> 3.3.2 | CD1: =CE150 -> 291.74339 | CF1: =QQP!B39 -> 3.3.3 | CG1: =CH150 -> 1090.2145 | CI1: =QQP!B40 -> 3.3.4 | CJ1: =CK150 -> 805.09644 | CL1: =QQP!B41 -> 3.3.5 | CM1: =CN150 -> 134773.34 | CO1: =QQP!B42 -> 3.3.6 | CP1: =CQ150 -> 10251.194 | CR1: =QQP!B45 -> 4.1.1 | CS1: =CT150 -> 6506.1806 | CU1: =QQP!B46 -> 4.1.2 | CV1: =CW150 -> 10951.444 | CX1: =QQP!B47 -> 4.1.3 | CY1: =CZ150 -> 6225.1563 | DA1: =QQP!B48 -> 4.1.4 | DB1: =DC150 -> 4812.7722 | DD1: =QQP!B50 -> 4.2.1 | DE1: =DF150 -> 7243.7829 | DG1: =QQP!B51 -> 4.2.2 | DH1: =DI150 -> 5598.4716 | DJ1: =QQP!B53 -> 4.3.1 | DK1: =DL150 -> 17115.651 | DM1: =QQP!B54 -> 4.3.2 | DN1: =DO150 -> 10534.406
B2: Composição de Preços Unitários | F2: =_xlfn.XLOOKUP(F1,QQP!$B$8:$B$54,QQP!$C$8:$C$54) -> Mobilização | I2: =_xlfn.XLOOKUP(I1,QQP!$B$8:$B$54,QQP!$C$8:$C$54) -> Desmobilização | L2: =_xlfn.XLOOKUP(L1,QQP!$B$8:$B$54,QQP!$C$8:$C$54) -> Canteiro de Obras | O2: =_xlfn.XLOOKUP(O1,QQP!$B$8:$B$54,QQP!$C$8:$C$54) -> Comissionamento e Start Up | R2: =_xlfn.XLOOKUP(R1,QQP!$B$8:$B$54,QQP!$C$8:$C$54) -> Databook | U2: =_xlfn.XLOOKUP(U1,QQP!$B$8:$B$54,QQP!$C$8:$C$54) -> Levantamento de Campo | X2: =_xlfn.XLOOKUP(X1,QQP!$B$8:$B$54,QQP!$C$8:$C$54) -> Topografia | AA2: =_xlfn.XLOOKUP(AA1,QQP!$B$8:$B$54,QQP!$C$8:$C$54) -> Lista de Desenhos e Documentos (LDD) | AD2: =_xlfn.XLOOKUP(AD1,QQP!$B$8:$B$54,QQP!$C$8:$C$54) -> Memorial de Cálculo | AG2: =_xlfn.XLOOKUP(AG1,QQP!$B$8:$B$54,QQP!$C$8:$C$54) -> Especificação Técnica dos Perfis | AJ2: =_xlfn.XLOOKUP(AJ1,QQP!$B$8:$B$54,QQP!$C$8:$C$54) -> Planilha de Quantidades (PQ) | AM2: =_xlfn.XLOOKUP(AM1,QQP!$B$8:$B$54,QQP!$C$8:$C$54) -> As-Built | AP2: =_xlfn.XLOOKUP(AP1,QQP!$B$8:$B$54,QQP!$C$8:$C$54) -> Cabo múltiplo de energia (tetrapolar), condutores flexíveis de cobre (classe 5), classe de tensão de 0.6/1kV, isolamento de PVC 70ºC, nas cores preto, vermelho e azul e verde, condutor flexível de cobre nú, capa externa de PVC na cor laranja, retardante à chama, imune a radiação ultravioleta, Seção 1x4/c # 10.0mm². | AS2: =_xlfn.XLOOKUP(AS1,QQP!$B$8:$B$54,QQP!$C$8:$C$54) -> Chave seccionadora 30A TYPE 3R/4/12 CLAS S H 600V, NCM:8536.50.90 CF:5102 MR:ROCKWELL | AV2: =_xlfn.XLOOKUP(AV1,QQP!$B$8:$B$54,QQP!$C$8:$C$54) -> Terminal olhal de cobre à compressão #10mm² com furo M8, TM-10-8 da Intelli ou similar. | AY2: =_xlfn.XLOOKUP(AY1,QQP!$B$8:$B$54,QQP!$C$8:$C$54) -> Fusível NH Sitor Ultra Rápido Gr 32A 1000V 100Ka T-0, Indicador Frontal 3NE4 101 da Siemens ou similar | BB2: =_xlfn.XLOOKUP(BB1,QQP!$B$8:$B$54,QQP!$C$8:$C$54) -> Base para Fusível NH Sitor Ultra Rápido Gr 32A 1000V 100Ka, T-0 tipo: 3NH3 230- 0RC da Siemens ou similar | BE2: =_xlfn.XLOOKUP(BE1,QQP!$B$8:$B$54,QQP!$C$8:$C$54) -> Miscelâneas | BH2: =_xlfn.XLOOKUP(BH1,QQP!$B$8:$B$54,QQP!$C$8:$C$54) -> Desmontagem do Cabo de Alimentação do Quadro de Distribuição QD-161T-11 até a Chave Seccionadora 440V no Campo | BK2: =_xlfn.XLOOKUP(BK1,QQP!$B$8:$B$54,QQP!$C$8:$C$54) -> Desmontagem da Caixa da Chave Seccionadora 440V no Campo | BN2: =_xlfn.XLOOKUP(BN1,QQP!$B$8:$B$54,QQP!$C$8:$C$54) -> Desmontagem da Cortina de Cabos Existente com Trole no Campo | BQ2: =_xlfn.XLOOKUP(BQ1,QQP!$B$8:$B$54,QQP!$C$8:$C$54) -> Desmontagem da Talha Elétrica 1 Tonelada no Campo | BT2: =_xlfn.XLOOKUP(BT1,QQP!$B$8:$B$54,QQP!$C$8:$C$54) -> Desmontagem dos Componentes Internos do Quadro de distribuição QD-161T-11 | BW2: =_xlfn.XLOOKUP(BW1,QQP!$B$8:$B$54,QQP!$C$8:$C$54) -> Desmontagem do Suporte Existente da Chave Seccionadora no Campo | BZ2: =_xlfn.XLOOKUP(BZ1,QQP!$B$8:$B$54,QQP!$C$8:$C$54) -> Montagem dos Componentes Internos do Quadro de distribuição QD-161T-11 | CC2: =_xlfn.XLOOKUP(CC1,QQP!$B$8:$B$54,QQP!$C$8:$C$54) -> Montagem do Cabo de Alimentação do Quadro de Distribuição QD-161T-11 até a Chave Seccionadora 440V no Campo | CF2: =_xlfn.XLOOKUP(CF1,QQP!$B$8:$B$54,QQP!$C$8:$C$54) -> Montagem do Suporte Existente da Chave Seccionadora no Campo | CI2: =_xlfn.XLOOKUP(CI1,QQP!$B$8:$B$54,QQP!$C$8:$C$54) -> Montagem da Caixa da Chave Seccionadora no Campo | CL2: =_xlfn.XLOOKUP(CL1,QQP!$B$8:$B$54,QQP!$C$8:$C$54) -> Montagem da Talha Elétrica 1 Tonelada do Tipo CTX– Konecranes | CO2: =_xlfn.XLOOKUP(CO1,QQP!$B$8:$B$54,QQP!$C$8:$C$54) -> Montagem da Cortina de Cabos Completo Tipo Festoon com Troles Arrastador | CR2: =_xlfn.XLOOKUP(CR1,QQP!$B$8:$B$54,QQP!$C$8:$C$54) -> Fornecimento de perfis metálicos leve (< 25kg/m) | CU2: =_xlfn.XLOOKUP(CU1,QQP!$B$8:$B$54,QQP!$C$8:$C$54) -> Fornecimento de perfis metálicos médio (> 25kg/m < 80kg/m) | CX2: =_xlfn.XLOOKUP(CX1,QQP!$B$8:$B$54,QQP!$C$8:$C$54) -> Fornecimento de perfis metálicos médio pesado (> 80kg/m) | DA2: =_xlfn.XLOOKUP(DA1,QQP!$B$8:$B$54,QQP!$C$8:$C$54) -> Miscelâneas | DD2: =_xlfn.XLOOKUP(DD1,QQP!$B$8:$B$54,QQP!$C$8:$C$54) -> Desmontagem da monovia existente | DG2: =_xlfn.XLOOKUP(DG1,QQP!$B$8:$B$54,QQP!$C$8:$C$54) -> Desmontagem das estruturas transversais de apoio | DJ2: =_xlfn.XLOOKUP(DJ1,QQP!$B$8:$B$54,QQP!$C$8:$C$54) -> Montagem da monovia existente | DM2: =_xlfn.XLOOKUP(DM1,QQP!$B$8:$B$54,QQP!$C$8:$C$54) -> Montagem das estruturas transversais de apoio | DQ2: CHECK
G3: =_xlfn.XLOOKUP(F1,QQP!$B$8:$B$54,QQP!$D$8:$D$54) -> VB | H3: =_xlfn.XLOOKUP(F1,QQP!$B$8:$B$54,QQP!$E$8:$E$54) -> 1 | J3: =_xlfn.XLOOKUP(I1,QQP!$B$8:$B$54,QQP!$D$8:$D$54) -> VB | K3: =_xlfn.XLOOKUP(I1,QQP!$B$8:$B$54,QQP!$E$8:$E$54) -> 1 | M3: =_xlfn.XLOOKUP(L1,QQP!$B$8:$B$54,QQP!$D$8:$D$54) -> VB | N3: =_xlfn.XLOOKUP(L1,QQP!$B$8:$B$54,QQP!$E$8:$E$54) -> 1 | P3: =_xlfn.XLOOKUP(O1,QQP!$B$8:$B$54,QQP!$D$8:$D$54) -> VB | Q3: =_xlfn.XLOOKUP(O1,QQP!$B$8:$B$54,QQP!$E$8:$E$54) -> 1 | S3: =_xlfn.XLOOKUP(R1,QQP!$B$8:$B$54,QQP!$D$8:$D$54) -> VB | T3: =_xlfn.XLOOKUP(R1,QQP!$B$8:$B$54,QQP!$E$8:$E$54) -> 1 | V3: =_xlfn.XLOOKUP(U1,QQP!$B$8:$B$54,QQP!$D$8:$D$54) -> VB | W3: =_xlfn.XLOOKUP(U1,QQP!$B$8:$B$54,QQP!$E$8:$E$54) -> 1 | Y3: =_xlfn.XLOOKUP(X1,QQP!$B$8:$B$54,QQP!$D$8:$D$54) -> VB | Z3: =_xlfn.XLOOKUP(X1,QQP!$B$8:$B$54,QQP!$E$8:$E$54) -> 1 | AB3: =_xlfn.XLOOKUP(AA1,QQP!$B$8:$B$54,QQP!$D$8:$D$54) -> VB | AC3: =_xlfn.XLOOKUP(AA1,QQP!$B$8:$B$54,QQP!$E$8:$E$54) -> 1 | AE3: =_xlfn.XLOOKUP(AD1,QQP!$B$8:$B$54,QQP!$D$8:$D$54) -> VB | AF3: =_xlfn.XLOOKUP(AD1,QQP!$B$8:$B$54,QQP!$E$8:$E$54) -> 1 | AH3: =_xlfn.XLOOKUP(AG1,QQP!$B$8:$B$54,QQP!$D$8:$D$54) -> VB | AI3: =_xlfn.XLOOKUP(AG1,QQP!$B$8:$B$54,QQP!$E$8:$E$54) -> 1 | AK3: =_xlfn.XLOOKUP(AJ1,QQP!$B$8:$B$54,QQP!$D$8:$D$54) -> VB | AL3: =_xlfn.XLOOKUP(AJ1,QQP!$B$8:$B$54,QQP!$E$8:$E$54) -> 1 | AN3: =_xlfn.XLOOKUP(AM1,QQP!$B$8:$B$54,QQP!$D$8:$D$54) -> VB | AO3: =_xlfn.XLOOKUP(AM1,QQP!$B$8:$B$54,QQP!$E$8:$E$54) -> 1 | AQ3: =_xlfn.XLOOKUP(AP1,QQP!$B$8:$B$54,QQP!$D$8:$D$54) -> M | AR3: =_xlfn.XLOOKUP(AP1,QQP!$B$8:$B$54,QQP!$E$8:$E$54) -> 100 | AT3: =_xlfn.XLOOKUP(AS1,QQP!$B$8:$B$54,QQP!$D$8:$D$54) -> UND | AU3: =_xlfn.XLOOKUP(AS1,QQP!$B$8:$B$54,QQP!$E$8:$E$54) -> 1 | AW3: =_xlfn.XLOOKUP(AV1,QQP!$B$8:$B$54,QQP!$D$8:$D$54) -> UND | AX3: =_xlfn.XLOOKUP(AV1,QQP!$B$8:$B$54,QQP!$E$8:$E$54) -> 8 | AZ3: =_xlfn.XLOOKUP(AY1,QQP!$B$8:$B$54,QQP!$D$8:$D$54) -> UND | BA3: =_xlfn.XLOOKUP(AY1,QQP!$B$8:$B$54,QQP!$E$8:$E$54) -> 6 | BC3: =_xlfn.XLOOKUP(BB1,QQP!$B$8:$B$54,QQP!$D$8:$D$54) -> UND | BD3: =_xlfn.XLOOKUP(BB1,QQP!$B$8:$B$54,QQP!$E$8:$E$54) -> 6 | BF3: =_xlfn.XLOOKUP(BE1,QQP!$B$8:$B$54,QQP!$D$8:$D$54) -> VB | BG3: =_xlfn.XLOOKUP(BE1,QQP!$B$8:$B$54,QQP!$E$8:$E$54) -> 1 | BI3: =_xlfn.XLOOKUP(BH1,QQP!$B$8:$B$54,QQP!$D$8:$D$54) -> M | BJ3: =_xlfn.XLOOKUP(BH1,QQP!$B$8:$B$54,QQP!$E$8:$E$54) -> 100 | BL3: =_xlfn.XLOOKUP(BK1,QQP!$B$8:$B$54,QQP!$D$8:$D$54) -> UND | BM3: =_xlfn.XLOOKUP(BK1,QQP!$B$8:$B$54,QQP!$E$8:$E$54) -> 1 | BO3: =_xlfn.XLOOKUP(BN1,QQP!$B$8:$B$54,QQP!$D$8:$D$54) -> UND | BP3: =_xlfn.XLOOKUP(BN1,QQP!$B$8:$B$54,QQP!$E$8:$E$54) -> 1 | BR3: =_xlfn.XLOOKUP(BQ1,QQP!$B$8:$B$54,QQP!$D$8:$D$54) -> UND | BS3: =_xlfn.XLOOKUP(BQ1,QQP!$B$8:$B$54,QQP!$E$8:$E$54) -> 1 | BU3: =_xlfn.XLOOKUP(BT1,QQP!$B$8:$B$54,QQP!$D$8:$D$54) -> UND | BV3: =_xlfn.XLOOKUP(BT1,QQP!$B$8:$B$54,QQP!$E$8:$E$54) -> 1 | BX3: =_xlfn.XLOOKUP(BW1,QQP!$B$8:$B$54,QQP!$D$8:$D$54) -> UND | BY3: =_xlfn.XLOOKUP(BW1,QQP!$B$8:$B$54,QQP!$E$8:$E$54) -> 1 | CA3: =_xlfn.XLOOKUP(BZ1,QQP!$B$8:$B$54,QQP!$D$8:$D$54) -> UND | CB3: =_xlfn.XLOOKUP(BZ1,QQP!$B$8:$B$54,QQP!$E$8:$E$54) -> 1 | CD3: =_xlfn.XLOOKUP(CC1,QQP!$B$8:$B$54,QQP!$D$8:$D$54) -> M | CE3: =_xlfn.XLOOKUP(CC1,QQP!$B$8:$B$54,QQP!$E$8:$E$54) -> 100 | CG3: =_xlfn.XLOOKUP(CF1,QQP!$B$8:$B$54,QQP!$D$8:$D$54) -> UND | CH3: =_xlfn.XLOOKUP(CF1,QQP!$B$8:$B$54,QQP!$E$8:$E$54) -> 1 | CJ3: =_xlfn.XLOOKUP(CI1,QQP!$B$8:$B$54,QQP!$D$8:$D$54) -> UND | CK3: =_xlfn.XLOOKUP(CI1,QQP!$B$8:$B$54,QQP!$E$8:$E$54) -> 1 | CM3: =_xlfn.XLOOKUP(CL1,QQP!$B$8:$B$54,QQP!$D$8:$D$54) -> UND | CN3: =_xlfn.XLOOKUP(CL1,QQP!$B$8:$B$54,QQP!$E$8:$E$54) -> 1 | CP3: =_xlfn.XLOOKUP(CO1,QQP!$B$8:$B$54,QQP!$D$8:$D$54) -> UND | CQ3: =_xlfn.XLOOKUP(CO1,QQP!$B$8:$B$54,QQP!$E$8:$E$54) -> 1 | CS3: =_xlfn.XLOOKUP(CR1,QQP!$B$8:$B$54,QQP!$D$8:$D$54) -> VB | CT3: =_xlfn.XLOOKUP(CR1,QQP!$B$8:$B$54,QQP!$E$8:$E$54) -> 1 | CV3: =_xlfn.XLOOKUP(CU1,QQP!$B$8:$B$54,QQP!$D$8:$D$54) -> VB | CW3: =_xlfn.XLOOKUP(CU1,QQP!$B$8:$B$54,QQP!$E$8:$E$54) -> 1 | CY3: =_xlfn.XLOOKUP(CX1,QQP!$B$8:$B$54,QQP!$D$8:$D$54) -> VB | CZ3: =_xlfn.XLOOKUP(CX1,QQP!$B$8:$B$54,QQP!$E$8:$E$54) -> 1 | DB3: =_xlfn.XLOOKUP(DA1,QQP!$B$8:$B$54,QQP!$D$8:$D$54) -> VB | DC3: =_xlfn.XLOOKUP(DA1,QQP!$B$8:$B$54,QQP!$E$8:$E$54) -> 1 | DE3: =_xlfn.XLOOKUP(DD1,QQP!$B$8:$B$54,QQP!$D$8:$D$54) -> VB | DF3: =_xlfn.XLOOKUP(DD1,QQP!$B$8:$B$54,QQP!$E$8:$E$54) -> 1 | DH3: =_xlfn.XLOOKUP(DG1,QQP!$B$8:$B$54,QQP!$D$8:$D$54) -> VB | DI3: =_xlfn.XLOOKUP(DG1,QQP!$B$8:$B$54,QQP!$E$8:$E$54) -> 1 | DK3: =_xlfn.XLOOKUP(DJ1,QQP!$B$8:$B$54,QQP!$D$8:$D$54) -> VB | DL3: =_xlfn.XLOOKUP(DJ1,QQP!$B$8:$B$54,QQP!$E$8:$E$54) -> 1 | DN3: =_xlfn.XLOOKUP(DM1,QQP!$B$8:$B$54,QQP!$D$8:$D$54) -> VB | DO3: =_xlfn.XLOOKUP(DM1,QQP!$B$8:$B$54,QQP!$E$8:$E$54) -> 1
F4: 8 | G4: 20 | H4: diárias | I4: 8 | J4: 10 | K4: diárias | L4: 8 | M4: 10 | N4: diárias | O4: 8 | P4: 14 | Q4: diárias | R4: 8 | S4: 7 | T4: diárias | U4: 8 | V4: 3 | W4: diárias | X4: 8 | Y4: 10 | Z4: diárias | AA4: 8 | AB4: 5 | AC4: diárias | AD4: 8 | AE4: 5 | AF4: diárias | AG4: 8 | AH4: 5 | AI4: diárias | AJ4: 8 | AK4: 5 | AL4: diárias | AM4: 8 | AN4: 8 | AO4: diárias | AP4: 8.8 | AQ4: 5 | AR4: diárias | AS4: 8.8 | AT4: 5 | AU4: diárias | AV4: 8.8 | AW4: 5 | AX4: diárias | AY4: 8.8 | AZ4: 5 | BA4: diárias | BB4: 8.8 | BC4: 5 | BD4: diárias | BE4: 8.8 | BF4: 5 | BG4: diárias | BN4: 8 | BO4: 2 | BP4: diárias | BQ4: 8 | BR4: 6 | BS4: diárias | BT4: 8 | BU4: 0.5 | BV4: diária | BW4: 8 | BX4: 0.32 | BY4: diária | BZ4: 8 | CA4: 0.56 | CB4: diária | CC4: 8 | CD4: 0.1 | CE4: diária | CF4: 8 | CG4: 0.15 | CH4: diária | CI4: 8 | CJ4: 0.05 | CK4: diária | CL4: 8 | CM4: 7 | CN4: diárias | CO4: 8 | CP4: 3 | CQ4: diárias | DD4: 8 | DE4: 2 | DF4: diárias | DG4: 8 | DH4: 1.5 | DI4: diárias | DJ4: 8 | DK4: 5 | DL4: diárias | DM4: 8 | DN4: 3 | DO4: diárias
B5: A - Mão de Obra + Encargos
B6: Cód. | C6: Discriminação | D6: Unid | E6: P.Unit | F6: Quant | G6: F.utiliz | H6: Custo | I6: Quant | J6: F.utiliz | K6: Custo | L6: Quant | M6: F.utiliz | N6: Custo | O6: Quant | P6: F.utiliz | Q6: Custo | R6: Quant | S6: F.utiliz | T6: Custo | U6: Quant | V6: F.utiliz | W6: Custo | X6: Quant | Y6: F.utiliz | Z6: Custo | AA6: Quant | AB6: F.utiliz | AC6: Custo | AD6: Quant | AE6: F.utiliz | AF6: Custo | AG6: Quant | AH6: F.utiliz | AI6: Custo | AJ6: Quant | AK6: F.utiliz | AL6: Custo | AM6: Quant | AN6: F.utiliz | AO6: Custo | AP6: Quant | AQ6: F.utiliz | AR6: Custo | AS6: Quant | AT6: F.utiliz | AU6: Custo | AV6: Quant | AW6: F.utiliz | AX6: Custo | AY6: Quant | AZ6: F.utiliz | BA6: Custo | BB6: Quant | BC6: F.utiliz | BD6: Custo | BE6: Quant | BF6: F.utiliz | BG6: Custo | BH6: Quant | BI6: F.utiliz | BJ6: Custo | BK6: Quant | BL6: F.utiliz | BM6: Custo | BN6: Quant | BO6: F.utiliz | BP6: Custo | BQ6: Quant | BR6: F.utiliz | BS6: Custo | BT6: Quant | BU6: F.utiliz | BV6: Custo | BW6: Quant | BX6: F.utiliz | BY6: Custo | BZ6: Quant | CA6: F.utiliz | CB6: Custo | CC6: Quant | CD6: F.utiliz | CE6: Custo | CF6: Quant | CG6: F.utiliz | CH6: Custo | CI6: Quant | CJ6: F.utiliz | CK6: Custo | CL6: Quant | CM6: F.utiliz | CN6: Custo | CO6: Quant | CP6: F.utiliz | CQ6: Custo | CR6: Quant | CS6: F.utiliz | CT6: Custo | CU6: Quant | CV6: F.utiliz | CW6: Custo | CX6: Quant | CY6: F.utiliz | CZ6: Custo | DA6: Quant | DB6: F.utiliz | DC6: Custo | DD6: Quant | DE6: F.utiliz | DF6: Custo | DG6: Quant | DH6: F.utiliz | DI6: Custo | DJ6: Quant | DK6: F.utiliz | DL6: Custo | DM6: Quant | DN6: F.utiliz | DO6: Custo | DQ6: Quant | DR6: F.utiliz | DS6: Custo
B7: =MO!B3 -> P01 | C7: =MO!C3 -> Técnico SSMA | D7: hh | E7: =MO!I3 -> 30.027273 | F7: =$F$4*$G$4 -> 160 | G7: 1 | H7: =G7*F7*$E7 -> 4804.3636 | I7: =$I$4*$J$4 -> 80 | J7: 1 | K7: =J7*I7*$E7 -> 2402.1818 | N7: =M7*L7*$E7 -> 0 | Q7: =P7*O7*$E7 -> 0 | T7: =S7*R7*$E7 -> 0 | W7: =V7*U7*$E7 -> 0 | Z7: =Y7*X7*$E7 -> 0 | AC7: =AB7*AA7*$E7 -> 0 | AF7: =AE7*AD7*$E7 -> 0 | AI7: =AH7*AG7*$E7 -> 0 | AL7: =AK7*AJ7*$E7 -> 0 | AO7: =AN7*AM7*$E7 -> 0 | AR7: =AQ7*AP7*$E7 -> 0 | AU7: =AT7*AS7*$E7 -> 0 | AX7: =AW7*AV7*$E7 -> 0 | BA7: =AZ7*AY7*$E7 -> 0 | BD7: =BC7*BB7*$E7 -> 0 | BG7: =BF7*BE7*$E7 -> 0 | BH7: 0.12 | BI7: 1 | BJ7: =BI7*BH7*$E7 -> 3.6032727 | BK7: 1.26 | BL7: 1 | BM7: =BL7*BK7*$E7 -> 37.834364 | BN7: =$BN$4*$BO$4 -> 16 | BO7: 1 | BP7: =BO7*BN7*$E7 -> 480.43636 | BQ7: =$BQ$4*$BR$4 -> 48 | BR7: 1 | BS7: =BR7*BQ7*$E7 -> 1441.3091 | BT7: =$BT$4*$BU$4 -> 4 | BU7: 1 | BV7: =BU7*BT7*$E7 -> 120.10909 | BW7: =$BW$4*$BX$4 -> 2.56 | BX7: 1 | BY7: =BX7*BW7*$E7 -> 76.869818 | BZ7: =$BZ$4*$CA$4 -> 4.48 | CA7: 1 | CB7: =CA7*BZ7*$E7 -> 134.52218 | CC7: =$CC$4*$CD$4 -> 0.8 | CD7: 1 | CE7: =CD7*CC7*$E7 -> 24.021818 | CF7: =$CF$4*$CG$4 -> 1.2 | CG7: 1 | CH7: =CG7*CF7*$E7 -> 36.032727 | CI7: =$CI$4*$CJ$4 -> 0.4 | CJ7: 1 | CK7: =CJ7*CI7*$E7 -> 12.010909 | CL7: =$CL$4*$CM$4 -> 56 | CM7: 1 | CN7: =CM7*CL7*$E7 -> 1681.5273 | CO7: =$CO$4*$CP$4 -> 24 | CP7: 1 | CQ7: =CP7*CO7*$E7 -> 720.65455 | CT7: =CS7*CR7*$E7 -> 0 | CW7: =CV7*CU7*$E7 -> 0 | CZ7: =CY7*CX7*$E7 -> 0 | DC7: =DB7*DA7*$E7 -> 0 | DD7: =$DD$4*$DE$4 -> 16 | DE7: 1 | DF7: =DE7*DD7*$E7 -> 480.43636 | DG7: =$DG$4*$DH$4 -> 12 | DH7: 1 | DI7: =DH7*DG7*$E7 -> 360.32727 | DJ7: =$DJ$4*$DK$4 -> 40 | DK7: 1 | DL7: =DK7*DJ7*$E7 -> 1201.0909 | DM7: =$DM$4*$DN$4 -> 24 | DN7: 1 | DO7: =DN7*DM7*$E7 -> 720.65455 | DS7: =($H$3*H7+$K$3*K7+$N$3*N7+$Q$3*Q7+$T$3*T7+$W$3*W7+$Z$3*Z7+$AC$3*AC7+$AF$3*AF7+$AI$3*AI7+$AL$3*AL7+$AO$3*AO7+$AR$3*AR7+$AU$3*AU7+$AX$3*AX7+$BA$3*BA7+$BD$3*BD7+$BG$3*BG7+$BJ$3*BJ7+$BM$3*BM7+$BP$3*BP7+$BS$3*BS7+$BV$3*BV7+$BY$3*BY7+$CB$3*CB7+$CE$3*CE7+$CH$3*CH7+$CK$3*CK7+$CN$3*CN7+$CQ$3*CQ7+$CT$3*CT7+$CW$3*CW7+$CZ$3*CZ7+$DC$3*DC7+$DF$3*DF7+$DI$3*DI7+$DL$3*DL7+$DO$3*DO7) -> 17472.87 | DT7: =DS7/$DS$130 -> 0.035329604
B8: =MO!B4 -> P02 | C8: =MO!C4 -> Eletricista de força e controle | D8: hh | E8: =MO!I4 -> 35.63937 | F8: =$F$4*$G$4 -> 160 | G8: 1 | H8: =G8*F8*$E8 -> 5702.2992 | I8: =$I$4*$J$4 -> 80 | J8: 1 | K8: =J8*I8*$E8 -> 2851.1496 | N8: =M8*L8*$E8 -> 0 | Q8: =P8*O8*$E8 -> 0 | T8: =S8*R8*$E8 -> 0 | W8: =V8*U8*$E8 -> 0 | Z8: =Y8*X8*$E8 -> 0 | AC8: =AB8*AA8*$E8 -> 0 | AF8: =AE8*AD8*$E8 -> 0 | AI8: =AH8*AG8*$E8 -> 0 | AL8: =AK8*AJ8*$E8 -> 0 | AO8: =AN8*AM8*$E8 -> 0 | AR8: =AQ8*AP8*$E8 -> 0 | AU8: =AT8*AS8*$E8 -> 0 | AX8: =AW8*AV8*$E8 -> 0 | BA8: =AZ8*AY8*$E8 -> 0 | BD8: =BC8*BB8*$E8 -> 0 | BG8: =BF8*BE8*$E8 -> 0 | BH8: 0.12 | BI8: 1 | BJ8: =BI8*BH8*$E8 -> 4.2767244 | BK8: 1.26 | BL8: 1 | BM8: =BL8*BK8*$E8 -> 44.905606 | BN8: =$BN$4*$BO$4 -> 16 | BO8: 1 | BP8: =BO8*BN8*$E8 -> 570.22992 | BQ8: =$BQ$4*$BR$4 -> 48 | BR8: 1 | BS8: =BR8*BQ8*$E8 -> 1710.6898 | BT8: =$BT$4*$BU$4 -> 4 | BU8: 1 | BV8: =BU8*BT8*$E8 -> 142.55748 | BW8: =$BW$4*$BX$4 -> 2.56 | BX8: 1 | BY8: =BX8*BW8*$E8 -> 91.236787 | BZ8: =$BZ$4*$CA$4 -> 4.48 | CA8: 1 | CB8: =CA8*BZ8*$E8 -> 159.66438 | CC8: =$CC$4*$CD$4 -> 0.8 | CD8: 1 | CE8: =CD8*CC8*$E8 -> 28.511496 | CF8: =$CF$4*$CG$4 -> 1.2 | CG8: 1 | CH8: =CG8*CF8*$E8 -> 42.767244 | CI8: =$CI$4*$CJ$4 -> 0.4 | CJ8: 1 | CK8: =CJ8*CI8*$E8 -> 14.255748 | CL8: =$CL$4*$CM$4 -> 56 | CM8: 1 | CN8: =CM8*CL8*$E8 -> 1995.8047 | CO8: =$CO$4*$CP$4 -> 24 | CP8: 1 | CQ8: =CP8*CO8*$E8 -> 855.34488 | CT8: =CS8*CR8*$E8 -> 0 | CW8: =CV8*CU8*$E8 -> 0 | CZ8: =CY8*CX8*$E8 -> 0 | DC8: =DB8*DA8*$E8 -> 0 | DF8: =DE8*DD8*$E8 -> 0 | DI8: =DH8*DG8*$E8 -> 0 | DL8: =DK8*DJ8*$E8 -> 0 | DO8: =DN8*DM8*$E8 -> 0 | DS8: =($H$3*H8+$K$3*K8+$N$3*N8+$Q$3*Q8+$T$3*T8+$W$3*W8+$Z$3*Z8+$AC$3*AC8+$AF$3*AF8+$AI$3*AI8+$AL$3*AL8+$AO$3*AO8+$AR$3*AR8+$AU$3*AU8+$AX$3*AX8+$BA$3*BA8+$BD$3*BD8+$BG$3*BG8+$BJ$3*BJ8+$BM$3*BM8+$BP$3*BP8+$BS$3*BS8+$BV$3*BV8+$BY$3*BY8+$CB$3*CB8+$CE$3*CE8+$CH$3*CH8+$CK$3*CK8+$CN$3*CN8+$CQ$3*CQ8+$CT$3*CT8+$CW$3*CW8+$CZ$3*CZ8+$DC$3*DC8+$DF$3*DF8+$DI$3*DI8+$DL$3*DL8+$DO$3*DO8) -> 17459.727 | DT8: =DS8/$DS$130 -> 0.03530303
B9: =MO!B5 -> P03 | C9: =MO!C5 -> Ajudante de elétrica | D9: hh | E9: =MO!I5 -> 21.211866 | F9: =$F$4*$G$4 -> 160 | G9: 2 | H9: =G9*F9*$E9 -> 6787.7971 | I9: =$I$4*$J$4 -> 80 | J9: 2 | K9: =J9*I9*$E9 -> 3393.8986 | N9: =M9*L9*$E9 -> 0 | Q9: =P9*O9*$E9 -> 0 | T9: =S9*R9*$E9 -> 0 | W9: =V9*U9*$E9 -> 0 | Z9: =Y9*X9*$E9 -> 0 | AC9: =AB9*AA9*$E9 -> 0 | AF9: =AE9*AD9*$E9 -> 0 | AI9: =AH9*AG9*$E9 -> 0 | AL9: =AK9*AJ9*$E9 -> 0 | AO9: =AN9*AM9*$E9 -> 0 | AR9: =AQ9*AP9*$E9 -> 0 | AU9: =AT9*AS9*$E9 -> 0 | AX9: =AW9*AV9*$E9 -> 0 | BA9: =AZ9*AY9*$E9 -> 0 | BD9: =BC9*BB9*$E9 -> 0 | BG9: =BF9*BE9*$E9 -> 0 | BH9: 0.12 | BI9: 1 | BJ9: =BI9*BH9*$E9 -> 2.5454239 | BK9: 1.26 | BL9: 1 | BM9: =BL9*BK9*$E9 -> 26.726951 | BN9: =$BN$4*$BO$4 -> 16 | BO9: 1 | BP9: =BO9*BN9*$E9 -> 339.38986 | BQ9: =$BQ$4*$BR$4 -> 48 | BR9: 1 | BS9: =BR9*BQ9*$E9 -> 1018.1696 | BT9: =$BT$4*$BU$4 -> 4 | BU9: 1 | BV9: =BU9*BT9*$E9 -> 84.847464 | BW9: =$BW$4*$BX$4 -> 2.56 | BX9: 1 | BY9: =BX9*BW9*$E9 -> 54.302377 | BZ9: =$BZ$4*$CA$4 -> 4.48 | CA9: 1 | CB9: =CA9*BZ9*$E9 -> 95.02916 | CC9: =$CC$4*$CD$4 -> 0.8 | CD9: 1 | CE9: =CD9*CC9*$E9 -> 16.969493 | CF9: =$CF$4*$CG$4 -> 1.2 | CG9: 1 | CH9: =CG9*CF9*$E9 -> 25.454239 | CI9: =$CI$4*$CJ$4 -> 0.4 | CJ9: 1 | CK9: =CJ9*CI9*$E9 -> 8.4847464 | CL9: =$CL$4*$CM$4 -> 56 | CM9: 1 | CN9: =CM9*CL9*$E9 -> 1187.8645 | CO9: =$CO$4*$CP$4 -> 24 | CP9: 1 | CQ9: =CP9*CO9*$E9 -> 509.08478 | CT9: =CS9*CR9*$E9 -> 0 | CW9: =CV9*CU9*$E9 -> 0 | CZ9: =CY9*CX9*$E9 -> 0 | DC9: =DB9*DA9*$E9 -> 0 | DF9: =DE9*DD9*$E9 -> 0 | DI9: =DH9*DG9*$E9 -> 0 | DL9: =DK9*DJ9*$E9 -> 0 | DO9: =DN9*DM9*$E9 -> 0 | DS9: =($H$3*H9+$K$3*K9+$N$3*N9+$Q$3*Q9+$T$3*T9+$W$3*W9+$Z$3*Z9+$AC$3*AC9+$AF$3*AF9+$AI$3*AI9+$AL$3*AL9+$AO$3*AO9+$AR$3*AR9+$AU$3*AU9+$AX$3*AX9+$BA$3*BA9+$BD$3*BD9+$BG$3*BG9+$BJ$3*BJ9+$BM$3*BM9+$BP$3*BP9+$BS$3*BS9+$BV$3*BV9+$BY$3*BY9+$CB$3*CB9+$CE$3*CE9+$CH$3*CH9+$CK$3*CK9+$CN$3*CN9+$CQ$3*CQ9+$CT$3*CT9+$CW$3*CW9+$CZ$3*CZ9+$DC$3*DC9+$DF$3*DF9+$DI$3*DI9+$DL$3*DL9+$DO$3*DO9) -> 15482.541 | DT9: =DS9/$DS$130 -> 0.03130522
B10: =MO!B6 -> P04 | C10: =MO!C6 -> Engenheiro eletricista | D10: hh | E10: =MO!I6 -> 122.13093 | H10: =G10*F10*$E10 -> 0 | K10: =J10*I10*$E10 -> 0 | N10: =M10*L10*$E10 -> 0 | O10: =$O$4*$P$4 -> 112 | P10: 1 | Q10: =P10*O10*$E10 -> 13678.664 | R10: =$R$4*$S$4 -> 56 | S10: 1 | T10: =S10*R10*$E10 -> 6839.3319 | U10: =$U$4*$V$4 -> 24 | V10: 1 | W10: =V10*U10*$E10 -> 2931.1423 | Z10: =Y10*X10*$E10 -> 0 | AA10: =$AA$4*$AB$4 -> 40 | AB10: 0.4 | AC10: =AB10*AA10*$E10 -> 1954.0948 | AD10: =$AD$4*$AE$4 -> 40 | AE10: 0.5 | AF10: =AE10*AD10*$E10 -> 2442.6185 | AG10: =$AG$4*$AH$4 -> 40 | AH10: 0.1 | AI10: =AH10*AG10*$E10 -> 488.52371 | AJ10: =$AJ$4*$AK$4 -> 40 | AK10: 0.55 | AL10: =AK10*AJ10*$E10 -> 2686.8804 | AM10: =$AM$4*$AN$4 -> 64 | AN10: 0.55 | AO10: =AN10*AM10*$E10 -> 4299.0086 | AR10: =AQ10*AP10*$E10 -> 0 | AU10: =AT10*AS10*$E10 -> 0 | AX10: =AW10*AV10*$E10 -> 0 | BA10: =AZ10*AY10*$E10 -> 0 | BD10: =BC10*BB10*$E10 -> 0 | BG10: =BF10*BE10*$E10 -> 0 | BJ10: =BI10*BH10*$E10 -> 0 | BM10: =BL10*BK10*$E10 -> 0 | BN10: 0.15 | BO10: 1 | BP10: =BO10*BN10*$E10 -> 18.319639 | BS10: =BR10*BQ10*$E10 -> 0 | BV10: =BU10*BT10*$E10 -> 0 | BY10: =BX10*BW10*$E10 -> 0 | CB10: =CA10*BZ10*$E10 -> 0 | CE10: =CD10*CC10*$E10 -> 0 | CH10: =CG10*CF10*$E10 -> 0 | CK10: =CJ10*CI10*$E10 -> 0 | CL10: =$CL$4*$CM$4/5 -> 11.2 | CM10: 1 | CN10: =CM10*CL10*$E10 -> 1367.8664 | CQ10: =CP10*CO10*$E10 -> 0 | CT10: =CS10*CR10*$E10 -> 0 | CW10: =CV10*CU10*$E10 -> 0 | CZ10: =CY10*CX10*$E10 -> 0 | DC10: =DB10*DA10*$E10 -> 0 | DF10: =DE10*DD10*$E10 -> 0 | DI10: =DH10*DG10*$E10 -> 0 | DL10: =DK10*DJ10*$E10 -> 0 | DO10: =DN10*DM10*$E10 -> 0 | DS10: =($H$3*H10+$K$3*K10+$N$3*N10+$Q$3*Q10+$T$3*T10+$W$3*W10+$Z$3*Z10+$AC$3*AC10+$AF$3*AF10+$AI$3*AI10+$AL$3*AL10+$AO$3*AO10+$AR$3*AR10+$AU$3*AU10+$AX$3*AX10+$BA$3*BA10+$BD$3*BD10+$BG$3*BG10+$BJ$3*BJ10+$BM$3*BM10+$BP$3*BP10+$BS$3*BS10+$BV$3*BV10+$BY$3*BY10+$CB$3*CB10+$CE$3*CE10+$CH$3*CH10+$CK$3*CK10+$CN$3*CN10+$CQ$3*CQ10+$CT$3*CT10+$CW$3*CW10+$CZ$3*CZ10+$DC$3*DC10+$DF$3*DF10+$DI$3*DI10+$DL$3*DL10+$DO$3*DO10) -> 36706.45 | DT10: =DS10/$DS$130 -> 0.07421931
B11: =MO!B7 -> P05 | C11: =MO!C7 -> Engenheiro mecânico - Especialista em estruturas metálicas | D11: hh | E11: =MO!I7 -> 122.13093 | H11: =G11*F11*$E11 -> 0 | K11: =J11*I11*$E11 -> 0 | N11: =M11*L11*$E11 -> 0 | Q11: =P11*O11*$E11 -> 0 | T11: =S11*R11*$E11 -> 0 | U11: =$U$4*$V$4 -> 24 | V11: 1 | W11: =V11*U11*$E11 -> 2931.1423 | Z11: =Y11*X11*$E11 -> 0 | AA11: =$AA$4*$AB$4 -> 40 | AB11: 0.6 | AC11: =AB11*AA11*$E11 -> 2931.1423 | AD11: =$AD$4*$AE$4 -> 40 | AE11: 0.5 | AF11: =AE11*AD11*$E11 -> 2442.6185 | AG11: =$AG$4*$AH$4 -> 40 | AH11: 0.9 | AI11: =AH11*AG11*$E11 -> 4396.7134 | AJ11: =$AJ$4*$AK$4 -> 40 | AK11: 0.45 | AL11: =AK11*AJ11*$E11 -> 2198.3567 | AM11: =$AM$4*$AN$4 -> 64 | AN11: 0.45 | AO11: =AN11*AM11*$E11 -> 3517.3707 | AR11: =AQ11*AP11*$E11 -> 0 | AU11: =AT11*AS11*$E11 -> 0 | AX11: =AW11*AV11*$E11 -> 0 | BA11: =AZ11*AY11*$E11 -> 0 | BD11: =BC11*BB11*$E11 -> 0 | BG11: =BF11*BE11*$E11 -> 0 | BJ11: =BI11*BH11*$E11 -> 0 | BM11: =BL11*BK11*$E11 -> 0 | BN11: 0.15 | BO11: 1 | BP11: =BO11*BN11*$E11 -> 18.319639 | BS11: =BR11*BQ11*$E11 -> 0 | BV11: =BU11*BT11*$E11 -> 0 | BY11: =BX11*BW11*$E11 -> 0 | CB11: =CA11*BZ11*$E11 -> 0 | CE11: =CD11*CC11*$E11 -> 0 | CH11: =CG11*CF11*$E11 -> 0 | CK11: =CJ11*CI11*$E11 -> 0 | CL11: =$CL$4*$CM$4/5 -> 11.2 | CM11: 1 | CN11: =CM11*CL11*$E11 -> 1367.8664 | CQ11: =CP11*CO11*$E11 -> 0 | CT11: =CS11*CR11*$E11 -> 0 | CW11: =CV11*CU11*$E11 -> 0 | CZ11: =CY11*CX11*$E11 -> 0 | DC11: =DB11*DA11*$E11 -> 0 | DF11: =DE11*DD11*$E11 -> 0 | DI11: =DH11*DG11*$E11 -> 0 | DL11: =DK11*DJ11*$E11 -> 0 | DO11: =DN11*DM11*$E11 -> 0 | DS11: =($H$3*H11+$K$3*K11+$N$3*N11+$Q$3*Q11+$T$3*T11+$W$3*W11+$Z$3*Z11+$AC$3*AC11+$AF$3*AF11+$AI$3*AI11+$AL$3*AL11+$AO$3*AO11+$AR$3*AR11+$AU$3*AU11+$AX$3*AX11+$BA$3*BA11+$BD$3*BD11+$BG$3*BG11+$BJ$3*BJ11+$BM$3*BM11+$BP$3*BP11+$BS$3*BS11+$BV$3*BV11+$BY$3*BY11+$CB$3*CB11+$CE$3*CE11+$CH$3*CH11+$CK$3*CK11+$CN$3*CN11+$CQ$3*CQ11+$CT$3*CT11+$CW$3*CW11+$CZ$3*CZ11+$DC$3*DC11+$DF$3*DF11+$DI$3*DI11+$DL$3*DL11+$DO$3*DO11) -> 19803.53 | DT11: =DS11/$DS$130 -> 0.040042126
B12: =MO!B8 -> P06 | C12: =MO!C8 -> Projetista (Cadista) | D12: hh | E12: =MO!I8 -> 28.525909 | H12: =G12*F12*$E12 -> 0 | K12: =J12*I12*$E12 -> 0 | N12: =M12*L12*$E12 -> 0 | O12: =$O$4*$P$4 -> 112 | P12: 1 | Q12: =P12*O12*$E12 -> 3194.9018 | R12: =$R$4*$S$4 -> 56 | S12: 1 | T12: =S12*R12*$E12 -> 1597.4509 | W12: =V12*U12*$E12 -> 0 | Z12: =Y12*X12*$E12 -> 0 | AC12: =AB12*AA12*$E12 -> 0 | AF12: =AE12*AD12*$E12 -> 0 | AI12: =AH12*AG12*$E12 -> 0 | AL12: =AK12*AJ12*$E12 -> 0 | AM12: =$AM$4*$AN$4 -> 64 | AN12: 0.25 | AO12: =AN12*AM12*$E12 -> 456.41455 | AR12: =AQ12*AP12*$E12 -> 0 | AU12: =AT12*AS12*$E12 -> 0 | AX12: =AW12*AV12*$E12 -> 0 | BA12: =AZ12*AY12*$E12 -> 0 | BD12: =BC12*BB12*$E12 -> 0 | BG12: =BF12*BE12*$E12 -> 0 | BJ12: =BI12*BH12*$E12 -> 0 | BM12: =BL12*BK12*$E12 -> 0 | BN12: 0.15 | BO12: 1 | BP12: =BO12*BN12*$E12 -> 4.2788864 | BS12: =BR12*BQ12*$E12 -> 0 | BV12: =BU12*BT12*$E12 -> 0 | BY12: =BX12*BW12*$E12 -> 0 | CB12: =CA12*BZ12*$E12 -> 0 | CE12: =CD12*CC12*$E12 -> 0 | CH12: =CG12*CF12*$E12 -> 0 | CK12: =CJ12*CI12*$E12 -> 0 | CN12: =CM12*CL12*$E12 -> 0 | CQ12: =CP12*CO12*$E12 -> 0 | CT12: =CS12*CR12*$E12 -> 0 | CW12: =CV12*CU12*$E12 -> 0 | CZ12: =CY12*CX12*$E12 -> 0 | DC12: =DB12*DA12*$E12 -> 0 | DF12: =DE12*DD12*$E12 -> 0 | DI12: =DH12*DG12*$E12 -> 0 | DL12: =DK12*DJ12*$E12 -> 0 | DO12: =DN12*DM12*$E12 -> 0 | DS12: =($H$3*H12+$K$3*K12+$N$3*N12+$Q$3*Q12+$T$3*T12+$W$3*W12+$Z$3*Z12+$AC$3*AC12+$AF$3*AF12+$AI$3*AI12+$AL$3*AL12+$AO$3*AO12+$AR$3*AR12+$AU$3*AU12+$AX$3*AX12+$BA$3*BA12+$BD$3*BD12+$BG$3*BG12+$BJ$3*BJ12+$BM$3*BM12+$BP$3*BP12+$BS$3*BS12+$BV$3*BV12+$BY$3*BY12+$CB$3*CB12+$CE$3*CE12+$CH$3*CH12+$CK$3*CK12+$CN$3*CN12+$CQ$3*CQ12+$CT$3*CT12+$CW$3*CW12+$CZ$3*CZ12+$DC$3*DC12+$DF$3*DF12+$DI$3*DI12+$DL$3*DL12+$DO$3*DO12) -> 5253.0462 | DT12: =DS12/$DS$130 -> 0.010621497
B13: =MO!B9 -> P07 | C13: =MO!C9 -> Alpinista industrial (Montador de andaime) | D13: hh | E13: =MO!I9 -> 34.667187 | F13: =$F$4*$G$4 -> 160 | G13: 1 | H13: =G13*F13*$E13 -> 5546.7499 | I13: =$I$4*$J$4 -> 80 | J13: 1 | K13: =J13*I13*$E13 -> 2773.375 | N13: =M13*L13*$E13 -> 0 | Q13: =P13*O13*$E13 -> 0 | T13: =S13*R13*$E13 -> 0 | W13: =V13*U13*$E13 -> 0 | Z13: =Y13*X13*$E13 -> 0 | AC13: =AB13*AA13*$E13 -> 0 | AF13: =AE13*AD13*$E13 -> 0 | AI13: =AH13*AG13*$E13 -> 0 | AL13: =AK13*AJ13*$E13 -> 0 | AO13: =AN13*AM13*$E13 -> 0 | AR13: =AQ13*AP13*$E13 -> 0 | AU13: =AT13*AS13*$E13 -> 0 | AX13: =AW13*AV13*$E13 -> 0 | BA13: =AZ13*AY13*$E13 -> 0 | BD13: =BC13*BB13*$E13 -> 0 | BG13: =BF13*BE13*$E13 -> 0 | BJ13: =BI13*BH13*$E13 -> 0 | BM13: =BL13*BK13*$E13 -> 0 | BN13: =$BN$4*$BO$4 -> 16 | BO13: 1 | BP13: =BO13*BN13*$E13 -> 554.67499 | BQ13: =$BQ$4*$BR$4 -> 48 | BR13: 1 | BS13: =BR13*BQ13*$E13 -> 1664.025 | BV13: =BU13*BT13*$E13 -> 0 | BY13: =BX13*BW13*$E13 -> 0 | CB13: =CA13*BZ13*$E13 -> 0 | CE13: =CD13*CC13*$E13 -> 0 | CH13: =CG13*CF13*$E13 -> 0 | CK13: =CJ13*CI13*$E13 -> 0 | CN13: =CM13*CL13*$E13 -> 0 | CQ13: =CP13*CO13*$E13 -> 0 | CT13: =CS13*CR13*$E13 -> 0 | CW13: =CV13*CU13*$E13 -> 0 | CZ13: =CY13*CX13*$E13 -> 0 | DC13: =DB13*DA13*$E13 -> 0 | DD13: =$DD$4*$DE$4 -> 16 | DE13: 1 | DF13: =DE13*DD13*$E13 -> 554.67499 | DG13: =$DG$4*$DH$4 -> 12 | DH13: 1 | DI13: =DH13*DG13*$E13 -> 416.00624 | DJ13: =$DJ$4*$DK$4 -> 40 | DK13: 1 | DL13: =DK13*DJ13*$E13 -> 1386.6875 | DM13: =$DM$4*$DN$4 -> 24 | DN13: 1 | DO13: =DN13*DM13*$E13 -> 832.01249 | DS13: =($H$3*H13+$K$3*K13+$N$3*N13+$Q$3*Q13+$T$3*T13+$W$3*W13+$Z$3*Z13+$AC$3*AC13+$AF$3*AF13+$AI$3*AI13+$AL$3*AL13+$AO$3*AO13+$AR$3*AR13+$AU$3*AU13+$AX$3*AX13+$BA$3*BA13+$BD$3*BD13+$BG$3*BG13+$BJ$3*BJ13+$BM$3*BM13+$BP$3*BP13+$BS$3*BS13+$BV$3*BV13+$BY$3*BY13+$CB$3*CB13+$CE$3*CE13+$CH$3*CH13+$CK$3*CK13+$CN$3*CN13+$CQ$3*CQ13+$CT$3*CT13+$CW$3*CW13+$CZ$3*CZ13+$DC$3*DC13+$DF$3*DF13+$DI$3*DI13+$DL$3*DL13+$DO$3*DO13) -> 13728.206 | DT13: =DS13/$DS$130 -> 0.027758009
B14: =MO!B10 -> P08 | C14: =MO!C10 -> Encarregado de elétrica ou andaimes | D14: hh | E14: =MO!I10 -> 42.538636 | F14: =$F$4*$G$4 -> 160 | G14: 1 | H14: =G14*F14*$E14 -> 6806.1818 | I14: =$I$4*$J$4 -> 80 | J14: 1 | K14: =J14*I14*$E14 -> 3403.0909 | N14: =M14*L14*$E14 -> 0 | Q14: =P14*O14*$E14 -> 0 | T14: =S14*R14*$E14 -> 0 | W14: =V14*U14*$E14 -> 0 | Z14: =Y14*X14*$E14 -> 0 | AC14: =AB14*AA14*$E14 -> 0 | AF14: =AE14*AD14*$E14 -> 0 | AI14: =AH14*AG14*$E14 -> 0 | AL14: =AK14*AJ14*$E14 -> 0 | AO14: =AN14*AM14*$E14 -> 0 | AR14: =AQ14*AP14*$E14 -> 0 | AU14: =AT14*AS14*$E14 -> 0 | AX14: =AW14*AV14*$E14 -> 0 | BA14: =AZ14*AY14*$E14 -> 0 | BD14: =BC14*BB14*$E14 -> 0 | BG14: =BF14*BE14*$E14 -> 0 | BJ14: =BI14*BH14*$E14 -> 0 | BM14: =BL14*BK14*$E14 -> 0 | BN14: =$BN$4*$BO$4 -> 16 | BO14: 1 | BP14: =BO14*BN14*$E14 -> 680.61818 | BQ14: =$BQ$4*$BR$4 -> 48 | BR14: 1 | BS14: =BR14*BQ14*$E14 -> 2041.8545 | BT14: =$BT$4*$BU$4 -> 4 | BU14: 1 | BV14: =BU14*BT14*$E14 -> 170.15455 | BW14: =$BW$4*$BX$4 -> 2.56 | BX14: 1 | BY14: =BX14*BW14*$E14 -> 108.89891 | BZ14: =$BZ$4*$CA$4 -> 4.48 | CA14: 1 | CB14: =CA14*BZ14*$E14 -> 190.57309 | CC14: =$CC$4*$CD$4 -> 0.8 | CD14: 1 | CE14: =CD14*CC14*$E14 -> 34.030909 | CF14: =$CF$4*$CG$4 -> 1.2 | CG14: 1 | CH14: =CG14*CF14*$E14 -> 51.046364 | CI14: =$CI$4*$CJ$4 -> 0.4 | CJ14: 1 | CK14: =CJ14*CI14*$E14 -> 17.015455 | CL14: =$CL$4*$CM$4 -> 56 | CM14: 1 | CN14: =CM14*CL14*$E14 -> 2382.1636 | CO14: =$CO$4*$CP$4 -> 24 | CP14: 1 | CQ14: =CP14*CO14*$E14 -> 1020.9273 | CT14: =CS14*CR14*$E14 -> 0 | CW14: =CV14*CU14*$E14 -> 0 | CZ14: =CY14*CX14*$E14 -> 0 | DC14: =DB14*DA14*$E14 -> 0 | DD14: =$DD$4*$DE$4 -> 16 | DE14: 1 | DF14: =DE14*DD14*$E14 -> 680.61818 | DG14: =$DG$4*$DH$4 -> 12 | DH14: 1 | DI14: =DH14*DG14*$E14 -> 510.46364 | DJ14: =$DJ$4*$DK$4 -> 40 | DK14: 1 | DL14: =DK14*DJ14*$E14 -> 1701.5455 | DM14: =$DM$4*$DN$4 -> 24 | DN14: 1 | DO14: =DN14*DM14*$E14 -> 1020.9273 | DS14: =($H$3*H14+$K$3*K14+$N$3*N14+$Q$3*Q14+$T$3*T14+$W$3*W14+$Z$3*Z14+$AC$3*AC14+$AF$3*AF14+$AI$3*AI14+$AL$3*AL14+$AO$3*AO14+$AR$3*AR14+$AU$3*AU14+$AX$3*AX14+$BA$3*BA14+$BD$3*BD14+$BG$3*BG14+$BJ$3*BJ14+$BM$3*BM14+$BP$3*BP14+$BS$3*BS14+$BV$3*BV14+$BY$3*BY14+$CB$3*CB14+$CE$3*CE14+$CH$3*CH14+$CK$3*CK14+$CN$3*CN14+$CQ$3*CQ14+$CT$3*CT14+$CW$3*CW14+$CZ$3*CZ14+$DC$3*DC14+$DF$3*DF14+$DI$3*DI14+$DL$3*DL14+$DO$3*DO14) -> 24189.17 | DT14: =DS14/$DS$130 -> 0.048909756
B15: =MO!B11 -> P09 | C15: =MO!C11 -> Montador de estruturas metálicas | D15: hh | E15: =MO!I11 -> 30.14538 | F15: =$F$4*$G$4 -> 160 | G15: 1 | H15: =G15*F15*$E15 -> 4823.2608 | I15: =$I$4*$J$4 -> 80 | J15: 1 | K15: =J15*I15*$E15 -> 2411.6304 | N15: =M15*L15*$E15 -> 0 | Q15: =P15*O15*$E15 -> 0 | T15: =S15*R15*$E15 -> 0 | W15: =V15*U15*$E15 -> 0 | Z15: =Y15*X15*$E15 -> 0 | AC15: =AB15*AA15*$E15 -> 0 | AF15: =AE15*AD15*$E15 -> 0 | AI15: =AH15*AG15*$E15 -> 0 | AL15: =AK15*AJ15*$E15 -> 0 | AO15: =AN15*AM15*$E15 -> 0 | AR15: =AQ15*AP15*$E15 -> 0 | AU15: =AT15*AS15*$E15 -> 0 | AX15: =AW15*AV15*$E15 -> 0 | BA15: =AZ15*AY15*$E15 -> 0 | BD15: =BC15*BB15*$E15 -> 0 | BG15: =BF15*BE15*$E15 -> 0 | BJ15: =BI15*BH15*$E15 -> 0 | BM15: =BL15*BK15*$E15 -> 0 | BN15: =$BN$4*$BO$4 -> 16 | BO15: 1 | BP15: =BO15*BN15*$E15 -> 482.32608 | BQ15: =$BQ$4*$BR$4 -> 48 | BR15: 1 | BS15: =BR15*BQ15*$E15 -> 1446.9782 | BV15: =BU15*BT15*$E15 -> 0 | BY15: =BX15*BW15*$E15 -> 0 | CB15: =CA15*BZ15*$E15 -> 0 | CE15: =CD15*CC15*$E15 -> 0 | CH15: =CG15*CF15*$E15 -> 0 | CK15: =CJ15*CI15*$E15 -> 0 | CN15: =CM15*CL15*$E15 -> 0 | CQ15: =CP15*CO15*$E15 -> 0 | CT15: =CS15*CR15*$E15 -> 0 | CW15: =CV15*CU15*$E15 -> 0 | CZ15: =CY15*CX15*$E15 -> 0 | DC15: =DB15*DA15*$E15 -> 0 | DD15: =$DD$4*$DE$4 -> 16 | DE15: 1 | DF15: =DE15*DD15*$E15 -> 482.32608 | DG15: =$DG$4*$DH$4 -> 12 | DH15: 1 | DI15: =DH15*DG15*$E15 -> 361.74456 | DJ15: =$DJ$4*$DK$4 -> 40 | DK15: 1 | DL15: =DK15*DJ15*$E15 -> 1205.8152 | DM15: =$DM$4*$DN$4 -> 24 | DN15: 1 | DO15: =DN15*DM15*$E15 -> 723.48912 | DS15: =($H$3*H15+$K$3*K15+$N$3*N15+$Q$3*Q15+$T$3*T15+$W$3*W15+$Z$3*Z15+$AC$3*AC15+$AF$3*AF15+$AI$3*AI15+$AL$3*AL15+$AO$3*AO15+$AR$3*AR15+$AU$3*AU15+$AX$3*AX15+$BA$3*BA15+$BD$3*BD15+$BG$3*BG15+$BJ$3*BJ15+$BM$3*BM15+$BP$3*BP15+$BS$3*BS15+$BV$3*BV15+$BY$3*BY15+$CB$3*CB15+$CE$3*CE15+$CH$3*CH15+$CK$3*CK15+$CN$3*CN15+$CQ$3*CQ15+$CT$3*CT15+$CW$3*CW15+$CZ$3*CZ15+$DC$3*DC15+$DF$3*DF15+$DI$3*DI15+$DL$3*DL15+$DO$3*DO15) -> 11937.57 | DT15: =DS15/$DS$130 -> 0.024137399
B16: =MO!B12 -> P10 | C16: =MO!C12 -> Topógrafo | D16: hh | E16: =MO!I12 -> 31.028182 | H16: =G16*F16*$E16 -> 0 | K16: =J16*I16*$E16 -> 0 | N16: =M16*L16*$E16 -> 0 | Q16: =P16*O16*$E16 -> 0 | T16: =S16*R16*$E16 -> 0 | W16: =V16*U16*$E16 -> 0 | X16: =$X$4*$Y$4 -> 80 | Y16: 1 | Z16: =Y16*X16*$E16 -> 2482.2545 | AC16: =AB16*AA16*$E16 -> 0 | AF16: =AE16*AD16*$E16 -> 0 | AI16: =AH16*AG16*$E16 -> 0 | AL16: =AK16*AJ16*$E16 -> 0 | AO16: =AN16*AM16*$E16 -> 0 | AR16: =AQ16*AP16*$E16 -> 0 | AU16: =AT16*AS16*$E16 -> 0 | AX16: =AW16*AV16*$E16 -> 0 | BA16: =AZ16*AY16*$E16 -> 0 | BD16: =BC16*BB16*$E16 -> 0 | BG16: =BF16*BE16*$E16 -> 0 | BJ16: =BI16*BH16*$E16 -> 0 | BM16: =BL16*BK16*$E16 -> 0 | BN16: =$BN$4*$BO$4 -> 16 | BO16: 1 | BP16: =BO16*BN16*$E16 -> 496.45091 | BQ16: =$BQ$4*$BR$4 -> 48 | BR16: 1 | BS16: =BR16*BQ16*$E16 -> 1489.3527 | BV16: =BU16*BT16*$E16 -> 0 | BY16: =BX16*BW16*$E16 -> 0 | CB16: =CA16*BZ16*$E16 -> 0 | CE16: =CD16*CC16*$E16 -> 0 | CH16: =CG16*CF16*$E16 -> 0 | CK16: =CJ16*CI16*$E16 -> 0 | CN16: =CM16*CL16*$E16 -> 0 | CQ16: =CP16*CO16*$E16 -> 0 | CT16: =CS16*CR16*$E16 -> 0 | CW16: =CV16*CU16*$E16 -> 0 | CZ16: =CY16*CX16*$E16 -> 0 | DC16: =DB16*DA16*$E16 -> 0 | DF16: =DE16*DD16*$E16 -> 0 | DI16: =DH16*DG16*$E16 -> 0 | DL16: =DK16*DJ16*$E16 -> 0 | DO16: =DN16*DM16*$E16 -> 0 | DS16: =($H$3*H16+$K$3*K16+$N$3*N16+$Q$3*Q16+$T$3*T16+$W$3*W16+$Z$3*Z16+$AC$3*AC16+$AF$3*AF16+$AI$3*AI16+$AL$3*AL16+$AO$3*AO16+$AR$3*AR16+$AU$3*AU16+$AX$3*AX16+$BA$3*BA16+$BD$3*BD16+$BG$3*BG16+$BJ$3*BJ16+$BM$3*BM16+$BP$3*BP16+$BS$3*BS16+$BV$3*BV16+$BY$3*BY16+$CB$3*CB16+$CE$3*CE16+$CH$3*CH16+$CK$3*CK16+$CN$3*CN16+$CQ$3*CQ16+$CT$3*CT16+$CW$3*CW16+$CZ$3*CZ16+$DC$3*DC16+$DF$3*DF16+$DI$3*DI16+$DL$3*DL16+$DO$3*DO16) -> 4468.0582 | DT16: =DS16/$DS$130 -> 0.0090342758
B17: =MO!B13 -> P11 | C17: =MO!C13 -> Auxiliar de topografia | D17: hh | E17: =MO!I13 -> 16.515 | H17: =G17*F17*$E17 -> 0 | K17: =J17*I17*$E17 -> 0 | N17: =M17*L17*$E17 -> 0 | Q17: =P17*O17*$E17 -> 0 | T17: =S17*R17*$E17 -> 0 | W17: =V17*U17*$E17 -> 0 | X17: =$X$4*$Y$4 -> 80 | Y17: 1 | Z17: =Y17*X17*$E17 -> 1321.2 | AC17: =AB17*AA17*$E17 -> 0 | AF17: =AE17*AD17*$E17 -> 0 | AI17: =AH17*AG17*$E17 -> 0 | AL17: =AK17*AJ17*$E17 -> 0 | AO17: =AN17*AM17*$E17 -> 0 | AR17: =AQ17*AP17*$E17 -> 0 | AU17: =AT17*AS17*$E17 -> 0 | AX17: =AW17*AV17*$E17 -> 0 | BA17: =AZ17*AY17*$E17 -> 0 | BD17: =BC17*BB17*$E17 -> 0 | BG17: =BF17*BE17*$E17 -> 0 | BJ17: =BI17*BH17*$E17 -> 0 | BM17: =BL17*BK17*$E17 -> 0 | BN17: =$BN$4*$BO$4 -> 16 | BO17: 1 | BP17: =BO17*BN17*$E17 -> 264.24 | BQ17: =$BQ$4*$BR$4 -> 48 | BR17: 1 | BS17: =BR17*BQ17*$E17 -> 792.72 | BV17: =BU17*BT17*$E17 -> 0 | BY17: =BX17*BW17*$E17 -> 0 | CB17: =CA17*BZ17*$E17 -> 0 | CE17: =CD17*CC17*$E17 -> 0 | CH17: =CG17*CF17*$E17 -> 0 | CK17: =CJ17*CI17*$E17 -> 0 | CN17: =CM17*CL17*$E17 -> 0 | CQ17: =CP17*CO17*$E17 -> 0 | CT17: =CS17*CR17*$E17 -> 0 | CW17: =CV17*CU17*$E17 -> 0 | CZ17: =CY17*CX17*$E17 -> 0 | DC17: =DB17*DA17*$E17 -> 0 | DF17: =DE17*DD17*$E17 -> 0 | DI17: =DH17*DG17*$E17 -> 0 | DL17: =DK17*DJ17*$E17 -> 0 | DO17: =DN17*DM17*$E17 -> 0 | DS17: =($H$3*H17+$K$3*K17+$N$3*N17+$Q$3*Q17+$T$3*T17+$W$3*W17+$Z$3*Z17+$AC$3*AC17+$AF$3*AF17+$AI$3*AI17+$AL$3*AL17+$AO$3*AO17+$AR$3*AR17+$AU$3*AU17+$AX$3*AX17+$BA$3*BA17+$BD$3*BD17+$BG$3*BG17+$BJ$3*BJ17+$BM$3*BM17+$BP$3*BP17+$BS$3*BS17+$BV$3*BV17+$BY$3*BY17+$CB$3*CB17+$CE$3*CE17+$CH$3*CH17+$CK$3*CK17+$CN$3*CN17+$CQ$3*CQ17+$CT$3*CT17+$CW$3*CW17+$CZ$3*CZ17+$DC$3*DC17+$DF$3*DF17+$DI$3*DI17+$DL$3*DL17+$DO$3*DO17) -> 2378.16 | DT17: =DS17/$DS$130 -> 0.0048085662
B18: =MO!B14 -> P12 | C18: =MO!C14 -> Sinaleiro de rigger | D18: hh | E18: =MO!I14 -> 21.88788 | F18: =$F$4*$G$4 -> 160 | G18: 1 | H18: =G18*F18*$E18 -> 3502.0608 | I18: =$I$4*$J$4 -> 80 | J18: 1 | K18: =J18*I18*$E18 -> 1751.0304 | N18: =M18*L18*$E18 -> 0 | Q18: =P18*O18*$E18 -> 0 | T18: =S18*R18*$E18 -> 0 | W18: =V18*U18*$E18 -> 0 | Z18: =Y18*X18*$E18 -> 0 | AC18: =AB18*AA18*$E18 -> 0 | AF18: =AE18*AD18*$E18 -> 0 | AI18: =AH18*AG18*$E18 -> 0 | AL18: =AK18*AJ18*$E18 -> 0 | AO18: =AN18*AM18*$E18 -> 0 | AR18: =AQ18*AP18*$E18 -> 0 | AU18: =AT18*AS18*$E18 -> 0 | AX18: =AW18*AV18*$E18 -> 0 | BA18: =AZ18*AY18*$E18 -> 0 | BD18: =BC18*BB18*$E18 -> 0 | BG18: =BF18*BE18*$E18 -> 0 | BJ18: =BI18*BH18*$E18 -> 0 | BM18: =BL18*BK18*$E18 -> 0 | BN18: =$BN$4*$BO$4 -> 16 | BO18: 1 | BP18: =BO18*BN18*$E18 -> 350.20608 | BQ18: =$BQ$4*$BR$4 -> 48 | BR18: 1 | BS18: =BR18*BQ18*$E18 -> 1050.6182 | BV18: =BU18*BT18*$E18 -> 0 | BY18: =BX18*BW18*$E18 -> 0 | CB18: =CA18*BZ18*$E18 -> 0 | CE18: =CD18*CC18*$E18 -> 0 | CH18: =CG18*CF18*$E18 -> 0 | CK18: =CJ18*CI18*$E18 -> 0 | CL18: =$CL$4*$CM$4 -> 56 | CM18: 1 | CN18: =CM18*CL18*$E18 -> 1225.7213 | CO18: =$CO$4*$CP$4 -> 24 | CP18: 1 | CQ18: =CP18*CO18*$E18 -> 525.30912 | CT18: =CS18*CR18*$E18 -> 0 | CW18: =CV18*CU18*$E18 -> 0 | CZ18: =CY18*CX18*$E18 -> 0 | DC18: =DB18*DA18*$E18 -> 0 | DD18: =$DD$4*$DE$4 -> 16 | DE18: 1 | DF18: =DE18*DD18*$E18 -> 350.20608 | DG18: =$DG$4*$DH$4 -> 12 | DH18: 1 | DI18: =DH18*DG18*$E18 -> 262.65456 | DJ18: =$DJ$4*$DK$4 -> 40 | DK18: 1 | DL18: =DK18*DJ18*$E18 -> 875.5152 | DM18: =$DM$4*$DN$4 -> 24 | DN18: 1 | DO18: =DN18*DM18*$E18 -> 525.30912 | DS18: =($H$3*H18+$K$3*K18+$N$3*N18+$Q$3*Q18+$T$3*T18+$W$3*W18+$Z$3*Z18+$AC$3*AC18+$AF$3*AF18+$AI$3*AI18+$AL$3*AL18+$AO$3*AO18+$AR$3*AR18+$AU$3*AU18+$AX$3*AX18+$BA$3*BA18+$BD$3*BD18+$BG$3*BG18+$BJ$3*BJ18+$BM$3*BM18+$BP$3*BP18+$BS$3*BS18+$BV$3*BV18+$BY$3*BY18+$CB$3*CB18+$CE$3*CE18+$CH$3*CH18+$CK$3*CK18+$CN$3*CN18+$CQ$3*CQ18+$CT$3*CT18+$CW$3*CW18+$CZ$3*CZ18+$DC$3*DC18+$DF$3*DF18+$DI$3*DI18+$DL$3*DL18+$DO$3*DO18) -> 10418.631 | DT18: =DS18/$DS$130 -> 0.02106615
B19: =MO!B15 -> P13 | C19: =MO!C15 -> Servente/Auxiliar de obras | D19: hh | E19: =MO!I15 -> 15.72228 | F19: =$F$4*$G$4 -> 160 | G19: 2 | H19: =G19*F19*$E19 -> 5031.1296 | I19: =$I$4*$J$4 -> 80 | J19: 2 | K19: =J19*I19*$E19 -> 2515.5648 | L19: =$L$4*$M$4 -> 80 | M19: 2 | N19: =M19*L19*$E19 -> 2515.5648 | Q19: =P19*O19*$E19 -> 0 | T19: =S19*R19*$E19 -> 0 | W19: =V19*U19*$E19 -> 0 | Z19: =Y19*X19*$E19 -> 0 | AC19: =AB19*AA19*$E19 -> 0 | AF19: =AE19*AD19*$E19 -> 0 | AI19: =AH19*AG19*$E19 -> 0 | AL19: =AK19*AJ19*$E19 -> 0 | AO19: =AN19*AM19*$E19 -> 0 | AR19: =AQ19*AP19*$E19 -> 0 | AU19: =AT19*AS19*$E19 -> 0 | AX19: =AW19*AV19*$E19 -> 0 | BA19: =AZ19*AY19*$E19 -> 0 | BD19: =BC19*BB19*$E19 -> 0 | BG19: =BF19*BE19*$E19 -> 0 | BJ19: =BI19*BH19*$E19 -> 0 | BM19: =BL19*BK19*$E19 -> 0 | BN19: =$BN$4*$BO$4 -> 16 | BO19: 1 | BP19: =BO19*BN19*$E19 -> 251.55648 | BQ19: =$BQ$4*$BR$4 -> 48 | BR19: 1 | BS19: =BR19*BQ19*$E19 -> 754.66944 | BT19: =$BT$4*$BU$4 -> 4 | BU19: 1 | BV19: =BU19*BT19*$E19 -> 62.88912 | BW19: =$BW$4*$BX$4 -> 2.56 | BX19: 1 | BY19: =BX19*BW19*$E19 -> 40.249037 | BZ19: =$BZ$4*$CA$4 -> 4.48 | CA19: 1 | CB19: =CA19*BZ19*$E19 -> 70.435814 | CC19: =$CC$4*$CD$4 -> 0.8 | CD19: 1 | CE19: =CD19*CC19*$E19 -> 12.577824 | CF19: =$CF$4*$CG$4 -> 1.2 | CG19: 1 | CH19: =CG19*CF19*$E19 -> 18.866736 | CI19: =$CI$4*$CJ$4 -> 0.4 | CJ19: 1 | CK19: =CJ19*CI19*$E19 -> 6.288912 | CL19: =$CL$4*$CM$4 -> 56 | CM19: 1 | CN19: =CM19*CL19*$E19 -> 880.44768 | CO19: =$CO$4*$CP$4 -> 24 | CP19: 1 | CQ19: =CP19*CO19*$E19 -> 377.33472 | CT19: =CS19*CR19*$E19 -> 0 | CW19: =CV19*CU19*$E19 -> 0 | CZ19: =CY19*CX19*$E19 -> 0 | DC19: =DB19*DA19*$E19 -> 0 | DD19: =$DD$4*$DE$4 -> 16 | DE19: 1 | DF19: =DE19*DD19*$E19 -> 251.55648 | DG19: =$DG$4*$DH$4 -> 12 | DH19: 1 | DI19: =DH19*DG19*$E19 -> 188.66736 | DJ19: =$DJ$4*$DK$4 -> 40 | DK19: 1 | DL19: =DK19*DJ19*$E19 -> 628.8912 | DM19: =$DM$4*$DN$4 -> 24 | DN19: 1 | DO19: =DN19*DM19*$E19 -> 377.33472 | DS19: =($H$3*H19+$K$3*K19+$N$3*N19+$Q$3*Q19+$T$3*T19+$W$3*W19+$Z$3*Z19+$AC$3*AC19+$AF$3*AF19+$AI$3*AI19+$AL$3*AL19+$AO$3*AO19+$AR$3*AR19+$AU$3*AU19+$AX$3*AX19+$BA$3*BA19+$BD$3*BD19+$BG$3*BG19+$BJ$3*BJ19+$BM$3*BM19+$BP$3*BP19+$BS$3*BS19+$BV$3*BV19+$BY$3*BY19+$CB$3*CB19+$CE$3*CE19+$CH$3*CH19+$CK$3*CK19+$CN$3*CN19+$CQ$3*CQ19+$CT$3*CT19+$CW$3*CW19+$CZ$3*CZ19+$DC$3*DC19+$DF$3*DF19+$DI$3*DI19+$DL$3*DL19+$DO$3*DO19) -> 15229.229 | DT19: =DS19/$DS$130 -> 0.030793032
B20: =MO!B16 -> P14 | C20: =MO!C16 -> Supervisor de obras | D20: hh | E20: =MO!I16 -> 52.047273 | F20: =$F$4*$G$4 -> 160 | G20: 1 | H20: =G20*F20*$E20 -> 8327.5636 | I20: =$I$4*$J$4 -> 80 | J20: 1 | K20: =J20*I20*$E20 -> 4163.7818 | N20: =M20*L20*$E20 -> 0 | Q20: =P20*O20*$E20 -> 0 | T20: =S20*R20*$E20 -> 0 | W20: =V20*U20*$E20 -> 0 | Z20: =Y20*X20*$E20 -> 0 | AC20: =AB20*AA20*$E20 -> 0 | AF20: =AE20*AD20*$E20 -> 0 | AI20: =AH20*AG20*$E20 -> 0 | AL20: =AK20*AJ20*$E20 -> 0 | AO20: =AN20*AM20*$E20 -> 0 | AR20: =AQ20*AP20*$E20 -> 0 | AU20: =AT20*AS20*$E20 -> 0 | AX20: =AW20*AV20*$E20 -> 0 | BA20: =AZ20*AY20*$E20 -> 0 | BD20: =BC20*BB20*$E20 -> 0 | BG20: =BF20*BE20*$E20 -> 0 | BJ20: =BI20*BH20*$E20 -> 0 | BM20: =BL20*BK20*$E20 -> 0 | BN20: =$BN$4*$BO$4 -> 16 | BO20: 1 | BP20: =BO20*BN20*$E20 -> 832.75636 | BQ20: =$BQ$4*$BR$4 -> 48 | BR20: 1 | BS20: =BR20*BQ20*$E20 -> 2498.2691 | BT20: =$BT$4*$BU$4 -> 4 | BU20: 1 | BV20: =BU20*BT20*$E20 -> 208.18909 | BW20: =$BW$4*$BX$4 -> 2.56 | BX20: 1 | BY20: =BX20*BW20*$E20 -> 133.24102 | BZ20: =$BZ$4*$CA$4 -> 4.48 | CA20: 1 | CB20: =CA20*BZ20*$E20 -> 233.17178 | CC20: =$CC$4*$CD$4 -> 0.8 | CD20: 1 | CE20: =CD20*CC20*$E20 -> 41.637818 | CF20: =$CF$4*$CG$4 -> 1.2 | CG20: 1 | CH20: =CG20*CF20*$E20 -> 62.456727 | CI20: =$CI$4*$CJ$4 -> 0.4 | CJ20: 1 | CK20: =CJ20*CI20*$E20 -> 20.818909 | CL20: =$CL$4*$CM$4 -> 56 | CM20: 1 | CN20: =CM20*CL20*$E20 -> 2914.6473 | CO20: =$CO$4*$CP$4 -> 24 | CP20: 1 | CQ20: =CP20*CO20*$E20 -> 1249.1345 | CT20: =CS20*CR20*$E20 -> 0 | CW20: =CV20*CU20*$E20 -> 0 | CZ20: =CY20*CX20*$E20 -> 0 | DC20: =DB20*DA20*$E20 -> 0 | DD20: =$DD$4*$DE$4 -> 16 | DE20: 1 | DF20: =DE20*DD20*$E20 -> 832.75636 | DG20: =$DG$4*$DH$4 -> 12 | DH20: 1 | DI20: =DH20*DG20*$E20 -> 624.56727 | DJ20: =$DJ$4*$DK$4 -> 40 | DK20: 1 | DL20: =DK20*DJ20*$E20 -> 2081.8909 | DM20: =$DM$4*$DN$4 -> 24 | DN20: 1 | DO20: =DN20*DM20*$E20 -> 1249.1345 | DS20: =($H$3*H20+$K$3*K20+$N$3*N20+$Q$3*Q20+$T$3*T20+$W$3*W20+$Z$3*Z20+$AC$3*AC20+$AF$3*AF20+$AI$3*AI20+$AL$3*AL20+$AO$3*AO20+$AR$3*AR20+$AU$3*AU20+$AX$3*AX20+$BA$3*BA20+$BD$3*BD20+$BG$3*BG20+$BJ$3*BJ20+$BM$3*BM20+$BP$3*BP20+$BS$3*BS20+$BV$3*BV20+$BY$3*BY20+$CB$3*CB20+$CE$3*CE20+$CH$3*CH20+$CK$3*CK20+$CN$3*CN20+$CQ$3*CQ20+$CT$3*CT20+$CW$3*CW20+$CZ$3*CZ20+$DC$3*DC20+$DF$3*DF20+$DI$3*DI20+$DL$3*DL20+$DO$3*DO20) -> 29596.161 | DT20: =DS20/$DS$130 -> 0.059842525
B21: A - Custo Total de Mão de Obra: | F21: =SUM(F7:F20) -> 1440 | G21: =SUM(G7:G20) -> 11 | H21: =SUM(H7:H20) -> 51331.407 | I21: =SUM(I7:I20) -> 720 | J21: =SUM(J7:J20) -> 11 | K21: =SUM(K7:K20) -> 25665.703 | L21: =SUM(L7:L20) -> 80 | M21: =SUM(M7:M20) -> 2 | ... DO21: =SUM(DO7:DO20) -> 5448.8618 | DQ21: =SUM(DQ7:DQ20) -> 0 | DR21: =SUM(DR7:DR20) -> 0 | DS21: =SUM(DS7:DS20) -> 224123.35
B22: B – Equipamentos e Ferramentas
B23: Cód. | C23: Discriminação | D23: Unid | E23: P.Unit | F23: Quant | G23: F.utiliz | H23: Custo | I23: Quant | J23: F.utiliz | K23: Custo | L23: Quant | M23: F.utiliz | N23: Custo | O23: Quant | P23: F.utiliz | Q23: Custo | R23: Quant | S23: F.utiliz | T23: Custo | U23: Quant | V23: F.utiliz | W23: Custo | X23: Quant | Y23: F.utiliz | Z23: Custo | AA23: Quant | AB23: F.utiliz | AC23: Custo | AD23: Quant | AE23: F.utiliz | AF23: Custo | AG23: Quant | AH23: F.utiliz | AI23: Custo | AJ23: Quant | AK23: F.utiliz | AL23: Custo | AM23: Quant | AN23: F.utiliz | AO23: Custo | AP23: Quant | AQ23: F.utiliz | AR23: Custo | AS23: Quant | AT23: F.utiliz | AU23: Custo | AV23: Quant | AW23: F.utiliz | AX23: Custo | AY23: Quant | AZ23: F.utiliz | BA23: Custo | BB23: Quant | BC23: F.utiliz | BD23: Custo | BE23: Quant | BF23: F.utiliz | BG23: Custo | BH23: Quant | BI23: F.utiliz | BJ23: Custo | BK23: Quant | BL23: F.utiliz | BM23: Custo | BN23: Quant | BO23: F.utiliz | BP23: Custo | BQ23: Quant | BR23: F.utiliz | BS23: Custo | BT23: Quant | BU23: F.utiliz | BV23: Custo | BW23: Quant | BX23: F.utiliz | BY23: Custo | BZ23: Quant | CA23: F.utiliz | CB23: Custo | CC23: Quant | CD23: F.utiliz | CE23: Custo | CF23: Quant | CG23: F.utiliz | CH23: Custo | CI23: Quant | CJ23: F.utiliz | CK23: Custo | CL23: Quant | CM23: F.utiliz | CN23: Custo | CO23: Quant | CP23: F.utiliz | CQ23: Custo | CR23: Quant | CS23: F.utiliz | CT23: Custo | CU23: Quant | CV23: F.utiliz | CW23: Custo | CX23: Quant | CY23: F.utiliz | CZ23: Custo | DA23: Quant | DB23: F.utiliz | DC23: Custo | DD23: Quant | DE23: F.utiliz | DF23: Custo | DG23: Quant | DH23: F.utiliz | DI23: Custo | DJ23: Quant | DK23: F.utiliz | DL23: Custo | DM23: Quant | DN23: F.utiliz | DO23: Custo | DQ23: Quant | DR23: F.utiliz | DS23: Custo
B24: E01 | C24: Conteiner escritório | D24: Vb/mês | E24: 1700 | H24: =G24*F24*$E24 -> 0 | K24: =J24*I24*$E24 -> 0 | L24: 1 | M24: =29/22 -> 1.3181818 | N24: =M24*L24*$E24 -> 2240.9091 | Q24: =P24*O24*$E24 -> 0 | T24: =S24*R24*$E24 -> 0 | W24: =V24*U24*$E24 -> 0 | Z24: =Y24*X24*$E24 -> 0 | AC24: =AB24*AA24*$E24 -> 0 | AF24: =AE24*AD24*$E24 -> 0 | AI24: =AH24*AG24*$E24 -> 0 | AL24: =AK24*AJ24*$E24 -> 0 | AO24: =AN24*AM24*$E24 -> 0 | AR24: =AQ24*AP24*$E24 -> 0 | AU24: =AT24*AS24*$E24 -> 0 | AX24: =AW24*AV24*$E24 -> 0 | BA24: =AZ24*AY24*$E24 -> 0 | BD24: =BC24*BB24*$E24 -> 0 | BG24: =BF24*BE24*$E24 -> 0 | BJ24: =BI24*BH24*$E24 -> 0 | BM24: =BL24*BK24*$E24 -> 0 | BP24: =BO24*BN24*$E24 -> 0 | BS24: =BR24*BQ24*$E24 -> 0 | BV24: =BU24*BT24*$E24 -> 0 | BY24: =BX24*BW24*$E24 -> 0 | CB24: =CA24*BZ24*$E24 -> 0 | CE24: =CD24*CC24*$E24 -> 0 | CH24: =CG24*CF24*$E24 -> 0 | CK24: =CJ24*CI24*$E24 -> 0 | CN24: =CM24*CL24*$E24 -> 0 | CQ24: =CP24*CO24*$E24 -> 0 | CT24: =CS24*CR24*$E24 -> 0 | CW24: =CV24*CU24*$E24 -> 0 | CZ24: =CY24*CX24*$E24 -> 0 | DC24: =DB24*DA24*$E24 -> 0 | DF24: =DE24*DD24*$E24 -> 0 | DI24: =DH24*DG24*$E24 -> 0 | DL24: =DK24*DJ24*$E24 -> 0 | DO24: =DN24*DM24*$E24 -> 0 | DS24: =($H$3*H24+$K$3*K24+$N$3*N24+$Q$3*Q24+$T$3*T24+$W$3*W24+$Z$3*Z24+$AC$3*AC24+$AF$3*AF24+$AI$3*AI24+$AL$3*AL24+$AO$3*AO24+$AR$3*AR24+$AU$3*AU24+$AX$3*AX24+$BA$3*BA24+$BD$3*BD24+$BG$3*BG24+$BJ$3*BJ24+$BM$3*BM24+$BP$3*BP24+$BS$3*BS24+$BV$3*BV24+$BY$3*BY24+$CB$3*CB24+$CE$3*CE24+$CH$3*CH24+$CK$3*CK24+$CN$3*CN24+$CQ$3*CQ24+$CT$3*CT24+$CW$3*CW24+$CZ$3*CZ24+$DC$3*DC24+$DF$3*DF24+$DI$3*DI24+$DL$3*DL24+$DO$3*DO24) -> 2240.9091 | DT24: =DS24/$DS$130 -> 0.0045310491
B25: E02 | C25: Banheiro químico | D25: Vb/mês | E25: 1200 | H25: =G25*F25*$E25 -> 0 | K25: =J25*I25*$E25 -> 0 | L25: 1 | M25: =29/22 -> 1.3181818 | N25: =M25*L25*$E25 -> 1581.8182 | Q25: =P25*O25*$E25 -> 0 | T25: =S25*R25*$E25 -> 0 | W25: =V25*U25*$E25 -> 0 | Z25: =Y25*X25*$E25 -> 0 | AC25: =AB25*AA25*$E25 -> 0 | AF25: =AE25*AD25*$E25 -> 0 | AI25: =AH25*AG25*$E25 -> 0 | AL25: =AK25*AJ25*$E25 -> 0 | AO25: =AN25*AM25*$E25 -> 0 | AR25: =AQ25*AP25*$E25 -> 0 | AU25: =AT25*AS25*$E25 -> 0 | AX25: =AW25*AV25*$E25 -> 0 | BA25: =AZ25*AY25*$E25 -> 0 | BD25: =BC25*BB25*$E25 -> 0 | BG25: =BF25*BE25*$E25 -> 0 | BJ25: =BI25*BH25*$E25 -> 0 | BM25: =BL25*BK25*$E25 -> 0 | BP25: =BO25*BN25*$E25 -> 0 | BS25: =BR25*BQ25*$E25 -> 0 | BV25: =BU25*BT25*$E25 -> 0 | BY25: =BX25*BW25*$E25 -> 0 | CB25: =CA25*BZ25*$E25 -> 0 | CE25: =CD25*CC25*$E25 -> 0 | CH25: =CG25*CF25*$E25 -> 0 | CK25: =CJ25*CI25*$E25 -> 0 | CN25: =CM25*CL25*$E25 -> 0 | CQ25: =CP25*CO25*$E25 -> 0 | CT25: =CS25*CR25*$E25 -> 0 | CW25: =CV25*CU25*$E25 -> 0 | CZ25: =CY25*CX25*$E25 -> 0 | DC25: =DB25*DA25*$E25 -> 0 | DF25: =DE25*DD25*$E25 -> 0 | DI25: =DH25*DG25*$E25 -> 0 | DL25: =DK25*DJ25*$E25 -> 0 | DO25: =DN25*DM25*$E25 -> 0 | DS25: =($H$3*H25+$K$3*K25+$N$3*N25+$Q$3*Q25+$T$3*T25+$W$3*W25+$Z$3*Z25+$AC$3*AC25+$AF$3*AF25+$AI$3*AI25+$AL$3*AL25+$AO$3*AO25+$AR$3*AR25+$AU$3*AU25+$AX$3*AX25+$BA$3*BA25+$BD$3*BD25+$BG$3*BG25+$BJ$3*BJ25+$BM$3*BM25+$BP$3*BP25+$BS$3*BS25+$BV$3*BV25+$BY$3*BY25+$CB$3*CB25+$CE$3*CE25+$CH$3*CH25+$CK$3*CK25+$CN$3*CN25+$CQ$3*CQ25+$CT$3*CT25+$CW$3*CW25+$CZ$3*CZ25+$DC$3*DC25+$DF$3*DF25+$DI$3*DI25+$DL$3*DL25+$DO$3*DO25) -> 1581.8182 | DT25: =DS25/$DS$130 -> 0.0031983876
B26: E03 | C26: Tenda lonada 6 x 6 m, piramidal - AQUISIÇÃO | D26: Vb | E26: 4500 | H26: =G26*F26*$E26 -> 0 | K26: =J26*I26*$E26 -> 0 | L26: 1 | M26: 1 | N26: =M26*L26*$E26 -> 4500 | Q26: =P26*O26*$E26 -> 0 | T26: =S26*R26*$E26 -> 0 | W26: =V26*U26*$E26 -> 0 | Z26: =Y26*X26*$E26 -> 0 | AC26: =AB26*AA26*$E26 -> 0 | AF26: =AE26*AD26*$E26 -> 0 | AI26: =AH26*AG26*$E26 -> 0 | AL26: =AK26*AJ26*$E26 -> 0 | AO26: =AN26*AM26*$E26 -> 0 | AR26: =AQ26*AP26*$E26 -> 0 | AU26: =AT26*AS26*$E26 -> 0 | AX26: =AW26*AV26*$E26 -> 0 | BA26: =AZ26*AY26*$E26 -> 0 | BD26: =BC26*BB26*$E26 -> 0 | BG26: =BF26*BE26*$E26 -> 0 | BJ26: =BI26*BH26*$E26 -> 0 | BM26: =BL26*BK26*$E26 -> 0 | BP26: =BO26*BN26*$E26 -> 0 | BS26: =BR26*BQ26*$E26 -> 0 | BV26: =BU26*BT26*$E26 -> 0 | BY26: =BX26*BW26*$E26 -> 0 | CB26: =CA26*BZ26*$E26 -> 0 | CE26: =CD26*CC26*$E26 -> 0 | CH26: =CG26*CF26*$E26 -> 0 | CK26: =CJ26*CI26*$E26 -> 0 | CN26: =CM26*CL26*$E26 -> 0 | CQ26: =CP26*CO26*$E26 -> 0 | CT26: =CS26*CR26*$E26 -> 0 | CW26: =CV26*CU26*$E26 -> 0 | CZ26: =CY26*CX26*$E26 -> 0 | DC26: =DB26*DA26*$E26 -> 0 | DF26: =DE26*DD26*$E26 -> 0 | DI26: =DH26*DG26*$E26 -> 0 | DL26: =DK26*DJ26*$E26 -> 0 | DO26: =DN26*DM26*$E26 -> 0 | DS26: =($H$3*H26+$K$3*K26+$N$3*N26+$Q$3*Q26+$T$3*T26+$W$3*W26+$Z$3*Z26+$AC$3*AC26+$AF$3*AF26+$AI$3*AI26+$AL$3*AL26+$AO$3*AO26+$AR$3*AR26+$AU$3*AU26+$AX$3*AX26+$BA$3*BA26+$BD$3*BD26+$BG$3*BG26+$BJ$3*BJ26+$BM$3*BM26+$BP$3*BP26+$BS$3*BS26+$BV$3*BV26+$BY$3*BY26+$CB$3*CB26+$CE$3*CE26+$CH$3*CH26+$CK$3*CK26+$CN$3*CN26+$CQ$3*CQ26+$CT$3*CT26+$CW$3*CW26+$CZ$3*CZ26+$DC$3*DC26+$DF$3*DF26+$DI$3*DI26+$DL$3*DL26+$DO$3*DO26) -> 4500 | DT26: =DS26/$DS$130 -> 0.0090988612
B27: E04 | C27: Mobiliário (Cadeiras e mesas plásticas) | D27: Vb | E27: 852.46 | H27: =G27*F27*$E27 -> 0 | K27: =J27*I27*$E27 -> 0 | L27: 1 | M27: 1 | N27: =M27*L27*$E27 -> 852.46 | Q27: =P27*O27*$E27 -> 0 | T27: =S27*R27*$E27 -> 0 | W27: =V27*U27*$E27 -> 0 | Z27: =Y27*X27*$E27 -> 0 | AC27: =AB27*AA27*$E27 -> 0 | AF27: =AE27*AD27*$E27 -> 0 | AI27: =AH27*AG27*$E27 -> 0 | AL27: =AK27*AJ27*$E27 -> 0 | AO27: =AN27*AM27*$E27 -> 0 | AR27: =AQ27*AP27*$E27 -> 0 | AU27: =AT27*AS27*$E27 -> 0 | AX27: =AW27*AV27*$E27 -> 0 | BA27: =AZ27*AY27*$E27 -> 0 | BD27: =BC27*BB27*$E27 -> 0 | BG27: =BF27*BE27*$E27 -> 0 | BJ27: =BI27*BH27*$E27 -> 0 | BM27: =BL27*BK27*$E27 -> 0 | BP27: =BO27*BN27*$E27 -> 0 | BS27: =BR27*BQ27*$E27 -> 0 | BV27: =BU27*BT27*$E27 -> 0 | BY27: =BX27*BW27*$E27 -> 0 | CB27: =CA27*BZ27*$E27 -> 0 | CE27: =CD27*CC27*$E27 -> 0 | CH27: =CG27*CF27*$E27 -> 0 | CK27: =CJ27*CI27*$E27 -> 0 | CN27: =CM27*CL27*$E27 -> 0 | CQ27: =CP27*CO27*$E27 -> 0 | CT27: =CS27*CR27*$E27 -> 0 | CW27: =CV27*CU27*$E27 -> 0 | CZ27: =CY27*CX27*$E27 -> 0 | DC27: =DB27*DA27*$E27 -> 0 | DF27: =DE27*DD27*$E27 -> 0 | DI27: =DH27*DG27*$E27 -> 0 | DL27: =DK27*DJ27*$E27 -> 0 | DO27: =DN27*DM27*$E27 -> 0 | DS27: =($H$3*H27+$K$3*K27+$N$3*N27+$Q$3*Q27+$T$3*T27+$W$3*W27+$Z$3*Z27+$AC$3*AC27+$AF$3*AF27+$AI$3*AI27+$AL$3*AL27+$AO$3*AO27+$AR$3*AR27+$AU$3*AU27+$AX$3*AX27+$BA$3*BA27+$BD$3*BD27+$BG$3*BG27+$BJ$3*BJ27+$BM$3*BM27+$BP$3*BP27+$BS$3*BS27+$BV$3*BV27+$BY$3*BY27+$CB$3*CB27+$CE$3*CE27+$CH$3*CH27+$CK$3*CK27+$CN$3*CN27+$CQ$3*CQ27+$CT$3*CT27+$CW$3*CW27+$CZ$3*CZ27+$DC$3*DC27+$DF$3*DF27+$DI$3*DI27+$DL$3*DL27+$DO$3*DO27) -> 852.46 | DT27: =DS27/$DS$130 -> 0.0017236478
B28: E05 | C28: Veículo de Locação - Fiat Ducato Minibus Luxo 2025 - 16 lugares | D28: Vb/mês | E28: 15852.96 | F28: 1 | G28: =QQP!$L$15 -> 0.028195865 | H28: =G28*F28*$E28 -> 446.98792 | I28: 1 | J28: =QQP!$L$15 -> 0.028195865 | K28: =J28*I28*$E28 -> 446.98792 | L28: 1 | M28: =QQP!$L$15 -> 0.028195865 | N28: =M28*L28*$E28 -> 446.98792 | O28: 1 | P28: =QQP!$L$15 -> 0.028195865 | Q28: =P28*O28*$E28 -> 446.98792 | R28: 1 | S28: =QQP!$L$15 -> 0.028195865 | T28: =S28*R28*$E28 -> 446.98792 | U28: 1 | V28: =QQP!$L$15 -> 0.028195865 | W28: =V28*U28*$E28 -> 446.98792 | X28: 1 | Y28: =QQP!$L$15 -> 0.028195865 | Z28: =Y28*X28*$E28 -> 446.98792 | AA28: 1 | AB28: =QQP!$L$15 -> 0.028195865 | AC28: =AB28*AA28*$E28 -> 446.98792 | AD28: 1 | AE28: =QQP!$L$15 -> 0.028195865 | AF28: =AE28*AD28*$E28 -> 446.98792 | AG28: 1 | AH28: =QQP!$L$15 -> 0.028195865 | AI28: =AH28*AG28*$E28 -> 446.98792 | AJ28: 1 | AK28: =QQP!$L$15 -> 0.028195865 | AL28: =AK28*AJ28*$E28 -> 446.98792 | AM28: 1 | AN28: =QQP!$L$15 -> 0.028195865 | AO28: =AN28*AM28*$E28 -> 446.98792 | AP28: 1 | AQ28: =QQP!$L$15/AR3 -> 0.00028195865 | AR28: =AQ28*AP28*$E28 -> 4.4698792 | AS28: 1 | AT28: =QQP!$L$15 -> 0.028195865 | AU28: =AT28*AS28*$E28 -> 446.98792 | AV28: 1 | AW28: =QQP!$L$15/AX3 -> 0.0035244831 | AX28: =AW28*AV28*$E28 -> 55.87349 | AY28: 1 | AZ28: =QQP!$L$15/BA3 -> 0.0046993109 | BA28: =AZ28*AY28*$E28 -> 74.497987 | BB28: 1 | BC28: =QQP!$L$15/BD3 -> 0.0046993109 | BD28: =BC28*BB28*$E28 -> 74.497987 | BE28: 1 | BF28: =QQP!$L$15 -> 0.028195865 | BG28: =BF28*BE28*$E28 -> 446.98792 | BH28: 1 | BI28: =QQP!$L$15/BJ3 -> 0.00028195865 | BJ28: =BI28*BH28*$E28 -> 4.4698792 | BK28: 1 | BL28: =QQP!$L$15 -> 0.028195865 | BM28: =BL28*BK28*$E28 -> 446.98792 | BN28: 1 | BO28: =QQP!$L$15 -> 0.028195865 | BP28: =BO28*BN28*$E28 -> 446.98792 | BQ28: 1 | BR28: =QQP!$L$15 -> 0.028195865 | BS28: =BR28*BQ28*$E28 -> 446.98792 | BT28: 1 | BU28: =QQP!$L$15 -> 0.028195865 | BV28: =BU28*BT28*$E28 -> 446.98792 | BW28: 1 | BX28: =QQP!$L$15 -> 0.028195865 | BY28: =BX28*BW28*$E28 -> 446.98792 | BZ28: 1 | CA28: =QQP!$L$15 -> 0.028195865 | CB28: =CA28*BZ28*$E28 -> 446.98792 | CC28: 1 | CD28: =QQP!$L$15/CE3 -> 0.00028195865 | CE28: =CD28*CC28*$E28 -> 4.4698792 | CF28: 1 | CG28: =QQP!$L$15 -> 0.028195865 | CH28: =CG28*CF28*$E28 -> 446.98792 | CI28: 1 | CJ28: =QQP!$L$15 -> 0.028195865 | CK28: =CJ28*CI28*$E28 -> 446.98792 | CL28: 1 | CM28: =QQP!$L$15 -> 0.028195865 | CN28: =CM28*CL28*$E28 -> 446.98792 | CO28: 1 | CP28: =QQP!$L$15 -> 0.028195865 | CQ28: =CP28*CO28*$E28 -> 446.98792 | CR28: 1 | CS28: =QQP!$L$15 -> 0.028195865 | CT28: =CS28*CR28*$E28 -> 446.98792 | CU28: 1 | CV28: =QQP!$L$15 -> 0.028195865 | CW28: =CV28*CU28*$E28 -> 446.98792 | CX28: 1 | CY28: =QQP!$L$15 -> 0.028195865 | CZ28: =CY28*CX28*$E28 -> 446.98792 | DA28: 1 | DB28: =QQP!$L$15 -> 0.028195865 | DC28: =DB28*DA28*$E28 -> 446.98792 | DD28: 1 | DE28: =QQP!$L$15 -> 0.028195865 | DF28: =DE28*DD28*$E28 -> 446.98792 | DG28: 1 | DH28: =QQP!$L$15 -> 0.028195865 | DI28: =DH28*DG28*$E28 -> 446.98792 | DJ28: 1 | DK28: =QQP!$L$15 -> 0.028195865 | DL28: =DK28*DJ28*$E28 -> 446.98792 | DM28: 1 | DN28: =QQP!$L$15 -> 0.028195865 | DO28: =DN28*DM28*$E28 -> 446.98792 | DS28: =($H$3*H28+$K$3*K28+$N$3*N28+$Q$3*Q28+$T$3*T28+$W$3*W28+$Z$3*Z28+$AC$3*AC28+$AF$3*AF28+$AI$3*AI28+$AL$3*AL28+$AO$3*AO28+$AR$3*AR28+$AU$3*AU28+$AX$3*AX28+$BA$3*BA28+$BD$3*BD28+$BG$3*BG28+$BJ$3*BJ28+$BM$3*BM28+$BP$3*BP28+$BS$3*BS28+$BV$3*BV28+$BY$3*BY28+$CB$3*CB28+$CE$3*CE28+$CH$3*CH28+$CK$3*CK28+$CN$3*CN28+$CQ$3*CQ28+$CT$3*CT28+$CW$3*CW28+$CZ$3*CZ28+$DC$3*DC28+$DF$3*DF28+$DI$3*DI28+$DL$3*DL28+$DO$3*DO28) -> 16985.541 | DT28: =DS28/$DS$130 -> 0.03434424
B29: E06 | C29: Nível DSZ automático com bolha | D29: Vb/Mês | E29: 275 | H29: =G29*F29*$E29 -> 0 | K29: =J29*I29*$E29 -> 0 | N29: =M29*L29*$E29 -> 0 | Q29: =P29*O29*$E29 -> 0 | T29: =S29*R29*$E29 -> 0 | W29: =V29*U29*$E29 -> 0 | X29: 1 | Y29: =$Y$4/22 -> 0.45454545 | Z29: =Y29*X29*$E29 -> 125 | AC29: =AB29*AA29*$E29 -> 0 | AF29: =AE29*AD29*$E29 -> 0 | AI29: =AH29*AG29*$E29 -> 0 | AL29: =AK29*AJ29*$E29 -> 0 | AO29: =AN29*AM29*$E29 -> 0 | AR29: =AQ29*AP29*$E29 -> 0 | AU29: =AT29*AS29*$E29 -> 0 | AX29: =AW29*AV29*$E29 -> 0 | BA29: =AZ29*AY29*$E29 -> 0 | BD29: =BC29*BB29*$E29 -> 0 | BG29: =BF29*BE29*$E29 -> 0 | BJ29: =BI29*BH29*$E29 -> 0 | BM29: =BL29*BK29*$E29 -> 0 | BP29: =BO29*BN29*$E29 -> 0 | BS29: =BR29*BQ29*$E29 -> 0 | BV29: =BU29*BT29*$E29 -> 0 | BY29: =BX29*BW29*$E29 -> 0 | CB29: =CA29*BZ29*$E29 -> 0 | CE29: =CD29*CC29*$E29 -> 0 | CH29: =CG29*CF29*$E29 -> 0 | CK29: =CJ29*CI29*$E29 -> 0 | CN29: =CM29*CL29*$E29 -> 0 | CQ29: =CP29*CO29*$E29 -> 0 | CT29: =CS29*CR29*$E29 -> 0 | CW29: =CV29*CU29*$E29 -> 0 | CZ29: =CY29*CX29*$E29 -> 0 | DC29: =DB29*DA29*$E29 -> 0 | DF29: =DE29*DD29*$E29 -> 0 | DI29: =DH29*DG29*$E29 -> 0 | DL29: =DK29*DJ29*$E29 -> 0 | DO29: =DN29*DM29*$E29 -> 0 | DS29: =($H$3*H29+$K$3*K29+$N$3*N29+$Q$3*Q29+$T$3*T29+$W$3*W29+$Z$3*Z29+$AC$3*AC29+$AF$3*AF29+$AI$3*AI29+$AL$3*AL29+$AO$3*AO29+$AR$3*AR29+$AU$3*AU29+$AX$3*AX29+$BA$3*BA29+$BD$3*BD29+$BG$3*BG29+$BJ$3*BJ29+$BM$3*BM29+$BP$3*BP29+$BS$3*BS29+$BV$3*BV29+$BY$3*BY29+$CB$3*CB29+$CE$3*CE29+$CH$3*CH29+$CK$3*CK29+$CN$3*CN29+$CQ$3*CQ29+$CT$3*CT29+$CW$3*CW29+$CZ$3*CZ29+$DC$3*DC29+$DF$3*DF29+$DI$3*DI29+$DL$3*DL29+$DO$3*DO29) -> 125 | DT29: =DS29/$DS$130 -> 0.00025274614
B30: E07 | C30: Estação total Kit GD2i-8 | D30: Vb/Mês | E30: 1250 | H30: =G30*F30*$E30 -> 0 | K30: =J30*I30*$E30 -> 0 | N30: =M30*L30*$E30 -> 0 | Q30: =P30*O30*$E30 -> 0 | T30: =S30*R30*$E30 -> 0 | W30: =V30*U30*$E30 -> 0 | X30: 1 | Y30: =$Y$4/22 -> 0.45454545 | Z30: =Y30*X30*$E30 -> 568.18182 | AC30: =AB30*AA30*$E30 -> 0 | AF30: =AE30*AD30*$E30 -> 0 | AI30: =AH30*AG30*$E30 -> 0 | AL30: =AK30*AJ30*$E30 -> 0 | AO30: =AN30*AM30*$E30 -> 0 | AR30: =AQ30*AP30*$E30 -> 0 | AU30: =AT30*AS30*$E30 -> 0 | AX30: =AW30*AV30*$E30 -> 0 | BA30: =AZ30*AY30*$E30 -> 0 | BD30: =BC30*BB30*$E30 -> 0 | BG30: =BF30*BE30*$E30 -> 0 | BJ30: =BI30*BH30*$E30 -> 0 | BM30: =BL30*BK30*$E30 -> 0 | BP30: =BO30*BN30*$E30 -> 0 | BS30: =BR30*BQ30*$E30 -> 0 | BV30: =BU30*BT30*$E30 -> 0 | BY30: =BX30*BW30*$E30 -> 0 | CB30: =CA30*BZ30*$E30 -> 0 | CE30: =CD30*CC30*$E30 -> 0 | CH30: =CG30*CF30*$E30 -> 0 | CK30: =CJ30*CI30*$E30 -> 0 | CN30: =CM30*CL30*$E30 -> 0 | CQ30: =CP30*CO30*$E30 -> 0 | CT30: =CS30*CR30*$E30 -> 0 | CW30: =CV30*CU30*$E30 -> 0 | CZ30: =CY30*CX30*$E30 -> 0 | DC30: =DB30*DA30*$E30 -> 0 | DF30: =DE30*DD30*$E30 -> 0 | DI30: =DH30*DG30*$E30 -> 0 | DL30: =DK30*DJ30*$E30 -> 0 | DO30: =DN30*DM30*$E30 -> 0 | DS30: =($H$3*H30+$K$3*K30+$N$3*N30+$Q$3*Q30+$T$3*T30+$W$3*W30+$Z$3*Z30+$AC$3*AC30+$AF$3*AF30+$AI$3*AI30+$AL$3*AL30+$AO$3*AO30+$AR$3*AR30+$AU$3*AU30+$AX$3*AX30+$BA$3*BA30+$BD$3*BD30+$BG$3*BG30+$BJ$3*BJ30+$BM$3*BM30+$BP$3*BP30+$BS$3*BS30+$BV$3*BV30+$BY$3*BY30+$CB$3*CB30+$CE$3*CE30+$CH$3*CH30+$CK$3*CK30+$CN$3*CN30+$CQ$3*CQ30+$CT$3*CT30+$CW$3*CW30+$CZ$3*CZ30+$DC$3*DC30+$DF$3*DF30+$DI$3*DI30+$DL$3*DL30+$DO$3*DO30) -> 568.18182 | DT30: =DS30/$DS$130 -> 0.0011488461
B31: E08 | C31: Receptor GNSS RTKCHC i50 | D31: Vb/Mês | E31: 1750 | H31: =G31*F31*$E31 -> 0 | K31: =J31*I31*$E31 -> 0 | N31: =M31*L31*$E31 -> 0 | Q31: =P31*O31*$E31 -> 0 | T31: =S31*R31*$E31 -> 0 | W31: =V31*U31*$E31 -> 0 | X31: 1 | Y31: =$Y$4/22 -> 0.45454545 | Z31: =Y31*X31*$E31 -> 795.45455 | AC31: =AB31*AA31*$E31 -> 0 | AF31: =AE31*AD31*$E31 -> 0 | AI31: =AH31*AG31*$E31 -> 0 | AL31: =AK31*AJ31*$E31 -> 0 | AO31: =AN31*AM31*$E31 -> 0 | AR31: =AQ31*AP31*$E31 -> 0 | AU31: =AT31*AS31*$E31 -> 0 | AX31: =AW31*AV31*$E31 -> 0 | BA31: =AZ31*AY31*$E31 -> 0 | BD31: =BC31*BB31*$E31 -> 0 | BG31: =BF31*BE31*$E31 -> 0 | BJ31: =BI31*BH31*$E31 -> 0 | BM31: =BL31*BK31*$E31 -> 0 | BP31: =BO31*BN31*$E31 -> 0 | BS31: =BR31*BQ31*$E31 -> 0 | BV31: =BU31*BT31*$E31 -> 0 | BY31: =BX31*BW31*$E31 -> 0 | CB31: =CA31*BZ31*$E31 -> 0 | CE31: =CD31*CC31*$E31 -> 0 | CH31: =CG31*CF31*$E31 -> 0 | CK31: =CJ31*CI31*$E31 -> 0 | CN31: =CM31*CL31*$E31 -> 0 | CQ31: =CP31*CO31*$E31 -> 0 | CT31: =CS31*CR31*$E31 -> 0 | CW31: =CV31*CU31*$E31 -> 0 | CZ31: =CY31*CX31*$E31 -> 0 | DC31: =DB31*DA31*$E31 -> 0 | DF31: =DE31*DD31*$E31 -> 0 | DI31: =DH31*DG31*$E31 -> 0 | DL31: =DK31*DJ31*$E31 -> 0 | DO31: =DN31*DM31*$E31 -> 0 | DS31: =($H$3*H31+$K$3*K31+$N$3*N31+$Q$3*Q31+$T$3*T31+$W$3*W31+$Z$3*Z31+$AC$3*AC31+$AF$3*AF31+$AI$3*AI31+$AL$3*AL31+$AO$3*AO31+$AR$3*AR31+$AU$3*AU31+$AX$3*AX31+$BA$3*BA31+$BD$3*BD31+$BG$3*BG31+$BJ$3*BJ31+$BM$3*BM31+$BP$3*BP31+$BS$3*BS31+$BV$3*BV31+$BY$3*BY31+$CB$3*CB31+$CE$3*CE31+$CH$3*CH31+$CK$3*CK31+$CN$3*CN31+$CQ$3*CQ31+$CT$3*CT31+$CW$3*CW31+$CZ$3*CZ31+$DC$3*DC31+$DF$3*DF31+$DI$3*DI31+$DL$3*DL31+$DO$3*DO31) -> 795.45455 | DT31: =DS31/$DS$130 -> 0.0016083846
B32: E09 | C32: Guindaste c/operador 30 ton | D32: Diária | E32: 7852.5 | H32: =G32*F32*$E32 -> 0 | K32: =J32*I32*$E32 -> 0 | N32: =M32*L32*$E32 -> 0 | Q32: =P32*O32*$E32 -> 0 | T32: =S32*R32*$E32 -> 0 | W32: =V32*U32*$E32 -> 0 | Z32: =Y32*X32*$E32 -> 0 | AC32: =AB32*AA32*$E32 -> 0 | AF32: =AE32*AD32*$E32 -> 0 | AI32: =AH32*AG32*$E32 -> 0 | AL32: =AK32*AJ32*$E32 -> 0 | AO32: =AN32*AM32*$E32 -> 0 | AR32: =AQ32*AP32*$E32 -> 0 | AU32: =AT32*AS32*$E32 -> 0 | AX32: =AW32*AV32*$E32 -> 0 | BA32: =AZ32*AY32*$E32 -> 0 | BD32: =BC32*BB32*$E32 -> 0 | BG32: =BF32*BE32*$E32 -> 0 | BJ32: =BI32*BH32*$E32 -> 0 | BM32: =BL32*BK32*$E32 -> 0 | BN32: 1 | BO32: =BO4 -> 2 | BP32: =BO32*BN32*$E32 -> 15705 | BQ32: 1 | BR32: =BR4 -> 6 | BS32: =BR32*BQ32*$E32 -> 47115 | BV32: =BU32*BT32*$E32 -> 0 | BY32: =BX32*BW32*$E32 -> 0 | CB32: =CA32*BZ32*$E32 -> 0 | CE32: =CD32*CC32*$E32 -> 0 | CH32: =CG32*CF32*$E32 -> 0 | CK32: =CJ32*CI32*$E32 -> 0 | CL32: =CM4 -> 7 | CM32: 1 | CN32: =CM32*CL32*$E32 -> 54967.5 | CQ32: =CP32*CO32*$E32 -> 0 | CT32: =CS32*CR32*$E32 -> 0 | CW32: =CV32*CU32*$E32 -> 0 | CZ32: =CY32*CX32*$E32 -> 0 | DC32: =DB32*DA32*$E32 -> 0 | DF32: =DE32*DD32*$E32 -> 0 | DI32: =DH32*DG32*$E32 -> 0 | DL32: =DK32*DJ32*$E32 -> 0 | DO32: =DN32*DM32*$E32 -> 0 | DS32: =($H$3*H32+$K$3*K32+$N$3*N32+$Q$3*Q32+$T$3*T32+$W$3*W32+$Z$3*Z32+$AC$3*AC32+$AF$3*AF32+$AI$3*AI32+$AL$3*AL32+$AO$3*AO32+$AR$3*AR32+$AU$3*AU32+$AX$3*AX32+$BA$3*BA32+$BD$3*BD32+$BG$3*BG32+$BJ$3*BJ32+$BM$3*BM32+$BP$3*BP32+$BS$3*BS32+$BV$3*BV32+$BY$3*BY32+$CB$3*CB32+$CE$3*CE32+$CH$3*CH32+$CK$3*CK32+$CN$3*CN32+$CQ$3*CQ32+$CT$3*CT32+$CW$3*CW32+$CZ$3*CZ32+$DC$3*DC32+$DF$3*DF32+$DI$3*DI32+$DL$3*DL32+$DO$3*DO32) -> 117787.5 | DT32: =DS32/$DS$130 -> 0.23816269
B33: E10 | C33: Plano de rigging | D33: Vb | E33: 15000 | H33: =G33*F33*$E33 -> 0 | K33: =J33*I33*$E33 -> 0 | N33: =M33*L33*$E33 -> 0 | Q33: =P33*O33*$E33 -> 0 | T33: =S33*R33*$E33 -> 0 | W33: =V33*U33*$E33 -> 0 | Z33: =Y33*X33*$E33 -> 0 | AC33: =AB33*AA33*$E33 -> 0 | AF33: =AE33*AD33*$E33 -> 0 | AI33: =AH33*AG33*$E33 -> 0 | AL33: =AK33*AJ33*$E33 -> 0 | AO33: =AN33*AM33*$E33 -> 0 | AR33: =AQ33*AP33*$E33 -> 0 | AU33: =AT33*AS33*$E33 -> 0 | AX33: =AW33*AV33*$E33 -> 0 | BA33: =AZ33*AY33*$E33 -> 0 | BD33: =BC33*BB33*$E33 -> 0 | BG33: =BF33*BE33*$E33 -> 0 | BJ33: =BI33*BH33*$E33 -> 0 | BM33: =BL33*BK33*$E33 -> 0 | BN33: 1 | BO33: 1 | BP33: =BO33*BN33*$E33 -> 15000 | BQ33: 1 | BR33: 1 | BS33: =BR33*BQ33*$E33 -> 15000 | BV33: =BU33*BT33*$E33 -> 0 | BY33: =BX33*BW33*$E33 -> 0 | CB33: =CA33*BZ33*$E33 -> 0 | CE33: =CD33*CC33*$E33 -> 0 | CH33: =CG33*CF33*$E33 -> 0 | CK33: =CJ33*CI33*$E33 -> 0 | CL33: 1 | CM33: 1 | CN33: =CM33*CL33*$E33 -> 15000 | CQ33: =CP33*CO33*$E33 -> 0 | CT33: =CS33*CR33*$E33 -> 0 | CW33: =CV33*CU33*$E33 -> 0 | CZ33: =CY33*CX33*$E33 -> 0 | DC33: =DB33*DA33*$E33 -> 0 | DF33: =DE33*DD33*$E33 -> 0 | DI33: =DH33*DG33*$E33 -> 0 | DL33: =DK33*DJ33*$E33 -> 0 | DO33: =DN33*DM33*$E33 -> 0 | DS33: =($H$3*H33+$K$3*K33+$N$3*N33+$Q$3*Q33+$T$3*T33+$W$3*W33+$Z$3*Z33+$AC$3*AC33+$AF$3*AF33+$AI$3*AI33+$AL$3*AL33+$AO$3*AO33+$AR$3*AR33+$AU$3*AU33+$AX$3*AX33+$BA$3*BA33+$BD$3*BD33+$BG$3*BG33+$BJ$3*BJ33+$BM$3*BM33+$BP$3*BP33+$BS$3*BS33+$BV$3*BV33+$BY$3*BY33+$CB$3*CB33+$CE$3*CE33+$CH$3*CH33+$CK$3*CK33+$CN$3*CN33+$CQ$3*CQ33+$CT$3*CT33+$CW$3*CW33+$CZ$3*CZ33+$DC$3*DC33+$DF$3*DF33+$DI$3*DI33+$DL$3*DL33+$DO$3*DO33) -> 45000 | DT33: =DS33/$DS$130 -> 0.090988612
B34: E11 | C34: Linha de vida | D34: Vb | E34: 2520 | H34: =G34*F34*$E34 -> 0 | K34: =J34*I34*$E34 -> 0 | N34: =M34*L34*$E34 -> 0 | Q34: =P34*O34*$E34 -> 0 | T34: =S34*R34*$E34 -> 0 | W34: =V34*U34*$E34 -> 0 | Z34: =Y34*X34*$E34 -> 0 | AC34: =AB34*AA34*$E34 -> 0 | AF34: =AE34*AD34*$E34 -> 0 | AI34: =AH34*AG34*$E34 -> 0 | AL34: =AK34*AJ34*$E34 -> 0 | AO34: =AN34*AM34*$E34 -> 0 | AR34: =AQ34*AP34*$E34 -> 0 | AU34: =AT34*AS34*$E34 -> 0 | AX34: =AW34*AV34*$E34 -> 0 | BA34: =AZ34*AY34*$E34 -> 0 | BD34: =BC34*BB34*$E34 -> 0 | BG34: =BF34*BE34*$E34 -> 0 | BJ34: =BI34*BH34*$E34 -> 0 | BM34: =BL34*BK34*$E34 -> 0 | BN34: 1 | BO34: 1 | BP34: =BO34*BN34*$E34 -> 2520 | BQ34: 1 | BR34: 1 | BS34: =BR34*BQ34*$E34 -> 2520 | BV34: =BU34*BT34*$E34 -> 0 | BY34: =BX34*BW34*$E34 -> 0 | CB34: =CA34*BZ34*$E34 -> 0 | CE34: =CD34*CC34*$E34 -> 0 | CH34: =CG34*CF34*$E34 -> 0 | CK34: =CJ34*CI34*$E34 -> 0 | CL34: 1 | CM34: 1 | CN34: =CM34*CL34*$E34 -> 2520 | CQ34: =CP34*CO34*$E34 -> 0 | CT34: =CS34*CR34*$E34 -> 0 | CW34: =CV34*CU34*$E34 -> 0 | CZ34: =CY34*CX34*$E34 -> 0 | DC34: =DB34*DA34*$E34 -> 0 | DF34: =DE34*DD34*$E34 -> 0 | DI34: =DH34*DG34*$E34 -> 0 | DL34: =DK34*DJ34*$E34 -> 0 | DO34: =DN34*DM34*$E34 -> 0 | DS34: =($H$3*H34+$K$3*K34+$N$3*N34+$Q$3*Q34+$T$3*T34+$W$3*W34+$Z$3*Z34+$AC$3*AC34+$AF$3*AF34+$AI$3*AI34+$AL$3*AL34+$AO$3*AO34+$AR$3*AR34+$AU$3*AU34+$AX$3*AX34+$BA$3*BA34+$BD$3*BD34+$BG$3*BG34+$BJ$3*BJ34+$BM$3*BM34+$BP$3*BP34+$BS$3*BS34+$BV$3*BV34+$BY$3*BY34+$CB$3*CB34+$CE$3*CE34+$CH$3*CH34+$CK$3*CK34+$CN$3*CN34+$CQ$3*CQ34+$CT$3*CT34+$CW$3*CW34+$CZ$3*CZ34+$DC$3*DC34+$DF$3*DF34+$DI$3*DI34+$DL$3*DL34+$DO$3*DO34) -> 7560 | DT34: =DS34/$DS$130 -> 0.015286087
B35: E12 | H35: =G35*F35*$E35 -> 0 | K35: =J35*I35*$E35 -> 0 | N35: =M35*L35*$E35 -> 0 | Q35: =P35*O35*$E35 -> 0 | T35: =S35*R35*$E35 -> 0 | W35: =V35*U35*$E35 -> 0 | Z35: =Y35*X35*$E35 -> 0 | AC35: =AB35*AA35*$E35 -> 0 | AF35: =AE35*AD35*$E35 -> 0 | AI35: =AH35*AG35*$E35 -> 0 | AL35: =AK35*AJ35*$E35 -> 0 | AO35: =AN35*AM35*$E35 -> 0 | AR35: =AQ35*AP35*$E35 -> 0 | AU35: =AT35*AS35*$E35 -> 0 | AX35: =AW35*AV35*$E35 -> 0 | BA35: =AZ35*AY35*$E35 -> 0 | BD35: =BC35*BB35*$E35 -> 0 | BG35: =BF35*BE35*$E35 -> 0 | BJ35: =BI35*BH35*$E35 -> 0 | BM35: =BL35*BK35*$E35 -> 0 | BP35: =BO35*BN35*$E35 -> 0 | BS35: =BR35*BQ35*$E35 -> 0 | BV35: =BU35*BT35*$E35 -> 0 | BY35: =BX35*BW35*$E35 -> 0 | CB35: =CA35*BZ35*$E35 -> 0 | CE35: =CD35*CC35*$E35 -> 0 | CH35: =CG35*CF35*$E35 -> 0 | CK35: =CJ35*CI35*$E35 -> 0 | CN35: =CM35*CL35*$E35 -> 0 | CQ35: =CP35*CO35*$E35 -> 0 | CT35: =CS35*CR35*$E35 -> 0 | CW35: =CV35*CU35*$E35 -> 0 | CZ35: =CY35*CX35*$E35 -> 0 | DC35: =DB35*DA35*$E35 -> 0 | DF35: =DE35*DD35*$E35 -> 0 | DI35: =DH35*DG35*$E35 -> 0 | DL35: =DK35*DJ35*$E35 -> 0 | DO35: =DN35*DM35*$E35 -> 0 | DS35: =($H$3*H35+$K$3*K35+$N$3*N35+$Q$3*Q35+$T$3*T35+$W$3*W35+$Z$3*Z35+$AC$3*AC35+$AF$3*AF35+$AI$3*AI35+$AL$3*AL35+$AO$3*AO35+$AR$3*AR35+$AU$3*AU35+$AX$3*AX35+$BA$3*BA35+$BD$3*BD35+$BG$3*BG35+$BJ$3*BJ35+$BM$3*BM35+$BP$3*BP35+$BS$3*BS35+$BV$3*BV35+$BY$3*BY35+$CB$3*CB35+$CE$3*CE35+$CH$3*CH35+$CK$3*CK35+$CN$3*CN35+$CQ$3*CQ35+$CT$3*CT35+$CW$3*CW35+$CZ$3*CZ35+$DC$3*DC35+$DF$3*DF35+$DI$3*DI35+$DL$3*DL35+$DO$3*DO35) -> 0 | DT35: =DS35/$DS$130 -> 0
B36: E13 | H36: =G36*F36*$E36 -> 0 | K36: =J36*I36*$E36 -> 0 | N36: =M36*L36*$E36 -> 0 | Q36: =P36*O36*$E36 -> 0 | T36: =S36*R36*$E36 -> 0 | W36: =V36*U36*$E36 -> 0 | Z36: =Y36*X36*$E36 -> 0 | AC36: =AB36*AA36*$E36 -> 0 | AF36: =AE36*AD36*$E36 -> 0 | AI36: =AH36*AG36*$E36 -> 0 | AL36: =AK36*AJ36*$E36 -> 0 | AO36: =AN36*AM36*$E36 -> 0 | AR36: =AQ36*AP36*$E36 -> 0 | AU36: =AT36*AS36*$E36 -> 0 | AX36: =AW36*AV36*$E36 -> 0 | BA36: =AZ36*AY36*$E36 -> 0 | BD36: =BC36*BB36*$E36 -> 0 | BG36: =BF36*BE36*$E36 -> 0 | BJ36: =BI36*BH36*$E36 -> 0 | BM36: =BL36*BK36*$E36 -> 0 | BP36: =BO36*BN36*$E36 -> 0 | BS36: =BR36*BQ36*$E36 -> 0 | BV36: =BU36*BT36*$E36 -> 0 | BY36: =BX36*BW36*$E36 -> 0 | CB36: =CA36*BZ36*$E36 -> 0 | CE36: =CD36*CC36*$E36 -> 0 | CH36: =CG36*CF36*$E36 -> 0 | CK36: =CJ36*CI36*$E36 -> 0 | CN36: =CM36*CL36*$E36 -> 0 | CQ36: =CP36*CO36*$E36 -> 0 | CT36: =CS36*CR36*$E36 -> 0 | CW36: =CV36*CU36*$E36 -> 0 | CZ36: =CY36*CX36*$E36 -> 0 | DC36: =DB36*DA36*$E36 -> 0 | DF36: =DE36*DD36*$E36 -> 0 | DI36: =DH36*DG36*$E36 -> 0 | DL36: =DK36*DJ36*$E36 -> 0 | DO36: =DN36*DM36*$E36 -> 0 | DS36: =($H$3*H36+$K$3*K36+$N$3*N36+$Q$3*Q36+$T$3*T36+$W$3*W36+$Z$3*Z36+$AC$3*AC36+$AF$3*AF36+$AI$3*AI36+$AL$3*AL36+$AO$3*AO36+$AR$3*AR36+$AU$3*AU36+$AX$3*AX36+$BA$3*BA36+$BD$3*BD36+$BG$3*BG36+$BJ$3*BJ36+$BM$3*BM36+$BP$3*BP36+$BS$3*BS36+$BV$3*BV36+$BY$3*BY36+$CB$3*CB36+$CE$3*CE36+$CH$3*CH36+$CK$3*CK36+$CN$3*CN36+$CQ$3*CQ36+$CT$3*CT36+$CW$3*CW36+$CZ$3*CZ36+$DC$3*DC36+$DF$3*DF36+$DI$3*DI36+$DL$3*DL36+$DO$3*DO36) -> 0 | DT36: =DS36/$DS$130 -> 0
B37: E14 | H37: =G37*F37*$E37 -> 0 | K37: =J37*I37*$E37 -> 0 | N37: =M37*L37*$E37 -> 0 | Q37: =P37*O37*$E37 -> 0 | T37: =S37*R37*$E37 -> 0 | W37: =V37*U37*$E37 -> 0 | Z37: =Y37*X37*$E37 -> 0 | AC37: =AB37*AA37*$E37 -> 0 | AF37: =AE37*AD37*$E37 -> 0 | AI37: =AH37*AG37*$E37 -> 0 | AL37: =AK37*AJ37*$E37 -> 0 | AO37: =AN37*AM37*$E37 -> 0 | AR37: =AQ37*AP37*$E37 -> 0 | AU37: =AT37*AS37*$E37 -> 0 | AX37: =AW37*AV37*$E37 -> 0 | BA37: =AZ37*AY37*$E37 -> 0 | BD37: =BC37*BB37*$E37 -> 0 | BG37: =BF37*BE37*$E37 -> 0 | BJ37: =BI37*BH37*$E37 -> 0 | BM37: =BL37*BK37*$E37 -> 0 | BP37: =BO37*BN37*$E37 -> 0 | BS37: =BR37*BQ37*$E37 -> 0 | BV37: =BU37*BT37*$E37 -> 0 | BY37: =BX37*BW37*$E37 -> 0 | CB37: =CA37*BZ37*$E37 -> 0 | CE37: =CD37*CC37*$E37 -> 0 | CH37: =CG37*CF37*$E37 -> 0 | CK37: =CJ37*CI37*$E37 -> 0 | CN37: =CM37*CL37*$E37 -> 0 | CQ37: =CP37*CO37*$E37 -> 0 | CT37: =CS37*CR37*$E37 -> 0 | CW37: =CV37*CU37*$E37 -> 0 | CZ37: =CY37*CX37*$E37 -> 0 | DC37: =DB37*DA37*$E37 -> 0 | DF37: =DE37*DD37*$E37 -> 0 | DI37: =DH37*DG37*$E37 -> 0 | DL37: =DK37*DJ37*$E37 -> 0 | DO37: =DN37*DM37*$E37 -> 0 | DS37: =($H$3*H37+$K$3*K37+$N$3*N37+$Q$3*Q37+$T$3*T37+$W$3*W37+$Z$3*Z37+$AC$3*AC37+$AF$3*AF37+$AI$3*AI37+$AL$3*AL37+$AO$3*AO37+$AR$3*AR37+$AU$3*AU37+$AX$3*AX37+$BA$3*BA37+$BD$3*BD37+$BG$3*BG37+$BJ$3*BJ37+$BM$3*BM37+$BP$3*BP37+$BS$3*BS37+$BV$3*BV37+$BY$3*BY37+$CB$3*CB37+$CE$3*CE37+$CH$3*CH37+$CK$3*CK37+$CN$3*CN37+$CQ$3*CQ37+$CT$3*CT37+$CW$3*CW37+$CZ$3*CZ37+$DC$3*DC37+$DF$3*DF37+$DI$3*DI37+$DL$3*DL37+$DO$3*DO37) -> 0 | DT37: =DS37/$DS$130 -> 0
B38: E15 | H38: =G38*F38*$E38 -> 0 | K38: =J38*I38*$E38 -> 0 | N38: =M38*L38*$E38 -> 0 | Q38: =P38*O38*$E38 -> 0 | T38: =S38*R38*$E38 -> 0 | W38: =V38*U38*$E38 -> 0 | Z38: =Y38*X38*$E38 -> 0 | AC38: =AB38*AA38*$E38 -> 0 | AF38: =AE38*AD38*$E38 -> 0 | AI38: =AH38*AG38*$E38 -> 0 | AL38: =AK38*AJ38*$E38 -> 0 | AO38: =AN38*AM38*$E38 -> 0 | AR38: =AQ38*AP38*$E38 -> 0 | AU38: =AT38*AS38*$E38 -> 0 | AX38: =AW38*AV38*$E38 -> 0 | BA38: =AZ38*AY38*$E38 -> 0 | BD38: =BC38*BB38*$E38 -> 0 | BG38: =BF38*BE38*$E38 -> 0 | BJ38: =BI38*BH38*$E38 -> 0 | BM38: =BL38*BK38*$E38 -> 0 | BP38: =BO38*BN38*$E38 -> 0 | BS38: =BR38*BQ38*$E38 -> 0 | BV38: =BU38*BT38*$E38 -> 0 | BY38: =BX38*BW38*$E38 -> 0 | CB38: =CA38*BZ38*$E38 -> 0 | CE38: =CD38*CC38*$E38 -> 0 | CH38: =CG38*CF38*$E38 -> 0 | CK38: =CJ38*CI38*$E38 -> 0 | CN38: =CM38*CL38*$E38 -> 0 | CQ38: =CP38*CO38*$E38 -> 0 | CT38: =CS38*CR38*$E38 -> 0 | CW38: =CV38*CU38*$E38 -> 0 | CZ38: =CY38*CX38*$E38 -> 0 | DC38: =DB38*DA38*$E38 -> 0 | DF38: =DE38*DD38*$E38 -> 0 | DI38: =DH38*DG38*$E38 -> 0 | DL38: =DK38*DJ38*$E38 -> 0 | DO38: =DN38*DM38*$E38 -> 0 | DS38: =($H$3*H38+$K$3*K38+$N$3*N38+$Q$3*Q38+$T$3*T38+$W$3*W38+$Z$3*Z38+$AC$3*AC38+$AF$3*AF38+$AI$3*AI38+$AL$3*AL38+$AO$3*AO38+$AR$3*AR38+$AU$3*AU38+$AX$3*AX38+$BA$3*BA38+$BD$3*BD38+$BG$3*BG38+$BJ$3*BJ38+$BM$3*BM38+$BP$3*BP38+$BS$3*BS38+$BV$3*BV38+$BY$3*BY38+$CB$3*CB38+$CE$3*CE38+$CH$3*CH38+$CK$3*CK38+$CN$3*CN38+$CQ$3*CQ38+$CT$3*CT38+$CW$3*CW38+$CZ$3*CZ38+$DC$3*DC38+$DF$3*DF38+$DI$3*DI38+$DL$3*DL38+$DO$3*DO38) -> 0 | DT38: =DS38/$DS$130 -> 0
B39: E16 | H39: =G39*F39*$E39 -> 0 | K39: =J39*I39*$E39 -> 0 | N39: =M39*L39*$E39 -> 0 | Q39: =P39*O39*$E39 -> 0 | T39: =S39*R39*$E39 -> 0 | W39: =V39*U39*$E39 -> 0 | Z39: =Y39*X39*$E39 -> 0 | AC39: =AB39*AA39*$E39 -> 0 | AF39: =AE39*AD39*$E39 -> 0 | AI39: =AH39*AG39*$E39 -> 0 | AL39: =AK39*AJ39*$E39 -> 0 | AO39: =AN39*AM39*$E39 -> 0 | AR39: =AQ39*AP39*$E39 -> 0 | AU39: =AT39*AS39*$E39 -> 0 | AX39: =AW39*AV39*$E39 -> 0 | BA39: =AZ39*AY39*$E39 -> 0 | BD39: =BC39*BB39*$E39 -> 0 | BG39: =BF39*BE39*$E39 -> 0 | BJ39: =BI39*BH39*$E39 -> 0 | BM39: =BL39*BK39*$E39 -> 0 | BP39: =BO39*BN39*$E39 -> 0 | BS39: =BR39*BQ39*$E39 -> 0 | BV39: =BU39*BT39*$E39 -> 0 | BY39: =BX39*BW39*$E39 -> 0 | CB39: =CA39*BZ39*$E39 -> 0 | CE39: =CD39*CC39*$E39 -> 0 | CH39: =CG39*CF39*$E39 -> 0 | CK39: =CJ39*CI39*$E39 -> 0 | CN39: =CM39*CL39*$E39 -> 0 | CQ39: =CP39*CO39*$E39 -> 0 | CT39: =CS39*CR39*$E39 -> 0 | CW39: =CV39*CU39*$E39 -> 0 | CZ39: =CY39*CX39*$E39 -> 0 | DC39: =DB39*DA39*$E39 -> 0 | DF39: =DE39*DD39*$E39 -> 0 | DI39: =DH39*DG39*$E39 -> 0 | DL39: =DK39*DJ39*$E39 -> 0 | DO39: =DN39*DM39*$E39 -> 0 | DS39: =($H$3*H39+$K$3*K39+$N$3*N39+$Q$3*Q39+$T$3*T39+$W$3*W39+$Z$3*Z39+$AC$3*AC39+$AF$3*AF39+$AI$3*AI39+$AL$3*AL39+$AO$3*AO39+$AR$3*AR39+$AU$3*AU39+$AX$3*AX39+$BA$3*BA39+$BD$3*BD39+$BG$3*BG39+$BJ$3*BJ39+$BM$3*BM39+$BP$3*BP39+$BS$3*BS39+$BV$3*BV39+$BY$3*BY39+$CB$3*CB39+$CE$3*CE39+$CH$3*CH39+$CK$3*CK39+$CN$3*CN39+$CQ$3*CQ39+$CT$3*CT39+$CW$3*CW39+$CZ$3*CZ39+$DC$3*DC39+$DF$3*DF39+$DI$3*DI39+$DL$3*DL39+$DO$3*DO39) -> 0 | DT39: =DS39/$DS$130 -> 0
B40: E17 | H40: =G40*F40*$E40 -> 0 | K40: =J40*I40*$E40 -> 0 | N40: =M40*L40*$E40 -> 0 | Q40: =P40*O40*$E40 -> 0 | T40: =S40*R40*$E40 -> 0 | W40: =V40*U40*$E40 -> 0 | Z40: =Y40*X40*$E40 -> 0 | AC40: =AB40*AA40*$E40 -> 0 | AF40: =AE40*AD40*$E40 -> 0 | AI40: =AH40*AG40*$E40 -> 0 | AL40: =AK40*AJ40*$E40 -> 0 | AO40: =AN40*AM40*$E40 -> 0 | AR40: =AQ40*AP40*$E40 -> 0 | AU40: =AT40*AS40*$E40 -> 0 | AX40: =AW40*AV40*$E40 -> 0 | BA40: =AZ40*AY40*$E40 -> 0 | BD40: =BC40*BB40*$E40 -> 0 | BG40: =BF40*BE40*$E40 -> 0 | BJ40: =BI40*BH40*$E40 -> 0 | BM40: =BL40*BK40*$E40 -> 0 | BP40: =BO40*BN40*$E40 -> 0 | BS40: =BR40*BQ40*$E40 -> 0 | BV40: =BU40*BT40*$E40 -> 0 | BY40: =BX40*BW40*$E40 -> 0 | CB40: =CA40*BZ40*$E40 -> 0 | CE40: =CD40*CC40*$E40 -> 0 | CH40: =CG40*CF40*$E40 -> 0 | CK40: =CJ40*CI40*$E40 -> 0 | CN40: =CM40*CL40*$E40 -> 0 | CQ40: =CP40*CO40*$E40 -> 0 | CT40: =CS40*CR40*$E40 -> 0 | CW40: =CV40*CU40*$E40 -> 0 | CZ40: =CY40*CX40*$E40 -> 0 | DC40: =DB40*DA40*$E40 -> 0 | DF40: =DE40*DD40*$E40 -> 0 | DI40: =DH40*DG40*$E40 -> 0 | DL40: =DK40*DJ40*$E40 -> 0 | DO40: =DN40*DM40*$E40 -> 0 | DS40: =($H$3*H40+$K$3*K40+$N$3*N40+$Q$3*Q40+$T$3*T40+$W$3*W40+$Z$3*Z40+$AC$3*AC40+$AF$3*AF40+$AI$3*AI40+$AL$3*AL40+$AO$3*AO40+$AR$3*AR40+$AU$3*AU40+$AX$3*AX40+$BA$3*BA40+$BD$3*BD40+$BG$3*BG40+$BJ$3*BJ40+$BM$3*BM40+$BP$3*BP40+$BS$3*BS40+$BV$3*BV40+$BY$3*BY40+$CB$3*CB40+$CE$3*CE40+$CH$3*CH40+$CK$3*CK40+$CN$3*CN40+$CQ$3*CQ40+$CT$3*CT40+$CW$3*CW40+$CZ$3*CZ40+$DC$3*DC40+$DF$3*DF40+$DI$3*DI40+$DL$3*DL40+$DO$3*DO40) -> 0 | DT40: =DS40/$DS$130 -> 0
B41: E18 | H41: =G41*F41*$E41 -> 0 | K41: =J41*I41*$E41 -> 0 | N41: =M41*L41*$E41 -> 0 | Q41: =P41*O41*$E41 -> 0 | T41: =S41*R41*$E41 -> 0 | W41: =V41*U41*$E41 -> 0 | Z41: =Y41*X41*$E41 -> 0 | AC41: =AB41*AA41*$E41 -> 0 | AF41: =AE41*AD41*$E41 -> 0 | AI41: =AH41*AG41*$E41 -> 0 | AL41: =AK41*AJ41*$E41 -> 0 | AO41: =AN41*AM41*$E41 -> 0 | AR41: =AQ41*AP41*$E41 -> 0 | AU41: =AT41*AS41*$E41 -> 0 | AX41: =AW41*AV41*$E41 -> 0 | BA41: =AZ41*AY41*$E41 -> 0 | BD41: =BC41*BB41*$E41 -> 0 | BG41: =BF41*BE41*$E41 -> 0 | BJ41: =BI41*BH41*$E41 -> 0 | BM41: =BL41*BK41*$E41 -> 0 | BP41: =BO41*BN41*$E41 -> 0 | BS41: =BR41*BQ41*$E41 -> 0 | BV41: =BU41*BT41*$E41 -> 0 | BY41: =BX41*BW41*$E41 -> 0 | CB41: =CA41*BZ41*$E41 -> 0 | CE41: =CD41*CC41*$E41 -> 0 | CH41: =CG41*CF41*$E41 -> 0 | CK41: =CJ41*CI41*$E41 -> 0 | CN41: =CM41*CL41*$E41 -> 0 | CQ41: =CP41*CO41*$E41 -> 0 | CT41: =CS41*CR41*$E41 -> 0 | CW41: =CV41*CU41*$E41 -> 0 | CZ41: =CY41*CX41*$E41 -> 0 | DC41: =DB41*DA41*$E41 -> 0 | DF41: =DE41*DD41*$E41 -> 0 | DI41: =DH41*DG41*$E41 -> 0 | DL41: =DK41*DJ41*$E41 -> 0 | DO41: =DN41*DM41*$E41 -> 0 | DS41: =($H$3*H41+$K$3*K41+$N$3*N41+$Q$3*Q41+$T$3*T41+$W$3*W41+$Z$3*Z41+$AC$3*AC41+$AF$3*AF41+$AI$3*AI41+$AL$3*AL41+$AO$3*AO41+$AR$3*AR41+$AU$3*AU41+$AX$3*AX41+$BA$3*BA41+$BD$3*BD41+$BG$3*BG41+$BJ$3*BJ41+$BM$3*BM41+$BP$3*BP41+$BS$3*BS41+$BV$3*BV41+$BY$3*BY41+$CB$3*CB41+$CE$3*CE41+$CH$3*CH41+$CK$3*CK41+$CN$3*CN41+$CQ$3*CQ41+$CT$3*CT41+$CW$3*CW41+$CZ$3*CZ41+$DC$3*DC41+$DF$3*DF41+$DI$3*DI41+$DL$3*DL41+$DO$3*DO41) -> 0 | DT41: =DS41/$DS$130 -> 0
B42: E19 | H42: =G42*F42*$E42 -> 0 | K42: =J42*I42*$E42 -> 0 | N42: =M42*L42*$E42 -> 0 | Q42: =P42*O42*$E42 -> 0 | T42: =S42*R42*$E42 -> 0 | W42: =V42*U42*$E42 -> 0 | Z42: =Y42*X42*$E42 -> 0 | AC42: =AB42*AA42*$E42 -> 0 | AF42: =AE42*AD42*$E42 -> 0 | AI42: =AH42*AG42*$E42 -> 0 | AL42: =AK42*AJ42*$E42 -> 0 | AO42: =AN42*AM42*$E42 -> 0 | AR42: =AQ42*AP42*$E42 -> 0 | AU42: =AT42*AS42*$E42 -> 0 | AX42: =AW42*AV42*$E42 -> 0 | BA42: =AZ42*AY42*$E42 -> 0 | BD42: =BC42*BB42*$E42 -> 0 | BG42: =BF42*BE42*$E42 -> 0 | BJ42: =BI42*BH42*$E42 -> 0 | BM42: =BL42*BK42*$E42 -> 0 | BP42: =BO42*BN42*$E42 -> 0 | BS42: =BR42*BQ42*$E42 -> 0 | BV42: =BU42*BT42*$E42 -> 0 | BY42: =BX42*BW42*$E42 -> 0 | CB42: =CA42*BZ42*$E42 -> 0 | CE42: =CD42*CC42*$E42 -> 0 | CH42: =CG42*CF42*$E42 -> 0 | CK42: =CJ42*CI42*$E42 -> 0 | CN42: =CM42*CL42*$E42 -> 0 | CQ42: =CP42*CO42*$E42 -> 0 | CT42: =CS42*CR42*$E42 -> 0 | CW42: =CV42*CU42*$E42 -> 0 | CZ42: =CY42*CX42*$E42 -> 0 | DC42: =DB42*DA42*$E42 -> 0 | DF42: =DE42*DD42*$E42 -> 0 | DI42: =DH42*DG42*$E42 -> 0 | DL42: =DK42*DJ42*$E42 -> 0 | DO42: =DN42*DM42*$E42 -> 0 | DS42: =($H$3*H42+$K$3*K42+$N$3*N42+$Q$3*Q42+$T$3*T42+$W$3*W42+$Z$3*Z42+$AC$3*AC42+$AF$3*AF42+$AI$3*AI42+$AL$3*AL42+$AO$3*AO42+$AR$3*AR42+$AU$3*AU42+$AX$3*AX42+$BA$3*BA42+$BD$3*BD42+$BG$3*BG42+$BJ$3*BJ42+$BM$3*BM42+$BP$3*BP42+$BS$3*BS42+$BV$3*BV42+$BY$3*BY42+$CB$3*CB42+$CE$3*CE42+$CH$3*CH42+$CK$3*CK42+$CN$3*CN42+$CQ$3*CQ42+$CT$3*CT42+$CW$3*CW42+$CZ$3*CZ42+$DC$3*DC42+$DF$3*DF42+$DI$3*DI42+$DL$3*DL42+$DO$3*DO42) -> 0 | DT42: =DS42/$DS$130 -> 0
B43: E20 | H43: =G43*F43*$E43 -> 0 | K43: =J43*I43*$E43 -> 0 | N43: =M43*L43*$E43 -> 0 | Q43: =P43*O43*$E43 -> 0 | T43: =S43*R43*$E43 -> 0 | W43: =V43*U43*$E43 -> 0 | Z43: =Y43*X43*$E43 -> 0 | AC43: =AB43*AA43*$E43 -> 0 | AF43: =AE43*AD43*$E43 -> 0 | AI43: =AH43*AG43*$E43 -> 0 | AL43: =AK43*AJ43*$E43 -> 0 | AO43: =AN43*AM43*$E43 -> 0 | AR43: =AQ43*AP43*$E43 -> 0 | AU43: =AT43*AS43*$E43 -> 0 | AX43: =AW43*AV43*$E43 -> 0 | BA43: =AZ43*AY43*$E43 -> 0 | BD43: =BC43*BB43*$E43 -> 0 | BG43: =BF43*BE43*$E43 -> 0 | BJ43: =BI43*BH43*$E43 -> 0 | BM43: =BL43*BK43*$E43 -> 0 | BP43: =BO43*BN43*$E43 -> 0 | BS43: =BR43*BQ43*$E43 -> 0 | BV43: =BU43*BT43*$E43 -> 0 | BY43: =BX43*BW43*$E43 -> 0 | CB43: =CA43*BZ43*$E43 -> 0 | CE43: =CD43*CC43*$E43 -> 0 | CH43: =CG43*CF43*$E43 -> 0 | CK43: =CJ43*CI43*$E43 -> 0 | CN43: =CM43*CL43*$E43 -> 0 | CQ43: =CP43*CO43*$E43 -> 0 | CT43: =CS43*CR43*$E43 -> 0 | CW43: =CV43*CU43*$E43 -> 0 | CZ43: =CY43*CX43*$E43 -> 0 | DC43: =DB43*DA43*$E43 -> 0 | DF43: =DE43*DD43*$E43 -> 0 | DI43: =DH43*DG43*$E43 -> 0 | DL43: =DK43*DJ43*$E43 -> 0 | DO43: =DN43*DM43*$E43 -> 0 | DS43: =($H$3*H43+$K$3*K43+$N$3*N43+$Q$3*Q43+$T$3*T43+$W$3*W43+$Z$3*Z43+$AC$3*AC43+$AF$3*AF43+$AI$3*AI43+$AL$3*AL43+$AO$3*AO43+$AR$3*AR43+$AU$3*AU43+$AX$3*AX43+$BA$3*BA43+$BD$3*BD43+$BG$3*BG43+$BJ$3*BJ43+$BM$3*BM43+$BP$3*BP43+$BS$3*BS43+$BV$3*BV43+$BY$3*BY43+$CB$3*CB43+$CE$3*CE43+$CH$3*CH43+$CK$3*CK43+$CN$3*CN43+$CQ$3*CQ43+$CT$3*CT43+$CW$3*CW43+$CZ$3*CZ43+$DC$3*DC43+$DF$3*DF43+$DI$3*DI43+$DL$3*DL43+$DO$3*DO43) -> 0 | DT43: =DS43/$DS$130 -> 0
B44: E21 | H44: =G44*F44*$E44 -> 0 | K44: =J44*I44*$E44 -> 0 | N44: =M44*L44*$E44 -> 0 | Q44: =P44*O44*$E44 -> 0 | T44: =S44*R44*$E44 -> 0 | W44: =V44*U44*$E44 -> 0 | Z44: =Y44*X44*$E44 -> 0 | AC44: =AB44*AA44*$E44 -> 0 | AF44: =AE44*AD44*$E44 -> 0 | AI44: =AH44*AG44*$E44 -> 0 | AL44: =AK44*AJ44*$E44 -> 0 | AO44: =AN44*AM44*$E44 -> 0 | AR44: =AQ44*AP44*$E44 -> 0 | AU44: =AT44*AS44*$E44 -> 0 | AX44: =AW44*AV44*$E44 -> 0 | BA44: =AZ44*AY44*$E44 -> 0 | BD44: =BC44*BB44*$E44 -> 0 | BG44: =BF44*BE44*$E44 -> 0 | BJ44: =BI44*BH44*$E44 -> 0 | BM44: =BL44*BK44*$E44 -> 0 | BP44: =BO44*BN44*$E44 -> 0 | BS44: =BR44*BQ44*$E44 -> 0 | BV44: =BU44*BT44*$E44 -> 0 | BY44: =BX44*BW44*$E44 -> 0 | CB44: =CA44*BZ44*$E44 -> 0 | CE44: =CD44*CC44*$E44 -> 0 | CH44: =CG44*CF44*$E44 -> 0 | CK44: =CJ44*CI44*$E44 -> 0 | CN44: =CM44*CL44*$E44 -> 0 | CQ44: =CP44*CO44*$E44 -> 0 | CT44: =CS44*CR44*$E44 -> 0 | CW44: =CV44*CU44*$E44 -> 0 | CZ44: =CY44*CX44*$E44 -> 0 | DC44: =DB44*DA44*$E44 -> 0 | DF44: =DE44*DD44*$E44 -> 0 | DI44: =DH44*DG44*$E44 -> 0 | DL44: =DK44*DJ44*$E44 -> 0 | DO44: =DN44*DM44*$E44 -> 0 | DS44: =($H$3*H44+$K$3*K44+$N$3*N44+$Q$3*Q44+$T$3*T44+$W$3*W44+$Z$3*Z44+$AC$3*AC44+$AF$3*AF44+$AI$3*AI44+$AL$3*AL44+$AO$3*AO44+$AR$3*AR44+$AU$3*AU44+$AX$3*AX44+$BA$3*BA44+$BD$3*BD44+$BG$3*BG44+$BJ$3*BJ44+$BM$3*BM44+$BP$3*BP44+$BS$3*BS44+$BV$3*BV44+$BY$3*BY44+$CB$3*CB44+$CE$3*CE44+$CH$3*CH44+$CK$3*CK44+$CN$3*CN44+$CQ$3*CQ44+$CT$3*CT44+$CW$3*CW44+$CZ$3*CZ44+$DC$3*DC44+$DF$3*DF44+$DI$3*DI44+$DL$3*DL44+$DO$3*DO44) -> 0 | DT44: =DS44/$DS$130 -> 0
B45: E22 | H45: =G45*F45*$E45 -> 0 | K45: =J45*I45*$E45 -> 0 | N45: =M45*L45*$E45 -> 0 | Q45: =P45*O45*$E45 -> 0 | T45: =S45*R45*$E45 -> 0 | W45: =V45*U45*$E45 -> 0 | Z45: =Y45*X45*$E45 -> 0 | AC45: =AB45*AA45*$E45 -> 0 | AF45: =AE45*AD45*$E45 -> 0 | AI45: =AH45*AG45*$E45 -> 0 | AL45: =AK45*AJ45*$E45 -> 0 | AO45: =AN45*AM45*$E45 -> 0 | AR45: =AQ45*AP45*$E45 -> 0 | AU45: =AT45*AS45*$E45 -> 0 | AX45: =AW45*AV45*$E45 -> 0 | BA45: =AZ45*AY45*$E45 -> 0 | BD45: =BC45*BB45*$E45 -> 0 | BG45: =BF45*BE45*$E45 -> 0 | BJ45: =BI45*BH45*$E45 -> 0 | BM45: =BL45*BK45*$E45 -> 0 | BP45: =BO45*BN45*$E45 -> 0 | BS45: =BR45*BQ45*$E45 -> 0 | BV45: =BU45*BT45*$E45 -> 0 | BY45: =BX45*BW45*$E45 -> 0 | CB45: =CA45*BZ45*$E45 -> 0 | CE45: =CD45*CC45*$E45 -> 0 | CH45: =CG45*CF45*$E45 -> 0 | CK45: =CJ45*CI45*$E45 -> 0 | CN45: =CM45*CL45*$E45 -> 0 | CQ45: =CP45*CO45*$E45 -> 0 | CT45: =CS45*CR45*$E45 -> 0 | CW45: =CV45*CU45*$E45 -> 0 | CZ45: =CY45*CX45*$E45 -> 0 | DC45: =DB45*DA45*$E45 -> 0 | DF45: =DE45*DD45*$E45 -> 0 | DI45: =DH45*DG45*$E45 -> 0 | DL45: =DK45*DJ45*$E45 -> 0 | DO45: =DN45*DM45*$E45 -> 0 | DS45: =($H$3*H45+$K$3*K45+$N$3*N45+$Q$3*Q45+$T$3*T45+$W$3*W45+$Z$3*Z45+$AC$3*AC45+$AF$3*AF45+$AI$3*AI45+$AL$3*AL45+$AO$3*AO45+$AR$3*AR45+$AU$3*AU45+$AX$3*AX45+$BA$3*BA45+$BD$3*BD45+$BG$3*BG45+$BJ$3*BJ45+$BM$3*BM45+$BP$3*BP45+$BS$3*BS45+$BV$3*BV45+$BY$3*BY45+$CB$3*CB45+$CE$3*CE45+$CH$3*CH45+$CK$3*CK45+$CN$3*CN45+$CQ$3*CQ45+$CT$3*CT45+$CW$3*CW45+$CZ$3*CZ45+$DC$3*DC45+$DF$3*DF45+$DI$3*DI45+$DL$3*DL45+$DO$3*DO45) -> 0 | DT45: =DS45/$DS$130 -> 0
B46: E23 | H46: =G46*F46*$E46 -> 0 | K46: =J46*I46*$E46 -> 0 | N46: =M46*L46*$E46 -> 0 | Q46: =P46*O46*$E46 -> 0 | T46: =S46*R46*$E46 -> 0 | W46: =V46*U46*$E46 -> 0 | Z46: =Y46*X46*$E46 -> 0 | AC46: =AB46*AA46*$E46 -> 0 | AF46: =AE46*AD46*$E46 -> 0 | AI46: =AH46*AG46*$E46 -> 0 | AL46: =AK46*AJ46*$E46 -> 0 | AO46: =AN46*AM46*$E46 -> 0 | AR46: =AQ46*AP46*$E46 -> 0 | AU46: =AT46*AS46*$E46 -> 0 | AX46: =AW46*AV46*$E46 -> 0 | BA46: =AZ46*AY46*$E46 -> 0 | BD46: =BC46*BB46*$E46 -> 0 | BG46: =BF46*BE46*$E46 -> 0 | BJ46: =BI46*BH46*$E46 -> 0 | BM46: =BL46*BK46*$E46 -> 0 | BP46: =BO46*BN46*$E46 -> 0 | BS46: =BR46*BQ46*$E46 -> 0 | BV46: =BU46*BT46*$E46 -> 0 | BY46: =BX46*BW46*$E46 -> 0 | CB46: =CA46*BZ46*$E46 -> 0 | CE46: =CD46*CC46*$E46 -> 0 | CH46: =CG46*CF46*$E46 -> 0 | CK46: =CJ46*CI46*$E46 -> 0 | CN46: =CM46*CL46*$E46 -> 0 | CQ46: =CP46*CO46*$E46 -> 0 | CT46: =CS46*CR46*$E46 -> 0 | CW46: =CV46*CU46*$E46 -> 0 | CZ46: =CY46*CX46*$E46 -> 0 | DC46: =DB46*DA46*$E46 -> 0 | DF46: =DE46*DD46*$E46 -> 0 | DI46: =DH46*DG46*$E46 -> 0 | DL46: =DK46*DJ46*$E46 -> 0 | DO46: =DN46*DM46*$E46 -> 0 | DS46: =($H$3*H46+$K$3*K46+$N$3*N46+$Q$3*Q46+$T$3*T46+$W$3*W46+$Z$3*Z46+$AC$3*AC46+$AF$3*AF46+$AI$3*AI46+$AL$3*AL46+$AO$3*AO46+$AR$3*AR46+$AU$3*AU46+$AX$3*AX46+$BA$3*BA46+$BD$3*BD46+$BG$3*BG46+$BJ$3*BJ46+$BM$3*BM46+$BP$3*BP46+$BS$3*BS46+$BV$3*BV46+$BY$3*BY46+$CB$3*CB46+$CE$3*CE46+$CH$3*CH46+$CK$3*CK46+$CN$3*CN46+$CQ$3*CQ46+$CT$3*CT46+$CW$3*CW46+$CZ$3*CZ46+$DC$3*DC46+$DF$3*DF46+$DI$3*DI46+$DL$3*DL46+$DO$3*DO46) -> 0 | DT46: =DS46/$DS$130 -> 0
... B77: E54 | H77: =G77*F77*$E77 -> 0 | K77: =J77*I77*$E77 -> 0 | N77: =M77*L77*$E77 -> 0 | Q77: =P77*O77*$E77 -> 0 | T77: =S77*R77*$E77 -> 0 | W77: =V77*U77*$E77 -> 0 | Z77: =Y77*X77*$E77 -> 0 | AC77: =AB77*AA77*$E77 -> 0 | AF77: =AE77*AD77*$E77 -> 0 | AI77: =AH77*AG77*$E77 -> 0 | AL77: =AK77*AJ77*$E77 -> 0 | AO77: =AN77*AM77*$E77 -> 0 | AR77: =AQ77*AP77*$E77 -> 0 | AU77: =AT77*AS77*$E77 -> 0 | AX77: =AW77*AV77*$E77 -> 0 | BA77: =AZ77*AY77*$E77 -> 0 | BD77: =BC77*BB77*$E77 -> 0 | BG77: =BF77*BE77*$E77 -> 0 | BJ77: =BI77*BH77*$E77 -> 0 | BM77: =BL77*BK77*$E77 -> 0 | BP77: =BO77*BN77*$E77 -> 0 | BS77: =BR77*BQ77*$E77 -> 0 | BV77: =BU77*BT77*$E77 -> 0 | BY77: =BX77*BW77*$E77 -> 0 | CB77: =CA77*BZ77*$E77 -> 0 | CE77: =CD77*CC77*$E77 -> 0 | CH77: =CG77*CF77*$E77 -> 0 | CK77: =CJ77*CI77*$E77 -> 0 | CN77: =CM77*CL77*$E77 -> 0 | CQ77: =CP77*CO77*$E77 -> 0 | CT77: =CS77*CR77*$E77 -> 0 | CW77: =CV77*CU77*$E77 -> 0 | CZ77: =CY77*CX77*$E77 -> 0 | DC77: =DB77*DA77*$E77 -> 0 | DF77: =DE77*DD77*$E77 -> 0 | DI77: =DH77*DG77*$E77 -> 0 | DL77: =DK77*DJ77*$E77 -> 0 | DO77: =DN77*DM77*$E77 -> 0 | DS77: =($H$3*H77+$K$3*K77+$N$3*N77+$Q$3*Q77+$T$3*T77+$W$3*W77+$Z$3*Z77+$AC$3*AC77+$AF$3*AF77+$AI$3*AI77+$AL$3*AL77+$AO$3*AO77+$AR$3*AR77+$AU$3*AU77+$AX$3*AX77+$BA$3*BA77+$BD$3*BD77+$BG$3*BG77+$BJ$3*BJ77+$BM$3*BM77+$BP$3*BP77+$BS$3*BS77+$BV$3*BV77+$BY$3*BY77+$CB$3*CB77+$CE$3*CE77+$CH$3*CH77+$CK$3*CK77+$CN$3*CN77+$CQ$3*CQ77+$CT$3*CT77+$CW$3*CW77+$CZ$3*CZ77+$DC$3*DC77+$DF$3*DF77+$DI$3*DI77+$DL$3*DL77+$DO$3*DO77) -> 0 | DT77: =DS77/$DS$130 -> 0
B78: B - Custo Total de Equipamentos e Ferramentas: | E78: =SUM(#REF!) -> #REF! | H78: =SUM(H24:H77) -> 446.98792 | K78: =SUM(K24:K77) -> 446.98792 | N78: =SUM(N24:N77) -> 9622.1752 | Q78: =SUM(Q24:Q77) -> 446.98792 | T78: =SUM(T24:T77) -> 446.98792 | W78: =SUM(W24:W77) -> 446.98792 | Z78: =SUM(Z24:Z77) -> 1935.6243 | AC78: =SUM(AC24:AC77) -> 446.98792 | AF78: =SUM(AF24:AF77) -> 446.98792 | AI78: =SUM(AI24:AI77) -> 446.98792 | AL78: =SUM(AL24:AL77) -> 446.98792 | AO78: =SUM(AO24:AO77) -> 446.98792 | AR78: =SUM(AR24:AR77) -> 4.4698792 | AU78: =SUM(AU24:AU77) -> 446.98792 | AX78: =SUM(AX24:AX77) -> 55.87349 | BA78: =SUM(BA24:BA77) -> 74.497987 | BD78: =SUM(BD24:BD77) -> 74.497987 | BG78: =SUM(BG24:BG77) -> 446.98792 | BJ78: =SUM(BJ24:BJ77) -> 4.4698792 | BM78: =SUM(BM24:BM77) -> 446.98792 | BP78: =SUM(BP24:BP77) -> 33671.988 | BS78: =SUM(BS24:BS77) -> 65081.988 | BV78: =SUM(BV24:BV77) -> 446.98792 | BY78: =SUM(BY24:BY77) -> 446.98792 | CB78: =SUM(CB24:CB77) -> 446.98792 | CE78: =SUM(CE24:CE77) -> 4.4698792 | CH78: =SUM(CH24:CH77) -> 446.98792 | CK78: =SUM(CK24:CK77) -> 446.98792 | CN78: =SUM(CN24:CN77) -> 72934.488 | CQ78: =SUM(CQ24:CQ77) -> 446.98792 | CT78: =SUM(CT24:CT77) -> 446.98792 | CW78: =SUM(CW24:CW77) -> 446.98792 | CZ78: =SUM(CZ24:CZ77) -> 446.98792 | DC78: =SUM(DC24:DC77) -> 446.98792 | DF78: =SUM(DF24:DF77) -> 446.98792 | DI78: =SUM(DI24:DI77) -> 446.98792 | DL78: =SUM(DL24:DL77) -> 446.98792 | DO78: =SUM(DO24:DO77) -> 446.98792 | DS78: =SUM(DS24:DS77) -> 197996.86
B79: C – Materiais
B80: Cód. | C80: Discriminação | D80: Unid | E80: P.Unit | F80: Quant | G80: F.utiliz | H80: Custo | I80: Quant | J80: F.utiliz | K80: Custo | L80: Quant | M80: F.utiliz | N80: Custo | O80: Quant | P80: F.utiliz | Q80: Custo | R80: Quant | S80: F.utiliz | T80: Custo | U80: Quant | V80: F.utiliz | W80: Custo | X80: Quant | Y80: F.utiliz | Z80: Custo | AA80: Quant | AB80: F.utiliz | AC80: Custo | AD80: Quant | AE80: F.utiliz | AF80: Custo | AG80: Quant | AH80: F.utiliz | AI80: Custo | AJ80: Quant | AK80: F.utiliz | AL80: Custo | AM80: Quant | AN80: F.utiliz | AO80: Custo | AP80: Quant | AQ80: F.utiliz | AR80: Custo | AS80: Quant | AT80: F.utiliz | AU80: Custo | AV80: Quant | AW80: F.utiliz | AX80: Custo | AY80: Quant | AZ80: F.utiliz | BA80: Custo | BB80: Quant | BC80: F.utiliz | BD80: Custo | BE80: Quant | BF80: F.utiliz | BG80: Custo | BH80: Quant | BI80: F.utiliz | BJ80: Custo | BK80: Quant | BL80: F.utiliz | BM80: Custo | BN80: Quant | BO80: F.utiliz | BP80: Custo | BQ80: Quant | BR80: F.utiliz | BS80: Custo | BT80: Quant | BU80: F.utiliz | BV80: Custo | BW80: Quant | BX80: F.utiliz | BY80: Custo | BZ80: Quant | CA80: F.utiliz | CB80: Custo | CC80: Quant | CD80: F.utiliz | CE80: Custo | CF80: Quant | CG80: F.utiliz | CH80: Custo | CI80: Quant | CJ80: F.utiliz | CK80: Custo | CL80: Quant | CM80: F.utiliz | CN80: Custo | CO80: Quant | CP80: F.utiliz | CQ80: Custo | CR80: Quant | CS80: F.utiliz | CT80: Custo | CU80: Quant | CV80: F.utiliz | CW80: Custo | CX80: Quant | CY80: F.utiliz | CZ80: Custo | DA80: Quant | DB80: F.utiliz | DC80: Custo | DD80: Quant | DE80: F.utiliz | DF80: Custo | DG80: Quant | DH80: F.utiliz | DI80: Custo | DJ80: Quant | DK80: F.utiliz | DL80: Custo | DM80: Quant | DN80: F.utiliz | DO80: Custo | DQ80: Quant | DR80: F.utiliz | DS80: Custo
B81: M01 | C81: Cabo múltiplo de energia (tetrapolar), condutores flexíveis de cobre (classe 5), classe de tensão de 0.6/1kV, isolamento de PVC 70ºC - Seção 1x4/c # 10.0mm². | D81: M | E81: 45.2 | H81: =G81*F81*$E81 -> 0 | K81: =J81*I81*$E81 -> 0 | N81: =M81*L81*$E81 -> 0 | Q81: =P81*O81*$E81 -> 0 | T81: =S81*R81*$E81 -> 0 | W81: =V81*U81*$E81 -> 0 | Z81: =Y81*X81*$E81 -> 0 | AC81: =AB81*AA81*$E81 -> 0 | AF81: =AE81*AD81*$E81 -> 0 | AI81: =AH81*AG81*$E81 -> 0 | AL81: =AK81*AJ81*$E81 -> 0 | AO81: =AN81*AM81*$E81 -> 0 | AP81: 1.05 | AQ81: 1 | AR81: =AQ81*AP81*$E81 -> 47.46 | AU81: =AT81*AS81*$E81 -> 0 | AX81: =AW81*AV81*$E81 -> 0 | BA81: =AZ81*AY81*$E81 -> 0 | BD81: =BC81*BB81*$E81 -> 0 | BG81: =BF81*BE81*$E81 -> 0 | BJ81: =BI81*BH81*$E81 -> 0 | BM81: =BL81*BK81*$E81 -> 0 | BP81: =BO81*BN81*$E81 -> 0 | BS81: =BR81*BQ81*$E81 -> 0 | BV81: =BU81*BT81*$E81 -> 0 | BY81: =BX81*BW81*$E81 -> 0 | CB81: =CA81*BZ81*$E81 -> 0 | CE81: =CD81*CC81*$E81 -> 0 | CH81: =CG81*CF81*$E81 -> 0 | CK81: =CJ81*CI81*$E81 -> 0 | CN81: =CM81*CL81*$E81 -> 0 | CQ81: =CP81*CO81*$E81 -> 0 | CT81: =CS81*CR81*$E81 -> 0 | CW81: =CV81*CU81*$E81 -> 0 | CZ81: =CY81*CX81*$E81 -> 0 | DC81: =DB81*DA81*$E81 -> 0 | DF81: =DE81*DD81*$E81 -> 0 | DI81: =DH81*DG81*$E81 -> 0 | DL81: =DK81*DJ81*$E81 -> 0 | DO81: =DN81*DM81*$E81 -> 0 | DS81: =($H$3*H81+$K$3*K81+$N$3*N81+$Q$3*Q81+$T$3*T81+$W$3*W81+$Z$3*Z81+$AC$3*AC81+$AF$3*AF81+$AI$3*AI81+$AL$3*AL81+$AO$3*AO81+$AR$3*AR81+$AU$3*AU81+$AX$3*AX81+$BA$3*BA81+$BD$3*BD81+$BG$3*BG81+$BJ$3*BJ81+$BM$3*BM81+$BP$3*BP81+$BS$3*BS81+$BV$3*BV81+$BY$3*BY81+$CB$3*CB81+$CE$3*CE81+$CH$3*CH81+$CK$3*CK81+$CN$3*CN81+$CQ$3*CQ81+$CT$3*CT81+$CW$3*CW81+$CZ$3*CZ81+$DC$3*DC81+$DF$3*DF81+$DI$3*DI81+$DL$3*DL81+$DO$3*DO81) -> 4746 | DT81: =DS81/$DS$130 -> 0.0095962656
B82: M02 | C82: Chave seccionadora 30A TYPE 3R/4/12 CLAS S H 600V, NCM:8536.50.90 CF:5102 MR:ROCKWELL | D82: UND | E82: 230.22 | H82: =G82*F82*$E82 -> 0 | K82: =J82*I82*$E82 -> 0 | N82: =M82*L82*$E82 -> 0 | Q82: =P82*O82*$E82 -> 0 | T82: =S82*R82*$E82 -> 0 | W82: =V82*U82*$E82 -> 0 | Z82: =Y82*X82*$E82 -> 0 | AC82: =AB82*AA82*$E82 -> 0 | AF82: =AE82*AD82*$E82 -> 0 | AI82: =AH82*AG82*$E82 -> 0 | AL82: =AK82*AJ82*$E82 -> 0 | AO82: =AN82*AM82*$E82 -> 0 | AR82: =AQ82*AP82*$E82 -> 0 | AS82: 1 | AT82: 1 | AU82: =AT82*AS82*$E82 -> 230.22 | AX82: =AW82*AV82*$E82 -> 0 | BA82: =AZ82*AY82*$E82 -> 0 | BD82: =BC82*BB82*$E82 -> 0 | BG82: =BF82*BE82*$E82 -> 0 | BJ82: =BI82*BH82*$E82 -> 0 | BM82: =BL82*BK82*$E82 -> 0 | BP82: =BO82*BN82*$E82 -> 0 | BS82: =BR82*BQ82*$E82 -> 0 | BV82: =BU82*BT82*$E82 -> 0 | BY82: =BX82*BW82*$E82 -> 0 | CB82: =CA82*BZ82*$E82 -> 0 | CE82: =CD82*CC82*$E82 -> 0 | CH82: =CG82*CF82*$E82 -> 0 | CK82: =CJ82*CI82*$E82 -> 0 | CN82: =CM82*CL82*$E82 -> 0 | CQ82: =CP82*CO82*$E82 -> 0 | CT82: =CS82*CR82*$E82 -> 0 | CW82: =CV82*CU82*$E82 -> 0 | CZ82: =CY82*CX82*$E82 -> 0 | DC82: =DB82*DA82*$E82 -> 0 | DF82: =DE82*DD82*$E82 -> 0 | DI82: =DH82*DG82*$E82 -> 0 | DL82: =DK82*DJ82*$E82 -> 0 | DO82: =DN82*DM82*$E82 -> 0 | DS82: =($H$3*H82+$K$3*K82+$N$3*N82+$Q$3*Q82+$T$3*T82+$W$3*W82+$Z$3*Z82+$AC$3*AC82+$AF$3*AF82+$AI$3*AI82+$AL$3*AL82+$AO$3*AO82+$AR$3*AR82+$AU$3*AU82+$AX$3*AX82+$BA$3*BA82+$BD$3*BD82+$BG$3*BG82+$BJ$3*BJ82+$BM$3*BM82+$BP$3*BP82+$BS$3*BS82+$BV$3*BV82+$BY$3*BY82+$CB$3*CB82+$CE$3*CE82+$CH$3*CH82+$CK$3*CK82+$CN$3*CN82+$CQ$3*CQ82+$CT$3*CT82+$CW$3*CW82+$CZ$3*CZ82+$DC$3*DC82+$DF$3*DF82+$DI$3*DI82+$DL$3*DL82+$DO$3*DO82) -> 230.22 | DT82: =DS82/$DS$130 -> 0.00046549774
B83: M03 | C83: Terminal olhal de cobre à compressão #10mm² com furo M8, TM-10-8 da Intelli ou similar. | D83: UND | E83: 5.66 | H83: =G83*F83*$E83 -> 0 | K83: =J83*I83*$E83 -> 0 | N83: =M83*L83*$E83 -> 0 | Q83: =P83*O83*$E83 -> 0 | T83: =S83*R83*$E83 -> 0 | W83: =V83*U83*$E83 -> 0 | Z83: =Y83*X83*$E83 -> 0 | AC83: =AB83*AA83*$E83 -> 0 | AF83: =AE83*AD83*$E83 -> 0 | AI83: =AH83*AG83*$E83 -> 0 | AL83: =AK83*AJ83*$E83 -> 0 | AO83: =AN83*AM83*$E83 -> 0 | AR83: =AQ83*AP83*$E83 -> 0 | AU83: =AT83*AS83*$E83 -> 0 | AV83: 1 | AW83: 1 | AX83: =AW83*AV83*$E83 -> 5.66 | BA83: =AZ83*AY83*$E83 -> 0 | BD83: =BC83*BB83*$E83 -> 0 | BG83: =BF83*BE83*$E83 -> 0 | BJ83: =BI83*BH83*$E83 -> 0 | BM83: =BL83*BK83*$E83 -> 0 | BP83: =BO83*BN83*$E83 -> 0 | BS83: =BR83*BQ83*$E83 -> 0 | BV83: =BU83*BT83*$E83 -> 0 | BY83: =BX83*BW83*$E83 -> 0 | CB83: =CA83*BZ83*$E83 -> 0 | CE83: =CD83*CC83*$E83 -> 0 | CH83: =CG83*CF83*$E83 -> 0 | CK83: =CJ83*CI83*$E83 -> 0 | CN83: =CM83*CL83*$E83 -> 0 | CQ83: =CP83*CO83*$E83 -> 0 | CT83: =CS83*CR83*$E83 -> 0 | CW83: =CV83*CU83*$E83 -> 0 | CZ83: =CY83*CX83*$E83 -> 0 | DC83: =DB83*DA83*$E83 -> 0 | DF83: =DE83*DD83*$E83 -> 0 | DI83: =DH83*DG83*$E83 -> 0 | DL83: =DK83*DJ83*$E83 -> 0 | DO83: =DN83*DM83*$E83 -> 0 | DS83: =($H$3*H83+$K$3*K83+$N$3*N83+$Q$3*Q83+$T$3*T83+$W$3*W83+$Z$3*Z83+$AC$3*AC83+$AF$3*AF83+$AI$3*AI83+$AL$3*AL83+$AO$3*AO83+$AR$3*AR83+$AU$3*AU83+$AX$3*AX83+$BA$3*BA83+$BD$3*BD83+$BG$3*BG83+$BJ$3*BJ83+$BM$3*BM83+$BP$3*BP83+$BS$3*BS83+$BV$3*BV83+$BY$3*BY83+$CB$3*CB83+$CE$3*CE83+$CH$3*CH83+$CK$3*CK83+$CN$3*CN83+$CQ$3*CQ83+$CT$3*CT83+$CW$3*CW83+$CZ$3*CZ83+$DC$3*DC83+$DF$3*DF83+$DI$3*DI83+$DL$3*DL83+$DO$3*DO83) -> 45.28 | DT83: =DS83/$DS$130 -> 9.1554763e-05
B84: M04 | C84: Fusível NH Sitor Ultra Rápido Gr 32A 1000V 100Ka T-0, Indicador Frontal 3NE4 101 da Siemens ou similar | D84: UND | E84: 84.66 | H84: =G84*F84*$E84 -> 0 | K84: =J84*I84*$E84 -> 0 | N84: =M84*L84*$E84 -> 0 | Q84: =P84*O84*$E84 -> 0 | T84: =S84*R84*$E84 -> 0 | W84: =V84*U84*$E84 -> 0 | Z84: =Y84*X84*$E84 -> 0 | AC84: =AB84*AA84*$E84 -> 0 | AF84: =AE84*AD84*$E84 -> 0 | AI84: =AH84*AG84*$E84 -> 0 | AL84: =AK84*AJ84*$E84 -> 0 | AO84: =AN84*AM84*$E84 -> 0 | AR84: =AQ84*AP84*$E84 -> 0 | AU84: =AT84*AS84*$E84 -> 0 | AX84: =AW84*AV84*$E84 -> 0 | AY84: 1 | AZ84: 1 | BA84: =AZ84*AY84*$E84 -> 84.66 | BD84: =BC84*BB84*$E84 -> 0 | BG84: =BF84*BE84*$E84 -> 0 | BJ84: =BI84*BH84*$E84 -> 0 | BM84: =BL84*BK84*$E84 -> 0 | BP84: =BO84*BN84*$E84 -> 0 | BS84: =BR84*BQ84*$E84 -> 0 | BV84: =BU84*BT84*$E84 -> 0 | BY84: =BX84*BW84*$E84 -> 0 | CB84: =CA84*BZ84*$E84 -> 0 | CE84: =CD84*CC84*$E84 -> 0 | CH84: =CG84*CF84*$E84 -> 0 | CK84: =CJ84*CI84*$E84 -> 0 | CN84: =CM84*CL84*$E84 -> 0 | CQ84: =CP84*CO84*$E84 -> 0 | CT84: =CS84*CR84*$E84 -> 0 | CW84: =CV84*CU84*$E84 -> 0 | CZ84: =CY84*CX84*$E84 -> 0 | DC84: =DB84*DA84*$E84 -> 0 | DF84: =DE84*DD84*$E84 -> 0 | DI84: =DH84*DG84*$E84 -> 0 | DL84: =DK84*DJ84*$E84 -> 0 | DO84: =DN84*DM84*$E84 -> 0 | DS84: =($H$3*H84+$K$3*K84+$N$3*N84+$Q$3*Q84+$T$3*T84+$W$3*W84+$Z$3*Z84+$AC$3*AC84+$AF$3*AF84+$AI$3*AI84+$AL$3*AL84+$AO$3*AO84+$AR$3*AR84+$AU$3*AU84+$AX$3*AX84+$BA$3*BA84+$BD$3*BD84+$BG$3*BG84+$BJ$3*BJ84+$BM$3*BM84+$BP$3*BP84+$BS$3*BS84+$BV$3*BV84+$BY$3*BY84+$CB$3*CB84+$CE$3*CE84+$CH$3*CH84+$CK$3*CK84+$CN$3*CN84+$CQ$3*CQ84+$CT$3*CT84+$CW$3*CW84+$CZ$3*CZ84+$DC$3*DC84+$DF$3*DF84+$DI$3*DI84+$DL$3*DL84+$DO$3*DO84) -> 507.96 | DT84: =DS84/$DS$130 -> 0.0010270794
B85: M05 | C85: Base para Fusível NH Sitor Ultra Rápido Gr 32A 1000V 100Ka, T-0 tipo: 3NH3 230- 0RC da Siemens ou similar | D85: UND | E85: 64.33 | H85: =G85*F85*$E85 -> 0 | K85: =J85*I85*$E85 -> 0 | N85: =M85*L85*$E85 -> 0 | Q85: =P85*O85*$E85 -> 0 | T85: =S85*R85*$E85 -> 0 | W85: =V85*U85*$E85 -> 0 | Z85: =Y85*X85*$E85 -> 0 | AC85: =AB85*AA85*$E85 -> 0 | AF85: =AE85*AD85*$E85 -> 0 | AI85: =AH85*AG85*$E85 -> 0 | AL85: =AK85*AJ85*$E85 -> 0 | AO85: =AN85*AM85*$E85 -> 0 | AR85: =AQ85*AP85*$E85 -> 0 | AU85: =AT85*AS85*$E85 -> 0 | AX85: =AW85*AV85*$E85 -> 0 | BA85: =AZ85*AY85*$E85 -> 0 | BB85: 1 | BC85: 1 | BD85: =BC85*BB85*$E85 -> 64.33 | BG85: =BF85*BE85*$E85 -> 0 | BJ85: =BI85*BH85*$E85 -> 0 | BM85: =BL85*BK85*$E85 -> 0 | BP85: =BO85*BN85*$E85 -> 0 | BS85: =BR85*BQ85*$E85 -> 0 | BV85: =BU85*BT85*$E85 -> 0 | BY85: =BX85*BW85*$E85 -> 0 | CB85: =CA85*BZ85*$E85 -> 0 | CE85: =CD85*CC85*$E85 -> 0 | CH85: =CG85*CF85*$E85 -> 0 | CK85: =CJ85*CI85*$E85 -> 0 | CN85: =CM85*CL85*$E85 -> 0 | CQ85: =CP85*CO85*$E85 -> 0 | CT85: =CS85*CR85*$E85 -> 0 | CW85: =CV85*CU85*$E85 -> 0 | CZ85: =CY85*CX85*$E85 -> 0 | DC85: =DB85*DA85*$E85 -> 0 | DF85: =DE85*DD85*$E85 -> 0 | DI85: =DH85*DG85*$E85 -> 0 | DL85: =DK85*DJ85*$E85 -> 0 | DO85: =DN85*DM85*$E85 -> 0 | DS85: =($H$3*H85+$K$3*K85+$N$3*N85+$Q$3*Q85+$T$3*T85+$W$3*W85+$Z$3*Z85+$AC$3*AC85+$AF$3*AF85+$AI$3*AI85+$AL$3*AL85+$AO$3*AO85+$AR$3*AR85+$AU$3*AU85+$AX$3*AX85+$BA$3*BA85+$BD$3*BD85+$BG$3*BG85+$BJ$3*BJ85+$BM$3*BM85+$BP$3*BP85+$BS$3*BS85+$BV$3*BV85+$BY$3*BY85+$CB$3*CB85+$CE$3*CE85+$CH$3*CH85+$CK$3*CK85+$CN$3*CN85+$CQ$3*CQ85+$CT$3*CT85+$CW$3*CW85+$CZ$3*CZ85+$DC$3*DC85+$DF$3*DF85+$DI$3*DI85+$DL$3*DL85+$DO$3*DO85) -> 385.98 | DT85: =DS85/$DS$130 -> 0.00078043965
B86: M06 | C86: Miscelâneas | D86: Vb | E86: 5600 | H86: =G86*F86*$E86 -> 0 | K86: =J86*I86*$E86 -> 0 | N86: =M86*L86*$E86 -> 0 | Q86: =P86*O86*$E86 -> 0 | T86: =S86*R86*$E86 -> 0 | W86: =V86*U86*$E86 -> 0 | Z86: =Y86*X86*$E86 -> 0 | AC86: =AB86*AA86*$E86 -> 0 | AF86: =AE86*AD86*$E86 -> 0 | AI86: =AH86*AG86*$E86 -> 0 | AL86: =AK86*AJ86*$E86 -> 0 | AO86: =AN86*AM86*$E86 -> 0 | AR86: =AQ86*AP86*$E86 -> 0 | AU86: =AT86*AS86*$E86 -> 0 | AX86: =AW86*AV86*$E86 -> 0 | BA86: =AZ86*AY86*$E86 -> 0 | BD86: =BC86*BB86*$E86 -> 0 | BE86: 0.25 | BF86: 1 | BG86: =BF86*BE86*$E86 -> 1400 | BJ86: =BI86*BH86*$E86 -> 0 | BM86: =BL86*BK86*$E86 -> 0 | BP86: =BO86*BN86*$E86 -> 0 | BS86: =BR86*BQ86*$E86 -> 0 | BV86: =BU86*BT86*$E86 -> 0 | BY86: =BX86*BW86*$E86 -> 0 | CB86: =CA86*BZ86*$E86 -> 0 | CE86: =CD86*CC86*$E86 -> 0 | CH86: =CG86*CF86*$E86 -> 0 | CK86: =CJ86*CI86*$E86 -> 0 | CN86: =CM86*CL86*$E86 -> 0 | CQ86: =CP86*CO86*$E86 -> 0 | CT86: =CS86*CR86*$E86 -> 0 | CW86: =CV86*CU86*$E86 -> 0 | CZ86: =CY86*CX86*$E86 -> 0 | DA86: 1 | DB86: 0.5 | DC86: =DB86*DA86*$E86 -> 2800 | DF86: =DE86*DD86*$E86 -> 0 | DI86: =DH86*DG86*$E86 -> 0 | DL86: =DK86*DJ86*$E86 -> 0 | DO86: =DN86*DM86*$E86 -> 0 | DS86: =($H$3*H86+$K$3*K86+$N$3*N86+$Q$3*Q86+$T$3*T86+$W$3*W86+$Z$3*Z86+$AC$3*AC86+$AF$3*AF86+$AI$3*AI86+$AL$3*AL86+$AO$3*AO86+$AR$3*AR86+$AU$3*AU86+$AX$3*AX86+$BA$3*BA86+$BD$3*BD86+$BG$3*BG86+$BJ$3*BJ86+$BM$3*BM86+$BP$3*BP86+$BS$3*BS86+$BV$3*BV86+$BY$3*BY86+$CB$3*CB86+$CE$3*CE86+$CH$3*CH86+$CK$3*CK86+$CN$3*CN86+$CQ$3*CQ86+$CT$3*CT86+$CW$3*CW86+$CZ$3*CZ86+$DC$3*DC86+$DF$3*DF86+$DI$3*DI86+$DL$3*DL86+$DO$3*DO86) -> 4200 | DT86: =DS86/$DS$130 -> 0.0084922704
B87: M07 | C87: Água mineral | D87: L | E87: 1 | H87: =G87*F87*$E87 -> 0 | K87: =J87*I87*$E87 -> 0 | N87: =M87*L87*$E87 -> 0 | Q87: =P87*O87*$E87 -> 0 | T87: =S87*R87*$E87 -> 0 | W87: =V87*U87*$E87 -> 0 | Z87: =Y87*X87*$E87 -> 0 | AC87: =AB87*AA87*$E87 -> 0 | AF87: =AE87*AD87*$E87 -> 0 | AI87: =AH87*AG87*$E87 -> 0 | AL87: =AK87*AJ87*$E87 -> 0 | AO87: =AN87*AM87*$E87 -> 0 | AR87: =AQ87*AP87*$E87 -> 0 | AU87: =AT87*AS87*$E87 -> 0 | AX87: =AW87*AV87*$E87 -> 0 | BA87: =AZ87*AY87*$E87 -> 0 | BD87: =BC87*BB87*$E87 -> 0 | BG87: =BF87*BE87*$E87 -> 0 | BJ87: =BI87*BH87*$E87 -> 0 | BM87: =BL87*BK87*$E87 -> 0 | BP87: =BO87*BN87*$E87 -> 0 | BS87: =BR87*BQ87*$E87 -> 0 | BV87: =BU87*BT87*$E87 -> 0 | BY87: =BX87*BW87*$E87 -> 0 | CB87: =CA87*BZ87*$E87 -> 0 | CE87: =CD87*CC87*$E87 -> 0 | CH87: =CG87*CF87*$E87 -> 0 | CK87: =CJ87*CI87*$E87 -> 0 | CN87: =CM87*CL87*$E87 -> 0 | CQ87: =CP87*CO87*$E87 -> 0 | CT87: =CS87*CR87*$E87 -> 0 | CW87: =CV87*CU87*$E87 -> 0 | CZ87: =CY87*CX87*$E87 -> 0 | DC87: =DB87*DA87*$E87 -> 0 | DF87: =DE87*DD87*$E87 -> 0 | DI87: =DH87*DG87*$E87 -> 0 | DL87: =DK87*DJ87*$E87 -> 0 | DO87: =DN87*DM87*$E87 -> 0 | DS87: =($H$3*H87+$K$3*K87+$N$3*N87+$Q$3*Q87+$T$3*T87+$W$3*W87+$Z$3*Z87+$AC$3*AC87+$AF$3*AF87+$AI$3*AI87+$AL$3*AL87+$AO$3*AO87+$AR$3*AR87+$AU$3*AU87+$AX$3*AX87+$BA$3*BA87+$BD$3*BD87+$BG$3*BG87+$BJ$3*BJ87+$BM$3*BM87+$BP$3*BP87+$BS$3*BS87+$BV$3*BV87+$BY$3*BY87+$CB$3*CB87+$CE$3*CE87+$CH$3*CH87+$CK$3*CK87+$CN$3*CN87+$CQ$3*CQ87+$CT$3*CT87+$CW$3*CW87+$CZ$3*CZ87+$DC$3*DC87+$DF$3*DF87+$DI$3*DI87+$DL$3*DL87+$DO$3*DO87) -> 0 | DT87: =DS87/$DS$130 -> 0
B88: M08 | C88: Gelo branco seco | D88: Pct | E88: 7 | H88: =G88*F88*$E88 -> 0 | K88: =J88*I88*$E88 -> 0 | N88: =M88*L88*$E88 -> 0 | Q88: =P88*O88*$E88 -> 0 | T88: =S88*R88*$E88 -> 0 | W88: =V88*U88*$E88 -> 0 | Z88: =Y88*X88*$E88 -> 0 | AC88: =AB88*AA88*$E88 -> 0 | AF88: =AE88*AD88*$E88 -> 0 | AI88: =AH88*AG88*$E88 -> 0 | AL88: =AK88*AJ88*$E88 -> 0 | AO88: =AN88*AM88*$E88 -> 0 | AR88: =AQ88*AP88*$E88 -> 0 | AU88: =AT88*AS88*$E88 -> 0 | AX88: =AW88*AV88*$E88 -> 0 | BA88: =AZ88*AY88*$E88 -> 0 | BD88: =BC88*BB88*$E88 -> 0 | BG88: =BF88*BE88*$E88 -> 0 | BJ88: =BI88*BH88*$E88 -> 0 | BM88: =BL88*BK88*$E88 -> 0 | BP88: =BO88*BN88*$E88 -> 0 | BS88: =BR88*BQ88*$E88 -> 0 | BV88: =BU88*BT88*$E88 -> 0 | BY88: =BX88*BW88*$E88 -> 0 | CB88: =CA88*BZ88*$E88 -> 0 | CE88: =CD88*CC88*$E88 -> 0 | CH88: =CG88*CF88*$E88 -> 0 | CK88: =CJ88*CI88*$E88 -> 0 | CN88: =CM88*CL88*$E88 -> 0 | CQ88: =CP88*CO88*$E88 -> 0 | CT88: =CS88*CR88*$E88 -> 0 | CW88: =CV88*CU88*$E88 -> 0 | CZ88: =CY88*CX88*$E88 -> 0 | DC88: =DB88*DA88*$E88 -> 0 | DF88: =DE88*DD88*$E88 -> 0 | DI88: =DH88*DG88*$E88 -> 0 | DL88: =DK88*DJ88*$E88 -> 0 | DO88: =DN88*DM88*$E88 -> 0 | DS88: =($H$3*H88+$K$3*K88+$N$3*N88+$Q$3*Q88+$T$3*T88+$W$3*W88+$Z$3*Z88+$AC$3*AC88+$AF$3*AF88+$AI$3*AI88+$AL$3*AL88+$AO$3*AO88+$AR$3*AR88+$AU$3*AU88+$AX$3*AX88+$BA$3*BA88+$BD$3*BD88+$BG$3*BG88+$BJ$3*BJ88+$BM$3*BM88+$BP$3*BP88+$BS$3*BS88+$BV$3*BV88+$BY$3*BY88+$CB$3*CB88+$CE$3*CE88+$CH$3*CH88+$CK$3*CK88+$CN$3*CN88+$CQ$3*CQ88+$CT$3*CT88+$CW$3*CW88+$CZ$3*CZ88+$DC$3*DC88+$DF$3*DF88+$DI$3*DI88+$DL$3*DL88+$DO$3*DO88) -> 0 | DT88: =DS88/$DS$130 -> 0
B89: M09 | C89: Garrafa térmica 12 L | D89: und | E89: 140 | H89: =G89*F89*$E89 -> 0 | K89: =J89*I89*$E89 -> 0 | N89: =M89*L89*$E89 -> 0 | Q89: =P89*O89*$E89 -> 0 | T89: =S89*R89*$E89 -> 0 | W89: =V89*U89*$E89 -> 0 | Z89: =Y89*X89*$E89 -> 0 | AC89: =AB89*AA89*$E89 -> 0 | AF89: =AE89*AD89*$E89 -> 0 | AI89: =AH89*AG89*$E89 -> 0 | AL89: =AK89*AJ89*$E89 -> 0 | AO89: =AN89*AM89*$E89 -> 0 | AR89: =AQ89*AP89*$E89 -> 0 | AU89: =AT89*AS89*$E89 -> 0 | AX89: =AW89*AV89*$E89 -> 0 | BA89: =AZ89*AY89*$E89 -> 0 | BD89: =BC89*BB89*$E89 -> 0 | BG89: =BF89*BE89*$E89 -> 0 | BJ89: =BI89*BH89*$E89 -> 0 | BM89: =BL89*BK89*$E89 -> 0 | BP89: =BO89*BN89*$E89 -> 0 | BS89: =BR89*BQ89*$E89 -> 0 | BV89: =BU89*BT89*$E89 -> 0 | BY89: =BX89*BW89*$E89 -> 0 | CB89: =CA89*BZ89*$E89 -> 0 | CE89: =CD89*CC89*$E89 -> 0 | CH89: =CG89*CF89*$E89 -> 0 | CK89: =CJ89*CI89*$E89 -> 0 | CN89: =CM89*CL89*$E89 -> 0 | CQ89: =CP89*CO89*$E89 -> 0 | CT89: =CS89*CR89*$E89 -> 0 | CW89: =CV89*CU89*$E89 -> 0 | CZ89: =CY89*CX89*$E89 -> 0 | DC89: =DB89*DA89*$E89 -> 0 | DF89: =DE89*DD89*$E89 -> 0 | DI89: =DH89*DG89*$E89 -> 0 | DL89: =DK89*DJ89*$E89 -> 0 | DO89: =DN89*DM89*$E89 -> 0 | DS89: =($H$3*H89+$K$3*K89+$N$3*N89+$Q$3*Q89+$T$3*T89+$W$3*W89+$Z$3*Z89+$AC$3*AC89+$AF$3*AF89+$AI$3*AI89+$AL$3*AL89+$AO$3*AO89+$AR$3*AR89+$AU$3*AU89+$AX$3*AX89+$BA$3*BA89+$BD$3*BD89+$BG$3*BG89+$BJ$3*BJ89+$BM$3*BM89+$BP$3*BP89+$BS$3*BS89+$BV$3*BV89+$BY$3*BY89+$CB$3*CB89+$CE$3*CE89+$CH$3*CH89+$CK$3*CK89+$CN$3*CN89+$CQ$3*CQ89+$CT$3*CT89+$CW$3*CW89+$CZ$3*CZ89+$DC$3*DC89+$DF$3*DF89+$DI$3*DI89+$DL$3*DL89+$DO$3*DO89) -> 0 | DT89: =DS89/$DS$130 -> 0
B90: M11 | C90: Estaca de madeira | D90: und | E90: 5 | H90: =G90*F90*$E90 -> 0 | K90: =J90*I90*$E90 -> 0 | N90: =M90*L90*$E90 -> 0 | Q90: =P90*O90*$E90 -> 0 | T90: =S90*R90*$E90 -> 0 | W90: =V90*U90*$E90 -> 0 | X90: 25 | Y90: 1 | Z90: =Y90*X90*$E90 -> 125 | AC90: =AB90*AA90*$E90 -> 0 | AF90: =AE90*AD90*$E90 -> 0 | AI90: =AH90*AG90*$E90 -> 0 | AL90: =AK90*AJ90*$E90 -> 0 | AO90: =AN90*AM90*$E90 -> 0 | AR90: =AQ90*AP90*$E90 -> 0 | AU90: =AT90*AS90*$E90 -> 0 | AX90: =AW90*AV90*$E90 -> 0 | BA90: =AZ90*AY90*$E90 -> 0 | BD90: =BC90*BB90*$E90 -> 0 | BG90: =BF90*BE90*$E90 -> 0 | BJ90: =BI90*BH90*$E90 -> 0 | BM90: =BL90*BK90*$E90 -> 0 | BP90: =BO90*BN90*$E90 -> 0 | BS90: =BR90*BQ90*$E90 -> 0 | BV90: =BU90*BT90*$E90 -> 0 | BY90: =BX90*BW90*$E90 -> 0 | CB90: =CA90*BZ90*$E90 -> 0 | CE90: =CD90*CC90*$E90 -> 0 | CH90: =CG90*CF90*$E90 -> 0 | CK90: =CJ90*CI90*$E90 -> 0 | CN90: =CM90*CL90*$E90 -> 0 | CQ90: =CP90*CO90*$E90 -> 0 | CT90: =CS90*CR90*$E90 -> 0 | CW90: =CV90*CU90*$E90 -> 0 | CZ90: =CY90*CX90*$E90 -> 0 | DC90: =DB90*DA90*$E90 -> 0 | DF90: =DE90*DD90*$E90 -> 0 | DI90: =DH90*DG90*$E90 -> 0 | DL90: =DK90*DJ90*$E90 -> 0 | DO90: =DN90*DM90*$E90 -> 0 | DS90: =($H$3*H90+$K$3*K90+$N$3*N90+$Q$3*Q90+$T$3*T90+$W$3*W90+$Z$3*Z90+$AC$3*AC90+$AF$3*AF90+$AI$3*AI90+$AL$3*AL90+$AO$3*AO90+$AR$3*AR90+$AU$3*AU90+$AX$3*AX90+$BA$3*BA90+$BD$3*BD90+$BG$3*BG90+$BJ$3*BJ90+$BM$3*BM90+$BP$3*BP90+$BS$3*BS90+$BV$3*BV90+$BY$3*BY90+$CB$3*CB90+$CE$3*CE90+$CH$3*CH90+$CK$3*CK90+$CN$3*CN90+$CQ$3*CQ90+$CT$3*CT90+$CW$3*CW90+$CZ$3*CZ90+$DC$3*DC90+$DF$3*DF90+$DI$3*DI90+$DL$3*DL90+$DO$3*DO90) -> 125 | DT90: =DS90/$DS$130 -> 0.00025274614
B91: M12 | C91: Piquete de madeira | D91: und | E91: 3.5 | H91: =G91*F91*$E91 -> 0 | K91: =J91*I91*$E91 -> 0 | N91: =M91*L91*$E91 -> 0 | Q91: =P91*O91*$E91 -> 0 | T91: =S91*R91*$E91 -> 0 | W91: =V91*U91*$E91 -> 0 | X91: 15 | Y91: 1 | Z91: =Y91*X91*$E91 -> 52.5 | AC91: =AB91*AA91*$E91 -> 0 | AF91: =AE91*AD91*$E91 -> 0 | AI91: =AH91*AG91*$E91 -> 0 | AL91: =AK91*AJ91*$E91 -> 0 | AO91: =AN91*AM91*$E91 -> 0 | AR91: =AQ91*AP91*$E91 -> 0 | AU91: =AT91*AS91*$E91 -> 0 | AX91: =AW91*AV91*$E91 -> 0 | BA91: =AZ91*AY91*$E91 -> 0 | BD91: =BC91*BB91*$E91 -> 0 | BG91: =BF91*BE91*$E91 -> 0 | BJ91: =BI91*BH91*$E91 -> 0 | BM91: =BL91*BK91*$E91 -> 0 | BP91: =BO91*BN91*$E91 -> 0 | BS91: =BR91*BQ91*$E91 -> 0 | BV91: =BU91*BT91*$E91 -> 0 | BY91: =BX91*BW91*$E91 -> 0 | CB91: =CA91*BZ91*$E91 -> 0 | CE91: =CD91*CC91*$E91 -> 0 | CH91: =CG91*CF91*$E91 -> 0 | CK91: =CJ91*CI91*$E91 -> 0 | CN91: =CM91*CL91*$E91 -> 0 | CQ91: =CP91*CO91*$E91 -> 0 | CT91: =CS91*CR91*$E91 -> 0 | CW91: =CV91*CU91*$E91 -> 0 | CZ91: =CY91*CX91*$E91 -> 0 | DC91: =DB91*DA91*$E91 -> 0 | DF91: =DE91*DD91*$E91 -> 0 | DI91: =DH91*DG91*$E91 -> 0 | DL91: =DK91*DJ91*$E91 -> 0 | DO91: =DN91*DM91*$E91 -> 0 | DS91: =($H$3*H91+$K$3*K91+$N$3*N91+$Q$3*Q91+$T$3*T91+$W$3*W91+$Z$3*Z91+$AC$3*AC91+$AF$3*AF91+$AI$3*AI91+$AL$3*AL91+$AO$3*AO91+$AR$3*AR91+$AU$3*AU91+$AX$3*AX91+$BA$3*BA91+$BD$3*BD91+$BG$3*BG91+$BJ$3*BJ91+$BM$3*BM91+$BP$3*BP91+$BS$3*BS91+$BV$3*BV91+$BY$3*BY91+$CB$3*CB91+$CE$3*CE91+$CH$3*CH91+$CK$3*CK91+$CN$3*CN91+$CQ$3*CQ91+$CT$3*CT91+$CW$3*CW91+$CZ$3*CZ91+$DC$3*DC91+$DF$3*DF91+$DI$3*DI91+$DL$3*DL91+$DO$3*DO91) -> 52.5 | DT91: =DS91/$DS$130 -> 0.00010615338
B92: M13 | C92: Tinta - 18L | D92: und | E92: 260 | H92: =G92*F92*$E92 -> 0 | K92: =J92*I92*$E92 -> 0 | N92: =M92*L92*$E92 -> 0 | Q92: =P92*O92*$E92 -> 0 | T92: =S92*R92*$E92 -> 0 | W92: =V92*U92*$E92 -> 0 | X92: 1 | Y92: 1 | Z92: =Y92*X92*$E92 -> 260 | AC92: =AB92*AA92*$E92 -> 0 | AF92: =AE92*AD92*$E92 -> 0 | AI92: =AH92*AG92*$E92 -> 0 | AL92: =AK92*AJ92*$E92 -> 0 | AO92: =AN92*AM92*$E92 -> 0 | AR92: =AQ92*AP92*$E92 -> 0 | AU92: =AT92*AS92*$E92 -> 0 | AX92: =AW92*AV92*$E92 -> 0 | BA92: =AZ92*AY92*$E92 -> 0 | BD92: =BC92*BB92*$E92 -> 0 | BG92: =BF92*BE92*$E92 -> 0 | BJ92: =BI92*BH92*$E92 -> 0 | BM92: =BL92*BK92*$E92 -> 0 | BP92: =BO92*BN92*$E92 -> 0 | BS92: =BR92*BQ92*$E92 -> 0 | BV92: =BU92*BT92*$E92 -> 0 | BY92: =BX92*BW92*$E92 -> 0 | CB92: =CA92*BZ92*$E92 -> 0 | CE92: =CD92*CC92*$E92 -> 0 | CH92: =CG92*CF92*$E92 -> 0 | CK92: =CJ92*CI92*$E92 -> 0 | CN92: =CM92*CL92*$E92 -> 0 | CQ92: =CP92*CO92*$E92 -> 0 | CT92: =CS92*CR92*$E92 -> 0 | CW92: =CV92*CU92*$E92 -> 0 | CZ92: =CY92*CX92*$E92 -> 0 | DC92: =DB92*DA92*$E92 -> 0 | DF92: =DE92*DD92*$E92 -> 0 | DI92: =DH92*DG92*$E92 -> 0 | DL92: =DK92*DJ92*$E92 -> 0 | DO92: =DN92*DM92*$E92 -> 0 | DS92: =($H$3*H92+$K$3*K92+$N$3*N92+$Q$3*Q92+$T$3*T92+$W$3*W92+$Z$3*Z92+$AC$3*AC92+$AF$3*AF92+$AI$3*AI92+$AL$3*AL92+$AO$3*AO92+$AR$3*AR92+$AU$3*AU92+$AX$3*AX92+$BA$3*BA92+$BD$3*BD92+$BG$3*BG92+$BJ$3*BJ92+$BM$3*BM92+$BP$3*BP92+$BS$3*BS92+$BV$3*BV92+$BY$3*BY92+$CB$3*CB92+$CE$3*CE92+$CH$3*CH92+$CK$3*CK92+$CN$3*CN92+$CQ$3*CQ92+$CT$3*CT92+$CW$3*CW92+$CZ$3*CZ92+$DC$3*DC92+$DF$3*DF92+$DI$3*DI92+$DL$3*DL92+$DO$3*DO92) -> 260 | DT92: =DS92/$DS$130 -> 0.00052571198
B93: M14 | C93: Marcador Industrial | D93: und | E93: 16.5 | H93: =G93*F93*$E93 -> 0 | K93: =J93*I93*$E93 -> 0 | N93: =M93*L93*$E93 -> 0 | Q93: =P93*O93*$E93 -> 0 | T93: =S93*R93*$E93 -> 0 | W93: =V93*U93*$E93 -> 0 | X93: 2 | Y93: 1 | Z93: =Y93*X93*$E93 -> 33 | AC93: =AB93*AA93*$E93 -> 0 | AF93: =AE93*AD93*$E93 -> 0 | AI93: =AH93*AG93*$E93 -> 0 | AL93: =AK93*AJ93*$E93 -> 0 | AO93: =AN93*AM93*$E93 -> 0 | AR93: =AQ93*AP93*$E93 -> 0 | AU93: =AT93*AS93*$E93 -> 0 | AX93: =AW93*AV93*$E93 -> 0 | BA93: =AZ93*AY93*$E93 -> 0 | BD93: =BC93*BB93*$E93 -> 0 | BG93: =BF93*BE93*$E93 -> 0 | BJ93: =BI93*BH93*$E93 -> 0 | BM93: =BL93*BK93*$E93 -> 0 | BP93: =BO93*BN93*$E93 -> 0 | BS93: =BR93*BQ93*$E93 -> 0 | BV93: =BU93*BT93*$E93 -> 0 | BY93: =BX93*BW93*$E93 -> 0 | CB93: =CA93*BZ93*$E93 -> 0 | CE93: =CD93*CC93*$E93 -> 0 | CH93: =CG93*CF93*$E93 -> 0 | CK93: =CJ93*CI93*$E93 -> 0 | CN93: =CM93*CL93*$E93 -> 0 | CQ93: =CP93*CO93*$E93 -> 0 | CT93: =CS93*CR93*$E93 -> 0 | CW93: =CV93*CU93*$E93 -> 0 | CZ93: =CY93*CX93*$E93 -> 0 | DC93: =DB93*DA93*$E93 -> 0 | DF93: =DE93*DD93*$E93 -> 0 | DI93: =DH93*DG93*$E93 -> 0 | DL93: =DK93*DJ93*$E93 -> 0 | DO93: =DN93*DM93*$E93 -> 0 | DS93: =($H$3*H93+$K$3*K93+$N$3*N93+$Q$3*Q93+$T$3*T93+$W$3*W93+$Z$3*Z93+$AC$3*AC93+$AF$3*AF93+$AI$3*AI93+$AL$3*AL93+$AO$3*AO93+$AR$3*AR93+$AU$3*AU93+$AX$3*AX93+$BA$3*BA93+$BD$3*BD93+$BG$3*BG93+$BJ$3*BJ93+$BM$3*BM93+$BP$3*BP93+$BS$3*BS93+$BV$3*BV93+$BY$3*BY93+$CB$3*CB93+$CE$3*CE93+$CH$3*CH93+$CK$3*CK93+$CN$3*CN93+$CQ$3*CQ93+$CT$3*CT93+$CW$3*CW93+$CZ$3*CZ93+$DC$3*DC93+$DF$3*DF93+$DI$3*DI93+$DL$3*DL93+$DO$3*DO93) -> 33 | DT93: =DS93/$DS$130 -> 6.6724982e-05
B94: M15 | C94: Estrutura metálica leve | D94: ton | E94: 9856.19 | H94: =G94*F94*$E94 -> 0 | K94: =J94*I94*$E94 -> 0 | N94: =M94*L94*$E94 -> 0 | Q94: =P94*O94*$E94 -> 0 | T94: =S94*R94*$E94 -> 0 | W94: =V94*U94*$E94 -> 0 | Z94: =Y94*X94*$E94 -> 0 | AC94: =AB94*AA94*$E94 -> 0 | AF94: =AE94*AD94*$E94 -> 0 | AI94: =AH94*AG94*$E94 -> 0 | AL94: =AK94*AJ94*$E94 -> 0 | AO94: =AN94*AM94*$E94 -> 0 | AR94: =AQ94*AP94*$E94 -> 0 | AU94: =AT94*AS94*$E94 -> 0 | AX94: =AW94*AV94*$E94 -> 0 | BA94: =AZ94*AY94*$E94 -> 0 | BD94: =BC94*BB94*$E94 -> 0 | BG94: =BF94*BE94*$E94 -> 0 | BJ94: =BI94*BH94*$E94 -> 0 | BM94: =BL94*BK94*$E94 -> 0 | BP94: =BO94*BN94*$E94 -> 0 | BS94: =BR94*BQ94*$E94 -> 0 | BV94: =BU94*BT94*$E94 -> 0 | BY94: =BX94*BW94*$E94 -> 0 | CB94: =CA94*BZ94*$E94 -> 0 | CE94: =CD94*CC94*$E94 -> 0 | CH94: =CG94*CF94*$E94 -> 0 | CK94: =CJ94*CI94*$E94 -> 0 | CN94: =CM94*CL94*$E94 -> 0 | CQ94: =CP94*CO94*$E94 -> 0 | CR94: 0.4 | CS94: 1 | CT94: =CS94*CR94*$E94 -> 3942.476 | CW94: =CV94*CU94*$E94 -> 0 | CZ94: =CY94*CX94*$E94 -> 0 | DC94: =DB94*DA94*$E94 -> 0 | DF94: =DE94*DD94*$E94 -> 0 | DI94: =DH94*DG94*$E94 -> 0 | DL94: =DK94*DJ94*$E94 -> 0 | DO94: =DN94*DM94*$E94 -> 0 | DS94: =($H$3*H94+$K$3*K94+$N$3*N94+$Q$3*Q94+$T$3*T94+$W$3*W94+$Z$3*Z94+$AC$3*AC94+$AF$3*AF94+$AI$3*AI94+$AL$3*AL94+$AO$3*AO94+$AR$3*AR94+$AU$3*AU94+$AX$3*AX94+$BA$3*BA94+$BD$3*BD94+$BG$3*BG94+$BJ$3*BJ94+$BM$3*BM94+$BP$3*BP94+$BS$3*BS94+$BV$3*BV94+$BY$3*BY94+$CB$3*CB94+$CE$3*CE94+$CH$3*CH94+$CK$3*CK94+$CN$3*CN94+$CQ$3*CQ94+$CT$3*CT94+$CW$3*CW94+$CZ$3*CZ94+$DC$3*DC94+$DF$3*DF94+$DI$3*DI94+$DL$3*DL94+$DO$3*DO94) -> 3942.476 | DT94: =DS94/$DS$130 -> 0.0079715648
B95: M16 | C95: Estrutura metálica média | D95: ton | E95: 15425.6 | H95: =G95*F95*$E95 -> 0 | K95: =J95*I95*$E95 -> 0 | N95: =M95*L95*$E95 -> 0 | Q95: =P95*O95*$E95 -> 0 | T95: =S95*R95*$E95 -> 0 | W95: =V95*U95*$E95 -> 0 | Z95: =Y95*X95*$E95 -> 0 | AC95: =AB95*AA95*$E95 -> 0 | AF95: =AE95*AD95*$E95 -> 0 | AI95: =AH95*AG95*$E95 -> 0 | AL95: =AK95*AJ95*$E95 -> 0 | AO95: =AN95*AM95*$E95 -> 0 | AR95: =AQ95*AP95*$E95 -> 0 | AU95: =AT95*AS95*$E95 -> 0 | AX95: =AW95*AV95*$E95 -> 0 | BA95: =AZ95*AY95*$E95 -> 0 | BD95: =BC95*BB95*$E95 -> 0 | BG95: =BF95*BE95*$E95 -> 0 | BJ95: =BI95*BH95*$E95 -> 0 | BM95: =BL95*BK95*$E95 -> 0 | BP95: =BO95*BN95*$E95 -> 0 | BS95: =BR95*BQ95*$E95 -> 0 | BV95: =BU95*BT95*$E95 -> 0 | BY95: =BX95*BW95*$E95 -> 0 | CB95: =CA95*BZ95*$E95 -> 0 | CE95: =CD95*CC95*$E95 -> 0 | CH95: =CG95*CF95*$E95 -> 0 | CK95: =CJ95*CI95*$E95 -> 0 | CN95: =CM95*CL95*$E95 -> 0 | CQ95: =CP95*CO95*$E95 -> 0 | CT95: =CS95*CR95*$E95 -> 0 | CU95: 0.45 | CV95: 1 | CW95: =CV95*CU95*$E95 -> 6941.52 | CZ95: =CY95*CX95*$E95 -> 0 | DC95: =DB95*DA95*$E95 -> 0 | DF95: =DE95*DD95*$E95 -> 0 | DI95: =DH95*DG95*$E95 -> 0 | DL95: =DK95*DJ95*$E95 -> 0 | DO95: =DN95*DM95*$E95 -> 0 | DS95: =($H$3*H95+$K$3*K95+$N$3*N95+$Q$3*Q95+$T$3*T95+$W$3*W95+$Z$3*Z95+$AC$3*AC95+$AF$3*AF95+$AI$3*AI95+$AL$3*AL95+$AO$3*AO95+$AR$3*AR95+$AU$3*AU95+$AX$3*AX95+$BA$3*BA95+$BD$3*BD95+$BG$3*BG95+$BJ$3*BJ95+$BM$3*BM95+$BP$3*BP95+$BS$3*BS95+$BV$3*BV95+$BY$3*BY95+$CB$3*CB95+$CE$3*CE95+$CH$3*CH95+$CK$3*CK95+$CN$3*CN95+$CQ$3*CQ95+$CT$3*CT95+$CW$3*CW95+$CZ$3*CZ95+$DC$3*DC95+$DF$3*DF95+$DI$3*DI95+$DL$3*DL95+$DO$3*DO95) -> 6941.52 | DT95: =DS95/$DS$130 -> 0.014035539
B96: M17 | C96: Estrutura metálica pesada | D96: ton | E96: 25019.2 | H96: =G96*F96*$E96 -> 0 | K96: =J96*I96*$E96 -> 0 | N96: =M96*L96*$E96 -> 0 | Q96: =P96*O96*$E96 -> 0 | T96: =S96*R96*$E96 -> 0 | W96: =V96*U96*$E96 -> 0 | Z96: =Y96*X96*$E96 -> 0 | AC96: =AB96*AA96*$E96 -> 0 | AF96: =AE96*AD96*$E96 -> 0 | AI96: =AH96*AG96*$E96 -> 0 | AL96: =AK96*AJ96*$E96 -> 0 | AO96: =AN96*AM96*$E96 -> 0 | AR96: =AQ96*AP96*$E96 -> 0 | AU96: =AT96*AS96*$E96 -> 0 | AX96: =AW96*AV96*$E96 -> 0 | BA96: =AZ96*AY96*$E96 -> 0 | BD96: =BC96*BB96*$E96 -> 0 | BG96: =BF96*BE96*$E96 -> 0 | BJ96: =BI96*BH96*$E96 -> 0 | BM96: =BL96*BK96*$E96 -> 0 | BP96: =BO96*BN96*$E96 -> 0 | BS96: =BR96*BQ96*$E96 -> 0 | BV96: =BU96*BT96*$E96 -> 0 | BY96: =BX96*BW96*$E96 -> 0 | CB96: =CA96*BZ96*$E96 -> 0 | CE96: =CD96*CC96*$E96 -> 0 | CH96: =CG96*CF96*$E96 -> 0 | CK96: =CJ96*CI96*$E96 -> 0 | CN96: =CM96*CL96*$E96 -> 0 | CQ96: =CP96*CO96*$E96 -> 0 | CT96: =CS96*CR96*$E96 -> 0 | CW96: =CV96*CU96*$E96 -> 0 | CX96: 0.15 | CY96: 1 | CZ96: =CY96*CX96*$E96 -> 3752.88 | DC96: =DB96*DA96*$E96 -> 0 | DF96: =DE96*DD96*$E96 -> 0 | DI96: =DH96*DG96*$E96 -> 0 | DL96: =DK96*DJ96*$E96 -> 0 | DO96: =DN96*DM96*$E96 -> 0 | DS96: =($H$3*H96+$K$3*K96+$N$3*N96+$Q$3*Q96+$T$3*T96+$W$3*W96+$Z$3*Z96+$AC$3*AC96+$AF$3*AF96+$AI$3*AI96+$AL$3*AL96+$AO$3*AO96+$AR$3*AR96+$AU$3*AU96+$AX$3*AX96+$BA$3*BA96+$BD$3*BD96+$BG$3*BG96+$BJ$3*BJ96+$BM$3*BM96+$BP$3*BP96+$BS$3*BS96+$BV$3*BV96+$BY$3*BY96+$CB$3*CB96+$CE$3*CE96+$CH$3*CH96+$CK$3*CK96+$CN$3*CN96+$CQ$3*CQ96+$CT$3*CT96+$CW$3*CW96+$CZ$3*CZ96+$DC$3*DC96+$DF$3*DF96+$DI$3*DI96+$DL$3*DL96+$DO$3*DO96) -> 3752.88 | DT96: =DS96/$DS$130 -> 0.0075882076
B97: M18 | H97: =G97*F97*$E97 -> 0 | K97: =J97*I97*$E97 -> 0 | N97: =M97*L97*$E97 -> 0 | Q97: =P97*O97*$E97 -> 0 | T97: =S97*R97*$E97 -> 0 | W97: =V97*U97*$E97 -> 0 | Z97: =Y97*X97*$E97 -> 0 | AC97: =AB97*AA97*$E97 -> 0 | AF97: =AE97*AD97*$E97 -> 0 | AI97: =AH97*AG97*$E97 -> 0 | AL97: =AK97*AJ97*$E97 -> 0 | AO97: =AN97*AM97*$E97 -> 0 | AR97: =AQ97*AP97*$E97 -> 0 | AU97: =AT97*AS97*$E97 -> 0 | AX97: =AW97*AV97*$E97 -> 0 | BA97: =AZ97*AY97*$E97 -> 0 | BD97: =BC97*BB97*$E97 -> 0 | BG97: =BF97*BE97*$E97 -> 0 | BJ97: =BI97*BH97*$E97 -> 0 | BM97: =BL97*BK97*$E97 -> 0 | BP97: =BO97*BN97*$E97 -> 0 | BS97: =BR97*BQ97*$E97 -> 0 | BV97: =BU97*BT97*$E97 -> 0 | BY97: =BX97*BW97*$E97 -> 0 | CB97: =CA97*BZ97*$E97 -> 0 | CE97: =CD97*CC97*$E97 -> 0 | CH97: =CG97*CF97*$E97 -> 0 | CK97: =CJ97*CI97*$E97 -> 0 | CN97: =CM97*CL97*$E97 -> 0 | CQ97: =CP97*CO97*$E97 -> 0 | CT97: =CS97*CR97*$E97 -> 0 | CW97: =CV97*CU97*$E97 -> 0 | CZ97: =CY97*CX97*$E97 -> 0 | DC97: =DB97*DA97*$E97 -> 0 | DF97: =DE97*DD97*$E97 -> 0 | DI97: =DH97*DG97*$E97 -> 0 | DL97: =DK97*DJ97*$E97 -> 0 | DO97: =DN97*DM97*$E97 -> 0 | DS97: =($H$3*H97+$K$3*K97+$N$3*N97+$Q$3*Q97+$T$3*T97+$W$3*W97+$Z$3*Z97+$AC$3*AC97+$AF$3*AF97+$AI$3*AI97+$AL$3*AL97+$AO$3*AO97+$AR$3*AR97+$AU$3*AU97+$AX$3*AX97+$BA$3*BA97+$BD$3*BD97+$BG$3*BG97+$BJ$3*BJ97+$BM$3*BM97+$BP$3*BP97+$BS$3*BS97+$BV$3*BV97+$BY$3*BY97+$CB$3*CB97+$CE$3*CE97+$CH$3*CH97+$CK$3*CK97+$CN$3*CN97+$CQ$3*CQ97+$CT$3*CT97+$CW$3*CW97+$CZ$3*CZ97+$DC$3*DC97+$DF$3*DF97+$DI$3*DI97+$DL$3*DL97+$DO$3*DO97) -> 0 | DT97: =DS97/$DS$130 -> 0
B98: M19 | H98: =G98*F98*$E98 -> 0 | K98: =J98*I98*$E98 -> 0 | N98: =M98*L98*$E98 -> 0 | Q98: =P98*O98*$E98 -> 0 | T98: =S98*R98*$E98 -> 0 | W98: =V98*U98*$E98 -> 0 | Z98: =Y98*X98*$E98 -> 0 | AC98: =AB98*AA98*$E98 -> 0 | AF98: =AE98*AD98*$E98 -> 0 | AI98: =AH98*AG98*$E98 -> 0 | AL98: =AK98*AJ98*$E98 -> 0 | AO98: =AN98*AM98*$E98 -> 0 | AR98: =AQ98*AP98*$E98 -> 0 | AU98: =AT98*AS98*$E98 -> 0 | AX98: =AW98*AV98*$E98 -> 0 | BA98: =AZ98*AY98*$E98 -> 0 | BD98: =BC98*BB98*$E98 -> 0 | BG98: =BF98*BE98*$E98 -> 0 | BJ98: =BI98*BH98*$E98 -> 0 | BM98: =BL98*BK98*$E98 -> 0 | BP98: =BO98*BN98*$E98 -> 0 | BS98: =BR98*BQ98*$E98 -> 0 | BV98: =BU98*BT98*$E98 -> 0 | BY98: =BX98*BW98*$E98 -> 0 | CB98: =CA98*BZ98*$E98 -> 0 | CE98: =CD98*CC98*$E98 -> 0 | CH98: =CG98*CF98*$E98 -> 0 | CK98: =CJ98*CI98*$E98 -> 0 | CN98: =CM98*CL98*$E98 -> 0 | CQ98: =CP98*CO98*$E98 -> 0 | CT98: =CS98*CR98*$E98 -> 0 | CW98: =CV98*CU98*$E98 -> 0 | CZ98: =CY98*CX98*$E98 -> 0 | DC98: =DB98*DA98*$E98 -> 0 | DF98: =DE98*DD98*$E98 -> 0 | DI98: =DH98*DG98*$E98 -> 0 | DL98: =DK98*DJ98*$E98 -> 0 | DO98: =DN98*DM98*$E98 -> 0 | DS98: =($H$3*H98+$K$3*K98+$N$3*N98+$Q$3*Q98+$T$3*T98+$W$3*W98+$Z$3*Z98+$AC$3*AC98+$AF$3*AF98+$AI$3*AI98+$AL$3*AL98+$AO$3*AO98+$AR$3*AR98+$AU$3*AU98+$AX$3*AX98+$BA$3*BA98+$BD$3*BD98+$BG$3*BG98+$BJ$3*BJ98+$BM$3*BM98+$BP$3*BP98+$BS$3*BS98+$BV$3*BV98+$BY$3*BY98+$CB$3*CB98+$CE$3*CE98+$CH$3*CH98+$CK$3*CK98+$CN$3*CN98+$CQ$3*CQ98+$CT$3*CT98+$CW$3*CW98+$CZ$3*CZ98+$DC$3*DC98+$DF$3*DF98+$DI$3*DI98+$DL$3*DL98+$DO$3*DO98) -> 0 | DT98: =DS98/$DS$130 -> 0
B99: M20 | H99: =G99*F99*$E99 -> 0 | K99: =J99*I99*$E99 -> 0 | N99: =M99*L99*$E99 -> 0 | Q99: =P99*O99*$E99 -> 0 | T99: =S99*R99*$E99 -> 0 | W99: =V99*U99*$E99 -> 0 | Z99: =Y99*X99*$E99 -> 0 | AC99: =AB99*AA99*$E99 -> 0 | AF99: =AE99*AD99*$E99 -> 0 | AI99: =AH99*AG99*$E99 -> 0 | AL99: =AK99*AJ99*$E99 -> 0 | AO99: =AN99*AM99*$E99 -> 0 | AR99: =AQ99*AP99*$E99 -> 0 | AU99: =AT99*AS99*$E99 -> 0 | AX99: =AW99*AV99*$E99 -> 0 | BA99: =AZ99*AY99*$E99 -> 0 | BD99: =BC99*BB99*$E99 -> 0 | BG99: =BF99*BE99*$E99 -> 0 | BJ99: =BI99*BH99*$E99 -> 0 | BM99: =BL99*BK99*$E99 -> 0 | BP99: =BO99*BN99*$E99 -> 0 | BS99: =BR99*BQ99*$E99 -> 0 | BV99: =BU99*BT99*$E99 -> 0 | BY99: =BX99*BW99*$E99 -> 0 | CB99: =CA99*BZ99*$E99 -> 0 | CE99: =CD99*CC99*$E99 -> 0 | CH99: =CG99*CF99*$E99 -> 0 | CK99: =CJ99*CI99*$E99 -> 0 | CN99: =CM99*CL99*$E99 -> 0 | CQ99: =CP99*CO99*$E99 -> 0 | CT99: =CS99*CR99*$E99 -> 0 | CW99: =CV99*CU99*$E99 -> 0 | CZ99: =CY99*CX99*$E99 -> 0 | DC99: =DB99*DA99*$E99 -> 0 | DF99: =DE99*DD99*$E99 -> 0 | DI99: =DH99*DG99*$E99 -> 0 | DL99: =DK99*DJ99*$E99 -> 0 | DO99: =DN99*DM99*$E99 -> 0 | DS99: =($H$3*H99+$K$3*K99+$N$3*N99+$Q$3*Q99+$T$3*T99+$W$3*W99+$Z$3*Z99+$AC$3*AC99+$AF$3*AF99+$AI$3*AI99+$AL$3*AL99+$AO$3*AO99+$AR$3*AR99+$AU$3*AU99+$AX$3*AX99+$BA$3*BA99+$BD$3*BD99+$BG$3*BG99+$BJ$3*BJ99+$BM$3*BM99+$BP$3*BP99+$BS$3*BS99+$BV$3*BV99+$BY$3*BY99+$CB$3*CB99+$CE$3*CE99+$CH$3*CH99+$CK$3*CK99+$CN$3*CN99+$CQ$3*CQ99+$CT$3*CT99+$CW$3*CW99+$CZ$3*CZ99+$DC$3*DC99+$DF$3*DF99+$DI$3*DI99+$DL$3*DL99+$DO$3*DO99) -> 0 | DT99: =DS99/$DS$130 -> 0
B100: C - Custo Total de Materiais: | E100: =SUM(#REF!) -> #REF! | H100: =SUM(H81:H99) -> 0 | K100: =SUM(K81:K99) -> 0 | N100: =SUM(N81:N99) -> 0 | Q100: =SUM(Q81:Q99) -> 0 | T100: =SUM(T81:T99) -> 0 | W100: =SUM(W81:W99) -> 0 | Z100: =SUM(Z81:Z99) -> 470.5 | AC100: =SUM(AC81:AC99) -> 0 | AF100: =SUM(AF81:AF99) -> 0 | AI100: =SUM(AI81:AI99) -> 0 | AL100: =SUM(AL81:AL99) -> 0 | AO100: =SUM(AO81:AO99) -> 0 | AR100: =SUM(AR81:AR99) -> 47.46 | AU100: =SUM(AU81:AU99) -> 230.22 | AX100: =SUM(AX81:AX99) -> 5.66 | BA100: =SUM(BA81:BA99) -> 84.66 | BD100: =SUM(BD81:BD99) -> 64.33 | BG100: =SUM(BG81:BG99) -> 1400 | BJ100: =SUM(BJ81:BJ99) -> 0 | BM100: =SUM(BM81:BM99) -> 0 | BP100: =SUM(BP81:BP99) -> 0 | BS100: =SUM(BS81:BS99) -> 0 | BV100: =SUM(BV81:BV99) -> 0 | BY100: =SUM(BY81:BY99) -> 0 | CB100: =SUM(CB81:CB99) -> 0 | CE100: =SUM(CE81:CE99) -> 0 | CH100: =SUM(CH81:CH99) -> 0 | CK100: =SUM(CK81:CK99) -> 0 | CN100: =SUM(CN81:CN99) -> 0 | CQ100: =SUM(CQ81:CQ99) -> 0 | CT100: =SUM(CT81:CT99) -> 3942.476 | CW100: =SUM(CW81:CW99) -> 6941.52 | CZ100: =SUM(CZ81:CZ99) -> 3752.88 | DC100: =SUM(DC81:DC99) -> 2800 | DF100: =SUM(DF81:DF99) -> 0 | DI100: =SUM(DI81:DI99) -> 0 | DL100: =SUM(DL81:DL99) -> 0 | DO100: =SUM(DO81:DO99) -> 0 | DS100: =SUM(DS81:DS99) -> 25222.816
B101: D – Outros
B102: Cód. | C102: Discriminação | D102: Unid | E102: P.Unit | F102: Quant | G102: F.utiliz | H102: Custo | I102: Quant | J102: F.utiliz | K102: Custo | L102: Quant | M102: F.utiliz | N102: Custo | O102: Quant | P102: F.utiliz | Q102: Custo | R102: Quant | S102: F.utiliz | T102: Custo | U102: Quant | V102: F.utiliz | W102: Custo | X102: Quant | Y102: F.utiliz | Z102: Custo | AA102: Quant | AB102: F.utiliz | AC102: Custo | AD102: Quant | AE102: F.utiliz | AF102: Custo | AG102: Quant | AH102: F.utiliz | AI102: Custo | AJ102: Quant | AK102: F.utiliz | AL102: Custo | AM102: Quant | AN102: F.utiliz | AO102: Custo | AP102: Quant | AQ102: F.utiliz | AR102: Custo | AS102: Quant | AT102: F.utiliz | AU102: Custo | AV102: Quant | AW102: F.utiliz | AX102: Custo | AY102: Quant | AZ102: F.utiliz | BA102: Custo | BB102: Quant | BC102: F.utiliz | BD102: Custo | BE102: Quant | BF102: F.utiliz | BG102: Custo | BH102: Quant | BI102: F.utiliz | BJ102: Custo | BK102: Quant | BL102: F.utiliz | BM102: Custo | BN102: Quant | BO102: F.utiliz | BP102: Custo | BQ102: Quant | BR102: F.utiliz | BS102: Custo | BT102: Quant | BU102: F.utiliz | BV102: Custo | BW102: Quant | BX102: F.utiliz | BY102: Custo | BZ102: Quant | CA102: F.utiliz | CB102: Custo | CC102: Quant | CD102: F.utiliz | CE102: Custo | CF102: Quant | CG102: F.utiliz | CH102: Custo | CI102: Quant | CJ102: F.utiliz | CK102: Custo | CL102: Quant | CM102: F.utiliz | CN102: Custo | CO102: Quant | CP102: F.utiliz | CQ102: Custo | CR102: Quant | CS102: F.utiliz | CT102: Custo | CU102: Quant | CV102: F.utiliz | CW102: Custo | CX102: Quant | CY102: F.utiliz | CZ102: Custo | DA102: Quant | DB102: F.utiliz | DC102: Custo | DD102: Quant | DE102: F.utiliz | DF102: Custo | DG102: Quant | DH102: F.utiliz | DI102: Custo | DJ102: Quant | DK102: F.utiliz | DL102: Custo | DM102: Quant | DN102: F.utiliz | DO102: Custo | DQ102: Quant | DR102: F.utiliz | DS102: Custo
B103: O01 | C103: ART | D103: Vb | E103: 271.52 | F103: 1 | G103: 1 | H103: =G103*F103*$E103 -> 271.52 | K103: =J103*I103*$E103 -> 0 | N103: =M103*L103*$E103 -> 0 | Q103: =P103*O103*$E103 -> 0 | T103: =S103*R103*$E103 -> 0 | W103: =V103*U103*$E103 -> 0 | Z103: =Y103*X103*$E103 -> 0 | AC103: =AB103*AA103*$E103 -> 0 | AF103: =AE103*AD103*$E103 -> 0 | AI103: =AH103*AG103*$E103 -> 0 | AL103: =AK103*AJ103*$E103 -> 0 | AO103: =AN103*AM103*$E103 -> 0 | AR103: =AQ103*AP103*$E103 -> 0 | AU103: =AT103*AS103*$E103 -> 0 | AX103: =AW103*AV103*$E103 -> 0 | BA103: =AZ103*AY103*$E103 -> 0 | BD103: =BC103*BB103*$E103 -> 0 | BG103: =BF103*BE103*$E103 -> 0 | BJ103: =BI103*BH103*$E103 -> 0 | BM103: =BL103*BK103*$E103 -> 0 | BP103: =BO103*BN103*$E103 -> 0 | BS103: =BR103*BQ103*$E103 -> 0 | BV103: =BU103*BT103*$E103 -> 0 | BY103: =BX103*BW103*$E103 -> 0 | CB103: =CA103*BZ103*$E103 -> 0 | CE103: =CD103*CC103*$E103 -> 0 | CH103: =CG103*CF103*$E103 -> 0 | CK103: =CJ103*CI103*$E103 -> 0 | CN103: =CM103*CL103*$E103 -> 0 | CQ103: =CP103*CO103*$E103 -> 0 | CT103: =CS103*CR103*$E103 -> 0 | CW103: =CV103*CU103*$E103 -> 0 | CZ103: =CY103*CX103*$E103 -> 0 | DC103: =DB103*DA103*$E103 -> 0 | DF103: =DE103*DD103*$E103 -> 0 | DI103: =DH103*DG103*$E103 -> 0 | DL103: =DK103*DJ103*$E103 -> 0 | DO103: =DN103*DM103*$E103 -> 0 | DS103: =($H$3*H103+$K$3*K103+$N$3*N103+$Q$3*Q103+$T$3*T103+$W$3*W103+$Z$3*Z103+$AC$3*AC103+$AF$3*AF103+$AI$3*AI103+$AL$3*AL103+$AO$3*AO103+$AR$3*AR103+$AU$3*AU103+$AX$3*AX103+$BA$3*BA103+$BD$3*BD103+$BG$3*BG103+$BJ$3*BJ103+$BM$3*BM103+$BP$3*BP103+$BS$3*BS103+$BV$3*BV103+$BY$3*BY103+$CB$3*CB103+$CE$3*CE103+$CH$3*CH103+$CK$3*CK103+$CN$3*CN103+$CQ$3*CQ103+$CT$3*CT103+$CW$3*CW103+$CZ$3*CZ103+$DC$3*DC103+$DF$3*DF103+$DI$3*DI103+$DL$3*DL103+$DO$3*DO103) -> 271.52 | DT103: =DS103/$DS$130 -> 0.00054900506
B104: O02 | C104: Exames médicos | D104: Vb | E104: 456 | F104: =G21 -> 11 | G104: 0.5 | H104: =G104*F104*$E104 -> 2508 | I104: =J21 -> 11 | J104: 0.5 | K104: =J104*I104*$E104 -> 2508 | N104: =M104*L104*$E104 -> 0 | Q104: =P104*O104*$E104 -> 0 | T104: =S104*R104*$E104 -> 0 | W104: =V104*U104*$E104 -> 0 | Z104: =Y104*X104*$E104 -> 0 | AC104: =AB104*AA104*$E104 -> 0 | AF104: =AE104*AD104*$E104 -> 0 | AI104: =AH104*AG104*$E104 -> 0 | AL104: =AK104*AJ104*$E104 -> 0 | AO104: =AN104*AM104*$E104 -> 0 | AR104: =AQ104*AP104*$E104 -> 0 | AU104: =AT104*AS104*$E104 -> 0 | AX104: =AW104*AV104*$E104 -> 0 | BA104: =AZ104*AY104*$E104 -> 0 | BD104: =BC104*BB104*$E104 -> 0 | BG104: =BF104*BE104*$E104 -> 0 | BJ104: =BI104*BH104*$E104 -> 0 | BM104: =BL104*BK104*$E104 -> 0 | BP104: =BO104*BN104*$E104 -> 0 | BS104: =BR104*BQ104*$E104 -> 0 | BV104: =BU104*BT104*$E104 -> 0 | BY104: =BX104*BW104*$E104 -> 0 | CB104: =CA104*BZ104*$E104 -> 0 | CE104: =CD104*CC104*$E104 -> 0 | CH104: =CG104*CF104*$E104 -> 0 | CK104: =CJ104*CI104*$E104 -> 0 | CN104: =CM104*CL104*$E104 -> 0 | CQ104: =CP104*CO104*$E104 -> 0 | CT104: =CS104*CR104*$E104 -> 0 | CW104: =CV104*CU104*$E104 -> 0 | CZ104: =CY104*CX104*$E104 -> 0 | DC104: =DB104*DA104*$E104 -> 0 | DF104: =DE104*DD104*$E104 -> 0 | DI104: =DH104*DG104*$E104 -> 0 | DL104: =DK104*DJ104*$E104 -> 0 | DO104: =DN104*DM104*$E104 -> 0 | DS104: =($H$3*H104+$K$3*K104+$N$3*N104+$Q$3*Q104+$T$3*T104+$W$3*W104+$Z$3*Z104+$AC$3*AC104+$AF$3*AF104+$AI$3*AI104+$AL$3*AL104+$AO$3*AO104+$AR$3*AR104+$AU$3*AU104+$AX$3*AX104+$BA$3*BA104+$BD$3*BD104+$BG$3*BG104+$BJ$3*BJ104+$BM$3*BM104+$BP$3*BP104+$BS$3*BS104+$BV$3*BV104+$BY$3*BY104+$CB$3*CB104+$CE$3*CE104+$CH$3*CH104+$CK$3*CK104+$CN$3*CN104+$CQ$3*CQ104+$CT$3*CT104+$CW$3*CW104+$CZ$3*CZ104+$DC$3*DC104+$DF$3*DF104+$DI$3*DI104+$DL$3*DL104+$DO$3*DO104) -> 5016 | DT104: =DS104/$DS$130 -> 0.010142197
B105: O03 | C105: Treinamentos | D105: Vb | E105: 426 | F105: =G21 -> 11 | G105: 1 | H105: =G105*F105*$E105 -> 4686 | K105: =J105*I105*$E105 -> 0 | N105: =M105*L105*$E105 -> 0 | Q105: =P105*O105*$E105 -> 0 | T105: =S105*R105*$E105 -> 0 | W105: =V105*U105*$E105 -> 0 | Z105: =Y105*X105*$E105 -> 0 | AC105: =AB105*AA105*$E105 -> 0 | AF105: =AE105*AD105*$E105 -> 0 | AI105: =AH105*AG105*$E105 -> 0 | AL105: =AK105*AJ105*$E105 -> 0 | AO105: =AN105*AM105*$E105 -> 0 | AR105: =AQ105*AP105*$E105 -> 0 | AU105: =AT105*AS105*$E105 -> 0 | AX105: =AW105*AV105*$E105 -> 0 | BA105: =AZ105*AY105*$E105 -> 0 | BD105: =BC105*BB105*$E105 -> 0 | BG105: =BF105*BE105*$E105 -> 0 | BJ105: =BI105*BH105*$E105 -> 0 | BM105: =BL105*BK105*$E105 -> 0 | BP105: =BO105*BN105*$E105 -> 0 | BS105: =BR105*BQ105*$E105 -> 0 | BV105: =BU105*BT105*$E105 -> 0 | BY105: =BX105*BW105*$E105 -> 0 | CB105: =CA105*BZ105*$E105 -> 0 | CE105: =CD105*CC105*$E105 -> 0 | CH105: =CG105*CF105*$E105 -> 0 | CK105: =CJ105*CI105*$E105 -> 0 | CN105: =CM105*CL105*$E105 -> 0 | CQ105: =CP105*CO105*$E105 -> 0 | CT105: =CS105*CR105*$E105 -> 0 | CW105: =CV105*CU105*$E105 -> 0 | CZ105: =CY105*CX105*$E105 -> 0 | DC105: =DB105*DA105*$E105 -> 0 | DF105: =DE105*DD105*$E105 -> 0 | DI105: =DH105*DG105*$E105 -> 0 | DL105: =DK105*DJ105*$E105 -> 0 | DO105: =DN105*DM105*$E105 -> 0 | DS105: =($H$3*H105+$K$3*K105+$N$3*N105+$Q$3*Q105+$T$3*T105+$W$3*W105+$Z$3*Z105+$AC$3*AC105+$AF$3*AF105+$AI$3*AI105+$AL$3*AL105+$AO$3*AO105+$AR$3*AR105+$AU$3*AU105+$AX$3*AX105+$BA$3*BA105+$BD$3*BD105+$BG$3*BG105+$BJ$3*BJ105+$BM$3*BM105+$BP$3*BP105+$BS$3*BS105+$BV$3*BV105+$BY$3*BY105+$CB$3*CB105+$CE$3*CE105+$CH$3*CH105+$CK$3*CK105+$CN$3*CN105+$CQ$3*CQ105+$CT$3*CT105+$CW$3*CW105+$CZ$3*CZ105+$DC$3*DC105+$DF$3*DF105+$DI$3*DI105+$DL$3*DL105+$DO$3*DO105) -> 4686 | DT105: =DS105/$DS$130 -> 0.0094749474
B106: O04 | C106: Plano de saúde | D106: Vb/mês | E106: 254.1 | F106: =G21 -> 11 | G106: =$G$4/22 -> 0.90909091 | H106: =G106*F106*$E106 -> 2541 | I106: =J21 -> 11 | J106: =J$4/22 -> 0.45454545 | K106: =J106*I106*$E106 -> 1270.5 | N106: =M106*L106*$E106 -> 0 | Q106: =P106*O106*$E106 -> 0 | T106: =S106*R106*$E106 -> 0 | W106: =V106*U106*$E106 -> 0 | Z106: =Y106*X106*$E106 -> 0 | AC106: =AB106*AA106*$E106 -> 0 | AF106: =AE106*AD106*$E106 -> 0 | AI106: =AH106*AG106*$E106 -> 0 | AL106: =AK106*AJ106*$E106 -> 0 | AO106: =AN106*AM106*$E106 -> 0 | AR106: =AQ106*AP106*$E106 -> 0 | AU106: =AT106*AS106*$E106 -> 0 | AX106: =AW106*AV106*$E106 -> 0 | BA106: =AZ106*AY106*$E106 -> 0 | BD106: =BC106*BB106*$E106 -> 0 | BG106: =BF106*BE106*$E106 -> 0 | BH106: =$BH$21 -> 0.36 | BI106: =1/176 -> 0.0056818182 | BJ106: =BI106*BH106*$E106 -> 0.51975 | BK106: =$BK$21 -> 3.78 | BL106: =1/176 -> 0.0056818182 | BM106: =BL106*BK106*$E106 -> 5.457375 | BN106: =$BN$21 -> 176.45 | BO106: =1/176 -> 0.0056818182 | BP106: =BO106*BN106*$E106 -> 254.74969 | BQ106: =$BQ$21 -> 528 | BR106: =1/176 -> 0.0056818182 | BS106: =BR106*BQ106*$E106 -> 762.3 | BT106: =$BT$21 -> 24 | BU106: =1/176 -> 0.0056818182 | BV106: =BU106*BT106*$E106 -> 34.65 | BW106: =$BW$21 -> 15.36 | BX106: =1/176 -> 0.0056818182 | BY106: =BX106*BW106*$E106 -> 22.176 | BZ106: =$BZ$21 -> 26.88 | CA106: =1/176 -> 0.0056818182 | CB106: =CA106*BZ106*$E106 -> 38.808 | CC106: =$CC$21 -> 4.8 | CD106: =1/176 -> 0.0056818182 | CE106: =CD106*CC106*$E106 -> 6.93 | CF106: =$CF$21 -> 7.2 | CG106: =1/176 -> 0.0056818182 | CH106: =CG106*CF106*$E106 -> 10.395 | CI106: =$CI$21 -> 2.4 | CJ106: =1/176 -> 0.0056818182 | CK106: =CJ106*CI106*$E106 -> 3.465 | CL106: =$CL$21 -> 414.4 | CM106: =1/176 -> 0.0056818182 | CN106: =CM106*CL106*$E106 -> 598.29 | CO106: =$CO$21 -> 168 | CP106: =1/176 -> 0.0056818182 | CQ106: =CP106*CO106*$E106 -> 242.55 | CT106: =CS106*CR106*$E106 -> 0 | CW106: =CV106*CU106*$E106 -> 0 | CZ106: =CY106*CX106*$E106 -> 0 | DC106: =DB106*DA106*$E106 -> 0 | DD106: =$DD$21 -> 112 | DE106: =1/176 -> 0.0056818182 | DF106: =DE106*DD106*$E106 -> 161.7 | DG106: =$DG$21 -> 84 | DH106: =1/176 -> 0.0056818182 | DI106: =DH106*DG106*$E106 -> 121.275 | DJ106: =$DJ$21 -> 280 | DK106: =1/176 -> 0.0056818182 | DL106: =DK106*DJ106*$E106 -> 404.25 | DM106: =$DM$21 -> 168 | DN106: =1/176 -> 0.0056818182 | DO106: =DN106*DM106*$E106 -> 242.55 | DS106: =($H$3*H106+$K$3*K106+$N$3*N106+$Q$3*Q106+$T$3*T106+$W$3*W106+$Z$3*Z106+$AC$3*AC106+$AF$3*AF106+$AI$3*AI106+$AL$3*AL106+$AO$3*AO106+$AR$3*AR106+$AU$3*AU106+$AX$3*AX106+$BA$3*BA106+$BD$3*BD106+$BG$3*BG106+$BJ$3*BJ106+$BM$3*BM106+$BP$3*BP106+$BS$3*BS106+$BV$3*BV106+$BY$3*BY106+$CB$3*CB106+$CE$3*CE106+$CH$3*CH106+$CK$3*CK106+$CN$3*CN106+$CQ$3*CQ106+$CT$3*CT106+$CW$3*CW106+$CZ$3*CZ106+$DC$3*DC106+$DF$3*DF106+$DI$3*DI106+$DL$3*DL106+$DO$3*DO106) -> 7459.0911 | DT106: =DS106/$DS$130 -> 0.015082052
B107: O05 | C107: Cesta básica | D107: Vb/mês | E107: 326.13 | F107: =G21 -> 11 | G107: =$G$4/22 -> 0.90909091 | H107: =G107*F107*$E107 -> 3261.3 | I107: =J21 -> 11 | J107: =J$4/22 -> 0.45454545 | K107: =J107*I107*$E107 -> 1630.65 | N107: =M107*L107*$E107 -> 0 | Q107: =P107*O107*$E107 -> 0 | T107: =S107*R107*$E107 -> 0 | W107: =V107*U107*$E107 -> 0 | Z107: =Y107*X107*$E107 -> 0 | AC107: =AB107*AA107*$E107 -> 0 | AF107: =AE107*AD107*$E107 -> 0 | AI107: =AH107*AG107*$E107 -> 0 | AL107: =AK107*AJ107*$E107 -> 0 | AO107: =AN107*AM107*$E107 -> 0 | AR107: =AQ107*AP107*$E107 -> 0 | AU107: =AT107*AS107*$E107 -> 0 | AX107: =AW107*AV107*$E107 -> 0 | BA107: =AZ107*AY107*$E107 -> 0 | BD107: =BC107*BB107*$E107 -> 0 | BG107: =BF107*BE107*$E107 -> 0 | BH107: =$BH$21 -> 0.36 | BI107: =1/176 -> 0.0056818182 | BJ107: =BI107*BH107*$E107 -> 0.66708409 | BK107: =$BK$21 -> 3.78 | BL107: =1/176 -> 0.0056818182 | BM107: =BL107*BK107*$E107 -> 7.004383 | BN107: =$BN$21 -> 176.45 | BO107: =1/176 -> 0.0056818182 | BP107: =BO107*BN107*$E107 -> 326.96386 | BQ107: =$BQ$21 -> 528 | BR107: =1/176 -> 0.0056818182 | BS107: =BR107*BQ107*$E107 -> 978.39 | BT107: =$BT$21 -> 24 | BU107: =1/176 -> 0.0056818182 | BV107: =BU107*BT107*$E107 -> 44.472273 | BW107: =$BW$21 -> 15.36 | BX107: =1/176 -> 0.0056818182 | BY107: =BX107*BW107*$E107 -> 28.462255 | BZ107: =$BZ$21 -> 26.88 | CA107: =1/176 -> 0.0056818182 | CB107: =CA107*BZ107*$E107 -> 49.808945 | CC107: =$CC$21 -> 4.8 | CD107: =1/176 -> 0.0056818182 | CE107: =CD107*CC107*$E107 -> 8.8944545 | CF107: =$CF$21 -> 7.2 | CG107: =1/176 -> 0.0056818182 | CH107: =CG107*CF107*$E107 -> 13.341682 | CI107: =$CI$21 -> 2.4 | CJ107: =1/176 -> 0.0056818182 | CK107: =CJ107*CI107*$E107 -> 4.4472273 | CL107: =$CL$21 -> 414.4 | CM107: =1/176 -> 0.0056818182 | CN107: =CM107*CL107*$E107 -> 767.88791 | CO107: =$CO$21 -> 168 | CP107: =1/176 -> 0.0056818182 | CQ107: =CP107*CO107*$E107 -> 311.30591 | CT107: =CS107*CR107*$E107 -> 0 | CW107: =CV107*CU107*$E107 -> 0 | CZ107: =CY107*CX107*$E107 -> 0 | DC107: =DB107*DA107*$E107 -> 0 | DD107: =$DD$21 -> 112 | DE107: =1/176 -> 0.0056818182 | DF107: =DE107*DD107*$E107 -> 207.53727 | DG107: =$DG$21 -> 84 | DH107: =1/176 -> 0.0056818182 | DI107: =DH107*DG107*$E107 -> 155.65295 | DJ107: =$DJ$21 -> 280 | DK107: =1/176 -> 0.0056818182 | DL107: =DK107*DJ107*$E107 -> 518.84318 | DM107: =$DM$21 -> 168 | DN107: =1/176 -> 0.0056818182 | DO107: =DN107*DM107*$E107 -> 311.30591 | DS107: =($H$3*H107+$K$3*K107+$N$3*N107+$Q$3*Q107+$T$3*T107+$W$3*W107+$Z$3*Z107+$AC$3*AC107+$AF$3*AF107+$AI$3*AI107+$AL$3*AL107+$AO$3*AO107+$AR$3*AR107+$AU$3*AU107+$AX$3*AX107+$BA$3*BA107+$BD$3*BD107+$BG$3*BG107+$BJ$3*BJ107+$BM$3*BM107+$BP$3*BP107+$BS$3*BS107+$BV$3*BV107+$BY$3*BY107+$CB$3*CB107+$CE$3*CE107+$CH$3*CH107+$CK$3*CK107+$CN$3*CN107+$CQ$3*CQ107+$CT$3*CT107+$CW$3*CW107+$CZ$3*CZ107+$DC$3*DC107+$DF$3*DF107+$DI$3*DI107+$DL$3*DL107+$DO$3*DO107) -> 9573.5276 | DT107: =DS107/$DS$130 -> 0.019357378
B108: O06 | C108: Seguro profissional | D108: Vb/mês | E108: 12.55 | F108: =G21 -> 11 | G108: =$G$4/22 -> 0.90909091 | H108: =G108*F108*$E108 -> 125.5 | I108: =J21 -> 11 | J108: =J$4/22 -> 0.45454545 | K108: =J108*I108*$E108 -> 62.75 | N108: =M108*L108*$E108 -> 0 | Q108: =P108*O108*$E108 -> 0 | T108: =S108*R108*$E108 -> 0 | W108: =V108*U108*$E108 -> 0 | Z108: =Y108*X108*$E108 -> 0 | AC108: =AB108*AA108*$E108 -> 0 | AF108: =AE108*AD108*$E108 -> 0 | AI108: =AH108*AG108*$E108 -> 0 | AL108: =AK108*AJ108*$E108 -> 0 | AO108: =AN108*AM108*$E108 -> 0 | AR108: =AQ108*AP108*$E108 -> 0 | AU108: =AT108*AS108*$E108 -> 0 | AX108: =AW108*AV108*$E108 -> 0 | BA108: =AZ108*AY108*$E108 -> 0 | BD108: =BC108*BB108*$E108 -> 0 | BG108: =BF108*BE108*$E108 -> 0 | BH108: =$BH$21 -> 0.36 | BI108: =1/176 -> 0.0056818182 | BJ108: =BI108*BH108*$E108 -> 0.025670455 | BK108: =$BK$21 -> 3.78 | BL108: =1/176 -> 0.0056818182 | BM108: =BL108*BK108*$E108 -> 0.26953977 | BN108: =$BN$21 -> 176.45 | BO108: =1/176 -> 0.0056818182 | BP108: =BO108*BN108*$E108 -> 12.582088 | BQ108: =$BQ$21 -> 528 | BR108: =1/176 -> 0.0056818182 | BS108: =BR108*BQ108*$E108 -> 37.65 | BT108: =$BT$21 -> 24 | BU108: =1/176 -> 0.0056818182 | BV108: =BU108*BT108*$E108 -> 1.7113636 | BW108: =$BW$21 -> 15.36 | BX108: =1/176 -> 0.0056818182 | BY108: =BX108*BW108*$E108 -> 1.0952727 | BZ108: =$BZ$21 -> 26.88 | CA108: =1/176 -> 0.0056818182 | CB108: =CA108*BZ108*$E108 -> 1.9167273 | CC108: =$CC$21 -> 4.8 | CD108: =1/176 -> 0.0056818182 | CE108: =CD108*CC108*$E108 -> 0.34227273 | CF108: =$CF$21 -> 7.2 | CG108: =1/176 -> 0.0056818182 | CH108: =CG108*CF108*$E108 -> 0.51340909 | CI108: =$CI$21 -> 2.4 | CJ108: =1/176 -> 0.0056818182 | CK108: =CJ108*CI108*$E108 -> 0.17113636 | CL108: =$CL$21 -> 414.4 | CM108: =1/176 -> 0.0056818182 | CN108: =CM108*CL108*$E108 -> 29.549545 | CO108: =$CO$21 -> 168 | CP108: =1/176 -> 0.0056818182 | CQ108: =CP108*CO108*$E108 -> 11.979545 | CT108: =CS108*CR108*$E108 -> 0 | CW108: =CV108*CU108*$E108 -> 0 | CZ108: =CY108*CX108*$E108 -> 0 | DC108: =DB108*DA108*$E108 -> 0 | DD108: =$DD$21 -> 112 | DE108: =1/176 -> 0.0056818182 | DF108: =DE108*DD108*$E108 -> 7.9863636 | DG108: =$DG$21 -> 84 | DH108: =1/176 -> 0.0056818182 | DI108: =DH108*DG108*$E108 -> 5.9897727 | DJ108: =$DJ$21 -> 280 | DK108: =1/176 -> 0.0056818182 | DL108: =DK108*DJ108*$E108 -> 19.965909 | DM108: =$DM$21 -> 168 | DN108: =1/176 -> 0.0056818182 | DO108: =DN108*DM108*$E108 -> 11.979545 | DS108: =($H$3*H108+$K$3*K108+$N$3*N108+$Q$3*Q108+$T$3*T108+$W$3*W108+$Z$3*Z108+$AC$3*AC108+$AF$3*AF108+$AI$3*AI108+$AL$3*AL108+$AO$3*AO108+$AR$3*AR108+$AU$3*AU108+$AX$3*AX108+$BA$3*BA108+$BD$3*BD108+$BG$3*BG108+$BJ$3*BJ108+$BM$3*BM108+$BP$3*BP108+$BS$3*BS108+$BV$3*BV108+$BY$3*BY108+$CB$3*CB108+$CE$3*CE108+$CH$3*CH108+$CK$3*CK108+$CN$3*CN108+$CQ$3*CQ108+$CT$3*CT108+$CW$3*CW108+$CZ$3*CZ108+$DC$3*DC108+$DF$3*DF108+$DI$3*DI108+$DL$3*DL108+$DO$3*DO108) -> 368.40454 | DT108: =DS108/$DS$130 -> 0.00074490261
B109: O07 | C109: Alimentação - Café da manhã | D109: Vb/mês | E109: 121 | F109: =G21 -> 11 | G109: =$G$4/22 -> 0.90909091 | H109: =G109*F109*$E109 -> 1210 | I109: =J21 -> 11 | J109: =J$4/22 -> 0.45454545 | K109: =J109*I109*$E109 -> 605 | N109: =M109*L109*$E109 -> 0 | Q109: =P109*O109*$E109 -> 0 | T109: =S109*R109*$E109 -> 0 | W109: =V109*U109*$E109 -> 0 | Z109: =Y109*X109*$E109 -> 0 | AC109: =AB109*AA109*$E109 -> 0 | AF109: =AE109*AD109*$E109 -> 0 | AI109: =AH109*AG109*$E109 -> 0 | AL109: =AK109*AJ109*$E109 -> 0 | AO109: =AN109*AM109*$E109 -> 0 | AR109: =AQ109*AP109*$E109 -> 0 | AU109: =AT109*AS109*$E109 -> 0 | AX109: =AW109*AV109*$E109 -> 0 | BA109: =AZ109*AY109*$E109 -> 0 | BD109: =BC109*BB109*$E109 -> 0 | BG109: =BF109*BE109*$E109 -> 0 | BH109: =$BH$21 -> 0.36 | BI109: =1/176 -> 0.0056818182 | BJ109: =BI109*BH109*$E109 -> 0.2475 | BK109: =$BK$21 -> 3.78 | BL109: =1/176 -> 0.0056818182 | BM109: =BL109*BK109*$E109 -> 2.59875 | BN109: =$BN$21 -> 176.45 | BO109: =1/176 -> 0.0056818182 | BP109: =BO109*BN109*$E109 -> 121.30937 | BQ109: =$BQ$21 -> 528 | BR109: =1/176 -> 0.0056818182 | BS109: =BR109*BQ109*$E109 -> 363 | BT109: =$BT$21 -> 24 | BU109: =1/176 -> 0.0056818182 | BV109: =BU109*BT109*$E109 -> 16.5 | BW109: =$BW$21 -> 15.36 | BX109: =1/176 -> 0.0056818182 | BY109: =BX109*BW109*$E109 -> 10.56 | BZ109: =$BZ$21 -> 26.88 | CA109: =1/176 -> 0.0056818182 | CB109: =CA109*BZ109*$E109 -> 18.48 | CC109: =$CC$21 -> 4.8 | CD109: =1/176 -> 0.0056818182 | CE109: =CD109*CC109*$E109 -> 3.3 | CF109: =$CF$21 -> 7.2 | CG109: =1/176 -> 0.0056818182 | CH109: =CG109*CF109*$E109 -> 4.95 | CI109: =$CI$21 -> 2.4 | CJ109: =1/176 -> 0.0056818182 | CK109: =CJ109*CI109*$E109 -> 1.65 | CL109: =$CL$21 -> 414.4 | CM109: =1/176 -> 0.0056818182 | CN109: =CM109*CL109*$E109 -> 284.9 | CO109: =$CO$21 -> 168 | CP109: =1/176 -> 0.0056818182 | CQ109: =CP109*CO109*$E109 -> 115.5 | CT109: =CS109*CR109*$E109 -> 0 | CW109: =CV109*CU109*$E109 -> 0 | CZ109: =CY109*CX109*$E109 -> 0 | DC109: =DB109*DA109*$E109 -> 0 | DD109: =$DD$21 -> 112 | DE109: =1/176 -> 0.0056818182 | DF109: =DE109*DD109*$E109 -> 77 | DG109: =$DG$21 -> 84 | DH109: =1/176 -> 0.0056818182 | DI109: =DH109*DG109*$E109 -> 57.75 | DJ109: =$DJ$21 -> 280 | DK109: =1/176 -> 0.0056818182 | DL109: =DK109*DJ109*$E109 -> 192.5 | DM109: =$DM$21 -> 168 | DN109: =1/176 -> 0.0056818182 | DO109: =DN109*DM109*$E109 -> 115.5 | DS109: =($H$3*H109+$K$3*K109+$N$3*N109+$Q$3*Q109+$T$3*T109+$W$3*W109+$Z$3*Z109+$AC$3*AC109+$AF$3*AF109+$AI$3*AI109+$AL$3*AL109+$AO$3*AO109+$AR$3*AR109+$AU$3*AU109+$AX$3*AX109+$BA$3*BA109+$BD$3*BD109+$BG$3*BG109+$BJ$3*BJ109+$BM$3*BM109+$BP$3*BP109+$BS$3*BS109+$BV$3*BV109+$BY$3*BY109+$CB$3*CB109+$CE$3*CE109+$CH$3*CH109+$CK$3*CK109+$CN$3*CN109+$CQ$3*CQ109+$CT$3*CT109+$CW$3*CW109+$CZ$3*CZ109+$DC$3*DC109+$DF$3*DF109+$DI$3*DI109+$DL$3*DL109+$DO$3*DO109) -> 3551.9481 | DT109: =DS109/$DS$130 -> 0.0071819295
B110: O08 | C110: Alimentação - Almoço | D110: Vb/mês | E110: 440 | F110: =G21 -> 11 | G110: =$G$4/22 -> 0.90909091 | H110: =G110*F110*$E110 -> 4400 | I110: =J21 -> 11 | J110: =J$4/22 -> 0.45454545 | K110: =J110*I110*$E110 -> 2200 | N110: =M110*L110*$E110 -> 0 | Q110: =P110*O110*$E110 -> 0 | T110: =S110*R110*$E110 -> 0 | W110: =V110*U110*$E110 -> 0 | Z110: =Y110*X110*$E110 -> 0 | AC110: =AB110*AA110*$E110 -> 0 | AF110: =AE110*AD110*$E110 -> 0 | AI110: =AH110*AG110*$E110 -> 0 | AL110: =AK110*AJ110*$E110 -> 0 | AO110: =AN110*AM110*$E110 -> 0 | AR110: =AQ110*AP110*$E110 -> 0 | AU110: =AT110*AS110*$E110 -> 0 | AX110: =AW110*AV110*$E110 -> 0 | BA110: =AZ110*AY110*$E110 -> 0 | BD110: =BC110*BB110*$E110 -> 0 | BG110: =BF110*BE110*$E110 -> 0 | BH110: =$BH$21 -> 0.36 | BI110: =1/176 -> 0.0056818182 | BJ110: =BI110*BH110*$E110 -> 0.9 | BK110: =$BK$21 -> 3.78 | BL110: =1/176 -> 0.0056818182 | BM110: =BL110*BK110*$E110 -> 9.45 | BN110: =$BN$21 -> 176.45 | BO110: =1/176 -> 0.0056818182 | BP110: =BO110*BN110*$E110 -> 441.125 | BQ110: =$BQ$21 -> 528 | BR110: =1/176 -> 0.0056818182 | BS110: =BR110*BQ110*$E110 -> 1320 | BT110: =$BT$21 -> 24 | BU110: =1/176 -> 0.0056818182 | BV110: =BU110*BT110*$E110 -> 60 | BW110: =$BW$21 -> 15.36 | BX110: =1/176 -> 0.0056818182 | BY110: =BX110*BW110*$E110 -> 38.4 | BZ110: =$BZ$21 -> 26.88 | CA110: =1/176 -> 0.0056818182 | CB110: =CA110*BZ110*$E110 -> 67.2 | CC110: =$CC$21 -> 4.8 | CD110: =1/176 -> 0.0056818182 | CE110: =CD110*CC110*$E110 -> 12 | CF110: =$CF$21 -> 7.2 | CG110: =1/176 -> 0.0056818182 | CH110: =CG110*CF110*$E110 -> 18 | CI110: =$CI$21 -> 2.4 | CJ110: =1/176 -> 0.0056818182 | CK110: =CJ110*CI110*$E110 -> 6 | CL110: =$CL$21 -> 414.4 | CM110: =1/176 -> 0.0056818182 | CN110: =CM110*CL110*$E110 -> 1036 | CO110: =$CO$21 -> 168 | CP110: =1/176 -> 0.0056818182 | CQ110: =CP110*CO110*$E110 -> 420 | CT110: =CS110*CR110*$E110 -> 0 | CW110: =CV110*CU110*$E110 -> 0 | CZ110: =CY110*CX110*$E110 -> 0 | DC110: =DB110*DA110*$E110 -> 0 | DD110: =$DD$21 -> 112 | DE110: =1/176 -> 0.0056818182 | DF110: =DE110*DD110*$E110 -> 280 | DG110: =$DG$21 -> 84 | DH110: =1/176 -> 0.0056818182 | DI110: =DH110*DG110*$E110 -> 210 | DJ110: =$DJ$21 -> 280 | DK110: =1/176 -> 0.0056818182 | DL110: =DK110*DJ110*$E110 -> 700 | DM110: =$DM$21 -> 168 | DN110: =1/176 -> 0.0056818182 | DO110: =DN110*DM110*$E110 -> 420 | DS110: =($H$3*H110+$K$3*K110+$N$3*N110+$Q$3*Q110+$T$3*T110+$W$3*W110+$Z$3*Z110+$AC$3*AC110+$AF$3*AF110+$AI$3*AI110+$AL$3*AL110+$AO$3*AO110+$AR$3*AR110+$AU$3*AU110+$AX$3*AX110+$BA$3*BA110+$BD$3*BD110+$BG$3*BG110+$BJ$3*BJ110+$BM$3*BM110+$BP$3*BP110+$BS$3*BS110+$BV$3*BV110+$BY$3*BY110+$CB$3*CB110+$CE$3*CE110+$CH$3*CH110+$CK$3*CK110+$CN$3*CN110+$CQ$3*CQ110+$CT$3*CT110+$CW$3*CW110+$CZ$3*CZ110+$DC$3*DC110+$DF$3*DF110+$DI$3*DI110+$DL$3*DL110+$DO$3*DO110) -> 12916.175 | DT110: =DS110/$DS$130 -> 0.026116107
B111: O09 | C111: Ferramentas para mão de obra | D111: Vb/mês | E111: 115.2 | F111: =G21 -> 11 | G111: =$G$4/22 -> 0.90909091 | H111: =G111*F111*$E111 -> 1152 | I111: =J21 -> 11 | J111: =J$4/22 -> 0.45454545 | K111: =J111*I111*$E111 -> 576 | N111: =M111*L111*$E111 -> 0 | Q111: =P111*O111*$E111 -> 0 | T111: =S111*R111*$E111 -> 0 | W111: =V111*U111*$E111 -> 0 | Z111: =Y111*X111*$E111 -> 0 | AC111: =AB111*AA111*$E111 -> 0 | AF111: =AE111*AD111*$E111 -> 0 | AI111: =AH111*AG111*$E111 -> 0 | AL111: =AK111*AJ111*$E111 -> 0 | AO111: =AN111*AM111*$E111 -> 0 | AR111: =AQ111*AP111*$E111 -> 0 | AU111: =AT111*AS111*$E111 -> 0 | AX111: =AW111*AV111*$E111 -> 0 | BA111: =AZ111*AY111*$E111 -> 0 | BD111: =BC111*BB111*$E111 -> 0 | BG111: =BF111*BE111*$E111 -> 0 | BH111: =$BH$21 -> 0.36 | BI111: =1/176 -> 0.0056818182 | BJ111: =BI111*BH111*$E111 -> 0.23563636 | BK111: =$BK$21 -> 3.78 | BL111: =1/176 -> 0.0056818182 | BM111: =BL111*BK111*$E111 -> 2.4741818 | BN111: =$BN$21 -> 176.45 | BO111: =1/176 -> 0.0056818182 | BP111: =BO111*BN111*$E111 -> 115.49455 | BQ111: =$BQ$21 -> 528 | BR111: =1/176 -> 0.0056818182 | BS111: =BR111*BQ111*$E111 -> 345.6 | BT111: =$BT$21 -> 24 | BU111: =1/176 -> 0.0056818182 | BV111: =BU111*BT111*$E111 -> 15.709091 | BW111: =$BW$21 -> 15.36 | BX111: =1/176 -> 0.0056818182 | BY111: =BX111*BW111*$E111 -> 10.053818 | BZ111: =$BZ$21 -> 26.88 | CA111: =1/176 -> 0.0056818182 | CB111: =CA111*BZ111*$E111 -> 17.594182 | CC111: =$CC$21 -> 4.8 | CD111: =1/176 -> 0.0056818182 | CE111: =CD111*CC111*$E111 -> 3.1418182 | CF111: =$CF$21 -> 7.2 | CG111: =1/176 -> 0.0056818182 | CH111: =CG111*CF111*$E111 -> 4.7127273 | CI111: =$CI$21 -> 2.4 | CJ111: =1/176 -> 0.0056818182 | CK111: =CJ111*CI111*$E111 -> 1.5709091 | CL111: =$CL$21 -> 414.4 | CM111: =1/176 -> 0.0056818182 | CN111: =CM111*CL111*$E111 -> 271.24364 | CO111: =$CO$21 -> 168 | CP111: =1/176 -> 0.0056818182 | CQ111: =CP111*CO111*$E111 -> 109.96364 | CT111: =CS111*CR111*$E111 -> 0 | CW111: =CV111*CU111*$E111 -> 0 | CZ111: =CY111*CX111*$E111 -> 0 | DC111: =DB111*DA111*$E111 -> 0 | DD111: =$DD$21 -> 112 | DE111: =1/176 -> 0.0056818182 | DF111: =DE111*DD111*$E111 -> 73.309091 | DG111: =$DG$21 -> 84 | DH111: =1/176 -> 0.0056818182 | DI111: =DH111*DG111*$E111 -> 54.981818 | DJ111: =$DJ$21 -> 280 | DK111: =1/176 -> 0.0056818182 | DL111: =DK111*DJ111*$E111 -> 183.27273 | DM111: =$DM$21 -> 168 | DN111: =1/176 -> 0.0056818182 | DO111: =DN111*DM111*$E111 -> 109.96364 | DS111: =($H$3*H111+$K$3*K111+$N$3*N111+$Q$3*Q111+$T$3*T111+$W$3*W111+$Z$3*Z111+$AC$3*AC111+$AF$3*AF111+$AI$3*AI111+$AL$3*AL111+$AO$3*AO111+$AR$3*AR111+$AU$3*AU111+$AX$3*AX111+$BA$3*BA111+$BD$3*BD111+$BG$3*BG111+$BJ$3*BJ111+$BM$3*BM111+$BP$3*BP111+$BS$3*BS111+$BV$3*BV111+$BY$3*BY111+$CB$3*CB111+$CE$3*CE111+$CH$3*CH111+$CK$3*CK111+$CN$3*CN111+$CQ$3*CQ111+$CT$3*CT111+$CW$3*CW111+$CZ$3*CZ111+$DC$3*DC111+$DF$3*DF111+$DI$3*DI111+$DL$3*DL111+$DO$3*DO111) -> 3381.6895 | DT111: =DS111/$DS$130 -> 0.0068376718
B112: O10 | C112: Combustível G/D | D112: L | E112: 6.8 | H112: =G112*F112*$E112 -> 0 | K112: =J112*I112*$E112 -> 0 | N112: =M112*L112*$E112 -> 0 | Q112: =P112*O112*$E112 -> 0 | T112: =S112*R112*$E112 -> 0 | W112: =V112*U112*$E112 -> 0 | Z112: =Y112*X112*$E112 -> 0 | AC112: =AB112*AA112*$E112 -> 0 | AF112: =AE112*AD112*$E112 -> 0 | AI112: =AH112*AG112*$E112 -> 0 | AL112: =AK112*AJ112*$E112 -> 0 | AO112: =AN112*AM112*$E112 -> 0 | AR112: =AQ112*AP112*$E112 -> 0 | AU112: =AT112*AS112*$E112 -> 0 | AX112: =AW112*AV112*$E112 -> 0 | BA112: =AZ112*AY112*$E112 -> 0 | BD112: =BC112*BB112*$E112 -> 0 | BG112: =BF112*BE112*$E112 -> 0 | BJ112: =BI112*BH112*$E112 -> 0 | BM112: =BL112*BK112*$E112 -> 0 | BP112: =BO112*BN112*$E112 -> 0 | BS112: =BR112*BQ112*$E112 -> 0 | BV112: =BU112*BT112*$E112 -> 0 | BY112: =BX112*BW112*$E112 -> 0 | CB112: =CA112*BZ112*$E112 -> 0 | CE112: =CD112*CC112*$E112 -> 0 | CH112: =CG112*CF112*$E112 -> 0 | CK112: =CJ112*CI112*$E112 -> 0 | CN112: =CM112*CL112*$E112 -> 0 | CQ112: =CP112*CO112*$E112 -> 0 | CT112: =CS112*CR112*$E112 -> 0 | CW112: =CV112*CU112*$E112 -> 0 | CZ112: =CY112*CX112*$E112 -> 0 | DC112: =DB112*DA112*$E112 -> 0 | DF112: =DE112*DD112*$E112 -> 0 | DI112: =DH112*DG112*$E112 -> 0 | DL112: =DK112*DJ112*$E112 -> 0 | DO112: =DN112*DM112*$E112 -> 0 | DS112: =($H$3*H112+$K$3*K112+$N$3*N112+$Q$3*Q112+$T$3*T112+$W$3*W112+$Z$3*Z112+$AC$3*AC112+$AF$3*AF112+$AI$3*AI112+$AL$3*AL112+$AO$3*AO112+$AR$3*AR112+$AU$3*AU112+$AX$3*AX112+$BA$3*BA112+$BD$3*BD112+$BG$3*BG112+$BJ$3*BJ112+$BM$3*BM112+$BP$3*BP112+$BS$3*BS112+$BV$3*BV112+$BY$3*BY112+$CB$3*CB112+$CE$3*CE112+$CH$3*CH112+$CK$3*CK112+$CN$3*CN112+$CQ$3*CQ112+$CT$3*CT112+$CW$3*CW112+$CZ$3*CZ112+$DC$3*DC112+$DF$3*DF112+$DI$3*DI112+$DL$3*DL112+$DO$3*DO112) -> 0 | DT112: =DS112/$DS$130 -> 0
B113: O11 | C113: Água mineral | D113: L | E113: 1.05 | H113: =G113*F113*$E113 -> 0 | K113: =J113*I113*$E113 -> 0 | N113: =M113*L113*$E113 -> 0 | Q113: =P113*O113*$E113 -> 0 | T113: =S113*R113*$E113 -> 0 | W113: =V113*U113*$E113 -> 0 | Z113: =Y113*X113*$E113 -> 0 | AC113: =AB113*AA113*$E113 -> 0 | AF113: =AE113*AD113*$E113 -> 0 | AI113: =AH113*AG113*$E113 -> 0 | AL113: =AK113*AJ113*$E113 -> 0 | AO113: =AN113*AM113*$E113 -> 0 | AR113: =AQ113*AP113*$E113 -> 0 | AU113: =AT113*AS113*$E113 -> 0 | AX113: =AW113*AV113*$E113 -> 0 | BA113: =AZ113*AY113*$E113 -> 0 | BD113: =BC113*BB113*$E113 -> 0 | BG113: =BF113*BE113*$E113 -> 0 | BJ113: =BI113*BH113*$E113 -> 0 | BM113: =BL113*BK113*$E113 -> 0 | BP113: =BO113*BN113*$E113 -> 0 | BS113: =BR113*BQ113*$E113 -> 0 | BV113: =BU113*BT113*$E113 -> 0 | BY113: =BX113*BW113*$E113 -> 0 | CB113: =CA113*BZ113*$E113 -> 0 | CE113: =CD113*CC113*$E113 -> 0 | CH113: =CG113*CF113*$E113 -> 0 | CK113: =CJ113*CI113*$E113 -> 0 | CN113: =CM113*CL113*$E113 -> 0 | CQ113: =CP113*CO113*$E113 -> 0 | CT113: =CS113*CR113*$E113 -> 0 | CW113: =CV113*CU113*$E113 -> 0 | CZ113: =CY113*CX113*$E113 -> 0 | DC113: =DB113*DA113*$E113 -> 0 | DF113: =DE113*DD113*$E113 -> 0 | DI113: =DH113*DG113*$E113 -> 0 | DL113: =DK113*DJ113*$E113 -> 0 | DO113: =DN113*DM113*$E113 -> 0 | DS113: =($H$3*H113+$K$3*K113+$N$3*N113+$Q$3*Q113+$T$3*T113+$W$3*W113+$Z$3*Z113+$AC$3*AC113+$AF$3*AF113+$AI$3*AI113+$AL$3*AL113+$AO$3*AO113+$AR$3*AR113+$AU$3*AU113+$AX$3*AX113+$BA$3*BA113+$BD$3*BD113+$BG$3*BG113+$BJ$3*BJ113+$BM$3*BM113+$BP$3*BP113+$BS$3*BS113+$BV$3*BV113+$BY$3*BY113+$CB$3*CB113+$CE$3*CE113+$CH$3*CH113+$CK$3*CK113+$CN$3*CN113+$CQ$3*CQ113+$CT$3*CT113+$CW$3*CW113+$CZ$3*CZ113+$DC$3*DC113+$DF$3*DF113+$DI$3*DI113+$DL$3*DL113+$DO$3*DO113) -> 0 | DT113: =DS113/$DS$130 -> 0
B114: O12 | C114: Gelo seco | D114: pct | E114: 25.6 | H114: =G114*F114*$E114 -> 0 | K114: =J114*I114*$E114 -> 0 | N114: =M114*L114*$E114 -> 0 | Q114: =P114*O114*$E114 -> 0 | T114: =S114*R114*$E114 -> 0 | W114: =V114*U114*$E114 -> 0 | Z114: =Y114*X114*$E114 -> 0 | AC114: =AB114*AA114*$E114 -> 0 | AF114: =AE114*AD114*$E114 -> 0 | AI114: =AH114*AG114*$E114 -> 0 | AL114: =AK114*AJ114*$E114 -> 0 | AO114: =AN114*AM114*$E114 -> 0 | AR114: =AQ114*AP114*$E114 -> 0 | AU114: =AT114*AS114*$E114 -> 0 | AX114: =AW114*AV114*$E114 -> 0 | BA114: =AZ114*AY114*$E114 -> 0 | BD114: =BC114*BB114*$E114 -> 0 | BG114: =BF114*BE114*$E114 -> 0 | BJ114: =BI114*BH114*$E114 -> 0 | BM114: =BL114*BK114*$E114 -> 0 | BP114: =BO114*BN114*$E114 -> 0 | BS114: =BR114*BQ114*$E114 -> 0 | BV114: =BU114*BT114*$E114 -> 0 | BY114: =BX114*BW114*$E114 -> 0 | CB114: =CA114*BZ114*$E114 -> 0 | CE114: =CD114*CC114*$E114 -> 0 | CH114: =CG114*CF114*$E114 -> 0 | CK114: =CJ114*CI114*$E114 -> 0 | CN114: =CM114*CL114*$E114 -> 0 | CQ114: =CP114*CO114*$E114 -> 0 | CT114: =CS114*CR114*$E114 -> 0 | CW114: =CV114*CU114*$E114 -> 0 | CZ114: =CY114*CX114*$E114 -> 0 | DC114: =DB114*DA114*$E114 -> 0 | DF114: =DE114*DD114*$E114 -> 0 | DI114: =DH114*DG114*$E114 -> 0 | DL114: =DK114*DJ114*$E114 -> 0 | DO114: =DN114*DM114*$E114 -> 0 | DS114: =($H$3*H114+$K$3*K114+$N$3*N114+$Q$3*Q114+$T$3*T114+$W$3*W114+$Z$3*Z114+$AC$3*AC114+$AF$3*AF114+$AI$3*AI114+$AL$3*AL114+$AO$3*AO114+$AR$3*AR114+$AU$3*AU114+$AX$3*AX114+$BA$3*BA114+$BD$3*BD114+$BG$3*BG114+$BJ$3*BJ114+$BM$3*BM114+$BP$3*BP114+$BS$3*BS114+$BV$3*BV114+$BY$3*BY114+$CB$3*CB114+$CE$3*CE114+$CH$3*CH114+$CK$3*CK114+$CN$3*CN114+$CQ$3*CQ114+$CT$3*CT114+$CW$3*CW114+$CZ$3*CZ114+$DC$3*DC114+$DF$3*DF114+$DI$3*DI114+$DL$3*DL114+$DO$3*DO114) -> 0 | DT114: =DS114/$DS$130 -> 0
B115: O13 | C115: Garrafa térmica | D115: und | E115: 220 | H115: =G115*F115*$E115 -> 0 | K115: =J115*I115*$E115 -> 0 | N115: =M115*L115*$E115 -> 0 | Q115: =P115*O115*$E115 -> 0 | T115: =S115*R115*$E115 -> 0 | W115: =V115*U115*$E115 -> 0 | Z115: =Y115*X115*$E115 -> 0 | AC115: =AB115*AA115*$E115 -> 0 | AF115: =AE115*AD115*$E115 -> 0 | AI115: =AH115*AG115*$E115 -> 0 | AL115: =AK115*AJ115*$E115 -> 0 | AO115: =AN115*AM115*$E115 -> 0 | AR115: =AQ115*AP115*$E115 -> 0 | AU115: =AT115*AS115*$E115 -> 0 | AX115: =AW115*AV115*$E115 -> 0 | BA115: =AZ115*AY115*$E115 -> 0 | BD115: =BC115*BB115*$E115 -> 0 | BG115: =BF115*BE115*$E115 -> 0 | BJ115: =BI115*BH115*$E115 -> 0 | BM115: =BL115*BK115*$E115 -> 0 | BP115: =BO115*BN115*$E115 -> 0 | BS115: =BR115*BQ115*$E115 -> 0 | BV115: =BU115*BT115*$E115 -> 0 | BY115: =BX115*BW115*$E115 -> 0 | CB115: =CA115*BZ115*$E115 -> 0 | CE115: =CD115*CC115*$E115 -> 0 | CH115: =CG115*CF115*$E115 -> 0 | CK115: =CJ115*CI115*$E115 -> 0 | CN115: =CM115*CL115*$E115 -> 0 | CQ115: =CP115*CO115*$E115 -> 0 | CT115: =CS115*CR115*$E115 -> 0 | CW115: =CV115*CU115*$E115 -> 0 | CZ115: =CY115*CX115*$E115 -> 0 | DC115: =DB115*DA115*$E115 -> 0 | DF115: =DE115*DD115*$E115 -> 0 | DI115: =DH115*DG115*$E115 -> 0 | DL115: =DK115*DJ115*$E115 -> 0 | DO115: =DN115*DM115*$E115 -> 0 | DS115: =($H$3*H115+$K$3*K115+$N$3*N115+$Q$3*Q115+$T$3*T115+$W$3*W115+$Z$3*Z115+$AC$3*AC115+$AF$3*AF115+$AI$3*AI115+$AL$3*AL115+$AO$3*AO115+$AR$3*AR115+$AU$3*AU115+$AX$3*AX115+$BA$3*BA115+$BD$3*BD115+$BG$3*BG115+$BJ$3*BJ115+$BM$3*BM115+$BP$3*BP115+$BS$3*BS115+$BV$3*BV115+$BY$3*BY115+$CB$3*CB115+$CE$3*CE115+$CH$3*CH115+$CK$3*CK115+$CN$3*CN115+$CQ$3*CQ115+$CT$3*CT115+$CW$3*CW115+$CZ$3*CZ115+$DC$3*DC115+$DF$3*DF115+$DI$3*DI115+$DL$3*DL115+$DO$3*DO115) -> 0 | DT115: =DS115/$DS$130 -> 0
B116: O14 | H116: =G116*F116*$E116 -> 0 | K116: =J116*I116*$E116 -> 0 | N116: =M116*L116*$E116 -> 0 | Q116: =P116*O116*$E116 -> 0 | T116: =S116*R116*$E116 -> 0 | W116: =V116*U116*$E116 -> 0 | Z116: =Y116*X116*$E116 -> 0 | AC116: =AB116*AA116*$E116 -> 0 | AF116: =AE116*AD116*$E116 -> 0 | AI116: =AH116*AG116*$E116 -> 0 | AL116: =AK116*AJ116*$E116 -> 0 | AO116: =AN116*AM116*$E116 -> 0 | AR116: =AQ116*AP116*$E116 -> 0 | AU116: =AT116*AS116*$E116 -> 0 | AX116: =AW116*AV116*$E116 -> 0 | BA116: =AZ116*AY116*$E116 -> 0 | BD116: =BC116*BB116*$E116 -> 0 | BG116: =BF116*BE116*$E116 -> 0 | BJ116: =BI116*BH116*$E116 -> 0 | BM116: =BL116*BK116*$E116 -> 0 | BP116: =BO116*BN116*$E116 -> 0 | BS116: =BR116*BQ116*$E116 -> 0 | BV116: =BU116*BT116*$E116 -> 0 | BY116: =BX116*BW116*$E116 -> 0 | CB116: =CA116*BZ116*$E116 -> 0 | CE116: =CD116*CC116*$E116 -> 0 | CH116: =CG116*CF116*$E116 -> 0 | CK116: =CJ116*CI116*$E116 -> 0 | CN116: =CM116*CL116*$E116 -> 0 | CQ116: =CP116*CO116*$E116 -> 0 | CT116: =CS116*CR116*$E116 -> 0 | CW116: =CV116*CU116*$E116 -> 0 | CZ116: =CY116*CX116*$E116 -> 0 | DC116: =DB116*DA116*$E116 -> 0 | DF116: =DE116*DD116*$E116 -> 0 | DI116: =DH116*DG116*$E116 -> 0 | DL116: =DK116*DJ116*$E116 -> 0 | DO116: =DN116*DM116*$E116 -> 0 | DS116: =($H$3*H116+$K$3*K116+$N$3*N116+$Q$3*Q116+$T$3*T116+$W$3*W116+$Z$3*Z116+$AC$3*AC116+$AF$3*AF116+$AI$3*AI116+$AL$3*AL116+$AO$3*AO116+$AR$3*AR116+$AU$3*AU116+$AX$3*AX116+$BA$3*BA116+$BD$3*BD116+$BG$3*BG116+$BJ$3*BJ116+$BM$3*BM116+$BP$3*BP116+$BS$3*BS116+$BV$3*BV116+$BY$3*BY116+$CB$3*CB116+$CE$3*CE116+$CH$3*CH116+$CK$3*CK116+$CN$3*CN116+$CQ$3*CQ116+$CT$3*CT116+$CW$3*CW116+$CZ$3*CZ116+$DC$3*DC116+$DF$3*DF116+$DI$3*DI116+$DL$3*DL116+$DO$3*DO116) -> 0 | DT116: =DS116/$DS$130 -> 0
B117: O15 | H117: =G117*F117*$E117 -> 0 | K117: =J117*I117*$E117 -> 0 | N117: =M117*L117*$E117 -> 0 | Q117: =P117*O117*$E117 -> 0 | T117: =S117*R117*$E117 -> 0 | W117: =V117*U117*$E117 -> 0 | Z117: =Y117*X117*$E117 -> 0 | AC117: =AB117*AA117*$E117 -> 0 | AF117: =AE117*AD117*$E117 -> 0 | AI117: =AH117*AG117*$E117 -> 0 | AL117: =AK117*AJ117*$E117 -> 0 | AO117: =AN117*AM117*$E117 -> 0 | AR117: =AQ117*AP117*$E117 -> 0 | AU117: =AT117*AS117*$E117 -> 0 | AX117: =AW117*AV117*$E117 -> 0 | BA117: =AZ117*AY117*$E117 -> 0 | BD117: =BC117*BB117*$E117 -> 0 | BG117: =BF117*BE117*$E117 -> 0 | BJ117: =BI117*BH117*$E117 -> 0 | BM117: =BL117*BK117*$E117 -> 0 | BP117: =BO117*BN117*$E117 -> 0 | BS117: =BR117*BQ117*$E117 -> 0 | BV117: =BU117*BT117*$E117 -> 0 | BY117: =BX117*BW117*$E117 -> 0 | CB117: =CA117*BZ117*$E117 -> 0 | CE117: =CD117*CC117*$E117 -> 0 | CH117: =CG117*CF117*$E117 -> 0 | CK117: =CJ117*CI117*$E117 -> 0 | CN117: =CM117*CL117*$E117 -> 0 | CQ117: =CP117*CO117*$E117 -> 0 | CT117: =CS117*CR117*$E117 -> 0 | CW117: =CV117*CU117*$E117 -> 0 | CZ117: =CY117*CX117*$E117 -> 0 | DC117: =DB117*DA117*$E117 -> 0 | DF117: =DE117*DD117*$E117 -> 0 | DI117: =DH117*DG117*$E117 -> 0 | DL117: =DK117*DJ117*$E117 -> 0 | DO117: =DN117*DM117*$E117 -> 0 | DS117: =($H$3*H117+$K$3*K117+$N$3*N117+$Q$3*Q117+$T$3*T117+$W$3*W117+$Z$3*Z117+$AC$3*AC117+$AF$3*AF117+$AI$3*AI117+$AL$3*AL117+$AO$3*AO117+$AR$3*AR117+$AU$3*AU117+$AX$3*AX117+$BA$3*BA117+$BD$3*BD117+$BG$3*BG117+$BJ$3*BJ117+$BM$3*BM117+$BP$3*BP117+$BS$3*BS117+$BV$3*BV117+$BY$3*BY117+$CB$3*CB117+$CE$3*CE117+$CH$3*CH117+$CK$3*CK117+$CN$3*CN117+$CQ$3*CQ117+$CT$3*CT117+$CW$3*CW117+$CZ$3*CZ117+$DC$3*DC117+$DF$3*DF117+$DI$3*DI117+$DL$3*DL117+$DO$3*DO117) -> 0 | DT117: =DS117/$DS$130 -> 0
B118: O16 | H118: =G118*F118*$E118 -> 0 | K118: =J118*I118*$E118 -> 0 | N118: =M118*L118*$E118 -> 0 | Q118: =P118*O118*$E118 -> 0 | T118: =S118*R118*$E118 -> 0 | W118: =V118*U118*$E118 -> 0 | Z118: =Y118*X118*$E118 -> 0 | AC118: =AB118*AA118*$E118 -> 0 | AF118: =AE118*AD118*$E118 -> 0 | AI118: =AH118*AG118*$E118 -> 0 | AL118: =AK118*AJ118*$E118 -> 0 | AO118: =AN118*AM118*$E118 -> 0 | AR118: =AQ118*AP118*$E118 -> 0 | AU118: =AT118*AS118*$E118 -> 0 | AX118: =AW118*AV118*$E118 -> 0 | BA118: =AZ118*AY118*$E118 -> 0 | BD118: =BC118*BB118*$E118 -> 0 | BG118: =BF118*BE118*$E118 -> 0 | BJ118: =BI118*BH118*$E118 -> 0 | BM118: =BL118*BK118*$E118 -> 0 | BP118: =BO118*BN118*$E118 -> 0 | BS118: =BR118*BQ118*$E118 -> 0 | BV118: =BU118*BT118*$E118 -> 0 | BY118: =BX118*BW118*$E118 -> 0 | CB118: =CA118*BZ118*$E118 -> 0 | CE118: =CD118*CC118*$E118 -> 0 | CH118: =CG118*CF118*$E118 -> 0 | CK118: =CJ118*CI118*$E118 -> 0 | CN118: =CM118*CL118*$E118 -> 0 | CQ118: =CP118*CO118*$E118 -> 0 | CT118: =CS118*CR118*$E118 -> 0 | CW118: =CV118*CU118*$E118 -> 0 | CZ118: =CY118*CX118*$E118 -> 0 | DC118: =DB118*DA118*$E118 -> 0 | DF118: =DE118*DD118*$E118 -> 0 | DI118: =DH118*DG118*$E118 -> 0 | DL118: =DK118*DJ118*$E118 -> 0 | DO118: =DN118*DM118*$E118 -> 0 | DS118: =($H$3*H118+$K$3*K118+$N$3*N118+$Q$3*Q118+$T$3*T118+$W$3*W118+$Z$3*Z118+$AC$3*AC118+$AF$3*AF118+$AI$3*AI118+$AL$3*AL118+$AO$3*AO118+$AR$3*AR118+$AU$3*AU118+$AX$3*AX118+$BA$3*BA118+$BD$3*BD118+$BG$3*BG118+$BJ$3*BJ118+$BM$3*BM118+$BP$3*BP118+$BS$3*BS118+$BV$3*BV118+$BY$3*BY118+$CB$3*CB118+$CE$3*CE118+$CH$3*CH118+$CK$3*CK118+$CN$3*CN118+$CQ$3*CQ118+$CT$3*CT118+$CW$3*CW118+$CZ$3*CZ118+$DC$3*DC118+$DF$3*DF118+$DI$3*DI118+$DL$3*DL118+$DO$3*DO118) -> 0 | DT118: =DS118/$DS$130 -> 0
B119: O17 | H119: =G119*F119*$E119 -> 0 | K119: =J119*I119*$E119 -> 0 | N119: =M119*L119*$E119 -> 0 | Q119: =P119*O119*$E119 -> 0 | T119: =S119*R119*$E119 -> 0 | W119: =V119*U119*$E119 -> 0 | Z119: =Y119*X119*$E119 -> 0 | AC119: =AB119*AA119*$E119 -> 0 | AF119: =AE119*AD119*$E119 -> 0 | AI119: =AH119*AG119*$E119 -> 0 | AL119: =AK119*AJ119*$E119 -> 0 | AO119: =AN119*AM119*$E119 -> 0 | AR119: =AQ119*AP119*$E119 -> 0 | AU119: =AT119*AS119*$E119 -> 0 | AX119: =AW119*AV119*$E119 -> 0 | BA119: =AZ119*AY119*$E119 -> 0 | BD119: =BC119*BB119*$E119 -> 0 | BG119: =BF119*BE119*$E119 -> 0 | BJ119: =BI119*BH119*$E119 -> 0 | BM119: =BL119*BK119*$E119 -> 0 | BP119: =BO119*BN119*$E119 -> 0 | BS119: =BR119*BQ119*$E119 -> 0 | BV119: =BU119*BT119*$E119 -> 0 | BY119: =BX119*BW119*$E119 -> 0 | CB119: =CA119*BZ119*$E119 -> 0 | CE119: =CD119*CC119*$E119 -> 0 | CH119: =CG119*CF119*$E119 -> 0 | CK119: =CJ119*CI119*$E119 -> 0 | CN119: =CM119*CL119*$E119 -> 0 | CQ119: =CP119*CO119*$E119 -> 0 | CT119: =CS119*CR119*$E119 -> 0 | CW119: =CV119*CU119*$E119 -> 0 | CZ119: =CY119*CX119*$E119 -> 0 | DC119: =DB119*DA119*$E119 -> 0 | DF119: =DE119*DD119*$E119 -> 0 | DI119: =DH119*DG119*$E119 -> 0 | DL119: =DK119*DJ119*$E119 -> 0 | DO119: =DN119*DM119*$E119 -> 0 | DS119: =($H$3*H119+$K$3*K119+$N$3*N119+$Q$3*Q119+$T$3*T119+$W$3*W119+$Z$3*Z119+$AC$3*AC119+$AF$3*AF119+$AI$3*AI119+$AL$3*AL119+$AO$3*AO119+$AR$3*AR119+$AU$3*AU119+$AX$3*AX119+$BA$3*BA119+$BD$3*BD119+$BG$3*BG119+$BJ$3*BJ119+$BM$3*BM119+$BP$3*BP119+$BS$3*BS119+$BV$3*BV119+$BY$3*BY119+$CB$3*CB119+$CE$3*CE119+$CH$3*CH119+$CK$3*CK119+$CN$3*CN119+$CQ$3*CQ119+$CT$3*CT119+$CW$3*CW119+$CZ$3*CZ119+$DC$3*DC119+$DF$3*DF119+$DI$3*DI119+$DL$3*DL119+$DO$3*DO119) -> 0 | DT119: =DS119/$DS$130 -> 0
