Workbook
Name \0: #REF!
Name \0: #REF!
Name \0: #REF!
Name \A: #REF!
Name \A: #REF!
Name \A: #REF!
Name \b: #REF!
Name \b: #REF!
Name \b: #REF!
Name \c: #REF!
Name \c: #REF!
Name \c: #REF!
Name \F: #REF!
Name \F: #REF!
Name \G: #REF!
Name \G: #REF!
Name \h: #REF!
Name \h: #REF!
Name \L: #REF!
Name \L: #REF!
Name \n: #REF!
Name \n: #REF!
Name \O: #REF!
Name \O: #REF!
Name \P: #REF!
Name \P: #REF!
Name \Q: #REF!
Name \Q: #REF!
Name \R: #REF!
Name \R: #REF!
Name \s: #REF!
Name \s: #REF!
Name \t: #REF!
Name \t: #REF!
Name \V: #REF!
Name \V: #REF!
Name \w: #REF!
Name \w: #REF!
Name \x: #N/A
Name \y: #REF!
Name \y: #REF!
Name \z: #N/A
Name _________________________________mm1: #REF!
Name _________________________________mm1: QQP!_________________________________mm1
Name _________________________________mm1: #REF!
Name ________________________________mm1: #REF!
Name ________________________________mm1: QQP!________________________________mm1
Name ________________________________mm1: #REF!
Name _______________________________mm1: #REF!
Name _______________________________mm1: QQP!_______________________________mm1
Name _______________________________mm1: #REF!
Name ______________________________mm1: #REF!
Name ______________________________mm1: QQP!______________________________mm1
Name ______________________________mm1: #REF!
Name _____________________________mm1: #REF!
Name _____________________________mm1: QQP!_____________________________mm1
Name _____________________________mm1: #REF!
Name ____________________________mm1: #REF!
Name ____________________________mm1: QQP!____________________________mm1
Name ____________________________mm1: #REF!

Sheet APR
C1: ANÁLISE DE RISCO | R1: PRO-000-24
R2: DATA: | S2: 45292
B4: 1ª ETAPA - ANÁLISE PRELIMINAR DE RISCO
B5: Nome do Contrato: | C5: PRO-021-24 - ALUMAR - RDC 4573033 SUBSTITUIÇÃO MÓDULO 08 CORREIA TRANSPORTADORA - 07 - O | M5: Dono do Risco: | O5: Márcio Lopes | Q5: Cliente: | R5: Tamires Paula
B6: Missão do Contrato: | C6: Contratação de empresa especializada para execução da substituição do módulo 08 da correia transportadora C-01 | M6: Prazo (dias): | N6: =30*5 -> 150 | O6: Prazo pgto (dd): | P6: 64 | Q6: Local: | R6: Porto
B7: ESTIMATIVA FINANCEIRAS
B8: Valor Estimado | C8: =R8*T8 -> 0 | D8: Nr. De Pessoas | F8: Custo M.obra | I8: Custo Equipam. | M8: Custo Consumiveis | O8: Outros | Q8: Custo Total | R8: =G8+J8+N8+P8 -> 0 | S8: K | T8: 1.72
B9: OBSERVAÇÕES
B12: 2ª ETAPA - ANÁLISE DE RISCO
B14: Riscos a Verificar
C17: Criterio de Avaliação do Nivel do Risco | AF17: Nota | AG17: Probabilidade | AH17: NR | AI17: NR
C18: Probabilidade do Risco Acontecer | E18: NR | G18: Nota | AF18: 1 | AG18: QUASE CERTO | AH18: Risco Alto | AI18: Alto | AK18: GRÁFICO | AQ18: VERMELHO | AT18: AMARELO | AW18: VERDE
C19: QUASE CERTO | E19: Alto | G19: 1 a 2,5 | AF19: 2 | AG19: QUASE CERTO | AH19: Risco Alto | AI19: Alto | AK19: =B26 -> Tipo de Riscos | AL19: Nivel | AM19: Vermelho | AN19: Amarelo | AO19: Verde | AQ19: =AK19 -> Tipo de Riscos | AR19: =" " | AT19: =AK19 -> Tipo de Riscos | AU19: =" " | AW19: =AK19 -> Tipo de Riscos | AX19: =" "
C20: MUITO PROVÁVEL | E20: Alto | G20: 2,6 a 4,9 | AF20: 2.5 | AG20: QUASE CERTO | AH20: Risco Alto | AI20: Alto | AJ20: 1 | AK20: =B27 -> 1-FINANCEIRO (Fluxo de caixa) | AL20: =F27 -> 3 | AM20: =IF(AL20<=4.9,AL20,"") -> 3 | AN20: =IF(AND(AL20>4.9,AL20<=8.5),AL20,"") | AO20: =IF(AL20>=8.6,AL20,"") | AQ20: =AK20 -> 1-FINANCEIRO (Fluxo de caixa) | AR20: =AM20 -> 3 | AT20: =AK20 -> 1-FINANCEIRO (Fluxo de caixa) | AU20: =AN20 | AW20: =AK20 -> 1-FINANCEIRO (Fluxo de caixa) | AX20: =AO20
C21: PROVÁVEL | E21: Médio | G21: 5 a 7,4 | AF21: 2.6 | AG21: MUITO PROVÁVEL | AH21: Risco Alto | AI21: Alto | AJ21: 2 | AK21: =B29 -> 2-CALOTE (SERASA) | AL21: =F29 -> 9 | AM21: =IF(AL21<=4.9,AL21,"") | AN21: =IF(AND(AL21>4.9,AL21<=8.5),AL21,"") | AO21: =IF(AL21>=8.6,AL21,"") -> 9 | AQ21: =AK21 -> 2-CALOTE (SERASA) | AR21: =AM21 | AT21: =AK21 -> 2-CALOTE (SERASA) | AU21: =AN21 | AW21: =AK21 -> 2-CALOTE (SERASA) | AX21: =AO21 -> 9
C22: POUCO PROVÁVEL | E22: Médio | G22: 7,5 a 8,5 | AF22: 3 | AG22: MUITO PROVÁVEL | AH22: Risco Alto | AI22: Alto | AJ22: 3 | AK22: =B31 -> 3-NIVEL DE COMPLEXIDADE | AL22: =F31 -> 1 | AM22: =IF(AL22<=4.9,AL22,"") -> 1 | AN22: =IF(AND(AL22>4.9,AL22<=8.5),AL22,"") | AO22: =IF(AL22>=8.6,AL22,"") | AQ22: =AK22 -> 3-NIVEL DE COMPLEXIDADE | AR22: =AM22 -> 1 | AT22: =AK22 -> 3-NIVEL DE COMPLEXIDADE | AU22: =AN22 | AW22: =AK22 -> 3-NIVEL DE COMPLEXIDADE | AX22: =AO22
C23: IMPROVÁVEL | E23: Baixo | G23: 8,6 a 9,3 | AF23: 4 | AG23: MUITO PROVÁVEL | AH23: Risco Alto | AI23: Alto | AJ23: 4 | AK23: =B33 -> 4-CAPACIDADE TÉCNICA | AL23: =F33 -> 1 | AM23: =IF(AL23<=4.9,AL23,"") -> 1 | AN23: =IF(AND(AL23>4.9,AL23<=8.5),AL23,"") | AO23: =IF(AL23>=8.6,AL23,"") | AQ23: =AK23 -> 4-CAPACIDADE TÉCNICA | AR23: =AM23 -> 1 | AT23: =AK23 -> 4-CAPACIDADE TÉCNICA | AU23: =AN23 | AW23: =AK23 -> 4-CAPACIDADE TÉCNICA | AX23: =AO23
C24: RARO | E24: Baixo | G24: 9,4 a 10 | AF24: 4.9 | AG24: MUITO PROVÁVEL | AH24: Risco Alto | AI24: Alto | AJ24: 5 | AK24: =B35 -> 5-SSMA | AL24: =F35 -> 6 | AM24: =IF(AL24<=4.9,AL24,"") | AN24: =IF(AND(AL24>4.9,AL24<=8.5),AL24,"") -> 6 | AO24: =IF(AL24>=8.6,AL24,"") | AQ24: =AK24 -> 5-SSMA | AR24: =AM24 | AT24: =AK24 -> 5-SSMA | AU24: =AN24 -> 6 | AW24: =AK24 -> 5-SSMA | AX24: =AO24
B25: Quanto maior a probabilidade do risco, menor a Nota atribuída e vice versa. | AF25: 5 | AG25: PROVÁVEL | AH25: Risco Médio | AI25: Médio | AJ25: 6 | AK25: =B37 -> 6-RISCO DE NÃO ACONTECER | AL25: =F37 -> 6 | AM25: =IF(AL25<=4.9,AL25,"") | AN25: =IF(AND(AL25>4.9,AL25<=8.5),AL25,"") -> 6 | AO25: =IF(AL25>=8.6,AL25,"") | AQ25: =AK25 -> 6-RISCO DE NÃO ACONTECER | AR25: =AM25 | AT25: =AK25 -> 6-RISCO DE NÃO ACONTECER | AU25: =AN25 -> 6 | AW25: =AK25 -> 6-RISCO DE NÃO ACONTECER | AX25: =AO25
B26: Tipo de Riscos | D26: Peso da Consequencia | E26: Nivel de Risco | I26: Yield | AF26: 6 | AG26: PROVÁVEL | AH26: Risco Médio | AI26: Médio | AJ26: 7 | AK26: =B39 -> 7-DISPONIBILIDADE DE RECURSOS (Mercado) | AL26: =F39 -> 4 | AM26: =IF(AL26<=4.9,AL26,"") -> 4 | AN26: =IF(AND(AL26>4.9,AL26<=8.5),AL26,"") | AO26: =IF(AL26>=8.6,AL26,"") | AQ26: =AK26 -> 7-DISPONIBILIDADE DE RECURSOS (Mercado) | AR26: =AM26 -> 4 | AT26: =AK26 -> 7-DISPONIBILIDADE DE RECURSOS (Mercado) | AU26: =AN26 | AW26: =AK26 -> 7-DISPONIBILIDADE DE RECURSOS (Mercado) | AX26: =AO26
B27: 1-FINANCEIRO (Fluxo de caixa) | D27: 2.5 | F27: 3 | H27: =VLOOKUP(F27,$AF$18:$AI$36,3,TRUE) -> Risco Alto | M27: Observações gerais a serem contempladas na APR | AF27: 7 | AG27: PROVÁVEL | AH27: Risco Médio | AI27: Médio | AJ27: 8 | AK27: =B41 -> 8-COMPETITIVIDADE (Concorrentes) | AL27: =F41 -> 2 | AM27: =IF(AL27<=4.9,AL27,"") -> 2 | AN27: =IF(AND(AL27>4.9,AL27<=8.5),AL27,"") | AO27: =IF(AL27>=8.6,AL27,"") | AQ27: =AK27 -> 8-COMPETITIVIDADE (Concorrentes) | AR27: =AM27 -> 2 | AT27: =AK27 -> 8-COMPETITIVIDADE (Concorrentes) | AU27: =AN27 | AW27: =AK27 -> 8-COMPETITIVIDADE (Concorrentes) | AX27: =AO27
M28: A Projeta não dispõe da expertise necessária para seguir com o processo e o nível de complexidade para o prazo requerido não possibilita a tentativa de participar do processo sem maiores riscos. | AF28: 7.4 | AG28: PROVÁVEL | AH28: Risco Médio | AI28: Médio | AJ28: 9 | AK28: =B43 -> 9-HH PARADO/EQUIPAMENTO | AL28: =F43 -> 2 | AM28: =IF(AL28<=4.9,AL28,"") -> 2 | AN28: =IF(AND(AL28>4.9,AL28<=8.5),AL28,"") | AO28: =IF(AL28>=8.6,AL28,"") | AQ28: =AK28 -> 9-HH PARADO/EQUIPAMENTO | AR28: =AM28 -> 2 | AT28: =AK28 -> 9-HH PARADO/EQUIPAMENTO | AU28: =AN28 | AW28: =AK28 -> 9-HH PARADO/EQUIPAMENTO | AX28: =AO28
B29: 2-CALOTE (SERASA) | D29: 2 | F29: 9 | H29: =VLOOKUP(F29,$AF$18:$AI$36,3,TRUE) -> Risco Baixo | I29: =ROUND((D27*F27+D29*F29+D31*F31+D33*F33+D35*F35+D37*F37+D41*F41+D43*F43+D45*F45+D47*F47+D39*F39+D51*F51+D53*F53+D49*F49)/D56,1) -> 4.7 | AF29: 7.5 | AG29: POUCO PROVÁVEL | AH29: Risco Médio | AI29: Médio | AJ29: 10 | AK29: =B45 -> 10-LOGISTICA | AL29: =F45 -> 1 | AM29: =IF(AL29<=4.9,AL29,"") -> 1 | AN29: =IF(AND(AL29>4.9,AL29<=8.5),AL29,"") | AO29: =IF(AL29>=8.6,AL29,"") | AQ29: =AK29 -> 10-LOGISTICA | AR29: =AM29 -> 1 | AT29: =AK29 -> 10-LOGISTICA | AU29: =AN29 | AW29: =AK29 -> 10-LOGISTICA | AX29: =AO29
AF30: 8 | AG30: POUCO PROVÁVEL | AH30: Risco Médio | AI30: Médio | AJ30: 11 | AK30: =B47 -> 11-NOTIFICAÇÕES E MULTAS | AL30: =F47 -> 8.6 | AM30: =IF(AL30<=4.9,AL30,"") | AN30: =IF(AND(AL30>4.9,AL30<=8.5),AL30,"") | AO30: =IF(AL30>=8.6,AL30,"") -> 8.6 | AQ30: =AK30 -> 11-NOTIFICAÇÕES E MULTAS | AR30: =AM30 | AT30: =AK30 -> 11-NOTIFICAÇÕES E MULTAS | AU30: =AN30 | AW30: =AK30 -> 11-NOTIFICAÇÕES E MULTAS | AX30: =AO30 -> 8.6
B31: 3-NIVEL DE COMPLEXIDADE | D31: 0.5 | F31: 1 | H31: =VLOOKUP(F31,$AF$18:$AI$36,3,TRUE) -> Risco Alto | AF31: 8.5 | AG31: POUCO PROVÁVEL | AH31: Risco Médio | AI31: Médio | AJ31: 12 | AK31: =B49 -> 12-PRAZO DE ELABORAÇÃO PROPOSTA | AL31: =F49 -> 3 | AM31: =IF(AL31<=4.9,AL31,"") -> 3 | AN31: =IF(AND(AL31>4.9,AL31<=8.5),AL31,"") | AO31: =IF(AL31>=8.6,AL31,"") | AQ31: =AK31 -> 12-PRAZO DE ELABORAÇÃO PROPOSTA | AR31: =AM31 -> 3 | AT31: =AK31 -> 12-PRAZO DE ELABORAÇÃO PROPOSTA | AU31: =AN31 | AW31: =AK31 -> 12-PRAZO DE ELABORAÇÃO PROPOSTA | AX31: =AO31
AF32: 8.6 | AG32: IMPROVÁVEL | AH32: Risco Baixo | AI32: Baixo | AJ32: 13 | AK32: =B51 -> 13-PRAZO DE EXECUÇÃO | AL32: =F51 -> 7 | AM32: =IF(AL32<=4.9,AL32,"") | AN32: =IF(AND(AL32>4.9,AL32<=8.5),AL32,"") -> 7 | AO32: =IF(AL32>=8.6,AL32,"") | AQ32: =AK32 -> 13-PRAZO DE EXECUÇÃO | AR32: =AM32 | AT32: =AK32 -> 13-PRAZO DE EXECUÇÃO | AU32: =AN32 -> 7 | AW32: =AK32 -> 13-PRAZO DE EXECUÇÃO | AX32: =AO32
B33: 4-CAPACIDADE TÉCNICA | D33: 0.5 | F33: 1 | H33: =VLOOKUP(F33,$AF$18:$AI$36,3,TRUE) -> Risco Alto | AF33: 9 | AG33: IMPROVÁVEL | AH33: Risco Baixo | AI33: Baixo | AJ33: 14 | AK33: =B53 -> 14-LEILÃO | AL33: =F53 -> 7 | AM33: =IF(AL33<=4.9,AL33,"") | AN33: =IF(AND(AL33>4.9,AL33<=8.5),AL33,"") -> 7 | AO33: =IF(AL33>=8.6,AL33,"") | AQ33: =AK33 -> 14-LEILÃO | AR33: =AM33 | AT33: =AK33 -> 14-LEILÃO | AU33: =AN33 -> 7 | AW33: =AK33 -> 14-LEILÃO | AX33: =AO33
AF34: 9.3 | AG34: IMPROVÁVEL | AH34: Risco Baixo | AI34: Baixo
B35: 5-SSMA | D35: 0.5 | F35: 6 | H35: =VLOOKUP(F35,$AF$18:$AI$36,3,TRUE) -> Risco Médio | AF35: 9.4 | AG35: RARO | AH35: Risco Baixo | AI35: Baixo
AF36: 10 | AG36: RARO | AH36: Risco Baixo | AI36: Baixo
B37: 6-RISCO DE NÃO ACONTECER | D37: 0.3 | F37: 6 | H37: =VLOOKUP(F37,$AF$18:$AI$36,3,TRUE) -> Risco Médio
B39: 7-DISPONIBILIDADE DE RECURSOS (Mercado) | D39: 0.5 | F39: 4 | H39: =VLOOKUP(F39,$AF$18:$AI$36,3,TRUE) -> Risco Alto
B41: 8-COMPETITIVIDADE (Concorrentes) | D41: 0.5 | F41: 2 | H41: =VLOOKUP(F41,$AF$18:$AI$36,3,TRUE) -> Risco Alto | I41: Nível de Risco:
B43: 9-HH PARADO/EQUIPAMENTO | D43: 0.5 | F43: 2 | H43: =VLOOKUP(F43,$AF$18:$AI$36,3,TRUE) -> Risco Alto | I43: =VLOOKUP(I29,AF18:AI36,4,TRUE) -> Alto
B45: 10-LOGISTICA | D45: 0.5 | F45: 1 | H45: =VLOOKUP(F45,$AF$18:$AI$36,3,TRUE) -> Risco Alto
B47: 11-NOTIFICAÇÕES E MULTAS | D47: 0.5 | F47: 8.6 | H47: =VLOOKUP(F47,$AF$18:$AI$36,3,TRUE) -> Risco Baixo
B49: 12-PRAZO DE ELABORAÇÃO PROPOSTA | D49: 0.5 | F49: 3 | H49: =VLOOKUP(F49,$AF$18:$AI$36,3,TRUE) -> Risco Alto
B51: 13-PRAZO DE EXECUÇÃO | D51: 0.5 | F51: 7 | H51: =VLOOKUP(F51,$AF$18:$AI$36,3,TRUE) -> Risco Médio
B53: 14-LEILÃO | D53: 0.2 | F53: 7 | H53: =VLOOKUP(F53,$AF$18:$AI$36,3,TRUE) -> Risco Médio
D56: =SUM(D27:D55) -> 10
B57: Nota 1 - Os Níveis de Risco considerados Médios e Altos (amarelo e vermelho) deverão ser contemplados na ARC (Análise de Risco do Contrato).
B58: Nota 2 - Yeld é o indicador qualitativo da oportunidade do contrato no que diz respeito ao risco, varia entre 1 e 10.
B59: Nota 3 - Yeld menor ou igual a 5, o processo será declinado, para Yeld > 5 e < 8,5, deverá ser elaborada Análise de Risco do Contrato com ações para mitigar os riscos | Q59: APROVADO
Q60: (Fazer a APR)
D62: Comercial | J62: Dono do Risco | Q62: REPROVADO | S62: X
B63: Trabalhar esse formulário junto com a APR | Q63: (Declinar do Processo)
B64: Este formulario deve ser utilizado como ferramenta de decisão de continuidade em processos de contratação. | R64: Rev. 03 | S64: 14 | T64: 11 | U64: 23
R65: Marcio Lopes

Sheet CHECK
B1: =QQP!G44 -> 0
G2: CHECK
B5: A - Mão de Obra + Encargos
B6: Cód. | C6: Discriminação | D6: Unid | E6: P.Unit | G6: Quant | H6: F.utiliz | I6: Custo
B7: ='CPU 1'!B7 -> P01 | C7: ='CPU 1'!C7 -> Supervisor | D7: ='CPU 1'!D7 -> hh | E7: ='CPU 1'!E7 -> 75.068182 | I7: ='CPU 1'!AG7+'CPU 2'!O7+'CPU 3'!AA7+'CPU 4'!AA7+'CPU 5'!U7 -> 0 | J7: =I7/$I$162 -> #DIV/0!
B8: ='CPU 1'!B8 -> P02 | C8: ='CPU 1'!C8 -> Encarregado | D8: ='CPU 1'!D8 -> hh | E8: ='CPU 1'!E8 -> 40.036364 | I8: ='CPU 1'!AG8+'CPU 2'!O8+'CPU 3'!AA8+'CPU 4'!AA8+'CPU 5'!U8 -> 0 | J8: =I8/$I$162 -> #DIV/0!
B9: ='CPU 1'!B9 -> P03 | C9: ='CPU 1'!C9 -> Técnico SSMA | D9: ='CPU 1'!D9 -> hh | E9: ='CPU 1'!E9 -> 40.036364 | I9: ='CPU 1'!AG9+'CPU 2'!O9+'CPU 3'!AA9+'CPU 4'!AA9+'CPU 5'!U9 -> 0 | J9: =I9/$I$162 -> #DIV/0!
B10: ='CPU 1'!B10 -> P04 | C10: ='CPU 1'!C10 -> Pedreiro | D10: ='CPU 1'!D10 -> hh | E10: ='CPU 1'!E10 -> 19.767955 | I10: ='CPU 1'!AG10+'CPU 2'!O10+'CPU 3'!AA10+'CPU 4'!AA10+'CPU 5'!U10 -> 0 | J10: =I10/$I$162 -> #DIV/0!
B11: ='CPU 1'!B11 -> P05 | C11: ='CPU 1'!C11 -> Carpinteiro | D11: ='CPU 1'!D11 -> hh | E11: ='CPU 1'!E11 -> 19.767955 | I11: ='CPU 1'!AG11+'CPU 2'!O11+'CPU 3'!AA11+'CPU 4'!AA11+'CPU 5'!U11 -> 0 | J11: =I11/$I$162 -> #DIV/0!
B12: ='CPU 1'!B12 -> P06 | C12: ='CPU 1'!C12 -> Eletricista | D12: ='CPU 1'!D12 -> hh | E12: ='CPU 1'!E12 -> 26.023636 | I12: ='CPU 1'!AG12+'CPU 2'!O12+'CPU 3'!AA12+'CPU 4'!AA12+'CPU 5'!U12 -> 0 | J12: =I12/$I$162 -> #DIV/0!
B13: ='CPU 1'!B13 -> P07 | C13: ='CPU 1'!C13 -> Ajudante | D13: ='CPU 1'!D13 -> hh | E13: ='CPU 1'!E13 -> 13.962682 | I13: ='CPU 1'!AG13+'CPU 2'!O13+'CPU 3'!AA13+'CPU 4'!AA13+'CPU 5'!U13 -> 0 | J13: =I13/$I$162 -> #DIV/0!
B14: ='CPU 1'!B14 -> P08 | C14: ='CPU 1'!C14 -> Armador | D14: ='CPU 1'!D14 -> hh | E14: ='CPU 1'!E14 -> 19.767955 | I14: ='CPU 1'!AG14+'CPU 2'!O14+'CPU 3'!AA14+'CPU 4'!AA14+'CPU 5'!U14 -> 0 | J14: =I14/$I$162 -> #DIV/0!
B15: ='CPU 1'!B15 -> P09 | C15: ='CPU 1'!C15 -> Engenheiro | D15: ='CPU 1'!D15 -> hh | E15: ='CPU 1'!E15 -> 112.302 | I15: ='CPU 1'!AG15+'CPU 2'!O15+'CPU 3'!AA15+'CPU 4'!AA15+'CPU 5'!U15 -> 0 | J15: =I15/$I$162 -> #DIV/0!
B16: ='CPU 1'!B16 -> P10 | C16: ='CPU 1'!C16 -> Planejador | D16: ='CPU 1'!D16 -> hh | E16: ='CPU 1'!E16 -> 60.054545 | I16: ='CPU 1'!AG16+'CPU 2'!O16+'CPU 3'!AA16+'CPU 4'!AA16+'CPU 5'!U16 -> 0 | J16: =I16/$I$162 -> #DIV/0!
B17: ='CPU 1'!B17 -> P11 | C17: ='CPU 1'!C17 -> Tópografo | D17: ='CPU 1'!D17 -> hh | E17: ='CPU 1'!E17 -> 38.034545 | I17: ='CPU 1'!AG17+'CPU 2'!O17+'CPU 3'!AA17+'CPU 4'!AA17+'CPU 5'!U17 -> 0 | J17: =I17/$I$162 -> #DIV/0!
B18: ='CPU 1'!B18 -> P12 | C18: ='CPU 1'!C18 -> Auxiliar de Topografia | D18: ='CPU 1'!D18 -> hh | E18: ='CPU 1'!E18 -> 17.015455 | I18: ='CPU 1'!AG18+'CPU 2'!O18+'CPU 3'!AA18+'CPU 4'!AA18+'CPU 5'!U18 -> 0 | J18: =I18/$I$162 -> #DIV/0!
... B22: ='CPU 1'!B22 -> P16 | C22: ='CPU 1'!C22 -> 0 | D22: ='CPU 1'!D22 -> hh | E22: ='CPU 1'!E22 -> 0 | I22: ='CPU 1'!AG22+'CPU 2'!O22+'CPU 3'!AA22+'CPU 4'!AA22+'CPU 5'!U22 -> 0 | J22: =I22/$I$162 -> #DIV/0!
B23: A - Custo Total de Mão de Obra: | G23: =SUM(G7:G22) -> 0 | H23: =SUM(H7:H22) -> 0 | I23: =SUM(I7:I22) -> 0
B24: B – Equipamentos e Ferramentas
B25: Cód. | C25: Discriminação | D25: Unid | E25: P.Unit | G25: Quant | H25: F.utiliz | I25: Custo
B26: ='CPU 1'!B26 -> E01 | C26: ='CPU 1'!C26 -> Alavanca, picareta, enxada, cavador, pá | D26: ='CPU 1'!D26 -> vb | E26: ='CPU 1'!E26 -> 790 | I26: ='CPU 1'!AG26+'CPU 2'!O26+'CPU 3'!AA26+'CPU 4'!AA26+'CPU 5'!U26 -> 0 | J26: =I26/$I$162 -> #DIV/0!
B27: ='CPU 1'!B27 -> E02 | C27: ='CPU 1'!C27 -> Banheiro hidraulico - locação | D27: ='CPU 1'!D27 -> vb/mês | E27: ='CPU 1'!E27 -> 4000 | I27: ='CPU 1'!AG27+'CPU 2'!O27+'CPU 3'!AA27+'CPU 4'!AA27+'CPU 5'!U27 -> 0 | J27: =I27/$I$162 -> #DIV/0!
B28: ='CPU 1'!B28 -> E03 | C28: ='CPU 1'!C28 -> Barreira física metalica | D28: ='CPU 1'!D28 -> pç | E28: ='CPU 1'!E28 -> 350 | I28: ='CPU 1'!AG28+'CPU 2'!O28+'CPU 3'!AA28+'CPU 4'!AA28+'CPU 5'!U28 -> 0 | J28: =I28/$I$162 -> #DIV/0!
B29: ='CPU 1'!B29 -> E04 | C29: ='CPU 1'!C29 -> Bebedouro 4 torneiras 50L | D29: ='CPU 1'!D29 -> unid | E29: ='CPU 1'!E29 -> 3500 | I29: ='CPU 1'!AG29+'CPU 2'!O29+'CPU 3'!AA29+'CPU 4'!AA29+'CPU 5'!U29 -> 0 | J29: =I29/$I$162 -> #DIV/0!
B30: ='CPU 1'!B30 -> E05 | C30: ='CPU 1'!C30 -> Caçamba de entulho 4m³ | D30: ='CPU 1'!D30 -> Vb/mês | E30: ='CPU 1'!E30 -> 800 | I30: ='CPU 1'!AG30+'CPU 2'!O30+'CPU 3'!AA30+'CPU 4'!AA30+'CPU 5'!U30 -> 0 | J30: =I30/$I$162 -> #DIV/0!
B31: ='CPU 1'!B31 -> E06 | C31: ='CPU 1'!C31 -> Cadinho solda exotermica | D31: ='CPU 1'!D31 -> pç | E31: ='CPU 1'!E31 -> 420 | I31: ='CPU 1'!AG31+'CPU 2'!O31+'CPU 3'!AA31+'CPU 4'!AA31+'CPU 5'!U31 -> 0 | J31: =I31/$I$162 -> #DIV/0!
B32: ='CPU 1'!B32 -> E07 | C32: ='CPU 1'!C32 -> Caixa dágua 1000L | D32: ='CPU 1'!D32 -> pç | E32: ='CPU 1'!E32 -> 480 | I32: ='CPU 1'!AG32+'CPU 2'!O32+'CPU 3'!AA32+'CPU 4'!AA32+'CPU 5'!U32 -> 0 | J32: =I32/$I$162 -> #DIV/0!
B33: ='CPU 1'!B33 -> E08 | C33: ='CPU 1'!C33 -> Caixa dágua 500L | D33: ='CPU 1'!D33 -> pç | E33: ='CPU 1'!E33 -> 250 | I33: ='CPU 1'!AG33+'CPU 2'!O33+'CPU 3'!AA33+'CPU 4'!AA33+'CPU 5'!U33 -> 0 | J33: =I33/$I$162 -> #DIV/0!
B34: ='CPU 1'!B34 -> E09 | C34: ='CPU 1'!C34 -> Caminhão munck | D34: ='CPU 1'!D34 -> vb/mês | E34: ='CPU 1'!E34 -> 40000 | I34: ='CPU 1'!AG34+'CPU 2'!O34+'CPU 3'!AA34+'CPU 4'!AA34+'CPU 5'!U34 -> 0 | J34: =I34/$I$162 -> #DIV/0!
B35: ='CPU 1'!B35 -> E10 | C35: ='CPU 1'!C35 -> Carro de mão | D35: ='CPU 1'!D35 -> pç | E35: ='CPU 1'!E35 -> 450 | I35: ='CPU 1'!AG35+'CPU 2'!O35+'CPU 3'!AA35+'CPU 4'!AA35+'CPU 5'!U35 -> 0 | J35: =I35/$I$162 -> #DIV/0!
B36: ='CPU 1'!B36 -> E11 | C36: ='CPU 1'!C36 -> Carro plataforma | D36: ='CPU 1'!D36 -> pç | E36: ='CPU 1'!E36 -> 1200 | I36: ='CPU 1'!AG36+'CPU 2'!O36+'CPU 3'!AA36+'CPU 4'!AA36+'CPU 5'!U36 -> 0 | J36: =I36/$I$162 -> #DIV/0!
B37: ='CPU 1'!B37 -> E12 | C37: ='CPU 1'!C37 -> Coletor de resíduo com pedal - 50L (V,V,A,A) | D37: ='CPU 1'!D37 -> kit | E37: ='CPU 1'!E37 -> 1200 | I37: ='CPU 1'!AG37+'CPU 2'!O37+'CPU 3'!AA37+'CPU 4'!AA37+'CPU 5'!U37 -> 0 | J37: =I37/$I$162 -> #DIV/0!
... B79: ='CPU 1'!B79 -> E54 | C79: ='CPU 1'!C79 -> 0 | D79: ='CPU 1'!D79 -> 0 | E79: ='CPU 1'!E79 -> 0 | I79: ='CPU 1'!AG79+'CPU 2'!O79+'CPU 3'!AA79+'CPU 4'!AA79+'CPU 5'!U79 -> 0 | J79: =I79/$I$162 -> #DIV/0!
B80: B - Custo Total de Equipamentos e Ferramentas: | E80: =SUM(#REF!) -> #REF! | I80: =SUM(I26:I79) -> 0
B81: C – Materiais
B82: Cód. | C82: Discriminação | D82: Unid | E82: P.Unit | G82: Quant | H82: F.utiliz | I82: Custo
B83: ='CPU 1'!B83 -> M01 | C83: ='CPU 1'!C83 -> Aço CA-50, (ferro 8.0) | D83: ='CPU 1'!D83 -> kg | E83: ='CPU 1'!E83 -> 12.5 | I83: ='CPU 1'!AG83+'CPU 2'!O83+'CPU 3'!AA83+'CPU 4'!AA83+'CPU 5'!U83 -> 0 | J83: =I83/$I$162 -> #DIV/0!
B84: ='CPU 1'!B84 -> M02 | C84: ='CPU 1'!C84 -> Agua Mineral | D84: ='CPU 1'!D84 -> litro | E84: ='CPU 1'!E84 -> 1 | I84: ='CPU 1'!AG84+'CPU 2'!O84+'CPU 3'!AA84+'CPU 4'!AA84+'CPU 5'!U84 -> 0 | J84: =I84/$I$162 -> #DIV/0!
B85: ='CPU 1'!B85 -> M03 | C85: ='CPU 1'!C85 -> Arame ovalado zincado | D85: ='CPU 1'!D85 -> m | E85: ='CPU 1'!E85 -> 1 | I85: ='CPU 1'!AG85+'CPU 2'!O85+'CPU 3'!AA85+'CPU 4'!AA85+'CPU 5'!U85 -> 0 | J85: =I85/$I$162 -> #DIV/0!
B86: ='CPU 1'!B86 -> M04 | C86: ='CPU 1'!C86 -> Areia | D86: ='CPU 1'!D86 -> m³ | E86: ='CPU 1'!E86 -> 120 | I86: ='CPU 1'!AG86+'CPU 2'!O86+'CPU 3'!AA86+'CPU 4'!AA86+'CPU 5'!U86 -> 0 | J86: =I86/$I$162 -> #DIV/0!
B87: ='CPU 1'!B87 -> M05 | C87: ='CPU 1'!C87 -> Arrame galganizado | D87: ='CPU 1'!D87 -> kg | E87: ='CPU 1'!E87 -> 16.8 | I87: ='CPU 1'!AG87+'CPU 2'!O87+'CPU 3'!AA87+'CPU 4'!AA87+'CPU 5'!U87 -> 0 | J87: =I87/$I$162 -> #DIV/0!
B88: ='CPU 1'!B88 -> M06 | C88: ='CPU 1'!C88 -> Arrame recozido | D88: ='CPU 1'!D88 -> kg | E88: ='CPU 1'!E88 -> 12 | I88: ='CPU 1'!AG88+'CPU 2'!O88+'CPU 3'!AA88+'CPU 4'!AA88+'CPU 5'!U88 -> 0 | J88: =I88/$I$162 -> #DIV/0!
B89: ='CPU 1'!B89 -> M07 | C89: ='CPU 1'!C89 -> Barrote de madeira 7x7cm | D89: ='CPU 1'!D89 -> m | E89: ='CPU 1'!E89 -> 15 | I89: ='CPU 1'!AG89+'CPU 2'!O89+'CPU 3'!AA89+'CPU 4'!AA89+'CPU 5'!U89 -> 0 | J89: =I89/$I$162 -> #DIV/0!
B90: ='CPU 1'!B90 -> M08 | C90: ='CPU 1'!C90 -> Bloco tipo canaleta (14x19x39cm) | D90: ='CPU 1'!D90 -> peça | E90: ='CPU 1'!E90 -> 8.9 | I90: ='CPU 1'!AG90+'CPU 2'!O90+'CPU 3'!AA90+'CPU 4'!AA90+'CPU 5'!U90 -> 0 | J90: =I90/$I$162 -> #DIV/0!
B91: ='CPU 1'!B91 -> M09 | C91: ='CPU 1'!C91 -> Brita 1 | D91: ='CPU 1'!D91 -> m³ | E91: ='CPU 1'!E91 -> 220 | I91: ='CPU 1'!AG91+'CPU 2'!O91+'CPU 3'!AA91+'CPU 4'!AA91+'CPU 5'!U91 -> 0 | J91: =I91/$I$162 -> #DIV/0!
B92: ='CPU 1'!B92 -> M11 | C92: ='CPU 1'!C92 -> Caixa de passagens para aterramento h600 diâmetro 30cm | D92: ='CPU 1'!D92 -> und | E92: ='CPU 1'!E92 -> 590 | I92: ='CPU 1'!AG92+'CPU 2'!O92+'CPU 3'!AA92+'CPU 4'!AA92+'CPU 5'!U92 -> 0 | J92: =I92/$I$162 -> #DIV/0!
B93: ='CPU 1'!B93 -> M12 | C93: ='CPU 1'!C93 -> Catoneira galvanizada 1"x1-1/4 | D93: ='CPU 1'!D93 -> m | E93: ='CPU 1'!E93 -> 25 | I93: ='CPU 1'!AG93+'CPU 2'!O93+'CPU 3'!AA93+'CPU 4'!AA93+'CPU 5'!U93 -> 0 | J93: =I93/$I$162 -> #DIV/0!
B94: ='CPU 1'!B94 -> M13 | C94: ='CPU 1'!C94 -> Cercamento e delimitação de canteiro de obra (15x30m) | D94: ='CPU 1'!D94 -> vb | E94: ='CPU 1'!E94 -> 10000 | I94: ='CPU 1'!AG94+'CPU 2'!O94+'CPU 3'!AA94+'CPU 4'!AA94+'CPU 5'!U94 -> 0 | J94: =I94/$I$162 -> #DIV/0!
... B131: ='CPU 1'!B131 -> M50 | C131: ='CPU 1'!C131 -> 0 | D131: ='CPU 1'!D131 -> 0 | E131: ='CPU 1'!E131 -> 0 | I131: ='CPU 1'!AG131+'CPU 2'!O131+'CPU 3'!AA131+'CPU 4'!AA131+'CPU 5'!U131 -> 0 | J131: =I131/$I$162 -> #DIV/0!
B132: C - Custo Total de Materiais: | E132: =SUM(#REF!) -> #REF! | I132: =SUM(I83:I131) -> 0
B133: D – Outros
B134: Cód. | C134: Discriminação | D134: Unid | E134: P.Unit | G134: Quant | H134: F.utiliz | I134: Custo
B135: ='CPU 1'!B135 -> O01 | C135: ='CPU 1'!C135 -> ART | D135: ='CPU 1'!D135 -> Vb | E135: ='CPU 1'!E135 -> 1000 | I135: ='CPU 1'!AG135+'CPU 2'!O135+'CPU 3'!AA135+'CPU 4'!AA135+'CPU 5'!U135 -> 0 | J135: =I135/$I$162 -> #DIV/0!
B136: ='CPU 1'!B136 -> O02 | C136: ='CPU 1'!C136 -> Exames medicos | D136: ='CPU 1'!D136 -> Vb | E136: ='CPU 1'!E136 -> 600 | I136: ='CPU 1'!AG136+'CPU 2'!O136+'CPU 3'!AA136+'CPU 4'!AA136+'CPU 5'!U136 -> 0 | J136: =I136/$I$162 -> #DIV/0!
B137: ='CPU 1'!B137 -> O03 | C137: ='CPU 1'!C137 -> Treinamentos | D137: ='CPU 1'!D137 -> Vb | E137: ='CPU 1'!E137 -> 426 | I137: ='CPU 1'!AG137+'CPU 2'!O137+'CPU 3'!AA137+'CPU 4'!AA137+'CPU 5'!U137 -> 0 | J137: =I137/$I$162 -> #DIV/0!
B138: ='CPU 1'!B138 -> O04 | C138: ='CPU 1'!C138 -> Plano de Saude | D138: ='CPU 1'!D138 -> Vb/mês | E138: ='CPU 1'!E138 -> 280 | I138: ='CPU 1'!AG138+'CPU 2'!O138+'CPU 3'!AA138+'CPU 4'!AA138+'CPU 5'!U138 -> 0 | J138: =I138/$I$162 -> #DIV/0!
B139: ='CPU 1'!B139 -> O05 | C139: ='CPU 1'!C139 -> Seguro de Vida | D139: ='CPU 1'!D139 -> Vb/mês | E139: ='CPU 1'!E139 -> 25 | I139: ='CPU 1'!AG139+'CPU 2'!O139+'CPU 3'!AA139+'CPU 4'!AA139+'CPU 5'!U139 -> 0 | J139: =I139/$I$162 -> #DIV/0!
B140: ='CPU 1'!B140 -> O06 | C140: ='CPU 1'!C140 -> Ticket Alimentação | D140: ='CPU 1'!D140 -> Vb/mês | E140: ='CPU 1'!E140 -> 350 | I140: ='CPU 1'!AG140+'CPU 2'!O140+'CPU 3'!AA140+'CPU 4'!AA140+'CPU 5'!U140 -> 0 | J140: =I140/$I$162 -> #DIV/0!
B141: ='CPU 1'!B141 -> O07 | C141: ='CPU 1'!C141 -> PCMSO / PGR / PCA / PPR | D141: ='CPU 1'!D141 -> Vb/ano | E141: ='CPU 1'!E141 -> 2300 | I141: ='CPU 1'!AG141+'CPU 2'!O141+'CPU 3'!AA141+'CPU 4'!AA141+'CPU 5'!U141 -> 0 | J141: =I141/$I$162 -> #DIV/0!
B142: ='CPU 1'!B142 -> O08 | C142: ='CPU 1'!C142 -> Quadros DDS e Gestão a vista | D142: ='CPU 1'!D142 -> Vb | E142: ='CPU 1'!E142 -> 1200 | I142: ='CPU 1'!AG142+'CPU 2'!O142+'CPU 3'!AA142+'CPU 4'!AA142+'CPU 5'!U142 -> 0 | J142: =I142/$I$162 -> #DIV/0!
B143: ='CPU 1'!B143 -> O09 | C143: ='CPU 1'!C143 -> Seguro Obra | D143: ='CPU 1'!D143 -> Vb | E143: ='CPU 1'!E143 -> 5000 | I143: ='CPU 1'!AG143+'CPU 2'!O143+'CPU 3'!AA143+'CPU 4'!AA143+'CPU 5'!U143 -> 0 | J143: =I143/$I$162 -> #DIV/0!
B144: ='CPU 1'!B144 -> O10 | C144: ='CPU 1'!C144 -> Fretes | D144: ='CPU 1'!D144 -> ud | E144: ='CPU 1'!E144 -> 2800 | I144: ='CPU 1'!AG144+'CPU 2'!O144+'CPU 3'!AA144+'CPU 4'!AA144+'CPU 5'!U144 -> 0 | J144: =I144/$I$162 -> #DIV/0!
B145: ='CPU 1'!B145 -> O11 | C145: ='CPU 1'!C145 -> Serviço de descarte de residuo | D145: ='CPU 1'!D145 -> coleta | E145: ='CPU 1'!E145 -> 2000 | I145: ='CPU 1'!AG145+'CPU 2'!O145+'CPU 3'!AA145+'CPU 4'!AA145+'CPU 5'!U145 -> 0 | J145: =I145/$I$162 -> #DIV/0!
B146: ='CPU 1'!B146 -> O12 | C146: ='CPU 1'!C146 -> Serviço de movimentação do Banheiro Hidráulico | D146: ='CPU 1'!D146 -> vb | E146: ='CPU 1'!E146 -> 200 | I146: ='CPU 1'!AG146+'CPU 2'!O146+'CPU 3'!AA146+'CPU 4'!AA146+'CPU 5'!U146 -> 0 | J146: =I146/$I$162 -> #DIV/0!
... B154: ='CPU 1'!B154 -> O20 | C154: ='CPU 1'!C154 -> 0 | D154: ='CPU 1'!D154 -> 0 | E154: ='CPU 1'!E154 -> 0 | I154: ='CPU 1'!AG154+'CPU 2'!O154+'CPU 3'!AA154+'CPU 4'!AA154+'CPU 5'!U154 -> 0 | J154: =I154/$I$162 -> #DIV/0!
B155: D - Custo Total de Outros: | E155: =SUM(#REF!) -> #REF! | I155: =SUM(I135:I154) -> 0
B157: Item | C157: CUSTOS | H157: % | I157: $
B158: A | C158: Mão de Obra | H158: =I158/I162 -> #DIV/0! | I158: =I23 -> 0
B159: B | C159: Equipamentos | H159: =I159/I162 -> #DIV/0! | I159: =I80 -> 0
B160: C | C160: Materiais | H160: =I160/I162 -> #DIV/0! | I160: =I132 -> 0
B161: D | C161: Outros | H161: =I161/I162 -> #DIV/0! | I161: =I155 -> 0
C162: Subtotal: | E162: =SUM(E158:E161) -> 0 | H162: =SUM(H158:H161) -> #DIV/0! | I162: =SUM(I158:I161) -> 0
B164: Item | C164: BDI | E164: Taxa | I164: $
B165: 1 | C165: Administração Local | E165: ='BDI-TRIBUTOS'!D8 -> 0.09 | I165: =I162*$E$165 -> 0
B166: 2 | C166: Administração Central | E166: ='BDI-TRIBUTOS'!D6 -> 0.06 | I166: =I162*$E$166 -> 0
B167: 3 | C167: Custo financ. capital giro | E167: ='BDI-TRIBUTOS'!D10 -> 0.035 | I167: =I162*$E$167 -> 0
B168: 4 | C168: Risco do empreendimento | E168: ='BDI-TRIBUTOS'!D12 -> 0.02 | I168: =I162*$E$168 -> 0
B169: 5 | C169: Outros | E169: ='BDI-TRIBUTOS'!D14 -> 0.01 | I169: =I162*$E$169 -> 0
B170: 6 | C170: Lucro | E170: ='BDI-TRIBUTOS'!D4 -> 0.1 | I170: =I182*$E$170 -> 0
C171: Subtotal: | E171: =SUM(E165:E170) -> 0.315 | H171: =SUM(I165:I169)+I162 -> 0 | I171: =SUM(I165:I170) -> 0
G172: =I171/I162 -> #DIV/0!
B173: Item | C173: TRIBUTOS | E173: Taxa | I173: $
B174: 1 | C174: ISS | E174: ='BDI-TRIBUTOS'!D20 -> 0.05 | I174: =$I$182*E174 -> 0
B175: 2 | C175: COFINS | E175: ='BDI-TRIBUTOS'!D21 -> 0.03 | I175: =$I$182*E175 -> 0
B176: 3 | C176: PIS | E176: ='BDI-TRIBUTOS'!D22 -> 0.0065 | I176: =$I$182*E176 -> 0
B177: 4 | C177: CSLL | E177: ='BDI-TRIBUTOS'!D23 -> 0.0288 | I177: =$I$182*E177 -> 0
B178: 5 | C178: IRPJ | E178: ='BDI-TRIBUTOS'!D24 -> 0.048 | I178: =$I$182*E178 -> 0
B179: 6 | C179: IRPJ Adicional 10% | E179: ='BDI-TRIBUTOS'!D25 -> 0.0318 | I179: =$I$182*E179 -> 0
B180: 7 | C180: Simples Nacional | E180: ='BDI-TRIBUTOS'!D26 -> 0
C181: Subtotal | E181: =SUM(E174:E180) -> 0.1951 | I181: =I182*$E$181 -> 0
C182: PREÇO | I182: =H171/(1-$E$181-$E$170) -> 0
I183: =I182/I162 -> #DIV/0!

Sheet QQP
C1: PROJETA CONSULTORIA E SERVIÇOS LTDA | E1: PRO-000-24 | H1: =G44 -> 0
C2: PROPOSTA COMERCIAL | E2: CLIENTE: | F2: XXXXXXXXXXXXXX
C3: PLANILHA DE QUANTIDADES E PREÇOS | E3: REV. 0 | F3: DATA: | G3: 45292
B4: OBJETO: | C4: XXXXXXXXXXXXXXXXXXXXXXXXXXXXXXXXXXX
B6: ITEM | C6: DESCRIÇÃO | D6: UNID. | E6: QUANT. | F6: P.UNITARIO | G6: P.TOTAL
A7: CPU 1 | B7: 1 | C7: XXXXXXXXXXXXXXXXXXXX
B8: 1.1 | C8: XXXXXXXXXXXXXXXXXXXXXXXXXXXXXXXXXXXXXXXXXX | D8: xx | E8: 1 | F8: =_xlfn.XLOOKUP(B8,'CPU 1'!$F$1:$CI$1,'CPU 1'!$F$182:$CI$182) -> 0 | G8: =F8*E8 -> 0 | H8: =G8/$G$44 -> #DIV/0!
B9: 1.2 | C9: XXXXXXXXXXXXXXXXXXXXXXXXXXXXXXXXXXXXXXXXXX | D9: xx | E9: 1 | F9: =_xlfn.XLOOKUP(B9,'CPU 1'!$F$1:$CI$1,'CPU 1'!$F$182:$CI$182) -> 0 | G9: =F9*E9 -> 0 | H9: =G9/$G$44 -> #DIV/0!
B10: 1.3 | C10: XXXXXXXXXXXXXXXXXXXXXXXXXXXXXXXXXXXXXXXXXX | D10: xx | E10: 1 | F10: =_xlfn.XLOOKUP(B10,'CPU 1'!$F$1:$CI$1,'CPU 1'!$F$182:$CI$182) -> 0 | G10: =F10*E10 -> 0 | H10: =G10/$G$44 -> #DIV/0!
B11: 1.4 | C11: XXXXXXXXXXXXXXXXXXXXXXXXXXXXXXXXXXXXXXXXXX | D11: xx | E11: 1 | F11: =_xlfn.XLOOKUP(B11,'CPU 1'!$F$1:$CI$1,'CPU 1'!$F$182:$CI$182) -> 0 | G11: =F11*E11 -> 0 | H11: =G11/$G$44 -> #DIV/0!
B12: 1.5 | C12: XXXXXXXXXXXXXXXXXXXXXXXXXXXXXXXXXXXXXXXXXX | D12: xx | E12: 1 | F12: =_xlfn.XLOOKUP(B12,'CPU 1'!$F$1:$CI$1,'CPU 1'!$F$182:$CI$182) -> 0 | G12: =F12*E12 -> 0 | H12: =G12/$G$44 -> #DIV/0!
B13: 1.6 | C13: XXXXXXXXXXXXXXXXXXXXXXXXXXXXXXXXXXXXXXXXXX | D13: xx | E13: 1 | F13: =_xlfn.XLOOKUP(B13,'CPU 1'!$F$1:$CI$1,'CPU 1'!$F$182:$CI$182) -> 0 | G13: =F13*E13 -> 0 | H13: =G13/$G$44 -> #DIV/0!
B14: 1.7 | C14: XXXXXXXXXXXXXXXXXXXXXXXXXXXXXXXXXXXXXXXXXX | D14: xx | E14: 1 | F14: =_xlfn.XLOOKUP(B14,'CPU 1'!$F$1:$CI$1,'CPU 1'!$F$182:$CI$182) -> 0 | G14: =F14*E14 -> 0 | H14: =G14/$G$44 -> #DIV/0!
B15: 1.8 | C15: XXXXXXXXXXXXXXXXXXXXXXXXXXXXXXXXXXXXXXXXXX | D15: xx | E15: 1 | F15: =_xlfn.XLOOKUP(B15,'CPU 1'!$F$1:$CI$1,'CPU 1'!$F$182:$CI$182) -> 0 | G15: =F15*E15 -> 0 | H15: =G15/$G$44 -> #DIV/0!
A16: CPU 2 | B16: 2 | C16: XXXXXXXXXXXXXXXXXXXX
B17: 2.1 | C17: XXXXXXXXXXXXXXXXXXXXXX | H17: =G17/$G$44 -> #DIV/0!
B18: 2.1.1 | C18: XXXXXXXXXXXXXXXXXXXXXXXXXXXXXXXXXXXXXXXXXX | D18: xx | E18: 1 | F18: =_xlfn.XLOOKUP(B18,'CPU 2'!$F$1:$CF$1,'CPU 2'!$F$182:$CF$182) -> 0 | G18: =F18*E18 -> 0 | H18: =G18/$G$44 -> #DIV/0!
B19: 2.1.2 | C19: XXXXXXXXXXXXXXXXXXXXXXXXXXXXXXXXXXXXXXXXXX | D19: xx | E19: 1 | F19: =_xlfn.XLOOKUP(B19,'CPU 2'!$F$1:$CF$1,'CPU 2'!$F$182:$CF$182) -> 0 | G19: =F19*E19 -> 0 | H19: =G19/$G$44 -> #DIV/0!
A20: CPU 3 | B20: 2.2 | C20: XXXXXXXXXXXXXXXXXXXXXX | H20: =G20/$G$44 -> #DIV/0!
B21: 2.2.1 | C21: XXXXXXXXXXXXXXXXXXXXXXXXXXXXXXXXXXXXXXXXXX | D21: xx | E21: 1 | F21: =_xlfn.XLOOKUP(B21,'CPU 3'!$F$1:$CL$1,'CPU 3'!$F$182:$CL$182) -> 0 | G21: =F21*E21 -> 0 | H21: =G21/$G$44 -> #DIV/0!
B22: 2.2.2 | C22: XXXXXXXXXXXXXXXXXXXXXXXXXXXXXXXXXXXXXXXXXX | D22: xx | E22: 1 | F22: =_xlfn.XLOOKUP(B22,'CPU 3'!$F$1:$CL$1,'CPU 3'!$F$182:$CL$182) -> 0 | G22: =F22*E22 -> 0 | H22: =G22/$G$44 -> #DIV/0!
B23: 2.2.3 | C23: XXXXXXXXXXXXXXXXXXXXXXXXXXXXXXXXXXXXXXXXXX | D23: xx | E23: 1 | F23: =_xlfn.XLOOKUP(B23,'CPU 3'!$F$1:$CL$1,'CPU 3'!$F$182:$CL$182) -> 0 | G23: =F23*E23 -> 0 | H23: =G23/$G$44 -> #DIV/0!
B24: 2.2.4 | C24: XXXXXXXXXXXXXXXXXXXXXXXXXXXXXXXXXXXXXXXXXX | D24: xx | E24: 1 | F24: =_xlfn.XLOOKUP(B24,'CPU 3'!$F$1:$CL$1,'CPU 3'!$F$182:$CL$182) -> 0 | G24: =F24*E24 -> 0 | H24: =G24/$G$44 -> #DIV/0!
B25: 2.3 | C25: XXXXXXXXXXXXXXXXXXXXXX | H25: =G25/$G$44 -> #DIV/0!
B26: 2.3.1 | C26: XXXXXXXXXXXXXXXXXXXXXXXXXXXXXXXXXXXXXXXXXX | D26: xx | E26: 1 | F26: =_xlfn.XLOOKUP(B26,'CPU 3'!$F$1:$CL$1,'CPU 3'!$F$182:$CL$182) -> 0 | G26: =F26*E26 -> 0 | H26: =G26/$G$44 -> #DIV/0!
B27: 2.3.2 | C27: XXXXXXXXXXXXXXXXXXXXXXXXXXXXXXXXXXXXXXXXXX | D27: xx | E27: 1 | F27: =_xlfn.XLOOKUP(B27,'CPU 3'!$F$1:$CL$1,'CPU 3'!$F$182:$CL$182) -> 0 | G27: =F27*E27 -> 0 | H27: =G27/$G$44 -> #DIV/0!
A28: CPU 4 | B28: 2.4 | C28: XXXXXXXXXXXXXXXXXXXXXX | H28: =G28/$G$44 -> #DIV/0!
B29: 2.4.1 | C29: XXXXXXXXXXXXXXXXXXXXXXXXXXXXXXXXXXXXXXXXXX | D29: xx | E29: 1 | F29: =_xlfn.XLOOKUP(B29,'CPU 4'!$F$1:$CL$1,'CPU 4'!$F$182:$CL$182) -> 0 | G29: =F29*E29 -> 0 | H29: =G29/$G$44 -> #DIV/0!
B30: 2.4.2 | C30: XXXXXXXXXXXXXXXXXXXXXXXXXXXXXXXXXXXXXXXXXX | D30: xx | E30: 1 | F30: =_xlfn.XLOOKUP(B30,'CPU 4'!$F$1:$CL$1,'CPU 4'!$F$182:$CL$182) -> 0 | G30: =F30*E30 -> 0 | H30: =G30/$G$44 -> #DIV/0!
B31: 2.4.3 | C31: XXXXXXXXXXXXXXXXXXXXXXXXXXXXXXXXXXXXXXXXXX | D31: xx | E31: 1 | F31: =_xlfn.XLOOKUP(B31,'CPU 4'!$F$1:$CL$1,'CPU 4'!$F$182:$CL$182) -> 0 | G31: =F31*E31 -> 0 | H31: =G31/$G$44 -> #DIV/0!
B32: 2.4.4 | C32: XXXXXXXXXXXXXXXXXXXXXXXXXXXXXXXXXXXXXXXXXX | D32: xx | E32: 1 | F32: =_xlfn.XLOOKUP(B32,'CPU 4'!$F$1:$CL$1,'CPU 4'!$F$182:$CL$182) -> 0 | G32: =F32*E32 -> 0 | H32: =G32/$G$44 -> #DIV/0!
B33: 2.5 | C33: XXXXXXXXXXXXXXXXXXXXXX | H33: =G33/$G$44 -> #DIV/0!
B34: 2.5.1 | C34: XXXXXXXXXXXXXXXXXXXXXXXXXXXXXXXXXXXXXXXXXX | D34: xx | E34: 1 | F34: =_xlfn.XLOOKUP(B34,'CPU 4'!$F$1:$CL$1,'CPU 4'!$F$182:$CL$182) -> 0 | G34: =F34*E34 -> 0 | H34: =G34/$G$44 -> #DIV/0!
B35: 2.5.2 | C35: XXXXXXXXXXXXXXXXXXXXXXXXXXXXXXXXXXXXXXXXXX | D35: xx | E35: 1 | F35: =_xlfn.XLOOKUP(B35,'CPU 4'!$F$1:$CL$1,'CPU 4'!$F$182:$CL$182) -> 0 | G35: =F35*E35 -> 0 | H35: =G35/$G$44 -> #DIV/0!
A36: CPU 5 | B36: 2.6 | C36: XXXXXXXXXXXXXXXXXXXXXX | H36: =G36/$G$44 -> #DIV/0!
B37: 2.6.1 | C37: XXXXXXXXXXXXXXXXXXXXXXXXXXXXXXXXXXXXXXXXXX | D37: xx | E37: 1 | F37: =_xlfn.XLOOKUP(B37,'CPU 5'!$F$1:$CC$1,'CPU 5'!$F$182:$CC$182) -> 0 | G37: =F37*E37 -> 0 | H37: =G37/$G$44 -> #DIV/0!
B38: 2.7 | C38: XXXXXXXXXXXXXXXXXXXXXX | H38: =G38/$G$44 -> #DIV/0!
B39: 2.7.1 | C39: XXXXXXXXXXXXXXXXXXXXXXXXXXXXXXXXXXXXXXXXXX | D39: xx | E39: 1 | F39: =_xlfn.XLOOKUP(B39,'CPU 5'!$F$1:$CC$1,'CPU 5'!$F$182:$CC$182) -> 0 | G39: =F39*E39 -> 0 | H39: =G39/$G$44 -> #DIV/0!
B40: 2.8 | C40: XXXXXXXXXXXXXXXXXXXXXX | H40: =G40/$G$44 -> #DIV/0!
B41: 2.8.1 | C41: XXXXXXXXXXXXXXXXXXXXXXXXXXXXXXXXXXXXXXXXXX | D41: xx | E41: 1 | F41: =_xlfn.XLOOKUP(B41,'CPU 5'!$F$1:$CC$1,'CPU 5'!$F$182:$CC$182) -> 0 | G41: =F41*E41 -> 0 | H41: =G41/$G$44 -> #DIV/0!
B42: 2.9 | C42: XXXXXXXXXXXXXXXXXXXXXX | H42: =G42/$G$44 -> #DIV/0!
B43: 2.9.1 | C43: XXXXXXXXXXXXXXXXXXXXXXXXXXXXXXXXXXXXXXXXXX | D43: xx | E43: 1 | F43: =_xlfn.XLOOKUP(B43,'CPU 5'!$F$1:$CC$1,'CPU 5'!$F$182:$CC$182) -> 0 | G43: =F43*E43 -> 0 | H43: =G43/$G$44 -> #DIV/0!
B44: TOTAL GERAL | G44: =SUM(G7:G43) -> 0
B45: NOTA: 1 - A base de cáculo para retenção do INSS pela contratante é somente sobre a parcela mão de obra que corresponde a XX% dos custos, por se tratar de um serviço que inclui equipamentos e materiais conforme IN 971/2009; 2 - A presente proposta prever a dedução de valor de material, para apuração da base de cálculo do INSS conforme instrução normativa de cada municipio; 3 - INSS e o ISS deverão ser sobre a parcela de mão de obra.
B46: PREMISSAS:
B54: LISTA DE DESVIOS:

Sheet CPU  1
B1: =QQP!G44 -> 0 | D1: CPU | E1: 1 | F1: =QQP!B8 -> 1.1 | G1: =H182 -> 0 | I1: =QQP!B9 -> 1.2 | J1: =K182 -> 0 | L1: =QQP!B10 -> 1.3 | M1: =N182 -> 0 | O1: =QQP!B11 -> 1.4 | P1: =Q182 -> 0 | R1: =QQP!B12 -> 1.5 | S1: =T182 -> 0 | U1: =QQP!B13 -> 1.6 | V1: =W182 -> 0 | X1: =QQP!B14 -> 1.7 | Y1: =Z182 -> 0 | AA1: =QQP!B15 -> 1.8 | AB1: =AC182 -> 0
B2: Composição de Preços Unitários | F2: =_xlfn.XLOOKUP(F1,QQP!$B$8:$B$43,QQP!$C$8:$C$43) -> XXXXXXXXXXXXXXXXXXXXXXXXXXXXXXXXXXXXXXXXXX | I2: =_xlfn.XLOOKUP(I1,QQP!$B$8:$B$43,QQP!$C$8:$C$43) -> XXXXXXXXXXXXXXXXXXXXXXXXXXXXXXXXXXXXXXXXXX | L2: =_xlfn.XLOOKUP(L1,QQP!$B$8:$B$43,QQP!$C$8:$C$43) -> XXXXXXXXXXXXXXXXXXXXXXXXXXXXXXXXXXXXXXXXXX | O2: =_xlfn.XLOOKUP(O1,QQP!$B$8:$B$43,QQP!$C$8:$C$43) -> XXXXXXXXXXXXXXXXXXXXXXXXXXXXXXXXXXXXXXXXXX | R2: =_xlfn.XLOOKUP(R1,QQP!$B$8:$B$43,QQP!$C$8:$C$43) -> XXXXXXXXXXXXXXXXXXXXXXXXXXXXXXXXXXXXXXXXXX | U2: =_xlfn.XLOOKUP(U1,QQP!$B$8:$B$43,QQP!$C$8:$C$43) -> XXXXXXXXXXXXXXXXXXXXXXXXXXXXXXXXXXXXXXXXXX | X2: =_xlfn.XLOOKUP(X1,QQP!$B$8:$B$43,QQP!$C$8:$C$43) -> XXXXXXXXXXXXXXXXXXXXXXXXXXXXXXXXXXXXXXXXXX | AA2: =_xlfn.XLOOKUP(AA1,QQP!$B$8:$B$43,QQP!$C$8:$C$43) -> XXXXXXXXXXXXXXXXXXXXXXXXXXXXXXXXXXXXXXXXXX | AE2: CHECK
G3: =_xlfn.XLOOKUP(F1,QQP!$B$8:$B$43,QQP!$D$8:$D$43) -> xx | H3: =_xlfn.XLOOKUP(F1,QQP!$B$8:$B$43,QQP!$E$8:$E$43) -> 1 | J3: =_xlfn.XLOOKUP(I1,QQP!$B$8:$B$43,QQP!$D$8:$D$43) -> xx | K3: =_xlfn.XLOOKUP(I1,QQP!$B$8:$B$43,QQP!$E$8:$E$43) -> 1 | M3: =_xlfn.XLOOKUP(L1,QQP!$B$8:$B$43,QQP!$D$8:$D$43) -> xx | N3: =_xlfn.XLOOKUP(L1,QQP!$B$8:$B$43,QQP!$E$8:$E$43) -> 1 | P3: =_xlfn.XLOOKUP(O1,QQP!$B$8:$B$43,QQP!$D$8:$D$43) -> xx | Q3: =_xlfn.XLOOKUP(O1,QQP!$B$8:$B$43,QQP!$E$8:$E$43) -> 1 | S3: =_xlfn.XLOOKUP(R1,QQP!$B$8:$B$43,QQP!$D$8:$D$43) -> xx | T3: =_xlfn.XLOOKUP(R1,QQP!$B$8:$B$43,QQP!$E$8:$E$43) -> 1 | V3: =_xlfn.XLOOKUP(U1,QQP!$B$8:$B$43,QQP!$D$8:$D$43) -> xx | W3: =_xlfn.XLOOKUP(U1,QQP!$B$8:$B$43,QQP!$E$8:$E$43) -> 1 | Y3: =_xlfn.XLOOKUP(X1,QQP!$B$8:$B$43,QQP!$D$8:$D$43) -> xx | Z3: =_xlfn.XLOOKUP(X1,QQP!$B$8:$B$43,QQP!$E$8:$E$43) -> 1 | AB3: =_xlfn.XLOOKUP(AA1,QQP!$B$8:$B$43,QQP!$D$8:$D$43) -> xx | AC3: =_xlfn.XLOOKUP(AA1,QQP!$B$8:$B$43,QQP!$E$8:$E$43) -> 1
B5: A - Mão de Obra + Encargos
B6: Cód. | C6: Discriminação | D6: Unid | E6: P.Unit | F6: Quant | G6: F.utiliz | H6: Custo | I6: Quant | J6: F.utiliz | K6: Custo | L6: Quant | M6: F.utiliz | N6: Custo | O6: Quant | P6: F.utiliz | Q6: Custo | R6: Quant | S6: F.utiliz | T6: Custo | U6: Quant | V6: F.utiliz | W6: Custo | X6: Quant | Y6: F.utiliz | Z6: Custo | AA6: Quant | AB6: F.utiliz | AC6: Custo | AE6: Quant | AF6: F.utiliz | AG6: Custo
B7: =MO!B3 -> P01 | C7: =MO!C3 -> Supervisor | D7: hh | E7: =MO!K3 -> 75.068182 | H7: =G7*F7*$E7 -> 0 | K7: =J7*I7*$E7 -> 0 | N7: =M7*L7*$E7 -> 0 | Q7: =P7*O7*$E7 -> 0 | T7: =S7*R7*$E7 -> 0 | W7: =V7*U7*$E7 -> 0 | Z7: =Y7*X7*$E7 -> 0 | AC7: =AB7*AA7*$E7 -> 0 | AG7: =K7*$K$3+Z7*$Z$3+H7*$H$3+N7*$N$3+Q7*$Q$3+T7*$T$3+W7*$W$3+AC7*$AC$3 -> 0 | AH7: =AG7/$AG$162 -> #DIV/0!
B8: =MO!B4 -> P02 | C8: =MO!C4 -> Encarregado | D8: hh | E8: =MO!K4 -> 40.036364 | H8: =G8*F8*$E8 -> 0 | K8: =J8*I8*$E8 -> 0 | N8: =M8*L8*$E8 -> 0 | Q8: =P8*O8*$E8 -> 0 | T8: =S8*R8*$E8 -> 0 | W8: =V8*U8*$E8 -> 0 | Z8: =Y8*X8*$E8 -> 0 | AC8: =AB8*AA8*$E8 -> 0 | AG8: =K8*$K$3+Z8*$Z$3+H8*$H$3+N8*$N$3+Q8*$Q$3+T8*$T$3+W8*$W$3+AC8*$AC$3 -> 0 | AH8: =AG8/$AG$162 -> #DIV/0!
B9: =MO!B5 -> P03 | C9: =MO!C5 -> Técnico SSMA | D9: hh | E9: =MO!K5 -> 40.036364 | H9: =G9*F9*$E9 -> 0 | K9: =J9*I9*$E9 -> 0 | N9: =M9*L9*$E9 -> 0 | Q9: =P9*O9*$E9 -> 0 | T9: =S9*R9*$E9 -> 0 | W9: =V9*U9*$E9 -> 0 | Z9: =Y9*X9*$E9 -> 0 | AC9: =AB9*AA9*$E9 -> 0 | AG9: =K9*$K$3+Z9*$Z$3+H9*$H$3+N9*$N$3+Q9*$Q$3+T9*$T$3+W9*$W$3+AC9*$AC$3 -> 0 | AH9: =AG9/$AG$162 -> #DIV/0!
B10: =MO!B6 -> P04 | C10: =MO!C6 -> Pedreiro | D10: hh | E10: =MO!K6 -> 19.767955 | H10: =G10*F10*$E10 -> 0 | K10: =J10*I10*$E10 -> 0 | N10: =M10*L10*$E10 -> 0 | Q10: =P10*O10*$E10 -> 0 | T10: =S10*R10*$E10 -> 0 | W10: =V10*U10*$E10 -> 0 | Z10: =Y10*X10*$E10 -> 0 | AC10: =AB10*AA10*$E10 -> 0 | AG10: =K10*$K$3+Z10*$Z$3+H10*$H$3+N10*$N$3+Q10*$Q$3+T10*$T$3+W10*$W$3+AC10*$AC$3 -> 0 | AH10: =AG10/$AG$162 -> #DIV/0!
B11: =MO!B7 -> P05 | C11: =MO!C7 -> Carpinteiro | D11: hh | E11: =MO!K7 -> 19.767955 | H11: =G11*F11*$E11 -> 0 | K11: =J11*I11*$E11 -> 0 | N11: =M11*L11*$E11 -> 0 | Q11: =P11*O11*$E11 -> 0 | T11: =S11*R11*$E11 -> 0 | W11: =V11*U11*$E11 -> 0 | Z11: =Y11*X11*$E11 -> 0 | AC11: =AB11*AA11*$E11 -> 0 | AG11: =K11*$K$3+Z11*$Z$3+H11*$H$3+N11*$N$3+Q11*$Q$3+T11*$T$3+W11*$W$3+AC11*$AC$3 -> 0 | AH11: =AG11/$AG$162 -> #DIV/0!
B12: =MO!B8 -> P06 | C12: =MO!C8 -> Eletricista | D12: hh | E12: =MO!K8 -> 26.023636 | H12: =G12*F12*$E12 -> 0 | K12: =J12*I12*$E12 -> 0 | N12: =M12*L12*$E12 -> 0 | Q12: =P12*O12*$E12 -> 0 | T12: =S12*R12*$E12 -> 0 | W12: =V12*U12*$E12 -> 0 | Z12: =Y12*X12*$E12 -> 0 | AC12: =AB12*AA12*$E12 -> 0 | AG12: =K12*$K$3+Z12*$Z$3+H12*$H$3+N12*$N$3+Q12*$Q$3+T12*$T$3+W12*$W$3+AC12*$AC$3 -> 0 | AH12: =AG12/$AG$162 -> #DIV/0!
B13: =MO!B9 -> P07 | C13: =MO!C9 -> Ajudante | D13: hh | E13: =MO!K9 -> 13.962682 | H13: =G13*F13*$E13 -> 0 | K13: =J13*I13*$E13 -> 0 | N13: =M13*L13*$E13 -> 0 | Q13: =P13*O13*$E13 -> 0 | T13: =S13*R13*$E13 -> 0 | W13: =V13*U13*$E13 -> 0 | Z13: =Y13*X13*$E13 -> 0 | AC13: =AB13*AA13*$E13 -> 0 | AG13: =K13*$K$3+Z13*$Z$3+H13*$H$3+N13*$N$3+Q13*$Q$3+T13*$T$3+W13*$W$3+AC13*$AC$3 -> 0 | AH13: =AG13/$AG$162 -> #DIV/0!
B14: =MO!B10 -> P08 | C14: =MO!C10 -> Armador | D14: hh | E14: =MO!K10 -> 19.767955 | H14: =G14*F14*$E14 -> 0 | K14: =J14*I14*$E14 -> 0 | N14: =M14*L14*$E14 -> 0 | Q14: =P14*O14*$E14 -> 0 | T14: =S14*R14*$E14 -> 0 | W14: =V14*U14*$E14 -> 0 | Z14: =Y14*X14*$E14 -> 0 | AC14: =AB14*AA14*$E14 -> 0 | AG14: =K14*$K$3+Z14*$Z$3+H14*$H$3+N14*$N$3+Q14*$Q$3+T14*$T$3+W14*$W$3+AC14*$AC$3 -> 0 | AH14: =AG14/$AG$162 -> #DIV/0!
B15: =MO!B11 -> P09 | C15: =MO!C11 -> Engenheiro | D15: hh | E15: =MO!K11 -> 112.302 | H15: =G15*F15*$E15 -> 0 | K15: =J15*I15*$E15 -> 0 | N15: =M15*L15*$E15 -> 0 | Q15: =P15*O15*$E15 -> 0 | T15: =S15*R15*$E15 -> 0 | W15: =V15*U15*$E15 -> 0 | Z15: =Y15*X15*$E15 -> 0 | AC15: =AB15*AA15*$E15 -> 0 | AG15: =K15*$K$3+Z15*$Z$3+H15*$H$3+N15*$N$3+Q15*$Q$3+T15*$T$3+W15*$W$3+AC15*$AC$3 -> 0 | AH15: =AG15/$AG$162 -> #DIV/0!
B16: =MO!B12 -> P10 | C16: =MO!C12 -> Planejador | D16: hh | E16: =MO!K12 -> 60.054545 | H16: =G16*F16*$E16 -> 0 | K16: =J16*I16*$E16 -> 0 | N16: =M16*L16*$E16 -> 0 | Q16: =P16*O16*$E16 -> 0 | T16: =S16*R16*$E16 -> 0 | W16: =V16*U16*$E16 -> 0 | Z16: =Y16*X16*$E16 -> 0 | AC16: =AB16*AA16*$E16 -> 0 | AG16: =K16*$K$3+Z16*$Z$3+H16*$H$3+N16*$N$3+Q16*$Q$3+T16*$T$3+W16*$W$3+AC16*$AC$3 -> 0 | AH16: =AG16/$AG$162 -> #DIV/0!
B17: =MO!B13 -> P11 | C17: =MO!C13 -> Tópografo | D17: hh | E17: =MO!K13 -> 38.034545 | H17: =G17*F17*$E17 -> 0 | K17: =J17*I17*$E17 -> 0 | N17: =M17*L17*$E17 -> 0 | Q17: =P17*O17*$E17 -> 0 | T17: =S17*R17*$E17 -> 0 | W17: =V17*U17*$E17 -> 0 | Z17: =Y17*X17*$E17 -> 0 | AC17: =AB17*AA17*$E17 -> 0 | AG17: =K17*$K$3+Z17*$Z$3+H17*$H$3+N17*$N$3+Q17*$Q$3+T17*$T$3+W17*$W$3+AC17*$AC$3 -> 0 | AH17: =AG17/$AG$162 -> #DIV/0!
B18: =MO!B14 -> P12 | C18: =MO!C14 -> Auxiliar de Topografia | D18: hh | E18: =MO!K14 -> 17.015455 | H18: =G18*F18*$E18 -> 0 | K18: =J18*I18*$E18 -> 0 | N18: =M18*L18*$E18 -> 0 | Q18: =P18*O18*$E18 -> 0 | T18: =S18*R18*$E18 -> 0 | W18: =V18*U18*$E18 -> 0 | Z18: =Y18*X18*$E18 -> 0 | AC18: =AB18*AA18*$E18 -> 0 | AG18: =K18*$K$3+Z18*$Z$3+H18*$H$3+N18*$N$3+Q18*$Q$3+T18*$T$3+W18*$W$3+AC18*$AC$3 -> 0 | AH18: =AG18/$AG$162 -> #DIV/0!
... B22: =MO!B18 -> P16 | C22: =MO!C18 -> 0 | D22: hh | E22: =MO!K18 -> 0 | H22: =G22*F22*$E22 -> 0 | K22: =J22*I22*$E22 -> 0 | N22: =M22*L22*$E22 -> 0 | Q22: =P22*O22*$E22 -> 0 | T22: =S22*R22*$E22 -> 0 | W22: =V22*U22*$E22 -> 0 | Z22: =Y22*X22*$E22 -> 0 | AC22: =AB22*AA22*$E22 -> 0 | AG22: =K22*$K$3+Z22*$Z$3+H22*$H$3+N22*$N$3+Q22*$Q$3+T22*$T$3+W22*$W$3+AC22*$AC$3 -> 0 | AH22: =AG22/$AG$162 -> #DIV/0!
B23: A - Custo Total de Mão de Obra: | F23: =SUM(F7:F22) -> 0 | G23: =SUM(G7:G22) -> 0 | H23: =SUM(H7:H22) -> 0 | I23: =SUM(I7:I22) -> 0 | J23: =SUM(J7:J22) -> 0 | K23: =SUM(K7:K22) -> 0 | L23: =SUM(L7:L22) -> 0 | M23: =SUM(M7:M22) -> 0 | ... AC23: =SUM(AC7:AC22) -> 0 | AE23: =SUM(AE7:AE22) -> 0 | AF23: =SUM(AF7:AF22) -> 0 | AG23: =SUM(AG7:AG22) -> 0
B24: B – Equipamentos e Ferramentas
B25: Cód. | C25: Discriminação | D25: Unid | E25: P.Unit | F25: Quant | G25: F.utiliz | H25: Custo | I25: Quant | J25: F.utiliz | K25: Custo | L25: Quant | M25: F.utiliz | N25: Custo | O25: Quant | P25: F.utiliz | Q25: Custo | R25: Quant | S25: F.utiliz | T25: Custo | U25: Quant | V25: F.utiliz | W25: Custo | X25: Quant | Y25: F.utiliz | Z25: Custo | AA25: Quant | AB25: F.utiliz | AC25: Custo | AE25: Quant | AF25: F.utiliz | AG25: Custo
B26: E01 | C26: Alavanca, picareta, enxada, cavador, pá | D26: vb | E26: =250+110+60+120+250 -> 790 | H26: =G26*F26*$E26 -> 0 | K26: =J26*I26*$E26 -> 0 | N26: =M26*L26*$E26 -> 0 | Q26: =P26*O26*$E26 -> 0 | T26: =S26*R26*$E26 -> 0 | W26: =V26*U26*$E26 -> 0 | Z26: =Y26*X26*$E26 -> 0 | AC26: =AB26*AA26*$E26 -> 0 | AG26: =K26*$K$3+Z26*$Z$3+H26*$H$3+N26*$N$3+Q26*$Q$3+T26*$T$3+W26*$W$3+AC26*$AC$3 -> 0 | AH26: =AG26/$AG$162 -> #DIV/0!
B27: E02 | C27: Banheiro hidraulico - locação | D27: vb/mês | E27: 4000 | H27: =G27*F27*$E27 -> 0 | K27: =J27*I27*$E27 -> 0 | N27: =M27*L27*$E27 -> 0 | Q27: =P27*O27*$E27 -> 0 | T27: =S27*R27*$E27 -> 0 | W27: =V27*U27*$E27 -> 0 | Z27: =Y27*X27*$E27 -> 0 | AC27: =AB27*AA27*$E27 -> 0 | AG27: =K27*$K$3+Z27*$Z$3+H27*$H$3+N27*$N$3+Q27*$Q$3+T27*$T$3+W27*$W$3+AC27*$AC$3 -> 0 | AH27: =AG27/$AG$162 -> #DIV/0!
B28: E03 | C28: Barreira física metalica | D28: pç | E28: 350 | H28: =G28*F28*$E28 -> 0 | K28: =J28*I28*$E28 -> 0 | N28: =M28*L28*$E28 -> 0 | Q28: =P28*O28*$E28 -> 0 | T28: =S28*R28*$E28 -> 0 | W28: =V28*U28*$E28 -> 0 | Z28: =Y28*X28*$E28 -> 0 | AC28: =AB28*AA28*$E28 -> 0 | AG28: =K28*$K$3+Z28*$Z$3+H28*$H$3+N28*$N$3+Q28*$Q$3+T28*$T$3+W28*$W$3+AC28*$AC$3 -> 0 | AH28: =AG28/$AG$162 -> #DIV/0!
B29: E04 | C29: Bebedouro 4 torneiras 50L | D29: unid | E29: 3500 | H29: =G29*F29*$E29 -> 0 | K29: =J29*I29*$E29 -> 0 | N29: =M29*L29*$E29 -> 0 | Q29: =P29*O29*$E29 -> 0 | T29: =S29*R29*$E29 -> 0 | W29: =V29*U29*$E29 -> 0 | Z29: =Y29*X29*$E29 -> 0 | AC29: =AB29*AA29*$E29 -> 0 | AG29: =K29*$K$3+Z29*$Z$3+H29*$H$3+N29*$N$3+Q29*$Q$3+T29*$T$3+W29*$W$3+AC29*$AC$3 -> 0 | AH29: =AG29/$AG$162 -> #DIV/0!
B30: E05 | C30: Caçamba de entulho 4m³ | D30: Vb/mês | E30: 800 | H30: =G30*F30*$E30 -> 0 | K30: =J30*I30*$E30 -> 0 | N30: =M30*L30*$E30 -> 0 | Q30: =P30*O30*$E30 -> 0 | T30: =S30*R30*$E30 -> 0 | W30: =V30*U30*$E30 -> 0 | Z30: =Y30*X30*$E30 -> 0 | AC30: =AB30*AA30*$E30 -> 0 | AG30: =K30*$K$3+Z30*$Z$3+H30*$H$3+N30*$N$3+Q30*$Q$3+T30*$T$3+W30*$W$3+AC30*$AC$3 -> 0 | AH30: =AG30/$AG$162 -> #DIV/0!
B31: E06 | C31: Cadinho solda exotermica | D31: pç | E31: 420 | H31: =G31*F31*$E31 -> 0 | K31: =J31*I31*$E31 -> 0 | N31: =M31*L31*$E31 -> 0 | Q31: =P31*O31*$E31 -> 0 | T31: =S31*R31*$E31 -> 0 | W31: =V31*U31*$E31 -> 0 | Z31: =Y31*X31*$E31 -> 0 | AC31: =AB31*AA31*$E31 -> 0 | AG31: =K31*$K$3+Z31*$Z$3+H31*$H$3+N31*$N$3+Q31*$Q$3+T31*$T$3+W31*$W$3+AC31*$AC$3 -> 0 | AH31: =AG31/$AG$162 -> #DIV/0!
B32: E07 | C32: Caixa dágua 1000L | D32: pç | E32: 480 | H32: =G32*F32*$E32 -> 0 | K32: =J32*I32*$E32 -> 0 | N32: =M32*L32*$E32 -> 0 | Q32: =P32*O32*$E32 -> 0 | T32: =S32*R32*$E32 -> 0 | W32: =V32*U32*$E32 -> 0 | Z32: =Y32*X32*$E32 -> 0 | AC32: =AB32*AA32*$E32 -> 0 | AG32: =K32*$K$3+Z32*$Z$3+H32*$H$3+N32*$N$3+Q32*$Q$3+T32*$T$3+W32*$W$3+AC32*$AC$3 -> 0 | AH32: =AG32/$AG$162 -> #DIV/0!
B33: E08 | C33: Caixa dágua 500L | D33: pç | E33: 250 | H33: =G33*F33*$E33 -> 0 | K33: =J33*I33*$E33 -> 0 | N33: =M33*L33*$E33 -> 0 | Q33: =P33*O33*$E33 -> 0 | T33: =S33*R33*$E33 -> 0 | W33: =V33*U33*$E33 -> 0 | Z33: =Y33*X33*$E33 -> 0 | AC33: =AB33*AA33*$E33 -> 0 | AG33: =K33*$K$3+Z33*$Z$3+H33*$H$3+N33*$N$3+Q33*$Q$3+T33*$T$3+W33*$W$3+AC33*$AC$3 -> 0 | AH33: =AG33/$AG$162 -> #DIV/0!
B34: E09 | C34: Caminhão munck | D34: vb/mês | E34: 40000 | H34: =G34*F34*$E34 -> 0 | K34: =J34*I34*$E34 -> 0 | N34: =M34*L34*$E34 -> 0 | Q34: =P34*O34*$E34 -> 0 | T34: =S34*R34*$E34 -> 0 | W34: =V34*U34*$E34 -> 0 | Z34: =Y34*X34*$E34 -> 0 | AC34: =AB34*AA34*$E34 -> 0 | AG34: =K34*$K$3+Z34*$Z$3+H34*$H$3+N34*$N$3+Q34*$Q$3+T34*$T$3+W34*$W$3+AC34*$AC$3 -> 0 | AH34: =AG34/$AG$162 -> #DIV/0!
B35: E10 | C35: Carro de mão | D35: pç | E35: 450 | H35: =G35*F35*$E35 -> 0 | K35: =J35*I35*$E35 -> 0 | N35: =M35*L35*$E35 -> 0 | Q35: =P35*O35*$E35 -> 0 | T35: =S35*R35*$E35 -> 0 | W35: =V35*U35*$E35 -> 0 | Z35: =Y35*X35*$E35 -> 0 | AC35: =AB35*AA35*$E35 -> 0 | AG35: =K35*$K$3+Z35*$Z$3+H35*$H$3+N35*$N$3+Q35*$Q$3+T35*$T$3+W35*$W$3+AC35*$AC$3 -> 0 | AH35: =AG35/$AG$162 -> #DIV/0!
B36: E11 | C36: Carro plataforma | D36: pç | E36: 1200 | H36: =G36*F36*$E36 -> 0 | K36: =J36*I36*$E36 -> 0 | N36: =M36*L36*$E36 -> 0 | Q36: =P36*O36*$E36 -> 0 | T36: =S36*R36*$E36 -> 0 | W36: =V36*U36*$E36 -> 0 | Z36: =Y36*X36*$E36 -> 0 | AC36: =AB36*AA36*$E36 -> 0 | AG36: =K36*$K$3+Z36*$Z$3+H36*$H$3+N36*$N$3+Q36*$Q$3+T36*$T$3+W36*$W$3+AC36*$AC$3 -> 0 | AH36: =AG36/$AG$162 -> #DIV/0!
B37: E12 | C37: Coletor de resíduo com pedal - 50L (V,V,A,A) | D37: kit | E37: 1200 | H37: =G37*F37*$E37 -> 0 | K37: =J37*I37*$E37 -> 0 | N37: =M37*L37*$E37 -> 0 | Q37: =P37*O37*$E37 -> 0 | T37: =S37*R37*$E37 -> 0 | W37: =V37*U37*$E37 -> 0 | Z37: =Y37*X37*$E37 -> 0 | AC37: =AB37*AA37*$E37 -> 0 | AG37: =K37*$K$3+Z37*$Z$3+H37*$H$3+N37*$N$3+Q37*$Q$3+T37*$T$3+W37*$W$3+AC37*$AC$3 -> 0 | AH37: =AG37/$AG$162 -> #DIV/0!
B38: E13 | C38: Compactador de solo manual | D38: vb | E38: 180 | H38: =G38*F38*$E38 -> 0 | K38: =J38*I38*$E38 -> 0 | N38: =M38*L38*$E38 -> 0 | Q38: =P38*O38*$E38 -> 0 | T38: =S38*R38*$E38 -> 0 | W38: =V38*U38*$E38 -> 0 | Z38: =Y38*X38*$E38 -> 0 | AC38: =AB38*AA38*$E38 -> 0 | AG38: =K38*$K$3+Z38*$Z$3+H38*$H$3+N38*$N$3+Q38*$Q$3+T38*$T$3+W38*$W$3+AC38*$AC$3 -> 0 | AH38: =AG38/$AG$162 -> #DIV/0!
... B41: E16 | C41: Container escritorio | D41: vb/mês | E41: 900 | H41: =G41*F41*$E41 -> 0 | K41: =J41*I41*$E41 -> 0 | N41: =M41*L41*$E41 -> 0 | Q41: =P41*O41*$E41 -> 0 | T41: =S41*R41*$E41 -> 0 | W41: =V41*U41*$E41 -> 0 | Z41: =Y41*X41*$E41 -> 0 | AC41: =AB41*AA41*$E41 -> 0 | AG41: =K41*$K$3+Z41*$Z$3+H41*$H$3+N41*$N$3+Q41*$Q$3+T41*$T$3+W41*$W$3+AC41*$AC$3 -> 0 | AH41: =AG41/$AG$162 -> #DIV/0!
B42: E17 | C42: EPIs | D42: vb/mês | E42: =EPIs!F22 -> 328.76667 | H42: =G42*F42*$E42 -> 0 | K42: =J42*I42*$E42 -> 0 | N42: =M42*L42*$E42 -> 0 | Q42: =P42*O42*$E42 -> 0 | T42: =S42*R42*$E42 -> 0 | W42: =V42*U42*$E42 -> 0 | Z42: =Y42*X42*$E42 -> 0 | AC42: =AB42*AA42*$E42 -> 0 | AG42: =K42*$K$3+Z42*$Z$3+H42*$H$3+N42*$N$3+Q42*$Q$3+T42*$T$3+W42*$W$3+AC42*$AC$3 -> 0 | AH42: =AG42/$AG$162 -> #DIV/0!
B43: E18 | C43: Esmerilhadeira 4-1/2" | D43: und | E43: 2000 | H43: =G43*F43*$E43 -> 0 | K43: =J43*I43*$E43 -> 0 | N43: =M43*L43*$E43 -> 0 | Q43: =P43*O43*$E43 -> 0 | T43: =S43*R43*$E43 -> 0 | W43: =V43*U43*$E43 -> 0 | Z43: =Y43*X43*$E43 -> 0 | AC43: =AB43*AA43*$E43 -> 0 | AG43: =K43*$K$3+Z43*$Z$3+H43*$H$3+N43*$N$3+Q43*$Q$3+T43*$T$3+W43*$W$3+AC43*$AC$3 -> 0 | AH43: =AG43/$AG$162 -> #DIV/0!
B44: E19 | C44: Estação total (com acessorios) | D44: vb/mês | E44: 1350 | H44: =G44*F44*$E44 -> 0 | K44: =J44*I44*$E44 -> 0 | N44: =M44*L44*$E44 -> 0 | Q44: =P44*O44*$E44 -> 0 | T44: =S44*R44*$E44 -> 0 | W44: =V44*U44*$E44 -> 0 | Z44: =Y44*X44*$E44 -> 0 | AC44: =AB44*AA44*$E44 -> 0 | AG44: =K44*$K$3+Z44*$Z$3+H44*$H$3+N44*$N$3+Q44*$Q$3+T44*$T$3+W44*$W$3+AC44*$AC$3 -> 0 | AH44: =AG44/$AG$162 -> #DIV/0!
B45: E20 | C45: Extensões eletricas (plug steck + DJ + DR) 40m | D45: vb | E45: =(40*12.5)+327.8+150+50+60 -> 1087.8 | H45: =G45*F45*$E45 -> 0 | K45: =J45*I45*$E45 -> 0 | N45: =M45*L45*$E45 -> 0 | Q45: =P45*O45*$E45 -> 0 | T45: =S45*R45*$E45 -> 0 | W45: =V45*U45*$E45 -> 0 | Z45: =Y45*X45*$E45 -> 0 | AC45: =AB45*AA45*$E45 -> 0 | AG45: =K45*$K$3+Z45*$Z$3+H45*$H$3+N45*$N$3+Q45*$Q$3+T45*$T$3+W45*$W$3+AC45*$AC$3 -> 0 | AH45: =AG45/$AG$162 -> #DIV/0!
B46: E21 | C46: Ferramentas gerais para obra | D46: vb | E46: 5000 | H46: =G46*F46*$E46 -> 0 | K46: =J46*I46*$E46 -> 0 | N46: =M46*L46*$E46 -> 0 | Q46: =P46*O46*$E46 -> 0 | T46: =S46*R46*$E46 -> 0 | W46: =V46*U46*$E46 -> 0 | Z46: =Y46*X46*$E46 -> 0 | AC46: =AB46*AA46*$E46 -> 0 | AG46: =K46*$K$3+Z46*$Z$3+H46*$H$3+N46*$N$3+Q46*$Q$3+T46*$T$3+W46*$W$3+AC46*$AC$3 -> 0 | AH46: =AG46/$AG$162 -> #DIV/0!
B47: E22 | C47: Freezer 300L | D47: vb | E47: 2500 | H47: =G47*F47*$E47 -> 0 | K47: =J47*I47*$E47 -> 0 | N47: =M47*L47*$E47 -> 0 | Q47: =P47*O47*$E47 -> 0 | T47: =S47*R47*$E47 -> 0 | W47: =V47*U47*$E47 -> 0 | Z47: =Y47*X47*$E47 -> 0 | AC47: =AB47*AA47*$E47 -> 0 | AG47: =K47*$K$3+Z47*$Z$3+H47*$H$3+N47*$N$3+Q47*$Q$3+T47*$T$3+W47*$W$3+AC47*$AC$3 -> 0 | AH47: =AG47/$AG$162 -> #DIV/0!
B48: E23 | C48: Furadeira | D48: pç | E48: 800 | H48: =G48*F48*$E48 -> 0 | K48: =J48*I48*$E48 -> 0 | N48: =M48*L48*$E48 -> 0 | Q48: =P48*O48*$E48 -> 0 | T48: =S48*R48*$E48 -> 0 | W48: =V48*U48*$E48 -> 0 | Z48: =Y48*X48*$E48 -> 0 | AC48: =AB48*AA48*$E48 -> 0 | AG48: =K48*$K$3+Z48*$Z$3+H48*$H$3+N48*$N$3+Q48*$Q$3+T48*$T$3+W48*$W$3+AC48*$AC$3 -> 0 | AH48: =AG48/$AG$162 -> #DIV/0!
B49: E24 | C49: Garrafa térmica 12 L | D49: pç | E49: 210 | H49: =G49*F49*$E49 -> 0 | K49: =J49*I49*$E49 -> 0 | N49: =M49*L49*$E49 -> 0 | Q49: =P49*O49*$E49 -> 0 | T49: =S49*R49*$E49 -> 0 | W49: =V49*U49*$E49 -> 0 | Z49: =Y49*X49*$E49 -> 0 | AC49: =AB49*AA49*$E49 -> 0 | AG49: =K49*$K$3+Z49*$Z$3+H49*$H$3+N49*$N$3+Q49*$Q$3+T49*$T$3+W49*$W$3+AC49*$AC$3 -> 0 | AH49: =AG49/$AG$162 -> #DIV/0!
B50: E25 | C50: Gerador 40KVA | D50: vb/mês | E50: 3200 | H50: =G50*F50*$E50 -> 0 | K50: =J50*I50*$E50 -> 0 | N50: =M50*L50*$E50 -> 0 | Q50: =P50*O50*$E50 -> 0 | T50: =S50*R50*$E50 -> 0 | W50: =V50*U50*$E50 -> 0 | Z50: =Y50*X50*$E50 -> 0 | AC50: =AB50*AA50*$E50 -> 0 | AG50: =K50*$K$3+Z50*$Z$3+H50*$H$3+N50*$N$3+Q50*$Q$3+T50*$T$3+W50*$W$3+AC50*$AC$3 -> 0 | AH50: =AG50/$AG$162 -> #DIV/0!
B51: E26 | C51: Gerador 6KVA | D51: vb/mês | E51: 1200 | H51: =G51*F51*$E51 -> 0 | K51: =J51*I51*$E51 -> 0 | N51: =M51*L51*$E51 -> 0 | Q51: =P51*O51*$E51 -> 0 | T51: =S51*R51*$E51 -> 0 | W51: =V51*U51*$E51 -> 0 | Z51: =Y51*X51*$E51 -> 0 | AC51: =AB51*AA51*$E51 -> 0 | AG51: =K51*$K$3+Z51*$Z$3+H51*$H$3+N51*$N$3+Q51*$Q$3+T51*$T$3+W51*$W$3+AC51*$AC$3 -> 0 | AH51: =AG51/$AG$162 -> #DIV/0!
B52: E27 | C52: Impressora | D52: vb/mês | E52: 350 | H52: =G52*F52*$E52 -> 0 | K52: =J52*I52*$E52 -> 0 | N52: =M52*L52*$E52 -> 0 | Q52: =P52*O52*$E52 -> 0 | T52: =S52*R52*$E52 -> 0 | W52: =V52*U52*$E52 -> 0 | Z52: =Y52*X52*$E52 -> 0 | AC52: =AB52*AA52*$E52 -> 0 | AG52: =K52*$K$3+Z52*$Z$3+H52*$H$3+N52*$N$3+Q52*$Q$3+T52*$T$3+W52*$W$3+AC52*$AC$3 -> 0 | AH52: =AG52/$AG$162 -> #DIV/0!
B53: E28 | C53: Martelete demolição | D53: vb/mês | E53: 900 | H53: =G53*F53*$E53 -> 0 | K53: =J53*I53*$E53 -> 0 | N53: =M53*L53*$E53 -> 0 | Q53: =P53*O53*$E53 -> 0 | T53: =S53*R53*$E53 -> 0 | W53: =V53*U53*$E53 -> 0 | Z53: =Y53*X53*$E53 -> 0 | AC53: =AB53*AA53*$E53 -> 0 | AG53: =K53*$K$3+Z53*$Z$3+H53*$H$3+N53*$N$3+Q53*$Q$3+T53*$T$3+W53*$W$3+AC53*$AC$3 -> 0 | AH53: =AG53/$AG$162 -> #DIV/0!
B54: E29 | C54: Masseira 2x1m | D54: pç | E54: =486.59 -> 486.59 | H54: =G54*F54*$E54 -> 0 | K54: =J54*I54*$E54 -> 0 | N54: =M54*L54*$E54 -> 0 | Q54: =P54*O54*$E54 -> 0 | T54: =S54*R54*$E54 -> 0 | W54: =V54*U54*$E54 -> 0 | Z54: =Y54*X54*$E54 -> 0 | AC54: =AB54*AA54*$E54 -> 0 | AG54: =K54*$K$3+Z54*$Z$3+H54*$H$3+N54*$N$3+Q54*$Q$3+T54*$T$3+W54*$W$3+AC54*$AC$3 -> 0 | AH54: =AG54/$AG$162 -> #DIV/0!
B55: E30 | C55: Misturador de argamassa | D55: pç | E55: 600 | H55: =G55*F55*$E55 -> 0 | K55: =J55*I55*$E55 -> 0 | N55: =M55*L55*$E55 -> 0 | Q55: =P55*O55*$E55 -> 0 | T55: =S55*R55*$E55 -> 0 | W55: =V55*U55*$E55 -> 0 | Z55: =Y55*X55*$E55 -> 0 | AC55: =AB55*AA55*$E55 -> 0 | AG55: =K55*$K$3+Z55*$Z$3+H55*$H$3+N55*$N$3+Q55*$Q$3+T55*$T$3+W55*$W$3+AC55*$AC$3 -> 0 | AH55: =AG55/$AG$162 -> #DIV/0!
B56: E31 | C56: Mobiliario (cadeira, mesa, etc.) | D56: vb/mês | E56: 6000 | H56: =G56*F56*$E56 -> 0 | K56: =J56*I56*$E56 -> 0 | N56: =M56*L56*$E56 -> 0 | Q56: =P56*O56*$E56 -> 0 | T56: =S56*R56*$E56 -> 0 | W56: =V56*U56*$E56 -> 0 | Z56: =Y56*X56*$E56 -> 0 | AC56: =AB56*AA56*$E56 -> 0 | AG56: =K56*$K$3+Z56*$Z$3+H56*$H$3+N56*$N$3+Q56*$Q$3+T56*$T$3+W56*$W$3+AC56*$AC$3 -> 0 | AH56: =AG56/$AG$162 -> #DIV/0!
B57: E32 | C57: Multimetro | D57: pç | E57: 2100 | H57: =G57*F57*$E57 -> 0 | K57: =J57*I57*$E57 -> 0 | N57: =M57*L57*$E57 -> 0 | Q57: =P57*O57*$E57 -> 0 | T57: =S57*R57*$E57 -> 0 | W57: =V57*U57*$E57 -> 0 | Z57: =Y57*X57*$E57 -> 0 | AC57: =AB57*AA57*$E57 -> 0 | AG57: =K57*$K$3+Z57*$Z$3+H57*$H$3+N57*$N$3+Q57*$Q$3+T57*$T$3+W57*$W$3+AC57*$AC$3 -> 0 | AH57: =AG57/$AG$162 -> #DIV/0!
B58: E33 | C58: Painel eletrico para canteiro | D58: vb | E58: 6500 | H58: =G58*F58*$E58 -> 0 | K58: =J58*I58*$E58 -> 0 | N58: =M58*L58*$E58 -> 0 | Q58: =P58*O58*$E58 -> 0 | T58: =S58*R58*$E58 -> 0 | W58: =V58*U58*$E58 -> 0 | Z58: =Y58*X58*$E58 -> 0 | AC58: =AB58*AA58*$E58 -> 0 | AG58: =K58*$K$3+Z58*$Z$3+H58*$H$3+N58*$N$3+Q58*$Q$3+T58*$T$3+W58*$W$3+AC58*$AC$3 -> 0 | AH58: =AG58/$AG$162 -> #DIV/0!
B59: E34 | C59: Painel eletrico para frente de serviço | D59: vb | E59: 3000 | H59: =G59*F59*$E59 -> 0 | K59: =J59*I59*$E59 -> 0 | N59: =M59*L59*$E59 -> 0 | Q59: =P59*O59*$E59 -> 0 | T59: =S59*R59*$E59 -> 0 | W59: =V59*U59*$E59 -> 0 | Z59: =Y59*X59*$E59 -> 0 | AC59: =AB59*AA59*$E59 -> 0 | AG59: =K59*$K$3+Z59*$Z$3+H59*$H$3+N59*$N$3+Q59*$Q$3+T59*$T$3+W59*$W$3+AC59*$AC$3 -> 0 | AH59: =AG59/$AG$162 -> #DIV/0!
B60: E35 | C60: Pedestais para isolamento | D60: vb | E60: 150 | H60: =G60*F60*$E60 -> 0 | K60: =J60*I60*$E60 -> 0 | N60: =M60*L60*$E60 -> 0 | Q60: =P60*O60*$E60 -> 0 | T60: =S60*R60*$E60 -> 0 | W60: =V60*U60*$E60 -> 0 | Z60: =Y60*X60*$E60 -> 0 | AC60: =AB60*AA60*$E60 -> 0 | AG60: =K60*$K$3+Z60*$Z$3+H60*$H$3+N60*$N$3+Q60*$Q$3+T60*$T$3+W60*$W$3+AC60*$AC$3 -> 0 | AH60: =AG60/$AG$162 -> #DIV/0!
B61: E36 | C61: Serra circular | D61: pç | E61: 850 | H61: =G61*F61*$E61 -> 0 | K61: =J61*I61*$E61 -> 0 | N61: =M61*L61*$E61 -> 0 | Q61: =P61*O61*$E61 -> 0 | T61: =S61*R61*$E61 -> 0 | W61: =V61*U61*$E61 -> 0 | Z61: =Y61*X61*$E61 -> 0 | AC61: =AB61*AA61*$E61 -> 0 | AG61: =K61*$K$3+Z61*$Z$3+H61*$H$3+N61*$N$3+Q61*$Q$3+T61*$T$3+W61*$W$3+AC61*$AC$3 -> 0 | AH61: =AG61/$AG$162 -> #DIV/0!
B62: E37 | C62: Tela cerquite | D62: pç | E62: 150 | H62: =G62*F62*$E62 -> 0 | K62: =J62*I62*$E62 -> 0 | N62: =M62*L62*$E62 -> 0 | Q62: =P62*O62*$E62 -> 0 | T62: =S62*R62*$E62 -> 0 | W62: =V62*U62*$E62 -> 0 | Z62: =Y62*X62*$E62 -> 0 | AC62: =AB62*AA62*$E62 -> 0 | AG62: =K62*$K$3+Z62*$Z$3+H62*$H$3+N62*$N$3+Q62*$Q$3+T62*$T$3+W62*$W$3+AC62*$AC$3 -> 0 | AH62: =AG62/$AG$162 -> #DIV/0!
B63: E38 | C63: Tenda 10 x 10m | D63: vb/mês | E63: 1800 | H63: =G63*F63*$E63 -> 0 | K63: =J63*I63*$E63 -> 0 | N63: =M63*L63*$E63 -> 0 | Q63: =P63*O63*$E63 -> 0 | T63: =S63*R63*$E63 -> 0 | W63: =V63*U63*$E63 -> 0 | Z63: =Y63*X63*$E63 -> 0 | AC63: =AB63*AA63*$E63 -> 0 | AG63: =K63*$K$3+Z63*$Z$3+H63*$H$3+N63*$N$3+Q63*$Q$3+T63*$T$3+W63*$W$3+AC63*$AC$3 -> 0 | AH63: =AG63/$AG$162 -> #DIV/0!
B64: E39 | C64: Tenda 3 x 3m | D64: vb | E64: 2000 | H64: =G64*F64*$E64 -> 0 | K64: =J64*I64*$E64 -> 0 | N64: =M64*L64*$E64 -> 0 | Q64: =P64*O64*$E64 -> 0 | T64: =S64*R64*$E64 -> 0 | W64: =V64*U64*$E64 -> 0 | Z64: =Y64*X64*$E64 -> 0 | AC64: =AB64*AA64*$E64 -> 0 | AG64: =K64*$K$3+Z64*$Z$3+H64*$H$3+N64*$N$3+Q64*$Q$3+T64*$T$3+W64*$W$3+AC64*$AC$3 -> 0 | AH64: =AG64/$AG$162 -> #DIV/0!
B65: E40 | C65: Terrometro | D65: diária | E65: 250 | H65: =G65*F65*$E65 -> 0 | K65: =J65*I65*$E65 -> 0 | N65: =M65*L65*$E65 -> 0 | Q65: =P65*O65*$E65 -> 0 | T65: =S65*R65*$E65 -> 0 | W65: =V65*U65*$E65 -> 0 | Z65: =Y65*X65*$E65 -> 0 | AC65: =AB65*AA65*$E65 -> 0 | AG65: =K65*$K$3+Z65*$Z$3+H65*$H$3+N65*$N$3+Q65*$Q$3+T65*$T$3+W65*$W$3+AC65*$AC$3 -> 0 | AH65: =AG65/$AG$162 -> #DIV/0!
B66: E41 | C66: Torquesa SID13 | D66: und | E66: 350 | H66: =G66*F66*$E66 -> 0 | K66: =J66*I66*$E66 -> 0 | N66: =M66*L66*$E66 -> 0 | Q66: =P66*O66*$E66 -> 0 | T66: =S66*R66*$E66 -> 0 | W66: =V66*U66*$E66 -> 0 | Z66: =Y66*X66*$E66 -> 0 | AC66: =AB66*AA66*$E66 -> 0 | AG66: =K66*$K$3+Z66*$Z$3+H66*$H$3+N66*$N$3+Q66*$Q$3+T66*$T$3+W66*$W$3+AC66*$AC$3 -> 0 | AH66: =AG66/$AG$162 -> #DIV/0!
... B74: E49 | C74: Caminhão Basculante | D74: vb/mês | E74: 37000 | H74: =G74*F74*$E74 -> 0 | K74: =J74*I74*$E74 -> 0 | N74: =M74*L74*$E74 -> 0 | Q74: =P74*O74*$E74 -> 0 | T74: =S74*R74*$E74 -> 0 | W74: =V74*U74*$E74 -> 0 | Z74: =Y74*X74*$E74 -> 0 | AC74: =AB74*AA74*$E74 -> 0 | AG74: =K74*$K$3+Z74*$Z$3+H74*$H$3+N74*$N$3+Q74*$Q$3+T74*$T$3+W74*$W$3+AC74*$AC$3 -> 0 | AH74: =AG74/$AG$162 -> #DIV/0!
B75: E50 | H75: =G75*F75*$E75 -> 0 | K75: =J75*I75*$E75 -> 0 | N75: =M75*L75*$E75 -> 0 | Q75: =P75*O75*$E75 -> 0 | T75: =S75*R75*$E75 -> 0 | W75: =V75*U75*$E75 -> 0 | Z75: =Y75*X75*$E75 -> 0 | AC75: =AB75*AA75*$E75 -> 0 | AG75: =K75*$K$3+Z75*$Z$3+H75*$H$3+N75*$N$3+Q75*$Q$3+T75*$T$3+W75*$W$3+AC75*$AC$3 -> 0 | AH75: =AG75/$AG$162 -> #DIV/0!
B76: E51 | H76: =G76*F76*$E76 -> 0 | K76: =J76*I76*$E76 -> 0 | N76: =M76*L76*$E76 -> 0 | Q76: =P76*O76*$E76 -> 0 | T76: =S76*R76*$E76 -> 0 | W76: =V76*U76*$E76 -> 0 | Z76: =Y76*X76*$E76 -> 0 | AC76: =AB76*AA76*$E76 -> 0 | AG76: =K76*$K$3+Z76*$Z$3+H76*$H$3+N76*$N$3+Q76*$Q$3+T76*$T$3+W76*$W$3+AC76*$AC$3 -> 0 | AH76: =AG76/$AG$162 -> #DIV/0!
B77: E52 | H77: =G77*F77*$E77 -> 0 | K77: =J77*I77*$E77 -> 0 | N77: =M77*L77*$E77 -> 0 | Q77: =P77*O77*$E77 -> 0 | T77: =S77*R77*$E77 -> 0 | W77: =V77*U77*$E77 -> 0 | Z77: =Y77*X77*$E77 -> 0 | AC77: =AB77*AA77*$E77 -> 0 | AG77: =K77*$K$3+Z77*$Z$3+H77*$H$3+N77*$N$3+Q77*$Q$3+T77*$T$3+W77*$W$3+AC77*$AC$3 -> 0 | AH77: =AG77/$AG$162 -> #DIV/0!
B78: E53 | H78: =G78*F78*$E78 -> 0 | K78: =J78*I78*$E78 -> 0 | N78: =M78*L78*$E78 -> 0 | Q78: =P78*O78*$E78 -> 0 | T78: =S78*R78*$E78 -> 0 | W78: =V78*U78*$E78 -> 0 | Z78: =Y78*X78*$E78 -> 0 | AC78: =AB78*AA78*$E78 -> 0 | AG78: =K78*$K$3+Z78*$Z$3+H78*$H$3+N78*$N$3+Q78*$Q$3+T78*$T$3+W78*$W$3+AC78*$AC$3 -> 0 | AH78: =AG78/$AG$162 -> #DIV/0!
B79: E54 | H79: =G79*F79*$E79 -> 0 | K79: =J79*I79*$E79 -> 0 | N79: =M79*L79*$E79 -> 0 | Q79: =P79*O79*$E79 -> 0 | T79: =S79*R79*$E79 -> 0 | W79: =V79*U79*$E79 -> 0 | Z79: =Y79*X79*$E79 -> 0 | AC79: =AB79*AA79*$E79 -> 0 | AG79: =K79*$K$3+Z79*$Z$3+H79*$H$3+N79*$N$3+Q79*$Q$3+T79*$T$3+W79*$W$3+AC79*$AC$3 -> 0 | AH79: =AG79/$AG$162 -> #DIV/0!
B80: B - Custo Total de Equipamentos e Ferramentas: | E80: =SUM(#REF!) -> #REF! | H80: =SUM(H26:H79) -> 0 | K80: =SUM(K26:K79) -> 0 | N80: =SUM(N26:N79) -> 0 | Q80: =SUM(Q26:Q79) -> 0 | T80: =SUM(T26:T79) -> 0 | W80: =SUM(W26:W79) -> 0 | Z80: =SUM(Z26:Z79) -> 0 | AC80: =SUM(AC26:AC79) -> 0 | AG80: =SUM(AG26:AG79) -> 0
B81: C – Materiais
B82: Cód. | C82: Discriminação | D82: Unid | E82: P.Unit | F82: Quant | G82: F.utiliz | H82: Custo | I82: Quant | J82: F.utiliz | K82: Custo | L82: Quant | M82: F.utiliz | N82: Custo | O82: Quant | P82: F.utiliz | Q82: Custo | R82: Quant | S82: F.utiliz | T82: Custo | U82: Quant | V82: F.utiliz | W82: Custo | X82: Quant | Y82: F.utiliz | Z82: Custo | AA82: Quant | AB82: F.utiliz | AC82: Custo | AE82: Quant | AF82: F.utiliz | AG82: Custo
B83: M01 | C83: Aço CA-50, (ferro 8.0) | D83: kg | E83: 12.5 | H83: =G83*F83*$E83 -> 0 | K83: =J83*I83*$E83 -> 0 | N83: =M83*L83*$E83 -> 0 | Q83: =P83*O83*$E83 -> 0 | T83: =S83*R83*$E83 -> 0 | W83: =V83*U83*$E83 -> 0 | Z83: =Y83*X83*$E83 -> 0 | AC83: =AB83*AA83*$E83 -> 0 | AG83: =K83*$K$3+Z83*$Z$3+H83*$H$3+N83*$N$3+Q83*$Q$3+T83*$T$3+W83*$W$3+AC83*$AC$3 -> 0 | AH83: =AG83/$AG$162 -> #DIV/0!
B84: M02 | C84: Agua Mineral | D84: litro | E84: 1 | H84: =G84*F84*$E84 -> 0 | K84: =J84*I84*$E84 -> 0 | N84: =M84*L84*$E84 -> 0 | Q84: =P84*O84*$E84 -> 0 | T84: =S84*R84*$E84 -> 0 | W84: =V84*U84*$E84 -> 0 | Z84: =Y84*X84*$E84 -> 0 | AC84: =AB84*AA84*$E84 -> 0 | AG84: =K84*$K$3+Z84*$Z$3+H84*$H$3+N84*$N$3+Q84*$Q$3+T84*$T$3+W84*$W$3+AC84*$AC$3 -> 0 | AH84: =AG84/$AG$162 -> #DIV/0!
B85: M03 | C85: Arame ovalado zincado | D85: m | E85: 1 | H85: =G85*F85*$E85 -> 0 | K85: =J85*I85*$E85 -> 0 | N85: =M85*L85*$E85 -> 0 | Q85: =P85*O85*$E85 -> 0 | T85: =S85*R85*$E85 -> 0 | W85: =V85*U85*$E85 -> 0 | Z85: =Y85*X85*$E85 -> 0 | AC85: =AB85*AA85*$E85 -> 0 | AG85: =K85*$K$3+Z85*$Z$3+H85*$H$3+N85*$N$3+Q85*$Q$3+T85*$T$3+W85*$W$3+AC85*$AC$3 -> 0 | AH85: =AG85/$AG$162 -> #DIV/0!
B86: M04 | C86: Areia | D86: m³ | E86: 120 | H86: =G86*F86*$E86 -> 0 | K86: =J86*I86*$E86 -> 0 | N86: =M86*L86*$E86 -> 0 | Q86: =P86*O86*$E86 -> 0 | T86: =S86*R86*$E86 -> 0 | W86: =V86*U86*$E86 -> 0 | Z86: =Y86*X86*$E86 -> 0 | AC86: =AB86*AA86*$E86 -> 0 | AG86: =K86*$K$3+Z86*$Z$3+H86*$H$3+N86*$N$3+Q86*$Q$3+T86*$T$3+W86*$W$3+AC86*$AC$3 -> 0 | AH86: =AG86/$AG$162 -> #DIV/0!
B87: M05 | C87: Arrame galganizado | D87: kg | E87: =14*1.2 -> 16.8 | H87: =G87*F87*$E87 -> 0 | K87: =J87*I87*$E87 -> 0 | N87: =M87*L87*$E87 -> 0 | Q87: =P87*O87*$E87 -> 0 | T87: =S87*R87*$E87 -> 0 | W87: =V87*U87*$E87 -> 0 | Z87: =Y87*X87*$E87 -> 0 | AC87: =AB87*AA87*$E87 -> 0 | AG87: =K87*$K$3+Z87*$Z$3+H87*$H$3+N87*$N$3+Q87*$Q$3+T87*$T$3+W87*$W$3+AC87*$AC$3 -> 0 | AH87: =AG87/$AG$162 -> #DIV/0!
B88: M06 | C88: Arrame recozido | D88: kg | E88: 12 | H88: =G88*F88*$E88 -> 0 | K88: =J88*I88*$E88 -> 0 | N88: =M88*L88*$E88 -> 0 | Q88: =P88*O88*$E88 -> 0 | T88: =S88*R88*$E88 -> 0 | W88: =V88*U88*$E88 -> 0 | Z88: =Y88*X88*$E88 -> 0 | AC88: =AB88*AA88*$E88 -> 0 | AG88: =K88*$K$3+Z88*$Z$3+H88*$H$3+N88*$N$3+Q88*$Q$3+T88*$T$3+W88*$W$3+AC88*$AC$3 -> 0 | AH88: =AG88/$AG$162 -> #DIV/0!
B89: M07 | C89: Barrote de madeira 7x7cm | D89: m | E89: 15 | H89: =G89*F89*$E89 -> 0 | K89: =J89*I89*$E89 -> 0 | N89: =M89*L89*$E89 -> 0 | Q89: =P89*O89*$E89 -> 0 | T89: =S89*R89*$E89 -> 0 | W89: =V89*U89*$E89 -> 0 | Z89: =Y89*X89*$E89 -> 0 | AC89: =AB89*AA89*$E89 -> 0 | AG89: =K89*$K$3+Z89*$Z$3+H89*$H$3+N89*$N$3+Q89*$Q$3+T89*$T$3+W89*$W$3+AC89*$AC$3 -> 0 | AH89: =AG89/$AG$162 -> #DIV/0!
B90: M08 | C90: Bloco tipo canaleta (14x19x39cm) | D90: peça | E90: 8.9 | H90: =G90*F90*$E90 -> 0 | K90: =J90*I90*$E90 -> 0 | N90: =M90*L90*$E90 -> 0 | Q90: =P90*O90*$E90 -> 0 | T90: =S90*R90*$E90 -> 0 | W90: =V90*U90*$E90 -> 0 | Z90: =Y90*X90*$E90 -> 0 | AC90: =AB90*AA90*$E90 -> 0 | AG90: =K90*$K$3+Z90*$Z$3+H90*$H$3+N90*$N$3+Q90*$Q$3+T90*$T$3+W90*$W$3+AC90*$AC$3 -> 0 | AH90: =AG90/$AG$162 -> #DIV/0!
B91: M09 | C91: Brita 1 | D91: m³ | E91: 220 | H91: =G91*F91*$E91 -> 0 | K91: =J91*I91*$E91 -> 0 | N91: =M91*L91*$E91 -> 0 | Q91: =P91*O91*$E91 -> 0 | T91: =S91*R91*$E91 -> 0 | W91: =V91*U91*$E91 -> 0 | Z91: =Y91*X91*$E91 -> 0 | AC91: =AB91*AA91*$E91 -> 0 | AG91: =K91*$K$3+Z91*$Z$3+H91*$H$3+N91*$N$3+Q91*$Q$3+T91*$T$3+W91*$W$3+AC91*$AC$3 -> 0 | AH91: =AG91/$AG$162 -> #DIV/0!
B92: M11 | C92: Caixa de passagens para aterramento h600 diâmetro 30cm | D92: und | E92: 590 | H92: =G92*F92*$E92 -> 0 | K92: =J92*I92*$E92 -> 0 | N92: =M92*L92*$E92 -> 0 | Q92: =P92*O92*$E92 -> 0 | T92: =S92*R92*$E92 -> 0 | W92: =V92*U92*$E92 -> 0 | Z92: =Y92*X92*$E92 -> 0 | AC92: =AB92*AA92*$E92 -> 0 | AG92: =K92*$K$3+Z92*$Z$3+H92*$H$3+N92*$N$3+Q92*$Q$3+T92*$T$3+W92*$W$3+AC92*$AC$3 -> 0 | AH92: =AG92/$AG$162 -> #DIV/0!
B93: M12 | C93: Catoneira galvanizada 1"x1-1/4 | D93: m | E93: =125/6*1.2 -> 25 | H93: =G93*F93*$E93 -> 0 | K93: =J93*I93*$E93 -> 0 | N93: =M93*L93*$E93 -> 0 | Q93: =P93*O93*$E93 -> 0 | T93: =S93*R93*$E93 -> 0 | W93: =V93*U93*$E93 -> 0 | Z93: =Y93*X93*$E93 -> 0 | AC93: =AB93*AA93*$E93 -> 0 | AG93: =K93*$K$3+Z93*$Z$3+H93*$H$3+N93*$N$3+Q93*$Q$3+T93*$T$3+W93*$W$3+AC93*$AC$3 -> 0 | AH93: =AG93/$AG$162 -> #DIV/0!
B94: M13 | C94: Cercamento e delimitação de canteiro de obra (15x30m) | D94: vb | E94: 10000 | H94: =G94*F94*$E94 -> 0 | K94: =J94*I94*$E94 -> 0 | N94: =M94*L94*$E94 -> 0 | Q94: =P94*O94*$E94 -> 0 | T94: =S94*R94*$E94 -> 0 | W94: =V94*U94*$E94 -> 0 | Z94: =Y94*X94*$E94 -> 0 | AC94: =AB94*AA94*$E94 -> 0 | AG94: =K94*$K$3+Z94*$Z$3+H94*$H$3+N94*$N$3+Q94*$Q$3+T94*$T$3+W94*$W$3+AC94*$AC$3 -> 0 | AH94: =AG94/$AG$162 -> #DIV/0!
B95: M14 | C95: Cimento | D95: saco | E95: 50 | H95: =G95*F95*$E95 -> 0 | K95: =J95*I95*$E95 -> 0 | N95: =M95*L95*$E95 -> 0 | Q95: =P95*O95*$E95 -> 0 | T95: =S95*R95*$E95 -> 0 | W95: =V95*U95*$E95 -> 0 | Z95: =Y95*X95*$E95 -> 0 | AC95: =AB95*AA95*$E95 -> 0 | AG95: =K95*$K$3+Z95*$Z$3+H95*$H$3+N95*$N$3+Q95*$Q$3+T95*$T$3+W95*$W$3+AC95*$AC$3 -> 0 | AH95: =AG95/$AG$162 -> #DIV/0!
B96: M15 | C96: Combustivel - Gasolina | D96: litro | E96: 6.5 | H96: =G96*F96*$E96 -> 0 | K96: =J96*I96*$E96 -> 0 | N96: =M96*L96*$E96 -> 0 | Q96: =P96*O96*$E96 -> 0 | T96: =S96*R96*$E96 -> 0 | W96: =V96*U96*$E96 -> 0 | Z96: =Y96*X96*$E96 -> 0 | AC96: =AB96*AA96*$E96 -> 0 | AG96: =K96*$K$3+Z96*$Z$3+H96*$H$3+N96*$N$3+Q96*$Q$3+T96*$T$3+W96*$W$3+AC96*$AC$3 -> 0 | AH96: =AG96/$AG$162 -> #DIV/0!
B97: M16 | C97: Combustivel - Diesel | D97: litro | E97: 7 | H97: =G97*F97*$E97 -> 0 | K97: =J97*I97*$E97 -> 0 | N97: =M97*L97*$E97 -> 0 | Q97: =P97*O97*$E97 -> 0 | T97: =S97*R97*$E97 -> 0 | W97: =V97*U97*$E97 -> 0 | Z97: =Y97*X97*$E97 -> 0 | AC97: =AB97*AA97*$E97 -> 0 | AG97: =K97*$K$3+Z97*$Z$3+H97*$H$3+N97*$N$3+Q97*$Q$3+T97*$T$3+W97*$W$3+AC97*$AC$3 -> 0 | AH97: =AG97/$AG$162 -> #DIV/0!
B98: M17 | C98: Compensado resinado espessura mínima de 10mm | D98: m² | E98: =120/(2.2*1.1) -> 49.586777 | H98: =G98*F98*$E98 -> 0 | K98: =J98*I98*$E98 -> 0 | N98: =M98*L98*$E98 -> 0 | Q98: =P98*O98*$E98 -> 0 | T98: =S98*R98*$E98 -> 0 | W98: =V98*U98*$E98 -> 0 | Z98: =Y98*X98*$E98 -> 0 | AC98: =AB98*AA98*$E98 -> 0 | AG98: =K98*$K$3+Z98*$Z$3+H98*$H$3+N98*$N$3+Q98*$Q$3+T98*$T$3+W98*$W$3+AC98*$AC$3 -> 0 | AH98: =AG98/$AG$162 -> #DIV/0!
B99: M18 | C99: Concertina dupla clipada 45cm perimetral galvanizada CBT 65 RL 10m com seus respectivos acessórios de fixação | D99: m | E99: =(350/10)*1.2 -> 42 | H99: =G99*F99*$E99 -> 0 | K99: =J99*I99*$E99 -> 0 | N99: =M99*L99*$E99 -> 0 | Q99: =P99*O99*$E99 -> 0 | T99: =S99*R99*$E99 -> 0 | W99: =V99*U99*$E99 -> 0 | Z99: =Y99*X99*$E99 -> 0 | AC99: =AB99*AA99*$E99 -> 0 | AG99: =K99*$K$3+Z99*$Z$3+H99*$H$3+N99*$N$3+Q99*$Q$3+T99*$T$3+W99*$W$3+AC99*$AC$3 -> 0 | AH99: =AG99/$AG$162 -> #DIV/0!
B100: M19 | C100: Concreto usinado 30MPa | D100: m³ | E100: 650 | H100: =G100*F100*$E100 -> 0 | K100: =J100*I100*$E100 -> 0 | N100: =M100*L100*$E100 -> 0 | Q100: =P100*O100*$E100 -> 0 | T100: =S100*R100*$E100 -> 0 | W100: =V100*U100*$E100 -> 0 | Z100: =Y100*X100*$E100 -> 0 | AC100: =AB100*AA100*$E100 -> 0 | AG100: =K100*$K$3+Z100*$Z$3+H100*$H$3+N100*$N$3+Q100*$Q$3+T100*$T$3+W100*$W$3+AC100*$AC$3 -> 0 | AH100: =AG100/$AG$162 -> #DIV/0!
B101: M20 | C101: Espaçadores de ferragem | D101: und | E101: 2 | H101: =G101*F101*$E101 -> 0 | K101: =J101*I101*$E101 -> 0 | N101: =M101*L101*$E101 -> 0 | Q101: =P101*O101*$E101 -> 0 | T101: =S101*R101*$E101 -> 0 | W101: =V101*U101*$E101 -> 0 | Z101: =Y101*X101*$E101 -> 0 | AC101: =AB101*AA101*$E101 -> 0 | AG101: =K101*$K$3+Z101*$Z$3+H101*$H$3+N101*$N$3+Q101*$Q$3+T101*$T$3+W101*$W$3+AC101*$AC$3 -> 0 | AH101: =AG101/$AG$162 -> #DIV/0!
B102: M21 | C102: Treliça - para viga baldrame | D102: m | E102: =45/6 -> 7.5 | H102: =G102*F102*$E102 -> 0 | K102: =J102*I102*$E102 -> 0 | N102: =M102*L102*$E102 -> 0 | Q102: =P102*O102*$E102 -> 0 | T102: =S102*R102*$E102 -> 0 | W102: =V102*U102*$E102 -> 0 | Z102: =Y102*X102*$E102 -> 0 | AC102: =AB102*AA102*$E102 -> 0 | AG102: =K102*$K$3+Z102*$Z$3+H102*$H$3+N102*$N$3+Q102*$Q$3+T102*$T$3+W102*$W$3+AC102*$AC$3 -> 0 | AH102: =AG102/$AG$162 -> #DIV/0!
B103: M22 | C103: Gelo | D103: pacote | E103: 5 | H103: =G103*F103*$E103 -> 0 | K103: =J103*I103*$E103 -> 0 | N103: =M103*L103*$E103 -> 0 | Q103: =P103*O103*$E103 -> 0 | T103: =S103*R103*$E103 -> 0 | W103: =V103*U103*$E103 -> 0 | Z103: =Y103*X103*$E103 -> 0 | AC103: =AB103*AA103*$E103 -> 0 | AG103: =K103*$K$3+Z103*$Z$3+H103*$H$3+N103*$N$3+Q103*$Q$3+T103*$T$3+W103*$W$3+AC103*$AC$3 -> 0 | AH103: =AG103/$AG$162 -> #DIV/0!
B104: M23 | C104: Kit ambiental | D104: vb | E104: 750 | H104: =G104*F104*$E104 -> 0 | K104: =J104*I104*$E104 -> 0 | N104: =M104*L104*$E104 -> 0 | Q104: =P104*O104*$E104 -> 0 | T104: =S104*R104*$E104 -> 0 | W104: =V104*U104*$E104 -> 0 | Z104: =Y104*X104*$E104 -> 0 | AC104: =AB104*AA104*$E104 -> 0 | AG104: =K104*$K$3+Z104*$Z$3+H104*$H$3+N104*$N$3+Q104*$Q$3+T104*$T$3+W104*$W$3+AC104*$AC$3 -> 0 | AH104: =AG104/$AG$162 -> #DIV/0!
B105: M24 | C105: Material de escritório (papel, tinta, grampos, pastas, ...) | D105: vb/mês | E105: 300 | H105: =G105*F105*$E105 -> 0 | K105: =J105*I105*$E105 -> 0 | N105: =M105*L105*$E105 -> 0 | Q105: =P105*O105*$E105 -> 0 | T105: =S105*R105*$E105 -> 0 | W105: =V105*U105*$E105 -> 0 | Z105: =Y105*X105*$E105 -> 0 | AC105: =AB105*AA105*$E105 -> 0 | AG105: =K105*$K$3+Z105*$Z$3+H105*$H$3+N105*$N$3+Q105*$Q$3+T105*$T$3+W105*$W$3+AC105*$AC$3 -> 0 | AH105: =AG105/$AG$162 -> #DIV/0!
B106: M25 | C106: Material de sinalização | D106: und | E106: 550 | H106: =G106*F106*$E106 -> 0 | K106: =J106*I106*$E106 -> 0 | N106: =M106*L106*$E106 -> 0 | Q106: =P106*O106*$E106 -> 0 | T106: =S106*R106*$E106 -> 0 | W106: =V106*U106*$E106 -> 0 | Z106: =Y106*X106*$E106 -> 0 | AC106: =AB106*AA106*$E106 -> 0 | AG106: =K106*$K$3+Z106*$Z$3+H106*$H$3+N106*$N$3+Q106*$Q$3+T106*$T$3+W106*$W$3+AC106*$AC$3 -> 0 | AH106: =AG106/$AG$162 -> #DIV/0!
B107: M26 | C107: Mourão tipo Y, 13 x 13 x 313cm fck 30mpa | D107: peça | E107: =216*1.15 -> 248.4 | H107: =G107*F107*$E107 -> 0 | K107: =J107*I107*$E107 -> 0 | N107: =M107*L107*$E107 -> 0 | Q107: =P107*O107*$E107 -> 0 | T107: =S107*R107*$E107 -> 0 | W107: =V107*U107*$E107 -> 0 | Z107: =Y107*X107*$E107 -> 0 | AC107: =AB107*AA107*$E107 -> 0 | AG107: =K107*$K$3+Z107*$Z$3+H107*$H$3+N107*$N$3+Q107*$Q$3+T107*$T$3+W107*$W$3+AC107*$AC$3 -> 0 | AH107: =AG107/$AG$162 -> #DIV/0!
B108: M27 | C108: Mourão em eucalipto 10cm x 273cm | D108: peça | E108: =87*1.2 -> 104.4 | H108: =G108*F108*$E108 -> 0 | K108: =J108*I108*$E108 -> 0 | N108: =M108*L108*$E108 -> 0 | Q108: =P108*O108*$E108 -> 0 | T108: =S108*R108*$E108 -> 0 | W108: =V108*U108*$E108 -> 0 | Z108: =Y108*X108*$E108 -> 0 | AC108: =AB108*AA108*$E108 -> 0 | AG108: =K108*$K$3+Z108*$Z$3+H108*$H$3+N108*$N$3+Q108*$Q$3+T108*$T$3+W108*$W$3+AC108*$AC$3 -> 0 | AH108: =AG108/$AG$162 -> #DIV/0!
B109: M28 | C109: Painel tipo gradil morla 2,03 x 2,5m, fio 5,10mm revestido | D109: peça | E109: =650*1.2 -> 780 | H109: =G109*F109*$E109 -> 0 | K109: =J109*I109*$E109 -> 0 | N109: =M109*L109*$E109 -> 0 | Q109: =P109*O109*$E109 -> 0 | T109: =S109*R109*$E109 -> 0 | W109: =V109*U109*$E109 -> 0 | Z109: =Y109*X109*$E109 -> 0 | AC109: =AB109*AA109*$E109 -> 0 | AG109: =K109*$K$3+Z109*$Z$3+H109*$H$3+N109*$N$3+Q109*$Q$3+T109*$T$3+W109*$W$3+AC109*$AC$3 -> 0 | AH109: =AG109/$AG$162 -> #DIV/0!
B110: M29 | C110: Painel, tomadas, lampadas, dijuntores, cabos | D110: vb | E110: 5000 | H110: =G110*F110*$E110 -> 0 | K110: =J110*I110*$E110 -> 0 | N110: =M110*L110*$E110 -> 0 | Q110: =P110*O110*$E110 -> 0 | T110: =S110*R110*$E110 -> 0 | W110: =V110*U110*$E110 -> 0 | Z110: =Y110*X110*$E110 -> 0 | AC110: =AB110*AA110*$E110 -> 0 | AG110: =K110*$K$3+Z110*$Z$3+H110*$H$3+N110*$N$3+Q110*$Q$3+T110*$T$3+W110*$W$3+AC110*$AC$3 -> 0 | AH110: =AG110/$AG$162 -> #DIV/0!
B111: M30 | C111: Placa de obra | D111: vb | E111: 2000 | H111: =G111*F111*$E111 -> 0 | K111: =J111*I111*$E111 -> 0 | N111: =M111*L111*$E111 -> 0 | Q111: =P111*O111*$E111 -> 0 | T111: =S111*R111*$E111 -> 0 | W111: =V111*U111*$E111 -> 0 | Z111: =Y111*X111*$E111 -> 0 | AC111: =AB111*AA111*$E111 -> 0 | AG111: =K111*$K$3+Z111*$Z$3+H111*$H$3+N111*$N$3+Q111*$Q$3+T111*$T$3+W111*$W$3+AC111*$AC$3 -> 0 | AH111: =AG111/$AG$162 -> #DIV/0!
B112: M31 | C112: Prego | D112: kg | E112: 25 | H112: =G112*F112*$E112 -> 0 | K112: =J112*I112*$E112 -> 0 | N112: =M112*L112*$E112 -> 0 | Q112: =P112*O112*$E112 -> 0 | T112: =S112*R112*$E112 -> 0 | W112: =V112*U112*$E112 -> 0 | Z112: =Y112*X112*$E112 -> 0 | AC112: =AB112*AA112*$E112 -> 0 | AG112: =K112*$K$3+Z112*$Z$3+H112*$H$3+N112*$N$3+Q112*$Q$3+T112*$T$3+W112*$W$3+AC112*$AC$3 -> 0 | AH112: =AG112/$AG$162 -> #DIV/0!
B113: M32 | C113: Sistema de fixação das telas (parafuso, porcas, arruelas, chapas), galvanizados | D113: conjunto | E113: 65 | H113: =G113*F113*$E113 -> 0 | K113: =J113*I113*$E113 -> 0 | N113: =M113*L113*$E113 -> 0 | Q113: =P113*O113*$E113 -> 0 | T113: =S113*R113*$E113 -> 0 | W113: =V113*U113*$E113 -> 0 | Z113: =Y113*X113*$E113 -> 0 | AC113: =AB113*AA113*$E113 -> 0 | AG113: =K113*$K$3+Z113*$Z$3+H113*$H$3+N113*$N$3+Q113*$Q$3+T113*$T$3+W113*$W$3+AC113*$AC$3 -> 0 | AH113: =AG113/$AG$162 -> #DIV/0!
...

Sheet CPU  2
B1: =QQP!G44 -> 0 | D1: CPU | E1: 2 | F1: =QQP!B18 -> 2.1.1 | G1: =H182 -> 0 | I1: =QQP!B19 -> 2.1.2 | J1: =K182 -> 0
B2: Composição de Preços Unitários | F2: =_xlfn.XLOOKUP(F1,QQP!$B$8:$B$43,QQP!$C$8:$C$43) -> XXXXXXXXXXXXXXXXXXXXXXXXXXXXXXXXXXXXXXXXXX | I2: =_xlfn.XLOOKUP(I1,QQP!$B$8:$B$43,QQP!$C$8:$C$43) -> XXXXXXXXXXXXXXXXXXXXXXXXXXXXXXXXXXXXXXXXXX | M2: CHECK
G3: =_xlfn.XLOOKUP(F1,QQP!$B$8:$B$43,QQP!$D$8:$D$43) -> xx | H3: =_xlfn.XLOOKUP(F1,QQP!$B$8:$B$43,QQP!$E$8:$E$43) -> 1 | J3: =_xlfn.XLOOKUP(I1,QQP!$B$8:$B$43,QQP!$D$8:$D$43) -> xx | K3: =_xlfn.XLOOKUP(I1,QQP!$B$8:$B$43,QQP!$E$8:$E$43) -> 1
G4: 22 | H4: dias | J4: =22*3 -> 66 | K4: dias
B5: A - Mão de Obra + Encargos
B6: Cód. | C6: Discriminação | D6: Unid | E6: P.Unit | F6: Quant | G6: F.utiliz | H6: Custo | I6: Quant | J6: F.utiliz | K6: Custo | M6: Quant | N6: F.utiliz | O6: Custo
B7: ='CPU 1'!B7 -> P01 | C7: ='CPU 1'!C7 -> Supervisor | D7: ='CPU 1'!D7 -> hh | E7: ='CPU 1'!E7 -> 75.068182 | H7: =G7*F7*$E7 -> 0 | K7: =J7*I7*$E7 -> 0 | O7: =K7*$K$3+H7*$H$3 -> 0 | P7: =O7/$O$162 -> #DIV/0!
B8: ='CPU 1'!B8 -> P02 | C8: ='CPU 1'!C8 -> Encarregado | D8: ='CPU 1'!D8 -> hh | E8: ='CPU 1'!E8 -> 40.036364 | H8: =G8*F8*$E8 -> 0 | K8: =J8*I8*$E8 -> 0 | O8: =K8*$K$3+H8*$H$3 -> 0 | P8: =O8/$O$162 -> #DIV/0!
B9: ='CPU 1'!B9 -> P03 | C9: ='CPU 1'!C9 -> Técnico SSMA | D9: ='CPU 1'!D9 -> hh | E9: ='CPU 1'!E9 -> 40.036364 | H9: =G9*F9*$E9 -> 0 | K9: =J9*I9*$E9 -> 0 | O9: =K9*$K$3+H9*$H$3 -> 0 | P9: =O9/$O$162 -> #DIV/0!
B10: ='CPU 1'!B10 -> P04 | C10: ='CPU 1'!C10 -> Pedreiro | D10: ='CPU 1'!D10 -> hh | E10: ='CPU 1'!E10 -> 19.767955 | H10: =G10*F10*$E10 -> 0 | K10: =J10*I10*$E10 -> 0 | O10: =K10*$K$3+H10*$H$3 -> 0 | P10: =O10/$O$162 -> #DIV/0!
B11: ='CPU 1'!B11 -> P05 | C11: ='CPU 1'!C11 -> Carpinteiro | D11: ='CPU 1'!D11 -> hh | E11: ='CPU 1'!E11 -> 19.767955 | H11: =G11*F11*$E11 -> 0 | K11: =J11*I11*$E11 -> 0 | O11: =K11*$K$3+H11*$H$3 -> 0 | P11: =O11/$O$162 -> #DIV/0!
B12: ='CPU 1'!B12 -> P06 | C12: ='CPU 1'!C12 -> Eletricista | D12: ='CPU 1'!D12 -> hh | E12: ='CPU 1'!E12 -> 26.023636 | H12: =G12*F12*$E12 -> 0 | K12: =J12*I12*$E12 -> 0 | O12: =K12*$K$3+H12*$H$3 -> 0 | P12: =O12/$O$162 -> #DIV/0!
B13: ='CPU 1'!B13 -> P07 | C13: ='CPU 1'!C13 -> Ajudante | D13: ='CPU 1'!D13 -> hh | E13: ='CPU 1'!E13 -> 13.962682 | H13: =G13*F13*$E13 -> 0 | K13: =J13*I13*$E13 -> 0 | O13: =K13*$K$3+H13*$H$3 -> 0 | P13: =O13/$O$162 -> #DIV/0!
B14: ='CPU 1'!B14 -> P08 | C14: ='CPU 1'!C14 -> Armador | D14: ='CPU 1'!D14 -> hh | E14: ='CPU 1'!E14 -> 19.767955 | H14: =G14*F14*$E14 -> 0 | K14: =J14*I14*$E14 -> 0 | O14: =K14*$K$3+H14*$H$3 -> 0 | P14: =O14/$O$162 -> #DIV/0!
B15: ='CPU 1'!B15 -> P09 | C15: ='CPU 1'!C15 -> Engenheiro | D15: ='CPU 1'!D15 -> hh | E15: ='CPU 1'!E15 -> 112.302 | H15: =G15*F15*$E15 -> 0 | K15: =J15*I15*$E15 -> 0 | O15: =K15*$K$3+H15*$H$3 -> 0 | P15: =O15/$O$162 -> #DIV/0!
B16: ='CPU 1'!B16 -> P10 | C16: ='CPU 1'!C16 -> Planejador | D16: ='CPU 1'!D16 -> hh | E16: ='CPU 1'!E16 -> 60.054545 | H16: =G16*F16*$E16 -> 0 | K16: =J16*I16*$E16 -> 0 | O16: =K16*$K$3+H16*$H$3 -> 0 | P16: =O16/$O$162 -> #DIV/0!
B17: ='CPU 1'!B17 -> P11 | C17: ='CPU 1'!C17 -> Tópografo | D17: ='CPU 1'!D17 -> hh | E17: ='CPU 1'!E17 -> 38.034545 | H17: =G17*F17*$E17 -> 0 | K17: =J17*I17*$E17 -> 0 | O17: =K17*$K$3+H17*$H$3 -> 0 | P17: =O17/$O$162 -> #DIV/0!
B18: ='CPU 1'!B18 -> P12 | C18: ='CPU 1'!C18 -> Auxiliar de Topografia | D18: ='CPU 1'!D18 -> hh | E18: ='CPU 1'!E18 -> 17.015455 | H18: =G18*F18*$E18 -> 0 | K18: =J18*I18*$E18 -> 0 | O18: =K18*$K$3+H18*$H$3 -> 0 | P18: =O18/$O$162 -> #DIV/0!
... B22: ='CPU 1'!B22 -> P16 | C22: ='CPU 1'!C22 -> 0 | D22: ='CPU 1'!D22 -> hh | E22: ='CPU 1'!E22 -> 0 | H22: =G22*F22*$E22 -> 0 | K22: =J22*I22*$E22 -> 0 | O22: =K22*$K$3+H22*$H$3 -> 0 | P22: =O22/$O$162 -> #DIV/0!
B23: A - Custo Total de Mão de Obra: | F23: =SUM(F7:F22) -> 0 | G23: =SUM(G7:G22) -> 0 | H23: =SUM(H7:H22) -> 0 | I23: =SUM(I7:I22) -> 0 | J23: =SUM(J7:J22) -> 0 | K23: =SUM(K7:K22) -> 0 | M23: =SUM(M7:M22) -> 0 | N23: =SUM(N7:N22) -> 0 | O23: =SUM(O7:O22) -> 0
B24: B – Equipamentos e Ferramentas
B25: Cód. | C25: Discriminação | D25: Unid | E25: P.Unit | F25: Quant | G25: F.utiliz | H25: Custo | I25: Quant | J25: F.utiliz | K25: Custo | M25: Quant | N25: F.utiliz | O25: Custo
B26: ='CPU 1'!B26 -> E01 | C26: ='CPU 1'!C26 -> Alavanca, picareta, enxada, cavador, pá | D26: ='CPU 1'!D26 -> vb | E26: ='CPU 1'!E26 -> 790 | H26: =G26*F26*$E26 -> 0 | K26: =J26*I26*$E26 -> 0 | O26: =K26*$K$3+H26*$H$3 -> 0 | P26: =O26/$O$162 -> #DIV/0!
B27: ='CPU 1'!B27 -> E02 | C27: ='CPU 1'!C27 -> Banheiro hidraulico - locação | D27: ='CPU 1'!D27 -> vb/mês | E27: ='CPU 1'!E27 -> 4000 | H27: =G27*F27*$E27 -> 0 | K27: =J27*I27*$E27 -> 0 | O27: =K27*$K$3+H27*$H$3 -> 0 | P27: =O27/$O$162 -> #DIV/0!
B28: ='CPU 1'!B28 -> E03 | C28: ='CPU 1'!C28 -> Barreira física metalica | D28: ='CPU 1'!D28 -> pç | E28: ='CPU 1'!E28 -> 350 | H28: =G28*F28*$E28 -> 0 | K28: =J28*I28*$E28 -> 0 | O28: =K28*$K$3+H28*$H$3 -> 0 | P28: =O28/$O$162 -> #DIV/0!
B29: ='CPU 1'!B29 -> E04 | C29: ='CPU 1'!C29 -> Bebedouro 4 torneiras 50L | D29: ='CPU 1'!D29 -> unid | E29: ='CPU 1'!E29 -> 3500 | H29: =G29*F29*$E29 -> 0 | K29: =J29*I29*$E29 -> 0 | O29: =K29*$K$3+H29*$H$3 -> 0 | P29: =O29/$O$162 -> #DIV/0!
B30: ='CPU 1'!B30 -> E05 | C30: ='CPU 1'!C30 -> Caçamba de entulho 4m³ | D30: ='CPU 1'!D30 -> Vb/mês | E30: ='CPU 1'!E30 -> 800 | H30: =G30*F30*$E30 -> 0 | K30: =J30*I30*$E30 -> 0 | O30: =K30*$K$3+H30*$H$3 -> 0 | P30: =O30/$O$162 -> #DIV/0!
B31: ='CPU 1'!B31 -> E06 | C31: ='CPU 1'!C31 -> Cadinho solda exotermica | D31: ='CPU 1'!D31 -> pç | E31: ='CPU 1'!E31 -> 420 | H31: =G31*F31*$E31 -> 0 | K31: =J31*I31*$E31 -> 0 | O31: =K31*$K$3+H31*$H$3 -> 0 | P31: =O31/$O$162 -> #DIV/0!
B32: ='CPU 1'!B32 -> E07 | C32: ='CPU 1'!C32 -> Caixa dágua 1000L | D32: ='CPU 1'!D32 -> pç | E32: ='CPU 1'!E32 -> 480 | H32: =G32*F32*$E32 -> 0 | K32: =J32*I32*$E32 -> 0 | O32: =K32*$K$3+H32*$H$3 -> 0 | P32: =O32/$O$162 -> #DIV/0!
B33: ='CPU 1'!B33 -> E08 | C33: ='CPU 1'!C33 -> Caixa dágua 500L | D33: ='CPU 1'!D33 -> pç | E33: ='CPU 1'!E33 -> 250 | H33: =G33*F33*$E33 -> 0 | K33: =J33*I33*$E33 -> 0 | O33: =K33*$K$3+H33*$H$3 -> 0 | P33: =O33/$O$162 -> #DIV/0!
B34: ='CPU 1'!B34 -> E09 | C34: ='CPU 1'!C34 -> Caminhão munck | D34: ='CPU 1'!D34 -> vb/mês | E34: ='CPU 1'!E34 -> 40000 | H34: =G34*F34*$E34 -> 0 | K34: =J34*I34*$E34 -> 0 | O34: =K34*$K$3+H34*$H$3 -> 0 | P34: =O34/$O$162 -> #DIV/0!
B35: ='CPU 1'!B35 -> E10 | C35: ='CPU 1'!C35 -> Carro de mão | D35: ='CPU 1'!D35 -> pç | E35: ='CPU 1'!E35 -> 450 | H35: =G35*F35*$E35 -> 0 | K35: =J35*I35*$E35 -> 0 | O35: =K35*$K$3+H35*$H$3 -> 0 | P35: =O35/$O$162 -> #DIV/0!
B36: ='CPU 1'!B36 -> E11 | C36: ='CPU 1'!C36 -> Carro plataforma | D36: ='CPU 1'!D36 -> pç | E36: ='CPU 1'!E36 -> 1200 | H36: =G36*F36*$E36 -> 0 | K36: =J36*I36*$E36 -> 0 | O36: =K36*$K$3+H36*$H$3 -> 0 | P36: =O36/$O$162 -> #DIV/0!
B37: ='CPU 1'!B37 -> E12 | C37: ='CPU 1'!C37 -> Coletor de resíduo com pedal - 50L (V,V,A,A) | D37: ='CPU 1'!D37 -> kit | E37: ='CPU 1'!E37 -> 1200 | H37: =G37*F37*$E37 -> 0 | K37: =J37*I37*$E37 -> 0 | O37: =K37*$K$3+H37*$H$3 -> 0 | P37: =O37/$O$162 -> #DIV/0!
... B79: ='CPU 1'!B79 -> E54 | C79: ='CPU 1'!C79 -> 0 | D79: ='CPU 1'!D79 -> 0 | E79: ='CPU 1'!E79 -> 0 | H79: =G79*F79*$E79 -> 0 | K79: =J79*I79*$E79 -> 0 | O79: =K79*$K$3+H79*$H$3 -> 0 | P79: =O79/$O$162 -> #DIV/0!
B80: B - Custo Total de Equipamentos e Ferramentas: | E80: =SUM(#REF!) -> #REF! | H80: =SUM(H26:H79) -> 0 | K80: =SUM(K26:K79) -> 0 | O80: =SUM(O26:O79) -> 0
B81: C – Materiais
B82: Cód. | C82: Discriminação | D82: Unid | E82: P.Unit | F82: Quant | G82: F.utiliz | H82: Custo | I82: Quant | J82: F.utiliz | K82: Custo | M82: Quant | N82: F.utiliz | O82: Custo
B83: ='CPU 1'!B83 -> M01 | C83: ='CPU 1'!C83 -> Aço CA-50, (ferro 8.0) | D83: ='CPU 1'!D83 -> kg | E83: ='CPU 1'!E83 -> 12.5 | H83: =G83*F83*$E83 -> 0 | K83: =J83*I83*$E83 -> 0 | O83: =K83*$K$3+H83*$H$3 -> 0 | P83: =O83/$O$162 -> #DIV/0!
B84: ='CPU 1'!B84 -> M02 | C84: ='CPU 1'!C84 -> Agua Mineral | D84: ='CPU 1'!D84 -> litro | E84: ='CPU 1'!E84 -> 1 | H84: =G84*F84*$E84 -> 0 | K84: =J84*I84*$E84 -> 0 | O84: =K84*$K$3+H84*$H$3 -> 0 | P84: =O84/$O$162 -> #DIV/0!
B85: ='CPU 1'!B85 -> M03 | C85: ='CPU 1'!C85 -> Arame ovalado zincado | D85: ='CPU 1'!D85 -> m | E85: ='CPU 1'!E85 -> 1 | H85: =G85*F85*$E85 -> 0 | K85: =J85*I85*$E85 -> 0 | O85: =K85*$K$3+H85*$H$3 -> 0 | P85: =O85/$O$162 -> #DIV/0!
B86: ='CPU 1'!B86 -> M04 | C86: ='CPU 1'!C86 -> Areia | D86: ='CPU 1'!D86 -> m³ | E86: ='CPU 1'!E86 -> 120 | H86: =G86*F86*$E86 -> 0 | K86: =J86*I86*$E86 -> 0 | O86: =K86*$K$3+H86*$H$3 -> 0 | P86: =O86/$O$162 -> #DIV/0!
B87: ='CPU 1'!B87 -> M05 | C87: ='CPU 1'!C87 -> Arrame galganizado | D87: ='CPU 1'!D87 -> kg | E87: ='CPU 1'!E87 -> 16.8 | H87: =G87*F87*$E87 -> 0 | K87: =J87*I87*$E87 -> 0 | O87: =K87*$K$3+H87*$H$3 -> 0 | P87: =O87/$O$162 -> #DIV/0!
B88: ='CPU 1'!B88 -> M06 | C88: ='CPU 1'!C88 -> Arrame recozido | D88: ='CPU 1'!D88 -> kg | E88: ='CPU 1'!E88 -> 12 | H88: =G88*F88*$E88 -> 0 | K88: =J88*I88*$E88 -> 0 | O88: =K88*$K$3+H88*$H$3 -> 0 | P88: =O88/$O$162 -> #DIV/0!
B89: ='CPU 1'!B89 -> M07 | C89: ='CPU 1'!C89 -> Barrote de madeira 7x7cm | D89: ='CPU 1'!D89 -> m | E89: ='CPU 1'!E89 -> 15 | H89: =G89*F89*$E89 -> 0 | K89: =J89*I89*$E89 -> 0 | O89: =K89*$K$3+H89*$H$3 -> 0 | P89: =O89/$O$162 -> #DIV/0!
B90: ='CPU 1'!B90 -> M08 | C90: ='CPU 1'!C90 -> Bloco tipo canaleta (14x19x39cm) | D90: ='CPU 1'!D90 -> peça | E90: ='CPU 1'!E90 -> 8.9 | H90: =G90*F90*$E90 -> 0 | K90: =J90*I90*$E90 -> 0 | O90: =K90*$K$3+H90*$H$3 -> 0 | P90: =O90/$O$162 -> #DIV/0!
B91: ='CPU 1'!B91 -> M09 | C91: ='CPU 1'!C91 -> Brita 1 | D91: ='CPU 1'!D91 -> m³ | E91: ='CPU 1'!E91 -> 220 | H91: =G91*F91*$E91 -> 0 | K91: =J91*I91*$E91 -> 0 | O91: =K91*$K$3+H91*$H$3 -> 0 | P91: =O91/$O$162 -> #DIV/0!
B92: ='CPU 1'!B92 -> M11 | C92: ='CPU 1'!C92 -> Caixa de passagens para aterramento h600 diâmetro 30cm | D92: ='CPU 1'!D92 -> und | E92: ='CPU 1'!E92 -> 590 | H92: =G92*F92*$E92 -> 0 | K92: =J92*I92*$E92 -> 0 | O92: =K92*$K$3+H92*$H$3 -> 0 | P92: =O92/$O$162 -> #DIV/0!
B93: ='CPU 1'!B93 -> M12 | C93: ='CPU 1'!C93 -> Catoneira galvanizada 1"x1-1/4 | D93: ='CPU 1'!D93 -> m | E93: ='CPU 1'!E93 -> 25 | H93: =G93*F93*$E93 -> 0 | K93: =J93*I93*$E93 -> 0 | O93: =K93*$K$3+H93*$H$3 -> 0 | P93: =O93/$O$162 -> #DIV/0!
B94: ='CPU 1'!B94 -> M13 | C94: ='CPU 1'!C94 -> Cercamento e delimitação de canteiro de obra (15x30m) | D94: ='CPU 1'!D94 -> vb | E94: ='CPU 1'!E94 -> 10000 | H94: =G94*F94*$E94 -> 0 | K94: =J94*I94*$E94 -> 0 | O94: =K94*$K$3+H94*$H$3 -> 0 | P94: =O94/$O$162 -> #DIV/0!
... B131: ='CPU 1'!B131 -> M50 | C131: ='CPU 1'!C131 -> 0 | D131: ='CPU 1'!D131 -> 0 | E131: ='CPU 1'!E131 -> 0 | H131: =G131*F131*$E131 -> 0 | K131: =J131*I131*$E131 -> 0 | O131: =K131*$K$3+H131*$H$3 -> 0 | P131: =O131/$O$162 -> #DIV/0!
B132: C - Custo Total de Materiais: | E132: =SUM(#REF!) -> #REF! | H132: =SUM(H83:H131) -> 0 | K132: =SUM(K83:K131) -> 0 | O132: =SUM(O83:O131) -> 0
B133: D – Outros
B134: Cód. | C134: Discriminação | D134: Unid | E134: P.Unit | F134: Quant | G134: F.utiliz | H134: Custo | I134: Quant | J134: F.utiliz | K134: Custo | M134: Quant | N134: F.utiliz | O134: Custo
B135: ='CPU 1'!B135 -> O01 | C135: ='CPU 1'!C135 -> ART | D135: ='CPU 1'!D135 -> Vb | E135: ='CPU 1'!E135 -> 1000 | H135: =G135*F135*$E135 -> 0 | K135: =J135*I135*$E135 -> 0 | O135: =K135*$K$3+H135*$H$3 -> 0 | P135: =O135/$O$162 -> #DIV/0!
B136: ='CPU 1'!B136 -> O02 | C136: ='CPU 1'!C136 -> Exames medicos | D136: ='CPU 1'!D136 -> Vb | E136: ='CPU 1'!E136 -> 600 | H136: =G136*F136*$E136 -> 0 | K136: =J136*I136*$E136 -> 0 | O136: =K136*$K$3+H136*$H$3 -> 0 | P136: =O136/$O$162 -> #DIV/0!
B137: ='CPU 1'!B137 -> O03 | C137: ='CPU 1'!C137 -> Treinamentos | D137: ='CPU 1'!D137 -> Vb | E137: ='CPU 1'!E137 -> 426 | H137: =G137*F137*$E137 -> 0 | K137: =J137*I137*$E137 -> 0 | O137: =K137*$K$3+H137*$H$3 -> 0 | P137: =O137/$O$162 -> #DIV/0!
B138: ='CPU 1'!B138 -> O04 | C138: ='CPU 1'!C138 -> Plano de Saude | D138: ='CPU 1'!D138 -> Vb/mês | E138: ='CPU 1'!E138 -> 280 | H138: =G138*F138*$E138 -> 0 | K138: =J138*I138*$E138 -> 0 | O138: =K138*$K$3+H138*$H$3 -> 0 | P138: =O138/$O$162 -> #DIV/0!
B139: ='CPU 1'!B139 -> O05 | C139: ='CPU 1'!C139 -> Seguro de Vida | D139: ='CPU 1'!D139 -> Vb/mês | E139: ='CPU 1'!E139 -> 25 | H139: =G139*F139*$E139 -> 0 | K139: =J139*I139*$E139 -> 0 | O139: =K139*$K$3+H139*$H$3 -> 0 | P139: =O139/$O$162 -> #DIV/0!
B140: ='CPU 1'!B140 -> O06 | C140: ='CPU 1'!C140 -> Ticket Alimentação | D140: ='CPU 1'!D140 -> Vb/mês | E140: ='CPU 1'!E140 -> 350 | H140: =G140*F140*$E140 -> 0 | K140: =J140*I140*$E140 -> 0 | O140: =K140*$K$3+H140*$H$3 -> 0 | P140: =O140/$O$162 -> #DIV/0!
B141: ='CPU 1'!B141 -> O07 | C141: ='CPU 1'!C141 -> PCMSO / PGR / PCA / PPR | D141: ='CPU 1'!D141 -> Vb/ano | E141: ='CPU 1'!E141 -> 2300 | H141: =G141*F141*$E141 -> 0 | K141: =J141*I141*$E141 -> 0 | O141: =K141*$K$3+H141*$H$3 -> 0 | P141: =O141/$O$162 -> #DIV/0!
B142: ='CPU 1'!B142 -> O08 | C142: ='CPU 1'!C142 -> Quadros DDS e Gestão a vista | D142: ='CPU 1'!D142 -> Vb | E142: ='CPU 1'!E142 -> 1200 | H142: =G142*F142*$E142 -> 0 | K142: =J142*I142*$E142 -> 0 | O142: =K142*$K$3+H142*$H$3 -> 0 | P142: =O142/$O$162 -> #DIV/0!
B143: ='CPU 1'!B143 -> O09 | C143: ='CPU 1'!C143 -> Seguro Obra | D143: ='CPU 1'!D143 -> Vb | E143: ='CPU 1'!E143 -> 5000 | H143: =G143*F143*$E143 -> 0 | K143: =J143*I143*$E143 -> 0 | O143: =K143*$K$3+H143*$H$3 -> 0 | P143: =O143/$O$162 -> #DIV/0!
B144: ='CPU 1'!B144 -> O10 | C144: ='CPU 1'!C144 -> Fretes | D144: ='CPU 1'!D144 -> ud | E144: ='CPU 1'!E144 -> 2800 | H144: =G144*F144*$E144 -> 0 | K144: =J144*I144*$E144 -> 0 | O144: =K144*$K$3+H144*$H$3 -> 0 | P144: =O144/$O$162 -> #DIV/0!
B145: ='CPU 1'!B145 -> O11 | C145: ='CPU 1'!C145 -> Serviço de descarte de residuo | D145: ='CPU 1'!D145 -> coleta | E145: ='CPU 1'!E145 -> 2000 | H145: =G145*F145*$E145 -> 0 | K145: =J145*I145*$E145 -> 0 | O145: =K145*$K$3+H145*$H$3 -> 0 | P145: =O145/$O$162 -> #DIV/0!
B146: ='CPU 1'!B146 -> O12 | C146: ='CPU 1'!C146 -> Serviço de movimentação do Banheiro Hidráulico | D146: ='CPU 1'!D146 -> vb | E146: ='CPU 1'!E146 -> 200 | H146: =G146*F146*$E146 -> 0 | K146: =J146*I146*$E146 -> 0 | O146: =K146*$K$3+H146*$H$3 -> 0 | P146: =O146/$O$162 -> #DIV/0!
... B154: ='CPU 1'!B154 -> O20 | C154: ='CPU 1'!C154 -> 0 | D154: ='CPU 1'!D154 -> 0 | E154: ='CPU 1'!E154 -> 0 | H154: =G154*F154*$E154 -> 0 | K154: =J154*I154*$E154 -> 0 | O154: =K154*$K$3+H154*$H$3 -> 0 | P154: =O154/$O$162 -> #DIV/0!
B155: D - Custo Total de Outros: | E155: =SUM(#REF!) -> #REF! | H155: =SUM(H135:H154) -> 0 | K155: =SUM(K135:K154) -> 0 | O155: =SUM(O135:O154) -> 0
B157: Item | C157: CUSTOS | G157: % | H157: $ | J157: % | K157: $ | N157: % | O157: $
B158: A | C158: Mão de Obra | G158: =H158/H162 -> #DIV/0! | H158: =H23 -> 0 | J158: =K158/K162 -> #DIV/0! | K158: =K23 -> 0 | N158: =O158/O162 -> #DIV/0! | O158: =O23 -> 0
B159: B | C159: Equipamentos | G159: =H159/H162 -> #DIV/0! | H159: =H80 -> 0 | J159: =K159/K162 -> #DIV/0! | K159: =K80 -> 0 | N159: =O159/O162 -> #DIV/0! | O159: =O80 -> 0
B160: C | C160: Materiais | G160: =H160/H162 -> #DIV/0! | H160: =H132 -> 0 | J160: =K160/K162 -> #DIV/0! | K160: =K132 -> 0 | N160: =O160/O162 -> #DIV/0! | O160: =O132 -> 0
B161: D | C161: Outros | G161: =H161/H162 -> #DIV/0! | H161: =H155 -> 0 | J161: =K161/K162 -> #DIV/0! | K161: =K155 -> 0 | N161: =O161/O162 -> #DIV/0! | O161: =O155 -> 0
C162: Subtotal: | E162: =SUM(E158:E161) -> 0 | G162: =SUM(G158:G161) -> #DIV/0! | H162: =SUM(H158:H161) -> 0 | J162: =SUM(J158:J161) -> #DIV/0! | K162: =SUM(K158:K161) -> 0 | N162: =SUM(N158:N161) -> #DIV/0! | O162: =SUM(O158:O161) -> 0
B164: Item | C164: BDI | E164: Taxa | H164: $ | K164: $ | O164: $
B165: 1 | C165: Administração Local | E165: ='BDI-TRIBUTOS'!D8 -> 0.09 | H165: =H162*$E$165 -> 0 | K165: =K162*$E$165 -> 0 | O165: =O162*$E$165 -> 0
B166: 2 | C166: Administração Central | E166: ='BDI-TRIBUTOS'!D6 -> 0.06 | H166: =H162*$E$166 -> 0 | K166: =K162*$E$166 -> 0 | O166: =O162*$E$166 -> 0
B167: 3 | C167: Custo financ. capital giro | E167: ='BDI-TRIBUTOS'!D10 -> 0.035 | H167: =H162*$E$167 -> 0 | K167: =K162*$E$167 -> 0 | O167: =O162*$E$167 -> 0
B168: 4 | C168: Risco do empreendimento | E168: ='BDI-TRIBUTOS'!D12 -> 0.02 | H168: =H162*$E$168 -> 0 | K168: =K162*$E$168 -> 0 | O168: =O162*$E$168 -> 0
B169: 5 | C169: Outros | E169: ='BDI-TRIBUTOS'!D14 -> 0.01 | H169: =H162*$E$169 -> 0 | K169: =K162*$E$169 -> 0 | O169: =O162*$E$169 -> 0
B170: 6 | C170: Lucro | E170: ='BDI-TRIBUTOS'!D4 -> 0.1 | H170: =H182*$E$170 -> 0 | K170: =K182*$E$170 -> 0 | O170: =O182*$E$170 -> 0
C171: Subtotal: | E171: =SUM(E165:E170) -> 0.315 | G171: =SUM(H165:H169)+H162 -> 0 | H171: =SUM(H165:H170) -> 0 | J171: =SUM(K165:K169)+K162 -> 0 | K171: =SUM(K165:K170) -> 0 | N171: =SUM(O165:O169)+O162 -> 0 | O171: =SUM(O165:O170) -> 0
F172: =H171/H162 -> #DIV/0! | I172: =K171/K162 -> #DIV/0! | M172: =O171/O162 -> #DIV/0!
B173: Item | C173: TRIBUTOS | E173: Taxa | H173: $ | K173: $ | O173: $
B174: 1 | C174: ISS | E174: ='BDI-TRIBUTOS'!D20 -> 0.05 | H174: =H$182*$E174 -> 0 | K174: =K$182*$E174 -> 0 | O174: =$O$182*E174 -> 0
B175: 2 | C175: COFINS | E175: ='BDI-TRIBUTOS'!D21 -> 0.03 | H175: =H$182*$E175 -> 0 | K175: =K$182*$E175 -> 0 | O175: =$O$182*E175 -> 0
B176: 3 | C176: PIS | E176: ='BDI-TRIBUTOS'!D22 -> 0.0065 | H176: =H$182*$E176 -> 0 | K176: =K$182*$E176 -> 0 | O176: =$O$182*E176 -> 0
B177: 4 | C177: CSLL | E177: ='BDI-TRIBUTOS'!D23 -> 0.0288 | H177: =H$182*$E177 -> 0 | K177: =K$182*$E177 -> 0 | O177: =$O$182*E177 -> 0
B178: 5 | C178: IRPJ | E178: ='BDI-TRIBUTOS'!D24 -> 0.048 | H178: =H$182*$E178 -> 0 | K178: =K$182*$E178 -> 0 | O178: =$O$182*E178 -> 0
B179: 6 | C179: IRPJ Adicional 10% | E179: ='BDI-TRIBUTOS'!D25 -> 0.0318 | H179: =H$182*$E179 -> 0 | K179: =K$182*$E179 -> 0 | O179: =$O$182*E179 -> 0
B180: 7 | C180: Simples Nacional | E180: ='BDI-TRIBUTOS'!D26 -> 0
C181: Subtotal | E181: =SUM(E174:E180) -> 0.1951 | H181: =H182*$E$181 -> 0 | K181: =K182*$E$181 -> 0 | O181: =O182*$E$181 -> 0
C182: PREÇO | F182: =ROUND(H182,2) -> 0 | H182: =G171/(1-$E$181-$E$170) -> 0 | I182: =ROUND(K182,2) -> 0 | K182: =J171/(1-$E$181-$E$170) -> 0 | O182: =N171/(1-$E$181-$E$170) -> 0
H183: =H182/H162 -> #DIV/0! | K183: =K182/K162 -> #DIV/0! | O183: =O182/O162 -> #DIV/0!

Sheet CPU  3
B1: =QQP!G44 -> 0 | D1: CPU | E1: 3 | F1: =QQP!B21 -> 2.2.1 | G1: =H182 -> 0 | I1: =QQP!B22 -> 2.2.2 | J1: =K182 -> 0 | L1: =QQP!B23 -> 2.2.3 | M1: =N182 -> 0 | O1: =QQP!B24 -> 2.2.4 | P1: =Q182 -> 0 | R1: =QQP!B26 -> 2.3.1 | S1: =T182 -> 0 | U1: =QQP!B27 -> 2.3.2 | V1: =W182 -> 0
B2: Composição de Preços Unitários | F2: =_xlfn.XLOOKUP(F1,QQP!$B$8:$B$43,QQP!$C$8:$C$43) -> XXXXXXXXXXXXXXXXXXXXXXXXXXXXXXXXXXXXXXXXXX | I2: =_xlfn.XLOOKUP(I1,QQP!$B$8:$B$43,QQP!$C$8:$C$43) -> XXXXXXXXXXXXXXXXXXXXXXXXXXXXXXXXXXXXXXXXXX | L2: =_xlfn.XLOOKUP(L1,QQP!$B$8:$B$43,QQP!$C$8:$C$43) -> XXXXXXXXXXXXXXXXXXXXXXXXXXXXXXXXXXXXXXXXXX | O2: =_xlfn.XLOOKUP(O1,QQP!$B$8:$B$43,QQP!$C$8:$C$43) -> XXXXXXXXXXXXXXXXXXXXXXXXXXXXXXXXXXXXXXXXXX | R2: =_xlfn.XLOOKUP(R1,QQP!$B$8:$B$43,QQP!$C$8:$C$43) -> XXXXXXXXXXXXXXXXXXXXXXXXXXXXXXXXXXXXXXXXXX | U2: =_xlfn.XLOOKUP(U1,QQP!$B$8:$B$43,QQP!$C$8:$C$43) -> XXXXXXXXXXXXXXXXXXXXXXXXXXXXXXXXXXXXXXXXXX | Y2: CHECK
G3: =_xlfn.XLOOKUP(F1,QQP!$B$8:$B$43,QQP!$D$8:$D$43) -> xx | H3: =_xlfn.XLOOKUP(F1,QQP!$B$8:$B$43,QQP!$E$8:$E$43) -> 1 | J3: =_xlfn.XLOOKUP(I1,QQP!$B$8:$B$43,QQP!$D$8:$D$43) -> xx | K3: =_xlfn.XLOOKUP(I1,QQP!$B$8:$B$43,QQP!$E$8:$E$43) -> 1 | M3: =_xlfn.XLOOKUP(L1,QQP!$B$8:$B$43,QQP!$D$8:$D$43) -> xx | N3: =_xlfn.XLOOKUP(L1,QQP!$B$8:$B$43,QQP!$E$8:$E$43) -> 1 | P3: =_xlfn.XLOOKUP(O1,QQP!$B$8:$B$43,QQP!$D$8:$D$43) -> xx | Q3: =_xlfn.XLOOKUP(O1,QQP!$B$8:$B$43,QQP!$E$8:$E$43) -> 1 | S3: =_xlfn.XLOOKUP(R1,QQP!$B$8:$B$43,QQP!$D$8:$D$43) -> xx | T3: =_xlfn.XLOOKUP(R1,QQP!$B$8:$B$43,QQP!$E$8:$E$43) -> 1 | V3: =_xlfn.XLOOKUP(U1,QQP!$B$8:$B$43,QQP!$D$8:$D$43) -> xx | W3: =_xlfn.XLOOKUP(U1,QQP!$B$8:$B$43,QQP!$E$8:$E$43) -> 1
B5: A - Mão de Obra + Encargos
B6: Cód. | C6: Discriminação | D6: Unid | E6: P.Unit | F6: Quant | G6: F.utiliz | H6: Custo | I6: Quant | J6: F.utiliz | K6: Custo | L6: Quant | M6: F.utiliz | N6: Custo | O6: Quant | P6: F.utiliz | Q6: Custo | R6: Quant | S6: F.utiliz | T6: Custo | U6: Quant | V6: F.utiliz | W6: Custo | Y6: Quant | Z6: F.utiliz | AA6: Custo
B7: ='CPU 1'!B7 -> P01 | C7: ='CPU 1'!C7 -> Supervisor | D7: ='CPU 1'!D7 -> hh | E7: ='CPU 1'!E7 -> 75.068182 | H7: =G7*F7*$E7 -> 0 | K7: =J7*I7*$E7 -> 0 | N7: =M7*L7*$E7 -> 0 | Q7: =P7*O7*$E7 -> 0 | T7: =S7*R7*$E7 -> 0 | W7: =V7*U7*$E7 -> 0 | AA7: =K7*$K$3+N7*$N$3+Q7*$Q$3+H7*$H$3+T7*$T$3+W7*$W$3 -> 0 | AB7: =AA7/$AA$162 -> #DIV/0!
B8: ='CPU 1'!B8 -> P02 | C8: ='CPU 1'!C8 -> Encarregado | D8: ='CPU 1'!D8 -> hh | E8: ='CPU 1'!E8 -> 40.036364 | H8: =G8*F8*$E8 -> 0 | K8: =J8*I8*$E8 -> 0 | N8: =M8*L8*$E8 -> 0 | Q8: =P8*O8*$E8 -> 0 | T8: =S8*R8*$E8 -> 0 | W8: =V8*U8*$E8 -> 0 | AA8: =K8*$K$3+N8*$N$3+Q8*$Q$3+H8*$H$3+T8*$T$3+W8*$W$3 -> 0 | AB8: =AA8/$AA$162 -> #DIV/0!
B9: ='CPU 1'!B9 -> P03 | C9: ='CPU 1'!C9 -> Técnico SSMA | D9: ='CPU 1'!D9 -> hh | E9: ='CPU 1'!E9 -> 40.036364 | H9: =G9*F9*$E9 -> 0 | K9: =J9*I9*$E9 -> 0 | N9: =M9*L9*$E9 -> 0 | Q9: =P9*O9*$E9 -> 0 | T9: =S9*R9*$E9 -> 0 | W9: =V9*U9*$E9 -> 0 | AA9: =K9*$K$3+N9*$N$3+Q9*$Q$3+H9*$H$3+T9*$T$3+W9*$W$3 -> 0 | AB9: =AA9/$AA$162 -> #DIV/0!
B10: ='CPU 1'!B10 -> P04 | C10: ='CPU 1'!C10 -> Pedreiro | D10: ='CPU 1'!D10 -> hh | E10: ='CPU 1'!E10 -> 19.767955 | H10: =G10*F10*$E10 -> 0 | K10: =J10*I10*$E10 -> 0 | N10: =M10*L10*$E10 -> 0 | Q10: =P10*O10*$E10 -> 0 | T10: =S10*R10*$E10 -> 0 | W10: =V10*U10*$E10 -> 0 | AA10: =K10*$K$3+N10*$N$3+Q10*$Q$3+H10*$H$3+T10*$T$3+W10*$W$3 -> 0 | AB10: =AA10/$AA$162 -> #DIV/0!
B11: ='CPU 1'!B11 -> P05 | C11: ='CPU 1'!C11 -> Carpinteiro | D11: ='CPU 1'!D11 -> hh | E11: ='CPU 1'!E11 -> 19.767955 | H11: =G11*F11*$E11 -> 0 | K11: =J11*I11*$E11 -> 0 | N11: =M11*L11*$E11 -> 0 | Q11: =P11*O11*$E11 -> 0 | T11: =S11*R11*$E11 -> 0 | W11: =V11*U11*$E11 -> 0 | AA11: =K11*$K$3+N11*$N$3+Q11*$Q$3+H11*$H$3+T11*$T$3+W11*$W$3 -> 0 | AB11: =AA11/$AA$162 -> #DIV/0!
B12: ='CPU 1'!B12 -> P06 | C12: ='CPU 1'!C12 -> Eletricista | D12: ='CPU 1'!D12 -> hh | E12: ='CPU 1'!E12 -> 26.023636 | H12: =G12*F12*$E12 -> 0 | K12: =J12*I12*$E12 -> 0 | N12: =M12*L12*$E12 -> 0 | Q12: =P12*O12*$E12 -> 0 | T12: =S12*R12*$E12 -> 0 | W12: =V12*U12*$E12 -> 0 | AA12: =K12*$K$3+N12*$N$3+Q12*$Q$3+H12*$H$3+T12*$T$3+W12*$W$3 -> 0 | AB12: =AA12/$AA$162 -> #DIV/0!
B13: ='CPU 1'!B13 -> P07 | C13: ='CPU 1'!C13 -> Ajudante | D13: ='CPU 1'!D13 -> hh | E13: ='CPU 1'!E13 -> 13.962682 | H13: =G13*F13*$E13 -> 0 | K13: =J13*I13*$E13 -> 0 | N13: =M13*L13*$E13 -> 0 | Q13: =P13*O13*$E13 -> 0 | T13: =S13*R13*$E13 -> 0 | W13: =V13*U13*$E13 -> 0 | AA13: =K13*$K$3+N13*$N$3+Q13*$Q$3+H13*$H$3+T13*$T$3+W13*$W$3 -> 0 | AB13: =AA13/$AA$162 -> #DIV/0!
B14: ='CPU 1'!B14 -> P08 | C14: ='CPU 1'!C14 -> Armador | D14: ='CPU 1'!D14 -> hh | E14: ='CPU 1'!E14 -> 19.767955 | H14: =G14*F14*$E14 -> 0 | K14: =J14*I14*$E14 -> 0 | N14: =M14*L14*$E14 -> 0 | Q14: =P14*O14*$E14 -> 0 | T14: =S14*R14*$E14 -> 0 | W14: =V14*U14*$E14 -> 0 | AA14: =K14*$K$3+N14*$N$3+Q14*$Q$3+H14*$H$3+T14*$T$3+W14*$W$3 -> 0 | AB14: =AA14/$AA$162 -> #DIV/0!
B15: ='CPU 1'!B15 -> P09 | C15: ='CPU 1'!C15 -> Engenheiro | D15: ='CPU 1'!D15 -> hh | E15: ='CPU 1'!E15 -> 112.302 | H15: =G15*F15*$E15 -> 0 | K15: =J15*I15*$E15 -> 0 | N15: =M15*L15*$E15 -> 0 | Q15: =P15*O15*$E15 -> 0 | T15: =S15*R15*$E15 -> 0 | W15: =V15*U15*$E15 -> 0 | AA15: =K15*$K$3+N15*$N$3+Q15*$Q$3+H15*$H$3+T15*$T$3+W15*$W$3 -> 0 | AB15: =AA15/$AA$162 -> #DIV/0!
B16: ='CPU 1'!B16 -> P10 | C16: ='CPU 1'!C16 -> Planejador | D16: ='CPU 1'!D16 -> hh | E16: ='CPU 1'!E16 -> 60.054545 | H16: =G16*F16*$E16 -> 0 | K16: =J16*I16*$E16 -> 0 | N16: =M16*L16*$E16 -> 0 | Q16: =P16*O16*$E16 -> 0 | T16: =S16*R16*$E16 -> 0 | W16: =V16*U16*$E16 -> 0 | AA16: =K16*$K$3+N16*$N$3+Q16*$Q$3+H16*$H$3+T16*$T$3+W16*$W$3 -> 0 | AB16: =AA16/$AA$162 -> #DIV/0!
B17: ='CPU 1'!B17 -> P11 | C17: ='CPU 1'!C17 -> Tópografo | D17: ='CPU 1'!D17 -> hh | E17: ='CPU 1'!E17 -> 38.034545 | H17: =G17*F17*$E17 -> 0 | K17: =J17*I17*$E17 -> 0 | N17: =M17*L17*$E17 -> 0 | Q17: =P17*O17*$E17 -> 0 | T17: =S17*R17*$E17 -> 0 | W17: =V17*U17*$E17 -> 0 | AA17: =K17*$K$3+N17*$N$3+Q17*$Q$3+H17*$H$3+T17*$T$3+W17*$W$3 -> 0 | AB17: =AA17/$AA$162 -> #DIV/0!
B18: ='CPU 1'!B18 -> P12 | C18: ='CPU 1'!C18 -> Auxiliar de Topografia | D18: ='CPU 1'!D18 -> hh | E18: ='CPU 1'!E18 -> 17.015455 | H18: =G18*F18*$E18 -> 0 | K18: =J18*I18*$E18 -> 0 | N18: =M18*L18*$E18 -> 0 | Q18: =P18*O18*$E18 -> 0 | T18: =S18*R18*$E18 -> 0 | W18: =V18*U18*$E18 -> 0 | AA18: =K18*$K$3+N18*$N$3+Q18*$Q$3+H18*$H$3+T18*$T$3+W18*$W$3 -> 0 | AB18: =AA18/$AA$162 -> #DIV/0!
... B22: ='CPU 1'!B22 -> P16 | C22: ='CPU 1'!C22 -> 0 | D22: ='CPU 1'!D22 -> hh | E22: ='CPU 1'!E22 -> 0 | H22: =G22*F22*$E22 -> 0 | K22: =J22*I22*$E22 -> 0 | N22: =M22*L22*$E22 -> 0 | Q22: =P22*O22*$E22 -> 0 | T22: =S22*R22*$E22 -> 0 | W22: =V22*U22*$E22 -> 0 | AA22: =K22*$K$3+N22*$N$3+Q22*$Q$3+H22*$H$3+T22*$T$3+W22*$W$3 -> 0 | AB22: =AA22/$AA$162 -> #DIV/0!
B23: A - Custo Total de Mão de Obra: | F23: =SUM(F7:F22) -> 0 | G23: =SUM(G7:G22)*H3 -> 0 | H23: =SUM(H7:H22) -> 0 | I23: =SUM(I7:I22) -> 0 | J23: =SUM(J7:J22)*K3 -> 0 | K23: =SUM(K7:K22) -> 0 | L23: =SUM(L7:L22) -> 0 | M23: =SUM(M7:M22)*N3 -> 0 | N23: =SUM(N7:N22) -> 0 | O23: =SUM(O7:O22) -> 0 | P23: =SUM(P7:P22)*Q3 -> 0 | Q23: =SUM(Q7:Q22) -> 0 | R23: =SUM(R7:R22) -> 0 | S23: =SUM(S7:S22)*T3 -> 0 | T23: =SUM(T7:T22) -> 0 | U23: =SUM(U7:U22) -> 0 | V23: =SUM(V7:V22)*W3 -> 0 | W23: =SUM(W7:W22) -> 0 | Y23: =SUM(Y7:Y22) -> 0 | Z23: =SUM(Z7:Z22) -> 0 | AA23: =SUM(AA7:AA22) -> 0
B24: B – Equipamentos e Ferramentas
B25: Cód. | C25: Discriminação | D25: Unid | E25: P.Unit | F25: Quant | G25: F.utiliz | H25: Custo | I25: Quant | J25: F.utiliz | K25: Custo | L25: Quant | M25: F.utiliz | N25: Custo | O25: Quant | P25: F.utiliz | Q25: Custo | R25: Quant | S25: F.utiliz | T25: Custo | U25: Quant | V25: F.utiliz | W25: Custo | Y25: Quant | Z25: F.utiliz | AA25: Custo
B26: ='CPU 1'!B26 -> E01 | C26: ='CPU 1'!C26 -> Alavanca, picareta, enxada, cavador, pá | D26: ='CPU 1'!D26 -> vb | E26: ='CPU 1'!E26 -> 790 | H26: =G26*F26*$E26 -> 0 | K26: =J26*I26*$E26 -> 0 | N26: =M26*L26*$E26 -> 0 | Q26: =P26*O26*$E26 -> 0 | T26: =S26*R26*$E26 -> 0 | W26: =V26*U26*$E26 -> 0 | AA26: =K26*$K$3+N26*$N$3+Q26*$Q$3+H26*$H$3+T26*$T$3+W26*$W$3 -> 0 | AB26: =AA26/$AA$162 -> #DIV/0!
B27: ='CPU 1'!B27 -> E02 | C27: ='CPU 1'!C27 -> Banheiro hidraulico - locação | D27: ='CPU 1'!D27 -> vb/mês | E27: ='CPU 1'!E27 -> 4000 | H27: =G27*F27*$E27 -> 0 | K27: =J27*I27*$E27 -> 0 | N27: =M27*L27*$E27 -> 0 | Q27: =P27*O27*$E27 -> 0 | T27: =S27*R27*$E27 -> 0 | W27: =V27*U27*$E27 -> 0 | AA27: =K27*$K$3+N27*$N$3+Q27*$Q$3+H27*$H$3+T27*$T$3+W27*$W$3 -> 0 | AB27: =AA27/$AA$162 -> #DIV/0!
B28: ='CPU 1'!B28 -> E03 | C28: ='CPU 1'!C28 -> Barreira física metalica | D28: ='CPU 1'!D28 -> pç | E28: ='CPU 1'!E28 -> 350 | H28: =G28*F28*$E28 -> 0 | K28: =J28*I28*$E28 -> 0 | N28: =M28*L28*$E28 -> 0 | Q28: =P28*O28*$E28 -> 0 | T28: =S28*R28*$E28 -> 0 | W28: =V28*U28*$E28 -> 0 | AA28: =K28*$K$3+N28*$N$3+Q28*$Q$3+H28*$H$3+T28*$T$3+W28*$W$3 -> 0 | AB28: =AA28/$AA$162 -> #DIV/0!
B29: ='CPU 1'!B29 -> E04 | C29: ='CPU 1'!C29 -> Bebedouro 4 torneiras 50L | D29: ='CPU 1'!D29 -> unid | E29: ='CPU 1'!E29 -> 3500 | H29: =G29*F29*$E29 -> 0 | K29: =J29*I29*$E29 -> 0 | N29: =M29*L29*$E29 -> 0 | Q29: =P29*O29*$E29 -> 0 | T29: =S29*R29*$E29 -> 0 | W29: =V29*U29*$E29 -> 0 | AA29: =K29*$K$3+N29*$N$3+Q29*$Q$3+H29*$H$3+T29*$T$3+W29*$W$3 -> 0 | AB29: =AA29/$AA$162 -> #DIV/0!
B30: ='CPU 1'!B30 -> E05 | C30: ='CPU 1'!C30 -> Caçamba de entulho 4m³ | D30: ='CPU 1'!D30 -> Vb/mês | E30: ='CPU 1'!E30 -> 800 | H30: =G30*F30*$E30 -> 0 | K30: =J30*I30*$E30 -> 0 | N30: =M30*L30*$E30 -> 0 | Q30: =P30*O30*$E30 -> 0 | T30: =S30*R30*$E30 -> 0 | W30: =V30*U30*$E30 -> 0 | AA30: =K30*$K$3+N30*$N$3+Q30*$Q$3+H30*$H$3+T30*$T$3+W30*$W$3 -> 0 | AB30: =AA30/$AA$162 -> #DIV/0!
B31: ='CPU 1'!B31 -> E06 | C31: ='CPU 1'!C31 -> Cadinho solda exotermica | D31: ='CPU 1'!D31 -> pç | E31: ='CPU 1'!E31 -> 420 | H31: =G31*F31*$E31 -> 0 | K31: =J31*I31*$E31 -> 0 | N31: =M31*L31*$E31 -> 0 | Q31: =P31*O31*$E31 -> 0 | T31: =S31*R31*$E31 -> 0 | W31: =V31*U31*$E31 -> 0 | AA31: =K31*$K$3+N31*$N$3+Q31*$Q$3+H31*$H$3+T31*$T$3+W31*$W$3 -> 0 | AB31: =AA31/$AA$162 -> #DIV/0!
B32: ='CPU 1'!B32 -> E07 | C32: ='CPU 1'!C32 -> Caixa dágua 1000L | D32: ='CPU 1'!D32 -> pç | E32: ='CPU 1'!E32 -> 480 | H32: =G32*F32*$E32 -> 0 | K32: =J32*I32*$E32 -> 0 | N32: =M32*L32*$E32 -> 0 | Q32: =P32*O32*$E32 -> 0 | T32: =S32*R32*$E32 -> 0 | W32: =V32*U32*$E32 -> 0 | AA32: =K32*$K$3+N32*$N$3+Q32*$Q$3+H32*$H$3+T32*$T$3+W32*$W$3 -> 0 | AB32: =AA32/$AA$162 -> #DIV/0!
B33: ='CPU 1'!B33 -> E08 | C33: ='CPU 1'!C33 -> Caixa dágua 500L | D33: ='CPU 1'!D33 -> pç | E33: ='CPU 1'!E33 -> 250 | H33: =G33*F33*$E33 -> 0 | K33: =J33*I33*$E33 -> 0 | N33: =M33*L33*$E33 -> 0 | Q33: =P33*O33*$E33 -> 0 | T33: =S33*R33*$E33 -> 0 | W33: =V33*U33*$E33 -> 0 | AA33: =K33*$K$3+N33*$N$3+Q33*$Q$3+H33*$H$3+T33*$T$3+W33*$W$3 -> 0 | AB33: =AA33/$AA$162 -> #DIV/0!
B34: ='CPU 1'!B34 -> E09 | C34: ='CPU 1'!C34 -> Caminhão munck | D34: ='CPU 1'!D34 -> vb/mês | E34: ='CPU 1'!E34 -> 40000 | H34: =G34*F34*$E34 -> 0 | K34: =J34*I34*$E34 -> 0 | N34: =M34*L34*$E34 -> 0 | Q34: =P34*O34*$E34 -> 0 | T34: =S34*R34*$E34 -> 0 | W34: =V34*U34*$E34 -> 0 | AA34: =K34*$K$3+N34*$N$3+Q34*$Q$3+H34*$H$3+T34*$T$3+W34*$W$3 -> 0 | AB34: =AA34/$AA$162 -> #DIV/0!
B35: ='CPU 1'!B35 -> E10 | C35: ='CPU 1'!C35 -> Carro de mão | D35: ='CPU 1'!D35 -> pç | E35: ='CPU 1'!E35 -> 450 | H35: =G35*F35*$E35 -> 0 | K35: =J35*I35*$E35 -> 0 | N35: =M35*L35*$E35 -> 0 | Q35: =P35*O35*$E35 -> 0 | T35: =S35*R35*$E35 -> 0 | W35: =V35*U35*$E35 -> 0 | AA35: =K35*$K$3+N35*$N$3+Q35*$Q$3+H35*$H$3+T35*$T$3+W35*$W$3 -> 0 | AB35: =AA35/$AA$162 -> #DIV/0!
B36: ='CPU 1'!B36 -> E11 | C36: ='CPU 1'!C36 -> Carro plataforma | D36: ='CPU 1'!D36 -> pç | E36: ='CPU 1'!E36 -> 1200 | H36: =G36*F36*$E36 -> 0 | K36: =J36*I36*$E36 -> 0 | N36: =M36*L36*$E36 -> 0 | Q36: =P36*O36*$E36 -> 0 | T36: =S36*R36*$E36 -> 0 | W36: =V36*U36*$E36 -> 0 | AA36: =K36*$K$3+N36*$N$3+Q36*$Q$3+H36*$H$3+T36*$T$3+W36*$W$3 -> 0 | AB36: =AA36/$AA$162 -> #DIV/0!
B37: ='CPU 1'!B37 -> E12 | C37: ='CPU 1'!C37 -> Coletor de resíduo com pedal - 50L (V,V,A,A) | D37: ='CPU 1'!D37 -> kit | E37: ='CPU 1'!E37 -> 1200 | H37: =G37*F37*$E37 -> 0 | K37: =J37*I37*$E37 -> 0 | N37: =M37*L37*$E37 -> 0 | Q37: =P37*O37*$E37 -> 0 | T37: =S37*R37*$E37 -> 0 | W37: =V37*U37*$E37 -> 0 | AA37: =K37*$K$3+N37*$N$3+Q37*$Q$3+H37*$H$3+T37*$T$3+W37*$W$3 -> 0 | AB37: =AA37/$AA$162 -> #DIV/0!
... B79: ='CPU 1'!B79 -> E54 | C79: ='CPU 1'!C79 -> 0 | D79: ='CPU 1'!D79 -> 0 | E79: ='CPU 1'!E79 -> 0 | H79: =G79*F79*$E79 -> 0 | K79: =J79*I79*$E79 -> 0 | N79: =M79*L79*$E79 -> 0 | Q79: =P79*O79*$E79 -> 0 | T79: =S79*R79*$E79 -> 0 | W79: =V79*U79*$E79 -> 0 | AA79: =K79*$K$3+N79*$N$3+Q79*$Q$3+H79*$H$3+T79*$T$3+W79*$W$3 -> 0 | AB79: =AA79/$AA$162 -> #DIV/0!
B80: B - Custo Total de Equipamentos e Ferramentas: | E80: =SUM(#REF!) -> #REF! | H80: =SUM(H26:H79) -> 0 | K80: =SUM(K26:K79) -> 0 | N80: =SUM(N26:N79) -> 0 | Q80: =SUM(Q26:Q79) -> 0 | T80: =SUM(T26:T79) -> 0 | W80: =SUM(W26:W79) -> 0 | AA80: =SUM(AA26:AA79) -> 0
B81: C – Materiais
B82: Cód. | C82: Discriminação | D82: Unid | E82: P.Unit | F82: Quant | G82: F.utiliz | H82: Custo | I82: Quant | J82: F.utiliz | K82: Custo | L82: Quant | M82: F.utiliz | N82: Custo | O82: Quant | P82: F.utiliz | Q82: Custo | R82: Quant | S82: F.utiliz | T82: Custo | U82: Quant | V82: F.utiliz | W82: Custo | Y82: Quant | Z82: F.utiliz | AA82: Custo
B83: ='CPU 1'!B83 -> M01 | C83: ='CPU 1'!C83 -> Aço CA-50, (ferro 8.0) | D83: ='CPU 1'!D83 -> kg | E83: ='CPU 1'!E83 -> 12.5 | H83: =G83*F83*$E83 -> 0 | K83: =J83*I83*$E83 -> 0 | N83: =M83*L83*$E83 -> 0 | Q83: =P83*O83*$E83 -> 0 | T83: =S83*R83*$E83 -> 0 | W83: =V83*U83*$E83 -> 0 | AA83: =K83*$K$3+N83*$N$3+Q83*$Q$3+H83*$H$3+T83*$T$3+W83*$W$3 -> 0 | AB83: =AA83/$AA$162 -> #DIV/0!
B84: ='CPU 1'!B84 -> M02 | C84: ='CPU 1'!C84 -> Agua Mineral | D84: ='CPU 1'!D84 -> litro | E84: ='CPU 1'!E84 -> 1 | H84: =G84*F84*$E84 -> 0 | K84: =J84*I84*$E84 -> 0 | N84: =M84*L84*$E84 -> 0 | Q84: =P84*O84*$E84 -> 0 | T84: =S84*R84*$E84 -> 0 | W84: =V84*U84*$E84 -> 0 | AA84: =K84*$K$3+N84*$N$3+Q84*$Q$3+H84*$H$3+T84*$T$3+W84*$W$3 -> 0 | AB84: =AA84/$AA$162 -> #DIV/0!
B85: ='CPU 1'!B85 -> M03 | C85: ='CPU 1'!C85 -> Arame ovalado zincado | D85: ='CPU 1'!D85 -> m | E85: ='CPU 1'!E85 -> 1 | H85: =G85*F85*$E85 -> 0 | K85: =J85*I85*$E85 -> 0 | N85: =M85*L85*$E85 -> 0 | Q85: =P85*O85*$E85 -> 0 | T85: =S85*R85*$E85 -> 0 | W85: =V85*U85*$E85 -> 0 | AA85: =K85*$K$3+N85*$N$3+Q85*$Q$3+H85*$H$3+T85*$T$3+W85*$W$3 -> 0 | AB85: =AA85/$AA$162 -> #DIV/0!
B86: ='CPU 1'!B86 -> M04 | C86: ='CPU 1'!C86 -> Areia | D86: ='CPU 1'!D86 -> m³ | E86: ='CPU 1'!E86 -> 120 | H86: =G86*F86*$E86 -> 0 | K86: =J86*I86*$E86 -> 0 | N86: =M86*L86*$E86 -> 0 | Q86: =P86*O86*$E86 -> 0 | T86: =S86*R86*$E86 -> 0 | W86: =V86*U86*$E86 -> 0 | AA86: =K86*$K$3+N86*$N$3+Q86*$Q$3+H86*$H$3+T86*$T$3+W86*$W$3 -> 0 | AB86: =AA86/$AA$162 -> #DIV/0!
B87: ='CPU 1'!B87 -> M05 | C87: ='CPU 1'!C87 -> Arrame galganizado | D87: ='CPU 1'!D87 -> kg | E87: ='CPU 1'!E87 -> 16.8 | H87: =G87*F87*$E87 -> 0 | K87: =J87*I87*$E87 -> 0 | N87: =M87*L87*$E87 -> 0 | Q87: =P87*O87*$E87 -> 0 | T87: =S87*R87*$E87 -> 0 | W87: =V87*U87*$E87 -> 0 | AA87: =K87*$K$3+N87*$N$3+Q87*$Q$3+H87*$H$3+T87*$T$3+W87*$W$3 -> 0 | AB87: =AA87/$AA$162 -> #DIV/0!
B88: ='CPU 1'!B88 -> M06 | C88: ='CPU 1'!C88 -> Arrame recozido | D88: ='CPU 1'!D88 -> kg | E88: ='CPU 1'!E88 -> 12 | H88: =G88*F88*$E88 -> 0 | K88: =J88*I88*$E88 -> 0 | N88: =M88*L88*$E88 -> 0 | Q88: =P88*O88*$E88 -> 0 | T88: =S88*R88*$E88 -> 0 | W88: =V88*U88*$E88 -> 0 | AA88: =K88*$K$3+N88*$N$3+Q88*$Q$3+H88*$H$3+T88*$T$3+W88*$W$3 -> 0 | AB88: =AA88/$AA$162 -> #DIV/0!
B89: ='CPU 1'!B89 -> M07 | C89: ='CPU 1'!C89 -> Barrote de madeira 7x7cm | D89: ='CPU 1'!D89 -> m | E89: ='CPU 1'!E89 -> 15 | H89: =G89*F89*$E89 -> 0 | K89: =J89*I89*$E89 -> 0 | N89: =M89*L89*$E89 -> 0 | Q89: =P89*O89*$E89 -> 0 | T89: =S89*R89*$E89 -> 0 | W89: =V89*U89*$E89 -> 0 | AA89: =K89*$K$3+N89*$N$3+Q89*$Q$3+H89*$H$3+T89*$T$3+W89*$W$3 -> 0 | AB89: =AA89/$AA$162 -> #DIV/0!
B90: ='CPU 1'!B90 -> M08 | C90: ='CPU 1'!C90 -> Bloco tipo canaleta (14x19x39cm) | D90: ='CPU 1'!D90 -> peça | E90: ='CPU 1'!E90 -> 8.9 | H90: =G90*F90*$E90 -> 0 | K90: =J90*I90*$E90 -> 0 | N90: =M90*L90*$E90 -> 0 | Q90: =P90*O90*$E90 -> 0 | T90: =S90*R90*$E90 -> 0 | W90: =V90*U90*$E90 -> 0 | AA90: =K90*$K$3+N90*$N$3+Q90*$Q$3+H90*$H$3+T90*$T$3+W90*$W$3 -> 0 | AB90: =AA90/$AA$162 -> #DIV/0!
B91: ='CPU 1'!B91 -> M09 | C91: ='CPU 1'!C91 -> Brita 1 | D91: ='CPU 1'!D91 -> m³ | E91: ='CPU 1'!E91 -> 220 | H91: =G91*F91*$E91 -> 0 | K91: =J91*I91*$E91 -> 0 | N91: =M91*L91*$E91 -> 0 | Q91: =P91*O91*$E91 -> 0 | T91: =S91*R91*$E91 -> 0 | W91: =V91*U91*$E91 -> 0 | AA91: =K91*$K$3+N91*$N$3+Q91*$Q$3+H91*$H$3+T91*$T$3+W91*$W$3 -> 0 | AB91: =AA91/$AA$162 -> #DIV/0!
B92: ='CPU 1'!B92 -> M11 | C92: ='CPU 1'!C92 -> Caixa de passagens para aterramento h600 diâmetro 30cm | D92: ='CPU 1'!D92 -> und | E92: ='CPU 1'!E92 -> 590 | H92: =G92*F92*$E92 -> 0 | K92: =J92*I92*$E92 -> 0 | N92: =M92*L92*$E92 -> 0 | Q92: =P92*O92*$E92 -> 0 | T92: =S92*R92*$E92 -> 0 | W92: =V92*U92*$E92 -> 0 | AA92: =K92*$K$3+N92*$N$3+Q92*$Q$3+H92*$H$3+T92*$T$3+W92*$W$3 -> 0 | AB92: =AA92/$AA$162 -> #DIV/0!
B93: ='CPU 1'!B93 -> M12 | C93: ='CPU 1'!C93 -> Catoneira galvanizada 1"x1-1/4 | D93: ='CPU 1'!D93 -> m | E93: ='CPU 1'!E93 -> 25 | H93: =G93*F93*$E93 -> 0 | K93: =J93*I93*$E93 -> 0 | N93: =M93*L93*$E93 -> 0 | Q93: =P93*O93*$E93 -> 0 | T93: =S93*R93*$E93 -> 0 | W93: =V93*U93*$E93 -> 0 | AA93: =K93*$K$3+N93*$N$3+Q93*$Q$3+H93*$H$3+T93*$T$3+W93*$W$3 -> 0 | AB93: =AA93/$AA$162 -> #DIV/0!
B94: ='CPU 1'!B94 -> M13 | C94: ='CPU 1'!C94 -> Cercamento e delimitação de canteiro de obra (15x30m) | D94: ='CPU 1'!D94 -> vb | E94: ='CPU 1'!E94 -> 10000 | H94: =G94*F94*$E94 -> 0 | K94: =J94*I94*$E94 -> 0 | N94: =M94*L94*$E94 -> 0 | Q94: =P94*O94*$E94 -> 0 | T94: =S94*R94*$E94 -> 0 | W94: =V94*U94*$E94 -> 0 | AA94: =K94*$K$3+N94*$N$3+Q94*$Q$3+H94*$H$3+T94*$T$3+W94*$W$3 -> 0 | AB94: =AA94/$AA$162 -> #DIV/0!
... B131: ='CPU 1'!B131 -> M50 | C131: ='CPU 1'!C131 -> 0 | D131: ='CPU 1'!D131 -> 0 | E131: ='CPU 1'!E131 -> 0 | H131: =G131*F131*$E131 -> 0 | K131: =J131*I131*$E131 -> 0 | N131: =M131*L131*$E131 -> 0 | Q131: =P131*O131*$E131 -> 0 | T131: =S131*R131*$E131 -> 0 | W131: =V131*U131*$E131 -> 0 | AA131: =K131*$K$3+N131*$N$3+Q131*$Q$3+H131*$H$3+T131*$T$3+W131*$W$3 -> 0 | AB131: =AA131/$AA$162 -> #DIV/0!
B132: C - Custo Total de Materiais: | E132: =SUM(#REF!) -> #REF! | H132: =SUM(H83:H131) -> 0 | K132: =SUM(K83:K131) -> 0 | N132: =SUM(N83:N131) -> 0 | Q132: =SUM(Q83:Q131) -> 0 | T132: =SUM(T83:T131) -> 0 | W132: =SUM(W83:W131) -> 0 | AA132: =SUM(AA83:AA131) -> 0
B133: D – Outros
B134: Cód. | C134: Discriminação | D134: Unid | E134: P.Unit | F134: Quant | G134: F.utiliz | H134: Custo | I134: Quant | J134: F.utiliz | K134: Custo | L134: Quant | M134: F.utiliz | N134: Custo | O134: Quant | P134: F.utiliz | Q134: Custo | R134: Quant | S134: F.utiliz | T134: Custo | U134: Quant | V134: F.utiliz | W134: Custo | Y134: Quant | Z134: F.utiliz | AA134: Custo
B135: ='CPU 1'!B135 -> O01 | C135: ='CPU 1'!C135 -> ART | D135: ='CPU 1'!D135 -> Vb | E135: ='CPU 1'!E135 -> 1000 | H135: =G135*F135*$E135 -> 0 | K135: =J135*I135*$E135 -> 0 | N135: =M135*L135*$E135 -> 0 | Q135: =P135*O135*$E135 -> 0 | T135: =S135*R135*$E135 -> 0 | W135: =V135*U135*$E135 -> 0 | AA135: =K135*$K$3+N135*$N$3+Q135*$Q$3+H135*$H$3+T135*$T$3+W135*$W$3 -> 0 | AB135: =AA135/$AA$162 -> #DIV/0!
B136: ='CPU 1'!B136 -> O02 | C136: ='CPU 1'!C136 -> Exames medicos | D136: ='CPU 1'!D136 -> Vb | E136: ='CPU 1'!E136 -> 600 | H136: =G136*F136*$E136 -> 0 | K136: =J136*I136*$E136 -> 0 | N136: =M136*L136*$E136 -> 0 | Q136: =P136*O136*$E136 -> 0 | T136: =S136*R136*$E136 -> 0 | W136: =V136*U136*$E136 -> 0 | AA136: =K136*$K$3+N136*$N$3+Q136*$Q$3+H136*$H$3+T136*$T$3+W136*$W$3 -> 0 | AB136: =AA136/$AA$162 -> #DIV/0!
B137: ='CPU 1'!B137 -> O03 | C137: ='CPU 1'!C137 -> Treinamentos | D137: ='CPU 1'!D137 -> Vb | E137: ='CPU 1'!E137 -> 426 | H137: =G137*F137*$E137 -> 0 | K137: =J137*I137*$E137 -> 0 | N137: =M137*L137*$E137 -> 0 | Q137: =P137*O137*$E137 -> 0 | T137: =S137*R137*$E137 -> 0 | W137: =V137*U137*$E137 -> 0 | AA137: =K137*$K$3+N137*$N$3+Q137*$Q$3+H137*$H$3+T137*$T$3+W137*$W$3 -> 0 | AB137: =AA137/$AA$162 -> #DIV/0!
B138: ='CPU 1'!B138 -> O04 | C138: ='CPU 1'!C138 -> Plano de Saude | D138: ='CPU 1'!D138 -> Vb/mês | E138: ='CPU 1'!E138 -> 280 | H138: =G138*F138*$E138 -> 0 | K138: =J138*I138*$E138 -> 0 | N138: =M138*L138*$E138 -> 0 | Q138: =P138*O138*$E138 -> 0 | T138: =S138*R138*$E138 -> 0 | W138: =V138*U138*$E138 -> 0 | AA138: =K138*$K$3+N138*$N$3+Q138*$Q$3+H138*$H$3+T138*$T$3+W138*$W$3 -> 0 | AB138: =AA138/$AA$162 -> #DIV/0!
B139: ='CPU 1'!B139 -> O05 | C139: ='CPU 1'!C139 -> Seguro de Vida | D139: ='CPU 1'!D139 -> Vb/mês | E139: ='CPU 1'!E139 -> 25 | H139: =G139*F139*$E139 -> 0 | K139: =J139*I139*$E139 -> 0 | N139: =M139*L139*$E139 -> 0 | Q139: =P139*O139*$E139 -> 0 | T139: =S139*R139*$E139 -> 0 | W139: =V139*U139*$E139 -> 0 | AA139: =K139*$K$3+N139*$N$3+Q139*$Q$3+H139*$H$3+T139*$T$3+W139*$W$3 -> 0 | AB139: =AA139/$AA$162 -> #DIV/0!
B140: ='CPU 1'!B140 -> O06 | C140: ='CPU 1'!C140 -> Ticket Alimentação | D140: ='CPU 1'!D140 -> Vb/mês | E140: ='CPU 1'!E140 -> 350 | H140: =G140*F140*$E140 -> 0 | K140: =J140*I140*$E140 -> 0 | N140: =M140*L140*$E140 -> 0 | Q140: =P140*O140*$E140 -> 0 | T140: =S140*R140*$E140 -> 0 | W140: =V140*U140*$E140 -> 0 | AA140: =K140*$K$3+N140*$N$3+Q140*$Q$3+H140*$H$3+T140*$T$3+W140*$W$3 -> 0 | AB140: =AA140/$AA$162 -> #DIV/0!
B141: ='CPU 1'!B141 -> O07 | C141: ='CPU 1'!C141 -> PCMSO / PGR / PCA / PPR | D141: ='CPU 1'!D141 -> Vb/ano | E141: ='CPU 1'!E141 -> 2300 | H141: =G141*F141*$E141 -> 0 | K141: =J141*I141*$E141 -> 0 | N141: =M141*L141*$E141 -> 0 | Q141: =P141*O141*$E141 -> 0 | T141: =S141*R141*$E141 -> 0 | W141: =V141*U141*$E141 -> 0 | AA141: =K141*$K$3+N141*$N$3+Q141*$Q$3+H141*$H$3+T141*$T$3+W141*$W$3 -> 0 | AB141: =AA141/$AA$162 -> #DIV/0!
B142: ='CPU 1'!B142 -> O08 | C142: ='CPU 1'!C142 -> Quadros DDS e Gestão a vista | D142: ='CPU 1'!D142 -> Vb | E142: ='CPU 1'!E142 -> 1200 | H142: =G142*F142*$E142 -> 0 | K142: =J142*I142*$E142 -> 0 | N142: =M142*L142*$E142 -> 0 | Q142: =P142*O142*$E142 -> 0 | T142: =S142*R142*$E142 -> 0 | W142: =V142*U142*$E142 -> 0 | AA142: =K142*$K$3+N142*$N$3+Q142*$Q$3+H142*$H$3+T142*$T$3+W142*$W$3 -> 0 | AB142: =AA142/$AA$162 -> #DIV/0!
B143: ='CPU 1'!B143 -> O09 | C143: ='CPU 1'!C143 -> Seguro Obra | D143: ='CPU 1'!D143 -> Vb | E143: ='CPU 1'!E143 -> 5000 | H143: =G143*F143*$E143 -> 0 | K143: =J143*I143*$E143 -> 0 | N143: =M143*L143*$E143 -> 0 | Q143: =P143*O143*$E143 -> 0 | T143: =S143*R143*$E143 -> 0 | W143: =V143*U143*$E143 -> 0 | AA143: =K143*$K$3+N143*$N$3+Q143*$Q$3+H143*$H$3+T143*$T$3+W143*$W$3 -> 0 | AB143: =AA143/$AA$162 -> #DIV/0!
B144: ='CPU 1'!B144 -> O10 | C144: ='CPU 1'!C144 -> Fretes | D144: ='CPU 1'!D144 -> ud | E144: ='CPU 1'!E144 -> 2800 | H144: =G144*F144*$E144 -> 0 | K144: =J144*I144*$E144 -> 0 | N144: =M144*L144*$E144 -> 0 | Q144: =P144*O144*$E144 -> 0 | T144: =S144*R144*$E144 -> 0 | W144: =V144*U144*$E144 -> 0 | AA144: =K144*$K$3+N144*$N$3+Q144*$Q$3+H144*$H$3+T144*$T$3+W144*$W$3 -> 0 | AB144: =AA144/$AA$162 -> #DIV/0!
B145: ='CPU 1'!B145 -> O11 | C145: ='CPU 1'!C145 -> Serviço de descarte de residuo | D145: ='CPU 1'!D145 -> coleta | E145: ='CPU 1'!E145 -> 2000 | H145: =G145*F145*$E145 -> 0 | K145: =J145*I145*$E145 -> 0 | N145: =M145*L145*$E145 -> 0 | Q145: =P145*O145*$E145 -> 0 | T145: =S145*R145*$E145 -> 0 | W145: =V145*U145*$E145 -> 0 | AA145: =K145*$K$3+N145*$N$3+Q145*$Q$3+H145*$H$3+T145*$T$3+W145*$W$3 -> 0 | AB145: =AA145/$AA$162 -> #DIV/0!
B146: ='CPU 1'!B146 -> O12 | C146: ='CPU 1'!C146 -> Serviço de movimentação do Banheiro Hidráulico | D146: ='CPU 1'!D146 -> vb | E146: ='CPU 1'!E146 -> 200 | H146: =G146*F146*$E146 -> 0 | K146: =J146*I146*$E146 -> 0 | N146: =M146*L146*$E146 -> 0 | Q146: =P146*O146*$E146 -> 0 | T146: =S146*R146*$E146 -> 0 | W146: =V146*U146*$E146 -> 0 | AA146: =K146*$K$3+N146*$N$3+Q146*$Q$3+H146*$H$3+T146*$T$3+W146*$W$3 -> 0 | AB146: =AA146/$AA$162 -> #DIV/0!
... B154: ='CPU 1'!B154 -> O20 | C154: ='CPU 1'!C154 -> 0 | D154: ='CPU 1'!D154 -> 0 | E154: ='CPU 1'!E154 -> 0 | H154: =G154*F154*$E154 -> 0 | K154: =J154*I154*$E154 -> 0 | N154: =M154*L154*$E154 -> 0 | Q154: =P154*O154*$E154 -> 0 | T154: =S154*R154*$E154 -> 0 | W154: =V154*U154*$E154 -> 0 | AA154: =K154*$K$3+N154*$N$3+Q154*$Q$3+H154*$H$3+T154*$T$3+W154*$W$3 -> 0 | AB154: =AA154/$AA$162 -> #DIV/0!
B155: D - Custo Total de Outros: | E155: =SUM(#REF!) -> #REF! | H155: =SUM(H135:H154) -> 0 | K155: =SUM(K135:K154) -> 0 | N155: =SUM(N135:N154) -> 0 | Q155: =SUM(Q135:Q154) -> 0 | T155: =SUM(T135:T154) -> 0 | W155: =SUM(W135:W154) -> 0 | AA155: =SUM(AA135:AA154) -> 0
B157: Item | C157: CUSTOS | G157: % | H157: $ | J157: % | K157: $ | M157: % | N157: $ | P157: % | Q157: $ | S157: % | T157: $ | V157: % | W157: $ | Z157: % | AA157: $
B158: A | C158: Mão de Obra | G158: =H158/H162 -> #DIV/0! | H158: =H23 -> 0 | J158: =K158/K162 -> #DIV/0! | K158: =K23 -> 0 | M158: =N158/N162 -> #DIV/0! | N158: =N23 -> 0 | P158: =Q158/Q162 -> #DIV/0! | Q158: =Q23 -> 0 | S158: =T158/T162 -> #DIV/0! | T158: =T23 -> 0 | V158: =W158/W162 -> #DIV/0! | W158: =W23 -> 0 | Z158: =AA158/AA162 -> #DIV/0! | AA158: =AA23 -> 0
B159: B | C159: Equipamentos | G159: =H159/H162 -> #DIV/0! | H159: =H80 -> 0 | J159: =K159/K162 -> #DIV/0! | K159: =K80 -> 0 | M159: =N159/N162 -> #DIV/0! | N159: =N80 -> 0 | P159: =Q159/Q162 -> #DIV/0! | Q159: =Q80 -> 0 | S159: =T159/T162 -> #DIV/0! | T159: =T80 -> 0 | V159: =W159/W162 -> #DIV/0! | W159: =W80 -> 0 | Z159: =AA159/AA162 -> #DIV/0! | AA159: =AA80 -> 0
B160: C | C160: Materiais | G160: =H160/H162 -> #DIV/0! | H160: =H132 -> 0 | J160: =K160/K162 -> #DIV/0! | K160: =K132 -> 0 | M160: =N160/N162 -> #DIV/0! | N160: =N132 -> 0 | P160: =Q160/Q162 -> #DIV/0! | Q160: =Q132 -> 0 | S160: =T160/T162 -> #DIV/0! | T160: =T132 -> 0 | V160: =W160/W162 -> #DIV/0! | W160: =W132 -> 0 | Z160: =AA160/AA162 -> #DIV/0! | AA160: =AA132 -> 0
B161: D | C161: Outros | G161: =H161/H162 -> #DIV/0! | H161: =H155 -> 0 | J161: =K161/K162 -> #DIV/0! | K161: =K155 -> 0 | M161: =N161/N162 -> #DIV/0! | N161: =N155 -> 0 | P161: =Q161/Q162 -> #DIV/0! | Q161: =Q155 -> 0 | S161: =T161/T162 -> #DIV/0! | T161: =T155 -> 0 | V161: =W161/W162 -> #DIV/0! | W161: =W155 -> 0 | Z161: =AA161/AA162 -> #DIV/0! | AA161: =AA155 -> 0
C162: Subtotal: | E162: =SUM(E158:E161) -> 0 | G162: =SUM(G158:G161) -> #DIV/0! | H162: =SUM(H158:H161) -> 0 | J162: =SUM(J158:J161) -> #DIV/0! | K162: =SUM(K158:K161) -> 0 | M162: =SUM(M158:M161) -> #DIV/0! | N162: =SUM(N158:N161) -> 0 | P162: =SUM(P158:P161) -> #DIV/0! | Q162: =SUM(Q158:Q161) -> 0 | S162: =SUM(S158:S161) -> #DIV/0! | T162: =SUM(T158:T161) -> 0 | V162: =SUM(V158:V161) -> #DIV/0! | W162: =SUM(W158:W161) -> 0 | Z162: =SUM(Z158:Z161) -> #DIV/0! | AA162: =SUM(AA158:AA161) -> 0
B164: Item | C164: BDI | E164: Taxa | H164: $ | K164: $ | N164: $ | Q164: $ | T164: $ | W164: $ | AA164: $
B165: 1 | C165: Administração Local | E165: ='BDI-TRIBUTOS'!D8 -> 0.09 | H165: =H162*$E$165 -> 0 | K165: =K162*$E$165 -> 0 | N165: =N162*$E$165 -> 0 | Q165: =Q162*$E$165 -> 0 | T165: =T162*$E$165 -> 0 | W165: =W162*$E$165 -> 0 | AA165: =AA162*$E$165 -> 0
B166: 2 | C166: Administração Central | E166: ='BDI-TRIBUTOS'!D6 -> 0.06 | H166: =H162*$E$166 -> 0 | K166: =K162*$E$166 -> 0 | N166: =N162*$E$166 -> 0 | Q166: =Q162*$E$166 -> 0 | T166: =T162*$E$166 -> 0 | W166: =W162*$E$166 -> 0 | AA166: =AA162*$E$166 -> 0
B167: 3 | C167: Custo financ. capital giro | E167: ='BDI-TRIBUTOS'!D10 -> 0.035 | H167: =H162*$E$167 -> 0 | K167: =K162*$E$167 -> 0 | N167: =N162*$E$167 -> 0 | Q167: =Q162*$E$167 -> 0 | T167: =T162*$E$167 -> 0 | W167: =W162*$E$167 -> 0 | AA167: =AA162*$E$167 -> 0
B168: 4 | C168: Risco do empreendimento | E168: ='BDI-TRIBUTOS'!D12 -> 0.02 | H168: =H162*$E$168 -> 0 | K168: =K162*$E$168 -> 0 | N168: =N162*$E$168 -> 0 | Q168: =Q162*$E$168 -> 0 | T168: =T162*$E$168 -> 0 | W168: =W162*$E$168 -> 0 | AA168: =AA162*$E$168 -> 0
B169: 5 | C169: Outros | E169: ='BDI-TRIBUTOS'!D14 -> 0.01 | H169: =H162*$E$169 -> 0 | K169: =K162*$E$169 -> 0 | N169: =N162*$E$169 -> 0 | Q169: =Q162*$E$169 -> 0 | T169: =T162*$E$169 -> 0 | W169: =W162*$E$169 -> 0 | AA169: =AA162*$E$169 -> 0
B170: 6 | C170: Lucro | E170: ='BDI-TRIBUTOS'!D4 -> 0.1 | H170: =H182*$E$170 -> 0 | K170: =K182*$E$170 -> 0 | N170: =N182*$E$170 -> 0 | Q170: =Q182*$E$170 -> 0 | T170: =T182*$E$170 -> 0 | W170: =W182*$E$170 -> 0 | AA170: =AA182*$E$170 -> 0
C171: Subtotal: | E171: =SUM(E165:E170) -> 0.315 | G171: =SUM(H165:H169)+H162 -> 0 | H171: =SUM(H165:H170) -> 0 | J171: =SUM(K165:K169)+K162 -> 0 | K171: =SUM(K165:K170) -> 0 | M171: =SUM(N165:N169)+N162 -> 0 | N171: =SUM(N165:N170) -> 0 | P171: =SUM(Q165:Q169)+Q162 -> 0 | Q171: =SUM(Q165:Q170) -> 0 | S171: =SUM(T165:T169)+T162 -> 0 | T171: =SUM(T165:T170) -> 0 | V171: =SUM(W165:W169)+W162 -> 0 | W171: =SUM(W165:W170) -> 0 | Z171: =SUM(AA165:AA169)+AA162 -> 0 | AA171: =SUM(AA165:AA170) -> 0
F172: =H171/H162 -> #DIV/0! | I172: =K171/K162 -> #DIV/0! | L172: =N171/N162 -> #DIV/0! | O172: =Q171/Q162 -> #DIV/0! | R172: =T171/T162 -> #DIV/0! | U172: =W171/W162 -> #DIV/0! | Y172: =AA171/AA162 -> #DIV/0!
B173: Item | C173: TRIBUTOS | E173: Taxa | H173: $ | K173: $ | N173: $ | Q173: $ | T173: $ | W173: $ | AA173: $
B174: 1 | C174: ISS | E174: ='BDI-TRIBUTOS'!D20 -> 0.05 | H174: =H$182*$E174 -> 0 | K174: =K$182*$E174 -> 0 | N174: =N$182*$E174 -> 0 | Q174: =Q$182*$E174 -> 0 | T174: =T$182*$E174 -> 0 | W174: =W$182*$E174 -> 0 | AA174: =$AA$182*E174 -> 0
B175: 2 | C175: COFINS | E175: ='BDI-TRIBUTOS'!D21 -> 0.03 | H175: =H$182*$E175 -> 0 | K175: =K$182*$E175 -> 0 | N175: =N$182*$E175 -> 0 | Q175: =Q$182*$E175 -> 0 | T175: =T$182*$E175 -> 0 | W175: =W$182*$E175 -> 0 | AA175: =$AA$182*E175 -> 0
B176: 3 | C176: PIS | E176: ='BDI-TRIBUTOS'!D22 -> 0.0065 | H176: =H$182*$E176 -> 0 | K176: =K$182*$E176 -> 0 | N176: =N$182*$E176 -> 0 | Q176: =Q$182*$E176 -> 0 | T176: =T$182*$E176 -> 0 | W176: =W$182*$E176 -> 0 | AA176: =$AA$182*E176 -> 0
B177: 4 | C177: CSLL | E177: ='BDI-TRIBUTOS'!D23 -> 0.0288 | H177: =H$182*$E177 -> 0 | K177: =K$182*$E177 -> 0 | N177: =N$182*$E177 -> 0 | Q177: =Q$182*$E177 -> 0 | T177: =T$182*$E177 -> 0 | W177: =W$182*$E177 -> 0 | AA177: =$AA$182*E177 -> 0
B178: 5 | C178: IRPJ | E178: ='BDI-TRIBUTOS'!D24 -> 0.048 | H178: =H$182*$E178 -> 0 | K178: =K$182*$E178 -> 0 | N178: =N$182*$E178 -> 0 | Q178: =Q$182*$E178 -> 0 | T178: =T$182*$E178 -> 0 | W178: =W$182*$E178 -> 0 | AA178: =$AA$182*E178 -> 0
B179: 6 | C179: IRPJ Adicional 10% | E179: ='BDI-TRIBUTOS'!D25 -> 0.0318 | H179: =H$182*$E179 -> 0 | K179: =K$182*$E179 -> 0 | N179: =N$182*$E179 -> 0 | Q179: =Q$182*$E179 -> 0 | T179: =T$182*$E179 -> 0 | W179: =W$182*$E179 -> 0 | AA179: =$AA$182*E179 -> 0
B180: 7 | C180: Simples Nacional | E180: ='BDI-TRIBUTOS'!D26 -> 0
C181: Subtotal | E181: =SUM(E174:E180) -> 0.1951 | H181: =H182*$E$181 -> 0 | K181: =K182*$E$181 -> 0 | N181: =N182*$E$181 -> 0 | Q181: =Q182*$E$181 -> 0 | T181: =T182*$E$181 -> 0 | W181: =W182*$E$181 -> 0 | AA181: =AA182*$E$181 -> 0
C182: PREÇO | F182: =ROUND(H182,2) -> 0 | H182: =G171/(1-$E$181-$E$170) -> 0 | I182: =ROUND(K182,2) -> 0 | K182: =J171/(1-$E$181-$E$170) -> 0 | L182: =ROUND(N182,2) -> 0 | N182: =M171/(1-$E$181-$E$170) -> 0 | O182: =ROUND(Q182,2) -> 0 | Q182: =P171/(1-$E$181-$E$170) -> 0 | R182: =ROUND(T182,2) -> 0 | T182: =S171/(1-$E$181-$E$170) -> 0 | U182: =ROUND(W182,2) -> 0 | W182: =V171/(1-$E$181-$E$170) -> 0 | AA182: =Z171/(1-$E$181-$E$170) -> 0
H183: =H182/H162 -> #DIV/0! | K183: =K182/K162 -> #DIV/0! | N183: =N182/N162 -> #DIV/0! | Q183: =Q182/Q162 -> #DIV/0! | T183: =T182/T162 -> #DIV/0! | W183: =W182/W162 -> #DIV/0! | AA183: =AA182/AA162 -> #DIV/0!

Sheet CPU  4
B1: =QQP!G44 -> 0 | D1: CPU | E1: 4 | F1: =QQP!B29 -> 2.4.1 | G1: =H182 -> 0 | I1: =QQP!B30 -> 2.4.2 | J1: =K182 -> 0 | L1: =QQP!B31 -> 2.4.3 | M1: =N182 -> 0 | O1: =QQP!B32 -> 2.4.4 | P1: =Q182 -> 0 | R1: =QQP!B34 -> 2.5.1 | S1: =T182 -> 0 | U1: =QQP!B35 -> 2.5.2 | V1: =W182 -> 0
B2: Composição de Preços Unitários | F2: =_xlfn.XLOOKUP(F1,QQP!$B$8:$B$43,QQP!$C$8:$C$43) -> XXXXXXXXXXXXXXXXXXXXXXXXXXXXXXXXXXXXXXXXXX | I2: =_xlfn.XLOOKUP(I1,QQP!$B$8:$B$43,QQP!$C$8:$C$43) -> XXXXXXXXXXXXXXXXXXXXXXXXXXXXXXXXXXXXXXXXXX | L2: =_xlfn.XLOOKUP(L1,QQP!$B$8:$B$43,QQP!$C$8:$C$43) -> XXXXXXXXXXXXXXXXXXXXXXXXXXXXXXXXXXXXXXXXXX | O2: =_xlfn.XLOOKUP(O1,QQP!$B$8:$B$43,QQP!$C$8:$C$43) -> XXXXXXXXXXXXXXXXXXXXXXXXXXXXXXXXXXXXXXXXXX | R2: =_xlfn.XLOOKUP(R1,QQP!$B$8:$B$43,QQP!$C$8:$C$43) -> XXXXXXXXXXXXXXXXXXXXXXXXXXXXXXXXXXXXXXXXXX | U2: =_xlfn.XLOOKUP(U1,QQP!$B$8:$B$43,QQP!$C$8:$C$43) -> XXXXXXXXXXXXXXXXXXXXXXXXXXXXXXXXXXXXXXXXXX | Y2: CHECK
G3: =_xlfn.XLOOKUP(F1,QQP!$B$8:$B$43,QQP!$D$8:$D$43) -> xx | H3: =_xlfn.XLOOKUP(F1,QQP!$B$8:$B$43,QQP!$E$8:$E$43) -> 1 | J3: =_xlfn.XLOOKUP(I1,QQP!$B$8:$B$43,QQP!$D$8:$D$43) -> xx | K3: =_xlfn.XLOOKUP(I1,QQP!$B$8:$B$43,QQP!$E$8:$E$43) -> 1 | M3: =_xlfn.XLOOKUP(L1,QQP!$B$8:$B$43,QQP!$D$8:$D$43) -> xx | N3: =_xlfn.XLOOKUP(L1,QQP!$B$8:$B$43,QQP!$E$8:$E$43) -> 1 | P3: =_xlfn.XLOOKUP(O1,QQP!$B$8:$B$43,QQP!$D$8:$D$43) -> xx | Q3: =_xlfn.XLOOKUP(O1,QQP!$B$8:$B$43,QQP!$E$8:$E$43) -> 1 | S3: =_xlfn.XLOOKUP(R1,QQP!$B$8:$B$43,QQP!$D$8:$D$43) -> xx | T3: =_xlfn.XLOOKUP(R1,QQP!$B$8:$B$43,QQP!$E$8:$E$43) -> 1 | V3: =_xlfn.XLOOKUP(U1,QQP!$B$8:$B$43,QQP!$D$8:$D$43) -> xx | W3: =_xlfn.XLOOKUP(U1,QQP!$B$8:$B$43,QQP!$E$8:$E$43) -> 1
B5: A - Mão de Obra + Encargos
B6: Cód. | C6: Discriminação | D6: Unid | E6: P.Unit | F6: Quant | G6: F.utiliz | H6: Custo | I6: Quant | J6: F.utiliz | K6: Custo | L6: Quant | M6: F.utiliz | N6: Custo | O6: Quant | P6: F.utiliz | Q6: Custo | R6: Quant | S6: F.utiliz | T6: Custo | U6: Quant | V6: F.utiliz | W6: Custo | Y6: Quant | Z6: F.utiliz | AA6: Custo
B7: ='CPU 1'!B7 -> P01 | C7: ='CPU 1'!C7 -> Supervisor | D7: ='CPU 1'!D7 -> hh | E7: ='CPU 1'!E7 -> 75.068182 | H7: =G7*F7*$E7 -> 0 | K7: =J7*I7*$E7 -> 0 | N7: =M7*L7*$E7 -> 0 | Q7: =P7*O7*$E7 -> 0 | T7: =S7*R7*$E7 -> 0 | W7: =V7*U7*$E7 -> 0 | AA7: =K7*$K$3+N7*$N$3+Q7*$Q$3+H7*$H$3+T7*$T$3+W7*$W$3 -> 0 | AB7: =AA7/$AA$162 -> #DIV/0!
B8: ='CPU 1'!B8 -> P02 | C8: ='CPU 1'!C8 -> Encarregado | D8: ='CPU 1'!D8 -> hh | E8: ='CPU 1'!E8 -> 40.036364 | H8: =G8*F8*$E8 -> 0 | K8: =J8*I8*$E8 -> 0 | N8: =M8*L8*$E8 -> 0 | Q8: =P8*O8*$E8 -> 0 | T8: =S8*R8*$E8 -> 0 | W8: =V8*U8*$E8 -> 0 | AA8: =K8*$K$3+N8*$N$3+Q8*$Q$3+H8*$H$3+T8*$T$3+W8*$W$3 -> 0 | AB8: =AA8/$AA$162 -> #DIV/0!
B9: ='CPU 1'!B9 -> P03 | C9: ='CPU 1'!C9 -> Técnico SSMA | D9: ='CPU 1'!D9 -> hh | E9: ='CPU 1'!E9 -> 40.036364 | H9: =G9*F9*$E9 -> 0 | K9: =J9*I9*$E9 -> 0 | N9: =M9*L9*$E9 -> 0 | Q9: =P9*O9*$E9 -> 0 | T9: =S9*R9*$E9 -> 0 | W9: =V9*U9*$E9 -> 0 | AA9: =K9*$K$3+N9*$N$3+Q9*$Q$3+H9*$H$3+T9*$T$3+W9*$W$3 -> 0 | AB9: =AA9/$AA$162 -> #DIV/0!
B10: ='CPU 1'!B10 -> P04 | C10: ='CPU 1'!C10 -> Pedreiro | D10: ='CPU 1'!D10 -> hh | E10: ='CPU 1'!E10 -> 19.767955 | H10: =G10*F10*$E10 -> 0 | K10: =J10*I10*$E10 -> 0 | N10: =M10*L10*$E10 -> 0 | Q10: =P10*O10*$E10 -> 0 | T10: =S10*R10*$E10 -> 0 | W10: =V10*U10*$E10 -> 0 | Z10: =AA10/E10/176/3 -> 0 | AA10: =K10*$K$3+N10*$N$3+Q10*$Q$3+H10*$H$3+T10*$T$3+W10*$W$3 -> 0 | AB10: =AA10/$AA$162 -> #DIV/0!
B11: ='CPU 1'!B11 -> P05 | C11: ='CPU 1'!C11 -> Carpinteiro | D11: ='CPU 1'!D11 -> hh | E11: ='CPU 1'!E11 -> 19.767955 | H11: =G11*F11*$E11 -> 0 | K11: =J11*I11*$E11 -> 0 | N11: =M11*L11*$E11 -> 0 | Q11: =P11*O11*$E11 -> 0 | T11: =S11*R11*$E11 -> 0 | W11: =V11*U11*$E11 -> 0 | AA11: =K11*$K$3+N11*$N$3+Q11*$Q$3+H11*$H$3+T11*$T$3+W11*$W$3 -> 0 | AB11: =AA11/$AA$162 -> #DIV/0!
B12: ='CPU 1'!B12 -> P06 | C12: ='CPU 1'!C12 -> Eletricista | D12: ='CPU 1'!D12 -> hh | E12: ='CPU 1'!E12 -> 26.023636 | H12: =G12*F12*$E12 -> 0 | K12: =J12*I12*$E12 -> 0 | N12: =M12*L12*$E12 -> 0 | Q12: =P12*O12*$E12 -> 0 | T12: =S12*R12*$E12 -> 0 | W12: =V12*U12*$E12 -> 0 | AA12: =K12*$K$3+N12*$N$3+Q12*$Q$3+H12*$H$3+T12*$T$3+W12*$W$3 -> 0 | AB12: =AA12/$AA$162 -> #DIV/0!
B13: ='CPU 1'!B13 -> P07 | C13: ='CPU 1'!C13 -> Ajudante | D13: ='CPU 1'!D13 -> hh | E13: ='CPU 1'!E13 -> 13.962682 | H13: =G13*F13*$E13 -> 0 | K13: =J13*I13*$E13 -> 0 | N13: =M13*L13*$E13 -> 0 | Q13: =P13*O13*$E13 -> 0 | T13: =S13*R13*$E13 -> 0 | W13: =V13*U13*$E13 -> 0 | AA13: =K13*$K$3+N13*$N$3+Q13*$Q$3+H13*$H$3+T13*$T$3+W13*$W$3 -> 0 | AB13: =AA13/$AA$162 -> #DIV/0!
B14: ='CPU 1'!B14 -> P08 | C14: ='CPU 1'!C14 -> Armador | D14: ='CPU 1'!D14 -> hh | E14: ='CPU 1'!E14 -> 19.767955 | H14: =G14*F14*$E14 -> 0 | K14: =J14*I14*$E14 -> 0 | N14: =M14*L14*$E14 -> 0 | Q14: =P14*O14*$E14 -> 0 | T14: =S14*R14*$E14 -> 0 | W14: =V14*U14*$E14 -> 0 | AA14: =K14*$K$3+N14*$N$3+Q14*$Q$3+H14*$H$3+T14*$T$3+W14*$W$3 -> 0 | AB14: =AA14/$AA$162 -> #DIV/0!
B15: ='CPU 1'!B15 -> P09 | C15: ='CPU 1'!C15 -> Engenheiro | D15: ='CPU 1'!D15 -> hh | E15: ='CPU 1'!E15 -> 112.302 | H15: =G15*F15*$E15 -> 0 | K15: =J15*I15*$E15 -> 0 | N15: =M15*L15*$E15 -> 0 | Q15: =P15*O15*$E15 -> 0 | T15: =S15*R15*$E15 -> 0 | W15: =V15*U15*$E15 -> 0 | AA15: =K15*$K$3+N15*$N$3+Q15*$Q$3+H15*$H$3+T15*$T$3+W15*$W$3 -> 0 | AB15: =AA15/$AA$162 -> #DIV/0!
B16: ='CPU 1'!B16 -> P10 | C16: ='CPU 1'!C16 -> Planejador | D16: ='CPU 1'!D16 -> hh | E16: ='CPU 1'!E16 -> 60.054545 | H16: =G16*F16*$E16 -> 0 | K16: =J16*I16*$E16 -> 0 | N16: =M16*L16*$E16 -> 0 | Q16: =P16*O16*$E16 -> 0 | T16: =S16*R16*$E16 -> 0 | W16: =V16*U16*$E16 -> 0 | AA16: =K16*$K$3+N16*$N$3+Q16*$Q$3+H16*$H$3+T16*$T$3+W16*$W$3 -> 0 | AB16: =AA16/$AA$162 -> #DIV/0!
B17: ='CPU 1'!B17 -> P11 | C17: ='CPU 1'!C17 -> Tópografo | D17: ='CPU 1'!D17 -> hh | E17: ='CPU 1'!E17 -> 38.034545 | H17: =G17*F17*$E17 -> 0 | K17: =J17*I17*$E17 -> 0 | N17: =M17*L17*$E17 -> 0 | Q17: =P17*O17*$E17 -> 0 | T17: =S17*R17*$E17 -> 0 | W17: =V17*U17*$E17 -> 0 | AA17: =K17*$K$3+N17*$N$3+Q17*$Q$3+H17*$H$3+T17*$T$3+W17*$W$3 -> 0 | AB17: =AA17/$AA$162 -> #DIV/0!
B18: ='CPU 1'!B18 -> P12 | C18: ='CPU 1'!C18 -> Auxiliar de Topografia | D18: ='CPU 1'!D18 -> hh | E18: ='CPU 1'!E18 -> 17.015455 | H18: =G18*F18*$E18 -> 0 | K18: =J18*I18*$E18 -> 0 | N18: =M18*L18*$E18 -> 0 | Q18: =P18*O18*$E18 -> 0 | T18: =S18*R18*$E18 -> 0 | W18: =V18*U18*$E18 -> 0 | AA18: =K18*$K$3+N18*$N$3+Q18*$Q$3+H18*$H$3+T18*$T$3+W18*$W$3 -> 0 | AB18: =AA18/$AA$162 -> #DIV/0!
B19: ='CPU 1'!B19 -> P13 | C19: ='CPU 1'!C19 -> Projetista | D19: ='CPU 1'!D19 -> hh | E19: ='CPU 1'!E19 -> 70.063636 | H19: =G19*F19*$E19 -> 0 | K19: =J19*I19*$E19 -> 0 | N19: =M19*L19*$E19 -> 0 | Q19: =P19*O19*$E19 -> 0 | T19: =S19*R19*$E19 -> 0 | W19: =V19*U19*$E19 -> 0 | AA19: =K19*$K$3+N19*$N$3+Q19*$Q$3+H19*$H$3+T19*$T$3+W19*$W$3 -> 0 | AB19: =AA19/$AA$162 -> #DIV/0!
B20: ='CPU 1'!B20 -> P14 | C20: ='CPU 1'!C20 -> Operador/motorista | D20: ='CPU 1'!D20 -> hh | E20: ='CPU 1'!E20 -> 25.022727 | H20: =G20*F20*$E20 -> 0 | K20: =J20*I20*$E20 -> 0 | N20: =M20*L20*$E20 -> 0 | Q20: =P20*O20*$E20 -> 0 | T20: =S20*R20*$E20 -> 0 | W20: =V20*U20*$E20 -> 0 | AA20: =K20*$K$3+N20*$N$3+Q20*$Q$3+H20*$H$3+T20*$T$3+W20*$W$3 -> 0 | AB20: =AA20/$AA$162 -> #DIV/0!
B21: ='CPU 1'!B21 -> P15 | C21: ='CPU 1'!C21 -> 0 | D21: ='CPU 1'!D21 -> hh | E21: ='CPU 1'!E21 -> 0 | H21: =G21*F21*$E21 -> 0 | K21: =J21*I21*$E21 -> 0 | N21: =M21*L21*$E21 -> 0 | Q21: =P21*O21*$E21 -> 0 | T21: =S21*R21*$E21 -> 0 | W21: =V21*U21*$E21 -> 0 | AA21: =K21*$K$3+N21*$N$3+Q21*$Q$3+H21*$H$3+T21*$T$3+W21*$W$3 -> 0 | AB21: =AA21/$AA$162 -> #DIV/0!
B22: ='CPU 1'!B22 -> P16 | C22: ='CPU 1'!C22 -> 0 | D22: ='CPU 1'!D22 -> hh | E22: ='CPU 1'!E22 -> 0 | H22: =G22*F22*$E22 -> 0 | K22: =J22*I22*$E22 -> 0 | N22: =M22*L22*$E22 -> 0 | Q22: =P22*O22*$E22 -> 0 | T22: =S22*R22*$E22 -> 0 | W22: =V22*U22*$E22 -> 0 | AA22: =K22*$K$3+N22*$N$3+Q22*$Q$3+H22*$H$3+T22*$T$3+W22*$W$3 -> 0 | AB22: =AA22/$AA$162 -> #DIV/0!
B23: A - Custo Total de Mão de Obra: | F23: =SUM(F7:F22) -> 0 | G23: =SUM(G7:G22)*H3 -> 0 | H23: =SUM(H7:H22) -> 0 | I23: =SUM(I7:I22) -> 0 | J23: =SUM(J7:J22)*K3 -> 0 | K23: =SUM(K7:K22) -> 0 | L23: =SUM(L7:L22) -> 0 | M23: =SUM(M7:M22)*N3 -> 0 | N23: =SUM(N7:N22) -> 0 | O23: =SUM(O7:O22) -> 0 | P23: =SUM(P7:P22)*Q3 -> 0 | Q23: =SUM(Q7:Q22) -> 0 | R23: =SUM(R7:R22) -> 0 | S23: =SUM(S7:S22)*T3 -> 0 | T23: =SUM(T7:T22) -> 0 | U23: =SUM(U7:U22) -> 0 | V23: =SUM(V7:V22)*W3 -> 0 | W23: =SUM(W7:W22) -> 0 | Y23: =SUM(Y7:Y22) -> 0 | Z23: =SUM(Z7:Z22) -> 0 | AA23: =SUM(AA7:AA22) -> 0
B24: B – Equipamentos e Ferramentas
B25: Cód. | C25: Discriminação | D25: Unid | E25: P.Unit | F25: Quant | G25: F.utiliz | H25: Custo | I25: Quant | J25: F.utiliz | K25: Custo | L25: Quant | M25: F.utiliz | N25: Custo | O25: Quant | P25: F.utiliz | Q25: Custo | R25: Quant | S25: F.utiliz | T25: Custo | U25: Quant | V25: F.utiliz | W25: Custo | Y25: Quant | Z25: F.utiliz | AA25: Custo
B26: ='CPU 1'!B26 -> E01 | C26: ='CPU 1'!C26 -> Alavanca, picareta, enxada, cavador, pá | D26: ='CPU 1'!D26 -> vb | E26: ='CPU 1'!E26 -> 790 | H26: =G26*F26*$E26 -> 0 | K26: =J26*I26*$E26 -> 0 | N26: =M26*L26*$E26 -> 0 | Q26: =P26*O26*$E26 -> 0 | T26: =S26*R26*$E26 -> 0 | W26: =V26*U26*$E26 -> 0 | AA26: =K26*$K$3+N26*$N$3+Q26*$Q$3+H26*$H$3+T26*$T$3+W26*$W$3 -> 0 | AB26: =AA26/$AA$162 -> #DIV/0!
B27: ='CPU 1'!B27 -> E02 | C27: ='CPU 1'!C27 -> Banheiro hidraulico - locação | D27: ='CPU 1'!D27 -> vb/mês | E27: ='CPU 1'!E27 -> 4000 | H27: =G27*F27*$E27 -> 0 | K27: =J27*I27*$E27 -> 0 | N27: =M27*L27*$E27 -> 0 | Q27: =P27*O27*$E27 -> 0 | T27: =S27*R27*$E27 -> 0 | W27: =V27*U27*$E27 -> 0 | AA27: =K27*$K$3+N27*$N$3+Q27*$Q$3+H27*$H$3+T27*$T$3+W27*$W$3 -> 0 | AB27: =AA27/$AA$162 -> #DIV/0!
B28: ='CPU 1'!B28 -> E03 | C28: ='CPU 1'!C28 -> Barreira física metalica | D28: ='CPU 1'!D28 -> pç | E28: ='CPU 1'!E28 -> 350 | H28: =G28*F28*$E28 -> 0 | K28: =J28*I28*$E28 -> 0 | N28: =M28*L28*$E28 -> 0 | Q28: =P28*O28*$E28 -> 0 | T28: =S28*R28*$E28 -> 0 | W28: =V28*U28*$E28 -> 0 | AA28: =K28*$K$3+N28*$N$3+Q28*$Q$3+H28*$H$3+T28*$T$3+W28*$W$3 -> 0 | AB28: =AA28/$AA$162 -> #DIV/0!
B29: ='CPU 1'!B29 -> E04 | C29: ='CPU 1'!C29 -> Bebedouro 4 torneiras 50L | D29: ='CPU 1'!D29 -> unid | E29: ='CPU 1'!E29 -> 3500 | H29: =G29*F29*$E29 -> 0 | K29: =J29*I29*$E29 -> 0 | N29: =M29*L29*$E29 -> 0 | Q29: =P29*O29*$E29 -> 0 | T29: =S29*R29*$E29 -> 0 | W29: =V29*U29*$E29 -> 0 | AA29: =K29*$K$3+N29*$N$3+Q29*$Q$3+H29*$H$3+T29*$T$3+W29*$W$3 -> 0 | AB29: =AA29/$AA$162 -> #DIV/0!
B30: ='CPU 1'!B30 -> E05 | C30: ='CPU 1'!C30 -> Caçamba de entulho 4m³ | D30: ='CPU 1'!D30 -> Vb/mês | E30: ='CPU 1'!E30 -> 800 | H30: =G30*F30*$E30 -> 0 | K30: =J30*I30*$E30 -> 0 | N30: =M30*L30*$E30 -> 0 | Q30: =P30*O30*$E30 -> 0 | T30: =S30*R30*$E30 -> 0 | W30: =V30*U30*$E30 -> 0 | AA30: =K30*$K$3+N30*$N$3+Q30*$Q$3+H30*$H$3+T30*$T$3+W30*$W$3 -> 0 | AB30: =AA30/$AA$162 -> #DIV/0!
B31: ='CPU 1'!B31 -> E06 | C31: ='CPU 1'!C31 -> Cadinho solda exotermica | D31: ='CPU 1'!D31 -> pç | E31: ='CPU 1'!E31 -> 420 | H31: =G31*F31*$E31 -> 0 | K31: =J31*I31*$E31 -> 0 | N31: =M31*L31*$E31 -> 0 | Q31: =P31*O31*$E31 -> 0 | T31: =S31*R31*$E31 -> 0 | W31: =V31*U31*$E31 -> 0 | AA31: =K31*$K$3+N31*$N$3+Q31*$Q$3+H31*$H$3+T31*$T$3+W31*$W$3 -> 0 | AB31: =AA31/$AA$162 -> #DIV/0!
B32: ='CPU 1'!B32 -> E07 | C32: ='CPU 1'!C32 -> Caixa dágua 1000L | D32: ='CPU 1'!D32 -> pç | E32: ='CPU 1'!E32 -> 480 | H32: =G32*F32*$E32 -> 0 | K32: =J32*I32*$E32 -> 0 | N32: =M32*L32*$E32 -> 0 | Q32: =P32*O32*$E32 -> 0 | T32: =S32*R32*$E32 -> 0 | W32: =V32*U32*$E32 -> 0 | AA32: =K32*$K$3+N32*$N$3+Q32*$Q$3+H32*$H$3+T32*$T$3+W32*$W$3 -> 0 | AB32: =AA32/$AA$162 -> #DIV/0!
B33: ='CPU 1'!B33 -> E08 | C33: ='CPU 1'!C33 -> Caixa dágua 500L | D33: ='CPU 1'!D33 -> pç | E33: ='CPU 1'!E33 -> 250 | H33: =G33*F33*$E33 -> 0 | K33: =J33*I33*$E33 -> 0 | N33: =M33*L33*$E33 -> 0 | Q33: =P33*O33*$E33 -> 0 | T33: =S33*R33*$E33 -> 0 | W33: =V33*U33*$E33 -> 0 | AA33: =K33*$K$3+N33*$N$3+Q33*$Q$3+H33*$H$3+T33*$T$3+W33*$W$3 -> 0 | AB33: =AA33/$AA$162 -> #DIV/0!
B34: ='CPU 1'!B34 -> E09 | C34: ='CPU 1'!C34 -> Caminhão munck | D34: ='CPU 1'!D34 -> vb/mês | E34: ='CPU 1'!E34 -> 40000 | H34: =G34*F34*$E34 -> 0 | K34: =J34*I34*$E34 -> 0 | N34: =M34*L34*$E34 -> 0 | Q34: =P34*O34*$E34 -> 0 | T34: =S34*R34*$E34 -> 0 | W34: =V34*U34*$E34 -> 0 | AA34: =K34*$K$3+N34*$N$3+Q34*$Q$3+H34*$H$3+T34*$T$3+W34*$W$3 -> 0 | AB34: =AA34/$AA$162 -> #DIV/0!
B35: ='CPU 1'!B35 -> E10 | C35: ='CPU 1'!C35 -> Carro de mão | D35: ='CPU 1'!D35 -> pç | E35: ='CPU 1'!E35 -> 450 | H35: =G35*F35*$E35 -> 0 | K35: =J35*I35*$E35 -> 0 | N35: =M35*L35*$E35 -> 0 | Q35: =P35*O35*$E35 -> 0 | T35: =S35*R35*$E35 -> 0 | W35: =V35*U35*$E35 -> 0 | AA35: =K35*$K$3+N35*$N$3+Q35*$Q$3+H35*$H$3+T35*$T$3+W35*$W$3 -> 0 | AB35: =AA35/$AA$162 -> #DIV/0!
B36: ='CPU 1'!B36 -> E11 | C36: ='CPU 1'!C36 -> Carro plataforma | D36: ='CPU 1'!D36 -> pç | E36: ='CPU 1'!E36 -> 1200 | H36: =G36*F36*$E36 -> 0 | K36: =J36*I36*$E36 -> 0 | N36: =M36*L36*$E36 -> 0 | Q36: =P36*O36*$E36 -> 0 | T36: =S36*R36*$E36 -> 0 | W36: =V36*U36*$E36 -> 0 | AA36: =K36*$K$3+N36*$N$3+Q36*$Q$3+H36*$H$3+T36*$T$3+W36*$W$3 -> 0 | AB36: =AA36/$AA$162 -> #DIV/0!
B37: ='CPU 1'!B37 -> E12 | C37: ='CPU 1'!C37 -> Coletor de resíduo com pedal - 50L (V,V,A,A) | D37: ='CPU 1'!D37 -> kit | E37: ='CPU 1'!E37 -> 1200 | H37: =G37*F37*$E37 -> 0 | K37: =J37*I37*$E37 -> 0 | N37: =M37*L37*$E37 -> 0 | Q37: =P37*O37*$E37 -> 0 | T37: =S37*R37*$E37 -> 0 | W37: =V37*U37*$E37 -> 0 | AA37: =K37*$K$3+N37*$N$3+Q37*$Q$3+H37*$H$3+T37*$T$3+W37*$W$3 -> 0 | AB37: =AA37/$AA$162 -> #DIV/0!
... B79: ='CPU 1'!B79 -> E54 | C79: ='CPU 1'!C79 -> 0 | D79: ='CPU 1'!D79 -> 0 | E79: ='CPU 1'!E79 -> 0 | H79: =G79*F79*$E79 -> 0 | K79: =J79*I79*$E79 -> 0 | N79: =M79*L79*$E79 -> 0 | Q79: =P79*O79*$E79 -> 0 | T79: =S79*R79*$E79 -> 0 | W79: =V79*U79*$E79 -> 0 | AA79: =K79*$K$3+N79*$N$3+Q79*$Q$3+H79*$H$3+T79*$T$3+W79*$W$3 -> 0 | AB79: =AA79/$AA$162 -> #DIV/0!
B80: B - Custo Total de Equipamentos e Ferramentas: | E80: =SUM(#REF!) -> #REF! | H80: =SUM(H26:H79) -> 0 | K80: =SUM(K26:K79) -> 0 | N80: =SUM(N26:N79) -> 0 | Q80: =SUM(Q26:Q79) -> 0 | T80: =SUM(T26:T79) -> 0 | W80: =SUM(W26:W79) -> 0 | AA80: =SUM(AA26:AA79) -> 0
B81: C – Materiais
B82: Cód. | C82: Discriminação | D82: Unid | E82: P.Unit | F82: Quant | G82: F.utiliz | H82: Custo | I82: Quant | J82: F.utiliz | K82: Custo | L82: Quant | M82: F.utiliz | N82: Custo | O82: Quant | P82: F.utiliz | Q82: Custo | R82: Quant | S82: F.utiliz | T82: Custo | U82: Quant | V82: F.utiliz | W82: Custo | Y82: Quant | Z82: F.utiliz | AA82: Custo
B83: ='CPU 1'!B83 -> M01 | C83: ='CPU 1'!C83 -> Aço CA-50, (ferro 8.0) | D83: ='CPU 1'!D83 -> kg | E83: ='CPU 1'!E83 -> 12.5 | H83: =G83*F83*$E83 -> 0 | K83: =J83*I83*$E83 -> 0 | N83: =M83*L83*$E83 -> 0 | Q83: =P83*O83*$E83 -> 0 | T83: =S83*R83*$E83 -> 0 | W83: =V83*U83*$E83 -> 0 | AA83: =K83*$K$3+N83*$N$3+Q83*$Q$3+H83*$H$3+T83*$T$3+W83*$W$3 -> 0 | AB83: =AA83/$AA$162 -> #DIV/0!
B84: ='CPU 1'!B84 -> M02 | C84: ='CPU 1'!C84 -> Agua Mineral | D84: ='CPU 1'!D84 -> litro | E84: ='CPU 1'!E84 -> 1 | H84: =G84*F84*$E84 -> 0 | K84: =J84*I84*$E84 -> 0 | N84: =M84*L84*$E84 -> 0 | Q84: =P84*O84*$E84 -> 0 | T84: =S84*R84*$E84 -> 0 | W84: =V84*U84*$E84 -> 0 | AA84: =K84*$K$3+N84*$N$3+Q84*$Q$3+H84*$H$3+T84*$T$3+W84*$W$3 -> 0 | AB84: =AA84/$AA$162 -> #DIV/0!
B85: ='CPU 1'!B85 -> M03 | C85: ='CPU 1'!C85 -> Arame ovalado zincado | D85: ='CPU 1'!D85 -> m | E85: ='CPU 1'!E85 -> 1 | H85: =G85*F85*$E85 -> 0 | K85: =J85*I85*$E85 -> 0 | N85: =M85*L85*$E85 -> 0 | Q85: =P85*O85*$E85 -> 0 | T85: =S85*R85*$E85 -> 0 | W85: =V85*U85*$E85 -> 0 | AA85: =K85*$K$3+N85*$N$3+Q85*$Q$3+H85*$H$3+T85*$T$3+W85*$W$3 -> 0 | AB85: =AA85/$AA$162 -> #DIV/0!
B86: ='CPU 1'!B86 -> M04 | C86: ='CPU 1'!C86 -> Areia | D86: ='CPU 1'!D86 -> m³ | E86: ='CPU 1'!E86 -> 120 | H86: =G86*F86*$E86 -> 0 | K86: =J86*I86*$E86 -> 0 | N86: =M86*L86*$E86 -> 0 | Q86: =P86*O86*$E86 -> 0 | T86: =S86*R86*$E86 -> 0 | W86: =V86*U86*$E86 -> 0 | AA86: =K86*$K$3+N86*$N$3+Q86*$Q$3+H86*$H$3+T86*$T$3+W86*$W$3 -> 0 | AB86: =AA86/$AA$162 -> #DIV/0!
B87: ='CPU 1'!B87 -> M05 | C87: ='CPU 1'!C87 -> Arrame galganizado | D87: ='CPU 1'!D87 -> kg | E87: ='CPU 1'!E87 -> 16.8 | H87: =G87*F87*$E87 -> 0 | K87: =J87*I87*$E87 -> 0 | N87: =M87*L87*$E87 -> 0 | Q87: =P87*O87*$E87 -> 0 | T87: =S87*R87*$E87 -> 0 | W87: =V87*U87*$E87 -> 0 | AA87: =K87*$K$3+N87*$N$3+Q87*$Q$3+H87*$H$3+T87*$T$3+W87*$W$3 -> 0 | AB87: =AA87/$AA$162 -> #DIV/0!
B88: ='CPU 1'!B88 -> M06 | C88: ='CPU 1'!C88 -> Arrame recozido | D88: ='CPU 1'!D88 -> kg | E88: ='CPU 1'!E88 -> 12 | H88: =G88*F88*$E88 -> 0 | K88: =J88*I88*$E88 -> 0 | N88: =M88*L88*$E88 -> 0 | Q88: =P88*O88*$E88 -> 0 | T88: =S88*R88*$E88 -> 0 | W88: =V88*U88*$E88 -> 0 | AA88: =K88*$K$3+N88*$N$3+Q88*$Q$3+H88*$H$3+T88*$T$3+W88*$W$3 -> 0 | AB88: =AA88/$AA$162 -> #DIV/0!
B89: ='CPU 1'!B89 -> M07 | C89: ='CPU 1'!C89 -> Barrote de madeira 7x7cm | D89: ='CPU 1'!D89 -> m | E89: ='CPU 1'!E89 -> 15 | H89: =G89*F89*$E89 -> 0 | K89: =J89*I89*$E89 -> 0 | N89: =M89*L89*$E89 -> 0 | Q89: =P89*O89*$E89 -> 0 | T89: =S89*R89*$E89 -> 0 | W89: =V89*U89*$E89 -> 0 | AA89: =K89*$K$3+N89*$N$3+Q89*$Q$3+H89*$H$3+T89*$T$3+W89*$W$3 -> 0 | AB89: =AA89/$AA$162 -> #DIV/0!
B90: ='CPU 1'!B90 -> M08 | C90: ='CPU 1'!C90 -> Bloco tipo canaleta (14x19x39cm) | D90: ='CPU 1'!D90 -> peça | E90: ='CPU 1'!E90 -> 8.9 | H90: =G90*F90*$E90 -> 0 | K90: =J90*I90*$E90 -> 0 | N90: =M90*L90*$E90 -> 0 | Q90: =P90*O90*$E90 -> 0 | T90: =S90*R90*$E90 -> 0 | W90: =V90*U90*$E90 -> 0 | AA90: =K90*$K$3+N90*$N$3+Q90*$Q$3+H90*$H$3+T90*$T$3+W90*$W$3 -> 0 | AB90: =AA90/$AA$162 -> #DIV/0!
B91: ='CPU 1'!B91 -> M09 | C91: ='CPU 1'!C91 -> Brita 1 | D91: ='CPU 1'!D91 -> m³ | E91: ='CPU 1'!E91 -> 220 | H91: =G91*F91*$E91 -> 0 | K91: =J91*I91*$E91 -> 0 | N91: =M91*L91*$E91 -> 0 | Q91: =P91*O91*$E91 -> 0 | T91: =S91*R91*$E91 -> 0 | W91: =V91*U91*$E91 -> 0 | AA91: =K91*$K$3+N91*$N$3+Q91*$Q$3+H91*$H$3+T91*$T$3+W91*$W$3 -> 0 | AB91: =AA91/$AA$162 -> #DIV/0!
B92: ='CPU 1'!B92 -> M11 | C92: ='CPU 1'!C92 -> Caixa de passagens para aterramento h600 diâmetro 30cm | D92: ='CPU 1'!D92 -> und | E92: ='CPU 1'!E92 -> 590 | H92: =G92*F92*$E92 -> 0 | K92: =J92*I92*$E92 -> 0 | N92: =M92*L92*$E92 -> 0 | Q92: =P92*O92*$E92 -> 0 | T92: =S92*R92*$E92 -> 0 | W92: =V92*U92*$E92 -> 0 | AA92: =K92*$K$3+N92*$N$3+Q92*$Q$3+H92*$H$3+T92*$T$3+W92*$W$3 -> 0 | AB92: =AA92/$AA$162 -> #DIV/0!
B93: ='CPU 1'!B93 -> M12 | C93: ='CPU 1'!C93 -> Catoneira galvanizada 1"x1-1/4 | D93: ='CPU 1'!D93 -> m | E93: ='CPU 1'!E93 -> 25 | H93: =G93*F93*$E93 -> 0 | K93: =J93*I93*$E93 -> 0 | N93: =M93*L93*$E93 -> 0 | Q93: =P93*O93*$E93 -> 0 | T93: =S93*R93*$E93 -> 0 | W93: =V93*U93*$E93 -> 0 | AA93: =K93*$K$3+N93*$N$3+Q93*$Q$3+H93*$H$3+T93*$T$3+W93*$W$3 -> 0 | AB93: =AA93/$AA$162 -> #DIV/0!
B94: ='CPU 1'!B94 -> M13 | C94: ='CPU 1'!C94 -> Cercamento e delimitação de canteiro de obra (15x30m) | D94: ='CPU 1'!D94 -> vb | E94: ='CPU 1'!E94 -> 10000 | H94: =G94*F94*$E94 -> 0 | K94: =J94*I94*$E94 -> 0 | N94: =M94*L94*$E94 -> 0 | Q94: =P94*O94*$E94 -> 0 | T94: =S94*R94*$E94 -> 0 | W94: =V94*U94*$E94 -> 0 | AA94: =K94*$K$3+N94*$N$3+Q94*$Q$3+H94*$H$3+T94*$T$3+W94*$W$3 -> 0 | AB94: =AA94/$AA$162 -> #DIV/0!
... B131: ='CPU 1'!B131 -> M50 | C131: ='CPU 1'!C131 -> 0 | D131: ='CPU 1'!D131 -> 0 | E131: ='CPU 1'!E131 -> 0 | H131: =G131*F131*$E131 -> 0 | K131: =J131*I131*$E131 -> 0 | N131: =M131*L131*$E131 -> 0 | Q131: =P131*O131*$E131 -> 0 | T131: =S131*R131*$E131 -> 0 | W131: =V131*U131*$E131 -> 0 | AA131: =K131*$K$3+N131*$N$3+Q131*$Q$3+H131*$H$3+T131*$T$3+W131*$W$3 -> 0 | AB131: =AA131/$AA$162 -> #DIV/0!
B132: C - Custo Total de Materiais: | E132: =SUM(#REF!) -> #REF! | H132: =SUM(H83:H131) -> 0 | K132: =SUM(K83:K131) -> 0 | N132: =SUM(N83:N131) -> 0 | Q132: =SUM(Q83:Q131) -> 0 | T132: =SUM(T83:T131) -> 0 | W132: =SUM(W83:W131) -> 0 | AA132: =SUM(AA83:AA131) -> 0
B133: D – Outros
B134: Cód. | C134: Discriminação | D134: Unid | E134: P.Unit | F134: Quant | G134: F.utiliz | H134: Custo | I134: Quant | J134: F.utiliz | K134: Custo | L134: Quant | M134: F.utiliz | N134: Custo | O134: Quant | P134: F.utiliz | Q134: Custo | R134: Quant | S134: F.utiliz | T134: Custo | U134: Quant | V134: F.utiliz | W134: Custo | Y134: Quant | Z134: F.utiliz | AA134: Custo
B135: ='CPU 1'!B135 -> O01 | C135: ='CPU 1'!C135 -> ART | D135: ='CPU 1'!D135 -> Vb | E135: ='CPU 1'!E135 -> 1000 | H135: =G135*F135*$E135 -> 0 | K135: =J135*I135*$E135 -> 0 | N135: =M135*L135*$E135 -> 0 | Q135: =P135*O135*$E135 -> 0 | T135: =S135*R135*$E135 -> 0 | W135: =V135*U135*$E135 -> 0 | AA135: =K135*$K$3+N135*$N$3+Q135*$Q$3+H135*$H$3+T135*$T$3+W135*$W$3 -> 0 | AB135: =AA135/$AA$162 -> #DIV/0!
B136: ='CPU 1'!B136 -> O02 | C136: ='CPU 1'!C136 -> Exames medicos | D136: ='CPU 1'!D136 -> Vb | E136: ='CPU 1'!E136 -> 600 | H136: =G136*F136*$E136 -> 0 | K136: =J136*I136*$E136 -> 0 | N136: =M136*L136*$E136 -> 0 | Q136: =P136*O136*$E136 -> 0 | T136: =S136*R136*$E136 -> 0 | W136: =V136*U136*$E136 -> 0 | AA136: =K136*$K$3+N136*$N$3+Q136*$Q$3+H136*$H$3+T136*$T$3+W136*$W$3 -> 0 | AB136: =AA136/$AA$162 -> #DIV/0!
B137: ='CPU 1'!B137 -> O03 | C137: ='CPU 1'!C137 -> Treinamentos | D137: ='CPU 1'!D137 -> Vb | E137: ='CPU 1'!E137 -> 426 | H137: =G137*F137*$E137 -> 0 | K137: =J137*I137*$E137 -> 0 | N137: =M137*L137*$E137 -> 0 | Q137: =P137*O137*$E137 -> 0 | T137: =S137*R137*$E137 -> 0 | W137: =V137*U137*$E137 -> 0 | AA137: =K137*$K$3+N137*$N$3+Q137*$Q$3+H137*$H$3+T137*$T$3+W137*$W$3 -> 0 | AB137: =AA137/$AA$162 -> #DIV/0!
B138: ='CPU 1'!B138 -> O04 | C138: ='CPU 1'!C138 -> Plano de Saude | D138: ='CPU 1'!D138 -> Vb/mês | E138: ='CPU 1'!E138 -> 280 | H138: =G138*F138*$E138 -> 0 | K138: =J138*I138*$E138 -> 0 | N138: =M138*L138*$E138 -> 0 | Q138: =P138*O138*$E138 -> 0 | T138: =S138*R138*$E138 -> 0 | W138: =V138*U138*$E138 -> 0 | AA138: =K138*$K$3+N138*$N$3+Q138*$Q$3+H138*$H$3+T138*$T$3+W138*$W$3 -> 0 | AB138: =AA138/$AA$162 -> #DIV/0!
B139: ='CPU 1'!B139 -> O05 | C139: ='CPU 1'!C139 -> Seguro de Vida | D139: ='CPU 1'!D139 -> Vb/mês | E139: ='CPU 1'!E139 -> 25 | H139: =G139*F139*$E139 -> 0 | K139: =J139*I139*$E139 -> 0 | N139: =M139*L139*$E139 -> 0 | Q139: =P139*O139*$E139 -> 0 | T139: =S139*R139*$E139 -> 0 | W139: =V139*U139*$E139 -> 0 | AA139: =K139*$K$3+N139*$N$3+Q139*$Q$3+H139*$H$3+T139*$T$3+W139*$W$3 -> 0 | AB139: =AA139/$AA$162 -> #DIV/0!
B140: ='CPU 1'!B140 -> O06 | C140: ='CPU 1'!C140 -> Ticket Alimentação | D140: ='CPU 1'!D140 -> Vb/mês | E140: ='CPU 1'!E140 -> 350 | H140: =G140*F140*$E140 -> 0 | K140: =J140*I140*$E140 -> 0 | N140: =M140*L140*$E140 -> 0 | Q140: =P140*O140*$E140 -> 0 | T140: =S140*R140*$E140 -> 0 | W140: =V140*U140*$E140 -> 0 | AA140: =K140*$K$3+N140*$N$3+Q140*$Q$3+H140*$H$3+T140*$T$3+W140*$W$3 -> 0 | AB140: =AA140/$AA$162 -> #DIV/0!
B141: ='CPU 1'!B141 -> O07 | C141: ='CPU 1'!C141 -> PCMSO / PGR / PCA / PPR | D141: ='CPU 1'!D141 -> Vb/ano | E141: ='CPU 1'!E141 -> 2300 | H141: =G141*F141*$E141 -> 0 | K141: =J141*I141*$E141 -> 0 | N141: =M141*L141*$E141 -> 0 | Q141: =P141*O141*$E141 -> 0 | T141: =S141*R141*$E141 -> 0 | W141: =V141*U141*$E141 -> 0 | AA141: =K141*$K$3+N141*$N$3+Q141*$Q$3+H141*$H$3+T141*$T$3+W141*$W$3 -> 0 | AB141: =AA141/$AA$162 -> #DIV/0!
B142: ='CPU 1'!B142 -> O08 | C142: ='CPU 1'!C142 -> Quadros DDS e Gestão a vista | D142: ='CPU 1'!D142 -> Vb | E142: ='CPU 1'!E142 -> 1200 | H142: =G142*F142*$E142 -> 0 | K142: =J142*I142*$E142 -> 0 | N142: =M142*L142*$E142 -> 0 | Q142: =P142*O142*$E142 -> 0 | T142: =S142*R142*$E142 -> 0 | W142: =V142*U142*$E142 -> 0 | AA142: =K142*$K$3+N142*$N$3+Q142*$Q$3+H142*$H$3+T142*$T$3+W142*$W$3 -> 0 | AB142: =AA142/$AA$162 -> #DIV/0!
B143: ='CPU 1'!B143 -> O09 | C143: ='CPU 1'!C143 -> Seguro Obra | D143: ='CPU 1'!D143 -> Vb | E143: ='CPU 1'!E143 -> 5000 | H143: =G143*F143*$E143 -> 0 | K143: =J143*I143*$E143 -> 0 | N143: =M143*L143*$E143 -> 0 | Q143: =P143*O143*$E143 -> 0 | T143: =S143*R143*$E143 -> 0 | W143: =V143*U143*$E143 -> 0 | AA143: =K143*$K$3+N143*$N$3+Q143*$Q$3+H143*$H$3+T143*$T$3+W143*$W$3 -> 0 | AB143: =AA143/$AA$162 -> #DIV/0!
B144: ='CPU 1'!B144 -> O10 | C144: ='CPU 1'!C144 -> Fretes | D144: ='CPU 1'!D144 -> ud | E144: ='CPU 1'!E144 -> 2800 | H144: =G144*F144*$E144 -> 0 | K144: =J144*I144*$E144 -> 0 | N144: =M144*L144*$E144 -> 0 | Q144: =P144*O144*$E144 -> 0 | T144: =S144*R144*$E144 -> 0 | W144: =V144*U144*$E144 -> 0 | AA144: =K144*$K$3+N144*$N$3+Q144*$Q$3+H144*$H$3+T144*$T$3+W144*$W$3 -> 0 | AB144: =AA144/$AA$162 -> #DIV/0!
B145: ='CPU 1'!B145 -> O11 | C145: ='CPU 1'!C145 -> Serviço de descarte de residuo | D145: ='CPU 1'!D145 -> coleta | E145: ='CPU 1'!E145 -> 2000 | H145: =G145*F145*$E145 -> 0 | K145: =J145*I145*$E145 -> 0 | N145: =M145*L145*$E145 -> 0 | Q145: =P145*O145*$E145 -> 0 | T145: =S145*R145*$E145 -> 0 | W145: =V145*U145*$E145 -> 0 | AA145: =K145*$K$3+N145*$N$3+Q145*$Q$3+H145*$H$3+T145*$T$3+W145*$W$3 -> 0 | AB145: =AA145/$AA$162 -> #DIV/0!
B146: ='CPU 1'!B146 -> O12 | C146: ='CPU 1'!C146 -> Serviço de movimentação do Banheiro Hidráulico | D146: ='CPU 1'!D146 -> vb | E146: ='CPU 1'!E146 -> 200 | H146: =G146*F146*$E146 -> 0 | K146: =J146*I146*$E146 -> 0 | N146: =M146*L146*$E146 -> 0 | Q146: =P146*O146*$E146 -> 0 | T146: =S146*R146*$E146 -> 0 | W146: =V146*U146*$E146 -> 0 | AA146: =K146*$K$3+N146*$N$3+Q146*$Q$3+H146*$H$3+T146*$T$3+W146*$W$3 -> 0 | AB146: =AA146/$AA$162 -> #DIV/0!
... B154: ='CPU 1'!B154 -> O20 | C154: ='CPU 1'!C154 -> 0 | D154: ='CPU 1'!D154 -> 0 | E154: ='CPU 1'!E154 -> 0 | H154: =G154*F154*$E154 -> 0 | K154: =J154*I154*$E154 -> 0 | N154: =M154*L154*$E154 -> 0 | Q154: =P154*O154*$E154 -> 0 | T154: =S154*R154*$E154 -> 0 | W154: =V154*U154*$E154 -> 0 | AA154: =K154*$K$3+N154*$N$3+Q154*$Q$3+H154*$H$3+T154*$T$3+W154*$W$3 -> 0 | AB154: =AA154/$AA$162 -> #DIV/0!
B155: D - Custo Total de Outros: | E155: =SUM(#REF!) -> #REF! | H155: =SUM(H135:H154) -> 0 | K155: =SUM(K135:K154) -> 0 | N155: =SUM(N135:N154) -> 0 | Q155: =SUM(Q135:Q154) -> 0 | T155: =SUM(T135:T154) -> 0 | W155: =SUM(W135:W154) -> 0 | AA155: =SUM(AA135:AA154) -> 0
B157: Item | C157: CUSTOS | G157: % | H157: $ | J157: % | K157: $ | M157: % | N157: $ | P157: % | Q157: $ | S157: % | T157: $ | V157: % | W157: $ | Z157: % | AA157: $
B158: A | C158: Mão de Obra | G158: =H158/H162 -> #DIV/0! | H158: =H23 -> 0 | J158: =K158/K162 -> #DIV/0! | K158: =K23 -> 0 | M158: =N158/N162 -> #DIV/0! | N158: =N23 -> 0 | P158: =Q158/Q162 -> #DIV/0! | Q158: =Q23 -> 0 | S158: =T158/T162 -> #DIV/0! | T158: =T23 -> 0 | V158: =W158/W162 -> #DIV/0! | W158: =W23 -> 0 | Z158: =AA158/AA162 -> #DIV/0! | AA158: =AA23 -> 0
B159: B | C159: Equipamentos | G159: =H159/H162 -> #DIV/0! | H159: =H80 -> 0 | J159: =K159/K162 -> #DIV/0! | K159: =K80 -> 0 | M159: =N159/N162 -> #DIV/0! | N159: =N80 -> 0 | P159: =Q159/Q162 -> #DIV/0! | Q159: =Q80 -> 0 | S159: =T159/T162 -> #DIV/0! | T159: =T80 -> 0 | V159: =W159/W162 -> #DIV/0! | W159: =W80 -> 0 | Z159: =AA159/AA162 -> #DIV/0! | AA159: =AA80 -> 0
B160: C | C160: Materiais | G160: =H160/H162 -> #DIV/0! | H160: =H132 -> 0 | J160: =K160/K162 -> #DIV/0! | K160: =K132 -> 0 | M160: =N160/N162 -> #DIV/0! | N160: =N132 -> 0 | P160: =Q160/Q162 -> #DIV/0! | Q160: =Q132 -> 0 | S160: =T160/T162 -> #DIV/0! | T160: =T132 -> 0 | V160: =W160/W162 -> #DIV/0! | W160: =W132 -> 0 | Z160: =AA160/AA162 -> #DIV/0! | AA160: =AA132 -> 0
B161: D | C161: Outros | G161: =H161/H162 -> #DIV/0! | H161: =H155 -> 0 | J161: =K161/K162 -> #DIV/0! | K161: =K155 -> 0 | M161: =N161/N162 -> #DIV/0! | N161: =N155 -> 0 | P161: =Q161/Q162 -> #DIV/0! | Q161: =Q155 -> 0 | S161: =T161/T162 -> #DIV/0! | T161: =T155 -> 0 | V161: =W161/W162 -> #DIV/0! | W161: =W155 -> 0 | Z161: =AA161/AA162 -> #DIV/0! | AA161: =AA155 -> 0
C162: Subtotal: | E162: =SUM(E158:E161) -> 0 | G162: =SUM(G158:G161) -> #DIV/0! | H162: =SUM(H158:H161) -> 0 | J162: =SUM(J158:J161) -> #DIV/0! | K162: =SUM(K158:K161) -> 0 | M162: =SUM(M158:M161) -> #DIV/0! | N162: =SUM(N158:N161) -> 0 | P162: =SUM(P158:P161) -> #DIV/0! | Q162: =SUM(Q158:Q161) -> 0 | S162: =SUM(S158:S161) -> #DIV/0! | T162: =SUM(T158:T161) -> 0 | V162: =SUM(V158:V161) -> #DIV/0! | W162: =SUM(W158:W161) -> 0 | Z162: =SUM(Z158:Z161) -> #DIV/0! | AA162: =SUM(AA158:AA161) -> 0
B164: Item | C164: BDI | E164: Taxa | H164: $ | K164: $ | N164: $ | Q164: $ | T164: $ | W164: $ | AA164: $
B165: 1 | C165: Administração Local | E165: ='BDI-TRIBUTOS'!D8 -> 0.09 | H165: =H162*$E$165 -> 0 | K165: =K162*$E$165 -> 0 | N165: =N162*$E$165 -> 0 | Q165: =Q162*$E$165 -> 0 | T165: =T162*$E$165 -> 0 | W165: =W162*$E$165 -> 0 | AA165: =AA162*$E$165 -> 0
B166: 2 | C166: Administração Central | E166: ='BDI-TRIBUTOS'!D6 -> 0.06 | H166: =H162*$E$166 -> 0 | K166: =K162*$E$166 -> 0 | N166: =N162*$E$166 -> 0 | Q166: =Q162*$E$166 -> 0 | T166: =T162*$E$166 -> 0 | W166: =W162*$E$166 -> 0 | AA166: =AA162*$E$166 -> 0
B167: 3 | C167: Custo financ. capital giro | E167: ='BDI-TRIBUTOS'!D10 -> 0.035 | H167: =H162*$E$167 -> 0 | K167: =K162*$E$167 -> 0 | N167: =N162*$E$167 -> 0 | Q167: =Q162*$E$167 -> 0 | T167: =T162*$E$167 -> 0 | W167: =W162*$E$167 -> 0 | AA167: =AA162*$E$167 -> 0
B168: 4 | C168: Risco do empreendimento | E168: ='BDI-TRIBUTOS'!D12 -> 0.02 | H168: =H162*$E$168 -> 0 | K168: =K162*$E$168 -> 0 | N168: =N162*$E$168 -> 0 | Q168: =Q162*$E$168 -> 0 | T168: =T162*$E$168 -> 0 | W168: =W162*$E$168 -> 0 | AA168: =AA162*$E$168 -> 0
B169: 5 | C169: Outros | E169: ='BDI-TRIBUTOS'!D14 -> 0.01 | H169: =H162*$E$169 -> 0 | K169: =K162*$E$169 -> 0 | N169: =N162*$E$169 -> 0 | Q169: =Q162*$E$169 -> 0 | T169: =T162*$E$169 -> 0 | W169: =W162*$E$169 -> 0 | AA169: =AA162*$E$169 -> 0
B170: 6 | C170: Lucro | E170: ='BDI-TRIBUTOS'!D4 -> 0.1 | H170: =H182*$E$170 -> 0 | K170: =K182*$E$170 -> 0 | N170: =N182*$E$170 -> 0 | Q170: =Q182*$E$170 -> 0 | T170: =T182*$E$170 -> 0 | W170: =W182*$E$170 -> 0 | AA170: =AA182*$E$170 -> 0
C171: Subtotal: | E171: =SUM(E165:E170) -> 0.315 | G171: =SUM(H165:H169)+H162 -> 0 | H171: =SUM(H165:H170) -> 0 | J171: =SUM(K165:K169)+K162 -> 0 | K171: =SUM(K165:K170) -> 0 | M171: =SUM(N165:N169)+N162 -> 0 | N171: =SUM(N165:N170) -> 0 | P171: =SUM(Q165:Q169)+Q162 -> 0 | Q171: =SUM(Q165:Q170) -> 0 | S171: =SUM(T165:T169)+T162 -> 0 | T171: =SUM(T165:T170) -> 0 | V171: =SUM(W165:W169)+W162 -> 0 | W171: =SUM(W165:W170) -> 0 | Z171: =SUM(AA165:AA169)+AA162 -> 0 | AA171: =SUM(AA165:AA170) -> 0
F172: =H171/H162 -> #DIV/0! | I172: =K171/K162 -> #DIV/0! | L172: =N171/N162 -> #DIV/0! | O172: =Q171/Q162 -> #DIV/0! | R172: =T171/T162 -> #DIV/0! | U172: =W171/W162 -> #DIV/0! | Y172: =AA171/AA162 -> #DIV/0!
B173: Item | C173: TRIBUTOS | E173: Taxa | H173: $ | K173: $ | N173: $ | Q173: $ | T173: $ | W173: $ | AA173: $
B174: 1 | C174: ISS | E174: ='BDI-TRIBUTOS'!D20 -> 0.05 | H174: =H$182*$E174 -> 0 | K174: =K$182*$E174 -> 0 | N174: =N$182*$E174 -> 0 | Q174: =Q$182*$E174 -> 0 | T174: =T$182*$E174 -> 0 | W174: =W$182*$E174 -> 0 | AA174: =$AA$182*E174 -> 0
B175: 2 | C175: COFINS | E175: ='BDI-TRIBUTOS'!D21 -> 0.03 | H175: =H$182*$E175 -> 0 | K175: =K$182*$E175 -> 0 | N175: =N$182*$E175 -> 0 | Q175: =Q$182*$E175 -> 0 | T175: =T$182*$E175 -> 0 | W175: =W$182*$E175 -> 0 | AA175: =$AA$182*E175 -> 0
B176: 3 | C176: PIS | E176: ='BDI-TRIBUTOS'!D22 -> 0.0065 | H176: =H$182*$E176 -> 0 | K176: =K$182*$E176 -> 0 | N176: =N$182*$E176 -> 0 | Q176: =Q$182*$E176 -> 0 | T176: =T$182*$E176 -> 0 | W176: =W$182*$E176 -> 0 | AA176: =$AA$182*E176 -> 0
B177: 4 | C177: CSLL | E177: ='BDI-TRIBUTOS'!D23 -> 0.0288 | H177: =H$182*$E177 -> 0 | K177: =K$182*$E177 -> 0 | N177: =N$182*$E177 -> 0 | Q177: =Q$182*$E177 -> 0 | T177: =T$182*$E177 -> 0 | W177: =W$182*$E177 -> 0 | AA177: =$AA$182*E177 -> 0
B178: 5 | C178: IRPJ | E178: ='BDI-TRIBUTOS'!D24 -> 0.048 | H178: =H$182*$E178 -> 0 | K178: =K$182*$E178 -> 0 | N178: =N$182*$E178 -> 0 | Q178: =Q$182*$E178 -> 0 | T178: =T$182*$E178 -> 0 | W178: =W$182*$E178 -> 0 | AA178: =$AA$182*E178 -> 0
B179: 6 | C179: IRPJ Adicional 10% | E179: ='BDI-TRIBUTOS'!D25 -> 0.0318 | H179: =H$182*$E179 -> 0 | K179: =K$182*$E179 -> 0 | N179: =N$182*$E179 -> 0 | Q179: =Q$182*$E179 -> 0 | T179: =T$182*$E179 -> 0 | W179: =W$182*$E179 -> 0 | AA179: =$AA$182*E179 -> 0
B180: 7 | C180: Simples Nacional | E180: ='BDI-TRIBUTOS'!D26 -> 0
C181: Subtotal | E181: =SUM(E174:E180) -> 0.1951 | H181: =H182*$E$181 -> 0 | K181: =K182*$E$181 -> 0 | N181: =N182*$E$181 -> 0 | Q181: =Q182*$E$181 -> 0 | T181: =T182*$E$181 -> 0 | W181: =W182*$E$181 -> 0 | AA181: =AA182*$E$181 -> 0
C182: PREÇO | F182: =ROUND(H182,2) -> 0 | H182: =G171/(1-$E$181-$E$170) -> 0 | I182: =ROUND(K182,2) -> 0 | K182: =J171/(1-$E$181-$E$170) -> 0 | L182: =ROUND(N182,2) -> 0 | N182: =M171/(1-$E$181-$E$170) -> 0 | O182: =ROUND(Q182,2) -> 0 | Q182: =P171/(1-$E$181-$E$170) -> 0 | R182: =ROUND(T182,2) -> 0 | T182: =S171/(1-$E$181-$E$170) -> 0 | U182: =ROUND(W182,2) -> 0 | W182: =V171/(1-$E$181-$E$170) -> 0 | AA182: =Z171/(1-$E$181-$E$170) -> 0
H183: =H182/H162 -> #DIV/0! | K183: =K182/K162 -> #DIV/0! | N183: =N182/N162 -> #DIV/0! | Q183: =Q182/Q162 -> #DIV/0! | T183: =T182/T162 -> #DIV/0! | W183: =W182/W162 -> #DIV/0! | AA183: =AA182/AA162 -> #DIV/0!

Sheet CPU  5
B1: =QQP!G44 -> 0 | D1: CPU | E1: 5 | F1: =QQP!B37 -> 2.6.1 | G1: =H182 -> 0 | I1: =QQP!B39 -> 2.7.1 | J1: =K182 -> 0 | L1: =QQP!B41 -> 2.8.1 | M1: =N182 -> 0 | O1: =QQP!B43 -> 2.9.1 | P1: =Q182 -> 0
B2: Composição de Preços Unitários | F2: =_xlfn.XLOOKUP(F1,QQP!$B$8:$B$43,QQP!$C$8:$C$43) -> XXXXXXXXXXXXXXXXXXXXXXXXXXXXXXXXXXXXXXXXXX | I2: =_xlfn.XLOOKUP(I1,QQP!$B$8:$B$43,QQP!$C$8:$C$43) -> XXXXXXXXXXXXXXXXXXXXXXXXXXXXXXXXXXXXXXXXXX | L2: =_xlfn.XLOOKUP(L1,QQP!$B$8:$B$43,QQP!$C$8:$C$43) -> XXXXXXXXXXXXXXXXXXXXXXXXXXXXXXXXXXXXXXXXXX | O2: =_xlfn.XLOOKUP(O1,QQP!$B$8:$B$43,QQP!$C$8:$C$43) -> XXXXXXXXXXXXXXXXXXXXXXXXXXXXXXXXXXXXXXXXXX | S2: CHECK
G3: =_xlfn.XLOOKUP(F1,QQP!$B$8:$B$43,QQP!$D$8:$D$43) -> xx | H3: =_xlfn.XLOOKUP(F1,QQP!$B$8:$B$43,QQP!$E$8:$E$43) -> 1 | J3: =_xlfn.XLOOKUP(I1,QQP!$B$8:$B$43,QQP!$D$8:$D$43) -> xx | K3: =_xlfn.XLOOKUP(I1,QQP!$B$8:$B$43,QQP!$E$8:$E$43) -> 1 | M3: =_xlfn.XLOOKUP(L1,QQP!$B$8:$B$43,QQP!$D$8:$D$43) -> xx | N3: =_xlfn.XLOOKUP(L1,QQP!$B$8:$B$43,QQP!$E$8:$E$43) -> 1 | P3: =_xlfn.XLOOKUP(O1,QQP!$B$8:$B$43,QQP!$D$8:$D$43) -> xx | Q3: =_xlfn.XLOOKUP(O1,QQP!$B$8:$B$43,QQP!$E$8:$E$43) -> 1
B5: A - Mão de Obra + Encargos
B6: Cód. | C6: Discriminação | D6: Unid | E6: P.Unit | F6: Quant | G6: F.utiliz | H6: Custo | I6: Quant | J6: F.utiliz | K6: Custo | L6: Quant | M6: F.utiliz | N6: Custo | O6: Quant | P6: F.utiliz | Q6: Custo | S6: Quant | T6: F.utiliz | U6: Custo
B7: ='CPU 1'!B7 -> P01 | C7: ='CPU 1'!C7 -> Supervisor | D7: ='CPU 1'!D7 -> hh | E7: ='CPU 1'!E7 -> 75.068182 | H7: =G7*F7*$E7 -> 0 | K7: =J7*I7*$E7 -> 0 | N7: =M7*L7*$E7 -> 0 | Q7: =P7*O7*$E7 -> 0 | U7: =H7*$H$3+K7*$K$3+N7*$N$3+Q7*$Q$3 -> 0 | V7: =U7/$U$162 -> #DIV/0!
B8: ='CPU 1'!B8 -> P02 | C8: ='CPU 1'!C8 -> Encarregado | D8: ='CPU 1'!D8 -> hh | E8: ='CPU 1'!E8 -> 40.036364 | H8: =G8*F8*$E8 -> 0 | K8: =J8*I8*$E8 -> 0 | N8: =M8*L8*$E8 -> 0 | Q8: =P8*O8*$E8 -> 0 | U8: =H8*$H$3+K8*$K$3+N8*$N$3+Q8*$Q$3 -> 0 | V8: =U8/$U$162 -> #DIV/0!
B9: ='CPU 1'!B9 -> P03 | C9: ='CPU 1'!C9 -> Técnico SSMA | D9: ='CPU 1'!D9 -> hh | E9: ='CPU 1'!E9 -> 40.036364 | H9: =G9*F9*$E9 -> 0 | K9: =J9*I9*$E9 -> 0 | N9: =M9*L9*$E9 -> 0 | Q9: =P9*O9*$E9 -> 0 | U9: =H9*$H$3+K9*$K$3+N9*$N$3+Q9*$Q$3 -> 0 | V9: =U9/$U$162 -> #DIV/0!
B10: ='CPU 1'!B10 -> P04 | C10: ='CPU 1'!C10 -> Pedreiro | D10: ='CPU 1'!D10 -> hh | E10: ='CPU 1'!E10 -> 19.767955 | H10: =G10*F10*$E10 -> 0 | K10: =J10*I10*$E10 -> 0 | N10: =M10*L10*$E10 -> 0 | Q10: =P10*O10*$E10 -> 0 | U10: =H10*$H$3+K10*$K$3+N10*$N$3+Q10*$Q$3 -> 0 | V10: =U10/$U$162 -> #DIV/0!
B11: ='CPU 1'!B11 -> P05 | C11: ='CPU 1'!C11 -> Carpinteiro | D11: ='CPU 1'!D11 -> hh | E11: ='CPU 1'!E11 -> 19.767955 | H11: =G11*F11*$E11 -> 0 | K11: =J11*I11*$E11 -> 0 | N11: =M11*L11*$E11 -> 0 | Q11: =P11*O11*$E11 -> 0 | U11: =H11*$H$3+K11*$K$3+N11*$N$3+Q11*$Q$3 -> 0 | V11: =U11/$U$162 -> #DIV/0!
B12: ='CPU 1'!B12 -> P06 | C12: ='CPU 1'!C12 -> Eletricista | D12: ='CPU 1'!D12 -> hh | E12: ='CPU 1'!E12 -> 26.023636 | H12: =G12*F12*$E12 -> 0 | K12: =J12*I12*$E12 -> 0 | N12: =M12*L12*$E12 -> 0 | Q12: =P12*O12*$E12 -> 0 | U12: =H12*$H$3+K12*$K$3+N12*$N$3+Q12*$Q$3 -> 0 | V12: =U12/$U$162 -> #DIV/0!
B13: ='CPU 1'!B13 -> P07 | C13: ='CPU 1'!C13 -> Ajudante | D13: ='CPU 1'!D13 -> hh | E13: ='CPU 1'!E13 -> 13.962682 | H13: =G13*F13*$E13 -> 0 | K13: =J13*I13*$E13 -> 0 | N13: =M13*L13*$E13 -> 0 | Q13: =P13*O13*$E13 -> 0 | U13: =H13*$H$3+K13*$K$3+N13*$N$3+Q13*$Q$3 -> 0 | V13: =U13/$U$162 -> #DIV/0!
B14: ='CPU 1'!B14 -> P08 | C14: ='CPU 1'!C14 -> Armador | D14: ='CPU 1'!D14 -> hh | E14: ='CPU 1'!E14 -> 19.767955 | H14: =G14*F14*$E14 -> 0 | K14: =J14*I14*$E14 -> 0 | N14: =M14*L14*$E14 -> 0 | Q14: =P14*O14*$E14 -> 0 | U14: =H14*$H$3+K14*$K$3+N14*$N$3+Q14*$Q$3 -> 0 | V14: =U14/$U$162 -> #DIV/0!
B15: ='CPU 1'!B15 -> P09 | C15: ='CPU 1'!C15 -> Engenheiro | D15: ='CPU 1'!D15 -> hh | E15: ='CPU 1'!E15 -> 112.302 | H15: =G15*F15*$E15 -> 0 | K15: =J15*I15*$E15 -> 0 | N15: =M15*L15*$E15 -> 0 | Q15: =P15*O15*$E15 -> 0 | U15: =H15*$H$3+K15*$K$3+N15*$N$3+Q15*$Q$3 -> 0 | V15: =U15/$U$162 -> #DIV/0!
B16: ='CPU 1'!B16 -> P10 | C16: ='CPU 1'!C16 -> Planejador | D16: ='CPU 1'!D16 -> hh | E16: ='CPU 1'!E16 -> 60.054545 | H16: =G16*F16*$E16 -> 0 | K16: =J16*I16*$E16 -> 0 | N16: =M16*L16*$E16 -> 0 | Q16: =P16*O16*$E16 -> 0 | U16: =H16*$H$3+K16*$K$3+N16*$N$3+Q16*$Q$3 -> 0 | V16: =U16/$U$162 -> #DIV/0!
B17: ='CPU 1'!B17 -> P11 | C17: ='CPU 1'!C17 -> Tópografo | D17: ='CPU 1'!D17 -> hh | E17: ='CPU 1'!E17 -> 38.034545 | H17: =G17*F17*$E17 -> 0 | K17: =J17*I17*$E17 -> 0 | N17: =M17*L17*$E17 -> 0 | Q17: =P17*O17*$E17 -> 0 | U17: =H17*$H$3+K17*$K$3+N17*$N$3+Q17*$Q$3 -> 0 | V17: =U17/$U$162 -> #DIV/0!
B18: ='CPU 1'!B18 -> P12 | C18: ='CPU 1'!C18 -> Auxiliar de Topografia | D18: ='CPU 1'!D18 -> hh | E18: ='CPU 1'!E18 -> 17.015455 | H18: =G18*F18*$E18 -> 0 | K18: =J18*I18*$E18 -> 0 | N18: =M18*L18*$E18 -> 0 | Q18: =P18*O18*$E18 -> 0 | U18: =H18*$H$3+K18*$K$3+N18*$N$3+Q18*$Q$3 -> 0 | V18: =U18/$U$162 -> #DIV/0!
... B22: ='CPU 1'!B22 -> P16 | C22: ='CPU 1'!C22 -> 0 | D22: ='CPU 1'!D22 -> hh | E22: ='CPU 1'!E22 -> 0 | H22: =G22*F22*$E22 -> 0 | K22: =J22*I22*$E22 -> 0 | N22: =M22*L22*$E22 -> 0 | Q22: =P22*O22*$E22 -> 0 | U22: =H22*$H$3+K22*$K$3+N22*$N$3+Q22*$Q$3 -> 0 | V22: =U22/$U$162 -> #DIV/0!
B23: A - Custo Total de Mão de Obra: | F23: =SUM(F7:F22) -> 0 | G23: =SUM(G7:G22)*H3 -> 0 | H23: =SUM(H7:H22) -> 0 | I23: =SUM(I7:I22) -> 0 | J23: =SUM(J7:J22)*K3 -> 0 | K23: =SUM(K7:K22) -> 0 | L23: =SUM(L7:L22) -> 0 | M23: =SUM(M7:M22)*N3 -> 0 | N23: =SUM(N7:N22) -> 0 | O23: =SUM(O7:O22) -> 0 | P23: =SUM(P7:P22)*Q3 -> 0 | Q23: =SUM(Q7:Q22) -> 0 | S23: =SUM(S7:S22) -> 0 | T23: =SUM(T7:T22) -> 0 | U23: =SUM(U7:U22) -> 0
B24: B – Equipamentos e Ferramentas
B25: Cód. | C25: Discriminação | D25: Unid | E25: P.Unit | F25: Quant | G25: F.utiliz | H25: Custo | I25: Quant | J25: F.utiliz | K25: Custo | L25: Quant | M25: F.utiliz | N25: Custo | O25: Quant | P25: F.utiliz | Q25: Custo | S25: Quant | T25: F.utiliz | U25: Custo
B26: ='CPU 1'!B26 -> E01 | C26: ='CPU 1'!C26 -> Alavanca, picareta, enxada, cavador, pá | D26: ='CPU 1'!D26 -> vb | E26: ='CPU 1'!E26 -> 790 | H26: =G26*F26*$E26 -> 0 | K26: =J26*I26*$E26 -> 0 | N26: =M26*L26*$E26 -> 0 | Q26: =P26*O26*$E26 -> 0 | U26: =H26*$H$3+K26*$K$3+N26*$N$3+Q26*$Q$3 -> 0 | V26: =U26/$U$162 -> #DIV/0!
B27: ='CPU 1'!B27 -> E02 | C27: ='CPU 1'!C27 -> Banheiro hidraulico - locação | D27: ='CPU 1'!D27 -> vb/mês | E27: ='CPU 1'!E27 -> 4000 | H27: =G27*F27*$E27 -> 0 | K27: =J27*I27*$E27 -> 0 | N27: =M27*L27*$E27 -> 0 | Q27: =P27*O27*$E27 -> 0 | U27: =H27*$H$3+K27*$K$3+N27*$N$3+Q27*$Q$3 -> 0 | V27: =U27/$U$162 -> #DIV/0!
B28: ='CPU 1'!B28 -> E03 | C28: ='CPU 1'!C28 -> Barreira física metalica | D28: ='CPU 1'!D28 -> pç | E28: ='CPU 1'!E28 -> 350 | H28: =G28*F28*$E28 -> 0 | K28: =J28*I28*$E28 -> 0 | N28: =M28*L28*$E28 -> 0 | Q28: =P28*O28*$E28 -> 0 | U28: =H28*$H$3+K28*$K$3+N28*$N$3+Q28*$Q$3 -> 0 | V28: =U28/$U$162 -> #DIV/0!
B29: ='CPU 1'!B29 -> E04 | C29: ='CPU 1'!C29 -> Bebedouro 4 torneiras 50L | D29: ='CPU 1'!D29 -> unid | E29: ='CPU 1'!E29 -> 3500 | H29: =G29*F29*$E29 -> 0 | K29: =J29*I29*$E29 -> 0 | N29: =M29*L29*$E29 -> 0 | Q29: =P29*O29*$E29 -> 0 | U29: =H29*$H$3+K29*$K$3+N29*$N$3+Q29*$Q$3 -> 0 | V29: =U29/$U$162 -> #DIV/0!
B30: ='CPU 1'!B30 -> E05 | C30: ='CPU 1'!C30 -> Caçamba de entulho 4m³ | D30: ='CPU 1'!D30 -> Vb/mês | E30: ='CPU 1'!E30 -> 800 | H30: =G30*F30*$E30 -> 0 | K30: =J30*I30*$E30 -> 0 | N30: =M30*L30*$E30 -> 0 | Q30: =P30*O30*$E30 -> 0 | U30: =H30*$H$3+K30*$K$3+N30*$N$3+Q30*$Q$3 -> 0 | V30: =U30/$U$162 -> #DIV/0!
B31: ='CPU 1'!B31 -> E06 | C31: ='CPU 1'!C31 -> Cadinho solda exotermica | D31: ='CPU 1'!D31 -> pç | E31: ='CPU 1'!E31 -> 420 | H31: =G31*F31*$E31 -> 0 | K31: =J31*I31*$E31 -> 0 | N31: =M31*L31*$E31 -> 0 | Q31: =P31*O31*$E31 -> 0 | U31: =H31*$H$3+K31*$K$3+N31*$N$3+Q31*$Q$3 -> 0 | V31: =U31/$U$162 -> #DIV/0!
B32: ='CPU 1'!B32 -> E07 | C32: ='CPU 1'!C32 -> Caixa dágua 1000L | D32: ='CPU 1'!D32 -> pç | E32: ='CPU 1'!E32 -> 480 | H32: =G32*F32*$E32 -> 0 | K32: =J32*I32*$E32 -> 0 | N32: =M32*L32*$E32 -> 0 | Q32: =P32*O32*$E32 -> 0 | U32: =H32*$H$3+K32*$K$3+N32*$N$3+Q32*$Q$3 -> 0 | V32: =U32/$U$162 -> #DIV/0!
B33: ='CPU 1'!B33 -> E08 | C33: ='CPU 1'!C33 -> Caixa dágua 500L | D33: ='CPU 1'!D33 -> pç | E33: ='CPU 1'!E33 -> 250 | H33: =G33*F33*$E33 -> 0 | K33: =J33*I33*$E33 -> 0 | N33: =M33*L33*$E33 -> 0 | Q33: =P33*O33*$E33 -> 0 | U33: =H33*$H$3+K33*$K$3+N33*$N$3+Q33*$Q$3 -> 0 | V33: =U33/$U$162 -> #DIV/0!
B34: ='CPU 1'!B34 -> E09 | C34: ='CPU 1'!C34 -> Caminhão munck | D34: ='CPU 1'!D34 -> vb/mês | E34: ='CPU 1'!E34 -> 40000 | H34: =G34*F34*$E34 -> 0 | K34: =J34*I34*$E34 -> 0 | N34: =M34*L34*$E34 -> 0 | Q34: =P34*O34*$E34 -> 0 | U34: =H34*$H$3+K34*$K$3+N34*$N$3+Q34*$Q$3 -> 0 | V34: =U34/$U$162 -> #DIV/0!
B35: ='CPU 1'!B35 -> E10 | C35: ='CPU 1'!C35 -> Carro de mão | D35: ='CPU 1'!D35 -> pç | E35: ='CPU 1'!E35 -> 450 | H35: =G35*F35*$E35 -> 0 | K35: =J35*I35*$E35 -> 0 | N35: =M35*L35*$E35 -> 0 | Q35: =P35*O35*$E35 -> 0 | U35: =H35*$H$3+K35*$K$3+N35*$N$3+Q35*$Q$3 -> 0 | V35: =U35/$U$162 -> #DIV/0!
B36: ='CPU 1'!B36 -> E11 | C36: ='CPU 1'!C36 -> Carro plataforma | D36: ='CPU 1'!D36 -> pç | E36: ='CPU 1'!E36 -> 1200 | H36: =G36*F36*$E36 -> 0 | K36: =J36*I36*$E36 -> 0 | N36: =M36*L36*$E36 -> 0 | Q36: =P36*O36*$E36 -> 0 | U36: =H36*$H$3+K36*$K$3+N36*$N$3+Q36*$Q$3 -> 0 | V36: =U36/$U$162 -> #DIV/0!
B37: ='CPU 1'!B37 -> E12 | C37: ='CPU 1'!C37 -> Coletor de resíduo com pedal - 50L (V,V,A,A) | D37: ='CPU 1'!D37 -> kit | E37: ='CPU 1'!E37 -> 1200 | H37: =G37*F37*$E37 -> 0 | K37: =J37*I37*$E37 -> 0 | N37: =M37*L37*$E37 -> 0 | Q37: =P37*O37*$E37 -> 0 | U37: =H37*$H$3+K37*$K$3+N37*$N$3+Q37*$Q$3 -> 0 | V37: =U37/$U$162 -> #DIV/0!
... B79: ='CPU 1'!B79 -> E54 | C79: ='CPU 1'!C79 -> 0 | D79: ='CPU 1'!D79 -> 0 | E79: ='CPU 1'!E79 -> 0 | H79: =G79*F79*$E79 -> 0 | K79: =J79*I79*$E79 -> 0 | N79: =M79*L79*$E79 -> 0 | Q79: =P79*O79*$E79 -> 0 | U79: =H79*$H$3+K79*$K$3+N79*$N$3+Q79*$Q$3 -> 0 | V79: =U79/$U$162 -> #DIV/0!
B80: B - Custo Total de Equipamentos e Ferramentas: | E80: =SUM(#REF!) -> #REF! | H80: =SUM(H26:H79) -> 0 | K80: =SUM(K26:K79) -> 0 | N80: =SUM(N26:N79) -> 0 | Q80: =SUM(Q26:Q79) -> 0 | U80: =SUM(U26:U79) -> 0
B81: C – Materiais
B82: Cód. | C82: Discriminação | D82: Unid | E82: P.Unit | F82: Quant | G82: F.utiliz | H82: Custo | I82: Quant | J82: F.utiliz | K82: Custo | L82: Quant | M82: F.utiliz | N82: Custo | O82: Quant | P82: F.utiliz | Q82: Custo | S82: Quant | T82: F.utiliz | U82: Custo
B83: ='CPU 1'!B83 -> M01 | C83: ='CPU 1'!C83 -> Aço CA-50, (ferro 8.0) | D83: ='CPU 1'!D83 -> kg | E83: ='CPU 1'!E83 -> 12.5 | H83: =G83*F83*$E83 -> 0 | K83: =J83*I83*$E83 -> 0 | N83: =M83*L83*$E83 -> 0 | Q83: =P83*O83*$E83 -> 0 | U83: =H83*$H$3+K83*$K$3+N83*$N$3+Q83*$Q$3 -> 0 | V83: =U83/$U$162 -> #DIV/0!
B84: ='CPU 1'!B84 -> M02 | C84: ='CPU 1'!C84 -> Agua Mineral | D84: ='CPU 1'!D84 -> litro | E84: ='CPU 1'!E84 -> 1 | H84: =G84*F84*$E84 -> 0 | K84: =J84*I84*$E84 -> 0 | N84: =M84*L84*$E84 -> 0 | Q84: =P84*O84*$E84 -> 0 | U84: =H84*$H$3+K84*$K$3+N84*$N$3+Q84*$Q$3 -> 0 | V84: =U84/$U$162 -> #DIV/0!
B85: ='CPU 1'!B85 -> M03 | C85: ='CPU 1'!C85 -> Arame ovalado zincado | D85: ='CPU 1'!D85 -> m | E85: ='CPU 1'!E85 -> 1 | H85: =G85*F85*$E85 -> 0 | K85: =J85*I85*$E85 -> 0 | N85: =M85*L85*$E85 -> 0 | Q85: =P85*O85*$E85 -> 0 | U85: =H85*$H$3+K85*$K$3+N85*$N$3+Q85*$Q$3 -> 0 | V85: =U85/$U$162 -> #DIV/0!
B86: ='CPU 1'!B86 -> M04 | C86: ='CPU 1'!C86 -> Areia | D86: ='CPU 1'!D86 -> m³ | E86: ='CPU 1'!E86 -> 120 | H86: =G86*F86*$E86 -> 0 | K86: =J86*I86*$E86 -> 0 | N86: =M86*L86*$E86 -> 0 | Q86: =P86*O86*$E86 -> 0 | U86: =H86*$H$3+K86*$K$3+N86*$N$3+Q86*$Q$3 -> 0 | V86: =U86/$U$162 -> #DIV/0!
B87: ='CPU 1'!B87 -> M05 | C87: ='CPU 1'!C87 -> Arrame galganizado | D87: ='CPU 1'!D87 -> kg | E87: ='CPU 1'!E87 -> 16.8 | H87: =G87*F87*$E87 -> 0 | K87: =J87*I87*$E87 -> 0 | N87: =M87*L87*$E87 -> 0 | Q87: =P87*O87*$E87 -> 0 | U87: =H87*$H$3+K87*$K$3+N87*$N$3+Q87*$Q$3 -> 0 | V87: =U87/$U$162 -> #DIV/0!
B88: ='CPU 1'!B88 -> M06 | C88: ='CPU 1'!C88 -> Arrame recozido | D88: ='CPU 1'!D88 -> kg | E88: ='CPU 1'!E88 -> 12 | H88: =G88*F88*$E88 -> 0 | K88: =J88*I88*$E88 -> 0 | N88: =M88*L88*$E88 -> 0 | Q88: =P88*O88*$E88 -> 0 | U88: =H88*$H$3+K88*$K$3+N88*$N$3+Q88*$Q$3 -> 0 | V88: =U88/$U$162 -> #DIV/0!
B89: ='CPU 1'!B89 -> M07 | C89: ='CPU 1'!C89 -> Barrote de madeira 7x7cm | D89: ='CPU 1'!D89 -> m | E89: ='CPU 1'!E89 -> 15 | H89: =G89*F89*$E89 -> 0 | K89: =J89*I89*$E89 -> 0 | N89: =M89*L89*$E89 -> 0 | Q89: =P89*O89*$E89 -> 0 | U89: =H89*$H$3+K89*$K$3+N89*$N$3+Q89*$Q$3 -> 0 | V89: =U89/$U$162 -> #DIV/0!
B90: ='CPU 1'!B90 -> M08 | C90: ='CPU 1'!C90 -> Bloco tipo canaleta (14x19x39cm) | D90: ='CPU 1'!D90 -> peça | E90: ='CPU 1'!E90 -> 8.9 | H90: =G90*F90*$E90 -> 0 | K90: =J90*I90*$E90 -> 0 | N90: =M90*L90*$E90 -> 0 | Q90: =P90*O90*$E90 -> 0 | U90: =H90*$H$3+K90*$K$3+N90*$N$3+Q90*$Q$3 -> 0 | V90: =U90/$U$162 -> #DIV/0!
B91: ='CPU 1'!B91 -> M09 | C91: ='CPU 1'!C91 -> Brita 1 | D91: ='CPU 1'!D91 -> m³ | E91: ='CPU 1'!E91 -> 220 | H91: =G91*F91*$E91 -> 0 | K91: =J91*I91*$E91 -> 0 | N91: =M91*L91*$E91 -> 0 | Q91: =P91*O91*$E91 -> 0 | U91: =H91*$H$3+K91*$K$3+N91*$N$3+Q91*$Q$3 -> 0 | V91: =U91/$U$162 -> #DIV/0!
B92: ='CPU 1'!B92 -> M11 | C92: ='CPU 1'!C92 -> Caixa de passagens para aterramento h600 diâmetro 30cm | D92: ='CPU 1'!D92 -> und | E92: ='CPU 1'!E92 -> 590 | H92: =G92*F92*$E92 -> 0 | K92: =J92*I92*$E92 -> 0 | N92: =M92*L92*$E92 -> 0 | Q92: =P92*O92*$E92 -> 0 | U92: =H92*$H$3+K92*$K$3+N92*$N$3+Q92*$Q$3 -> 0 | V92: =U92/$U$162 -> #DIV/0!
B93: ='CPU 1'!B93 -> M12 | C93: ='CPU 1'!C93 -> Catoneira galvanizada 1"x1-1/4 | D93: ='CPU 1'!D93 -> m | E93: ='CPU 1'!E93 -> 25 | H93: =G93*F93*$E93 -> 0 | K93: =J93*I93*$E93 -> 0 | N93: =M93*L93*$E93 -> 0 | Q93: =P93*O93*$E93 -> 0 | U93: =H93*$H$3+K93*$K$3+N93*$N$3+Q93*$Q$3 -> 0 | V93: =U93/$U$162 -> #DIV/0!
B94: ='CPU 1'!B94 -> M13 | C94: ='CPU 1'!C94 -> Cercamento e delimitação de canteiro de obra (15x30m) | D94: ='CPU 1'!D94 -> vb | E94: ='CPU 1'!E94 -> 10000 | H94: =G94*F94*$E94 -> 0 | K94: =J94*I94*$E94 -> 0 | N94: =M94*L94*$E94 -> 0 | Q94: =P94*O94*$E94 -> 0 | U94: =H94*$H$3+K94*$K$3+N94*$N$3+Q94*$Q$3 -> 0 | V94: =U94/$U$162 -> #DIV/0!
... B131: ='CPU 1'!B131 -> M50 | C131: ='CPU 1'!C131 -> 0 | D131: ='CPU 1'!D131 -> 0 | E131: ='CPU 1'!E131 -> 0 | H131: =G131*F131*$E131 -> 0 | K131: =J131*I131*$E131 -> 0 | N131: =M131*L131*$E131 -> 0 | Q131: =P131*O131*$E131 -> 0 | U131: =H131*$H$3+K131*$K$3+N131*$N$3+Q131*$Q$3 -> 0 | V131: =U131/$U$162 -> #DIV/0!
B132: C - Custo Total de Materiais: | E132: =SUM(#REF!) -> #REF! | H132: =SUM(H83:H131) -> 0 | K132: =SUM(K83:K131) -> 0 | N132: =SUM(N83:N131) -> 0 | Q132: =SUM(Q83:Q131) -> 0 | U132: =SUM(U83:U131) -> 0
B133: D – Outros
B134: Cód. | C134: Discriminação | D134: Unid | E134: P.Unit | F134: Quant | G134: F.utiliz | H134: Custo | I134: Quant | J134: F.utiliz | K134: Custo | L134: Quant | M134: F.utiliz | N134: Custo | O134: Quant | P134: F.utiliz | Q134: Custo | S134: Quant | T134: F.utiliz | U134: Custo
B135: ='CPU 1'!B135 -> O01 | C135: ='CPU 1'!C135 -> ART | D135: ='CPU 1'!D135 -> Vb | E135: ='CPU 1'!E135 -> 1000 | H135: =G135*F135*$E135 -> 0 | K135: =J135*I135*$E135 -> 0 | N135: =M135*L135*$E135 -> 0 | Q135: =P135*O135*$E135 -> 0 | U135: =H135*$H$3+K135*$K$3+N135*$N$3+Q135*$Q$3 -> 0 | V135: =U135/$U$162 -> #DIV/0!
B136: ='CPU 1'!B136 -> O02 | C136: ='CPU 1'!C136 -> Exames medicos | D136: ='CPU 1'!D136 -> Vb | E136: ='CPU 1'!E136 -> 600 | H136: =G136*F136*$E136 -> 0 | K136: =J136*I136*$E136 -> 0 | N136: =M136*L136*$E136 -> 0 | Q136: =P136*O136*$E136 -> 0 | U136: =H136*$H$3+K136*$K$3+N136*$N$3+Q136*$Q$3 -> 0 | V136: =U136/$U$162 -> #DIV/0!
B137: ='CPU 1'!B137 -> O03 | C137: ='CPU 1'!C137 -> Treinamentos | D137: ='CPU 1'!D137 -> Vb | E137: ='CPU 1'!E137 -> 426 | H137: =G137*F137*$E137 -> 0 | K137: =J137*I137*$E137 -> 0 | N137: =M137*L137*$E137 -> 0 | Q137: =P137*O137*$E137 -> 0 | U137: =H137*$H$3+K137*$K$3+N137*$N$3+Q137*$Q$3 -> 0 | V137: =U137/$U$162 -> #DIV/0!
B138: ='CPU 1'!B138 -> O04 | C138: ='CPU 1'!C138 -> Plano de Saude | D138: ='CPU 1'!D138 -> Vb/mês | E138: ='CPU 1'!E138 -> 280 | H138: =G138*F138*$E138 -> 0 | K138: =J138*I138*$E138 -> 0 | N138: =M138*L138*$E138 -> 0 | Q138: =P138*O138*$E138 -> 0 | U138: =H138*$H$3+K138*$K$3+N138*$N$3+Q138*$Q$3 -> 0 | V138: =U138/$U$162 -> #DIV/0!
B139: ='CPU 1'!B139 -> O05 | C139: ='CPU 1'!C139 -> Seguro de Vida | D139: ='CPU 1'!D139 -> Vb/mês | E139: ='CPU 1'!E139 -> 25 | H139: =G139*F139*$E139 -> 0 | K139: =J139*I139*$E139 -> 0 | N139: =M139*L139*$E139 -> 0 | Q139: =P139*O139*$E139 -> 0 | U139: =H139*$H$3+K139*$K$3+N139*$N$3+Q139*$Q$3 -> 0 | V139: =U139/$U$162 -> #DIV/0!
B140: ='CPU 1'!B140 -> O06 | C140: ='CPU 1'!C140 -> Ticket Alimentação | D140: ='CPU 1'!D140 -> Vb/mês | E140: ='CPU 1'!E140 -> 350 | H140: =G140*F140*$E140 -> 0 | K140: =J140*I140*$E140 -> 0 | N140: =M140*L140*$E140 -> 0 | Q140: =P140*O140*$E140 -> 0 | U140: =H140*$H$3+K140*$K$3+N140*$N$3+Q140*$Q$3 -> 0 | V140: =U140/$U$162 -> #DIV/0!
B141: ='CPU 1'!B141 -> O07 | C141: ='CPU 1'!C141 -> PCMSO / PGR / PCA / PPR | D141: ='CPU 1'!D141 -> Vb/ano | E141: ='CPU 1'!E141 -> 2300 | H141: =G141*F141*$E141 -> 0 | K141: =J141*I141*$E141 -> 0 | N141: =M141*L141*$E141 -> 0 | Q141: =P141*O141*$E141 -> 0 | U141: =H141*$H$3+K141*$K$3+N141*$N$3+Q141*$Q$3 -> 0 | V141: =U141/$U$162 -> #DIV/0!
B142: ='CPU 1'!B142 -> O08 | C142: ='CPU 1'!C142 -> Quadros DDS e Gestão a vista | D142: ='CPU 1'!D142 -> Vb | E142: ='CPU 1'!E142 -> 1200 | H142: =G142*F142*$E142 -> 0 | K142: =J142*I142*$E142 -> 0 | N142: =M142*L142*$E142 -> 0 | Q142: =P142*O142*$E142 -> 0 | U142: =H142*$H$3+K142*$K$3+N142*$N$3+Q142*$Q$3 -> 0 | V142: =U142/$U$162 -> #DIV/0!
B143: ='CPU 1'!B143 -> O09 | C143: ='CPU 1'!C143 -> Seguro Obra | D143: ='CPU 1'!D143 -> Vb | E143: ='CPU 1'!E143 -> 5000 | H143: =G143*F143*$E143 -> 0 | K143: =J143*I143*$E143 -> 0 | N143: =M143*L143*$E143 -> 0 | Q143: =P143*O143*$E143 -> 0 | U143: =H143*$H$3+K143*$K$3+N143*$N$3+Q143*$Q$3 -> 0 | V143: =U143/$U$162 -> #DIV/0!
B144: ='CPU 1'!B144 -> O10 | C144: ='CPU 1'!C144 -> Fretes | D144: ='CPU 1'!D144 -> ud | E144: ='CPU 1'!E144 -> 2800 | H144: =G144*F144*$E144 -> 0 | K144: =J144*I144*$E144 -> 0 | N144: =M144*L144*$E144 -> 0 | Q144: =P144*O144*$E144 -> 0 | U144: =H144*$H$3+K144*$K$3+N144*$N$3+Q144*$Q$3 -> 0 | V144: =U144/$U$162 -> #DIV/0!
B145: ='CPU 1'!B145 -> O11 | C145: ='CPU 1'!C145 -> Serviço de descarte de residuo | D145: ='CPU 1'!D145 -> coleta | E145: ='CPU 1'!E145 -> 2000 | H145: =G145*F145*$E145 -> 0 | K145: =J145*I145*$E145 -> 0 | N145: =M145*L145*$E145 -> 0 | Q145: =P145*O145*$E145 -> 0 | U145: =H145*$H$3+K145*$K$3+N145*$N$3+Q145*$Q$3 -> 0 | V145: =U145/$U$162 -> #DIV/0!
B146: ='CPU 1'!B146 -> O12 | C146: ='CPU 1'!C146 -> Serviço de movimentação do Banheiro Hidráulico | D146: ='CPU 1'!D146 -> vb | E146: ='CPU 1'!E146 -> 200 | H146: =G146*F146*$E146 -> 0 | K146: =J146*I146*$E146 -> 0 | N146: =M146*L146*$E146 -> 0 | Q146: =P146*O146*$E146 -> 0 | U146: =H146*$H$3+K146*$K$3+N146*$N$3+Q146*$Q$3 -> 0 | V146: =U146/$U$162 -> #DIV/0!
... B154: ='CPU 1'!B154 -> O20 | C154: ='CPU 1'!C154 -> 0 | D154: ='CPU 1'!D154 -> 0 | E154: ='CPU 1'!E154 -> 0 | H154: =G154*F154*$E154 -> 0 | K154: =J154*I154*$E154 -> 0 | N154: =M154*L154*$E154 -> 0 | Q154: =P154*O154*$E154 -> 0 | U154: =H154*$H$3+K154*$K$3+N154*$N$3+Q154*$Q$3 -> 0 | V154: =U154/$U$162 -> #DIV/0!
B155: D - Custo Total de Outros: | E155: =SUM(#REF!) -> #REF! | H155: =SUM(H135:H154) -> 0 | K155: =SUM(K135:K154) -> 0 | N155: =SUM(N135:N154) -> 0 | Q155: =SUM(Q135:Q154) -> 0 | U155: =SUM(U135:U154) -> 0
B157: Item | C157: CUSTOS | G157: % | H157: $ | J157: % | K157: $ | M157: % | N157: $ | P157: % | Q157: $ | T157: % | U157: $
B158: A | C158: Mão de Obra | G158: =H158/H162 -> #DIV/0! | H158: =H23 -> 0 | J158: =K158/K162 -> #DIV/0! | K158: =K23 -> 0 | M158: =N158/N162 -> #DIV/0! | N158: =N23 -> 0 | P158: =Q158/Q162 -> #DIV/0! | Q158: =Q23 -> 0 | T158: =U158/U162 -> #DIV/0! | U158: =U23 -> 0
B159: B | C159: Equipamentos | G159: =H159/H162 -> #DIV/0! | H159: =H80 -> 0 | J159: =K159/K162 -> #DIV/0! | K159: =K80 -> 0 | M159: =N159/N162 -> #DIV/0! | N159: =N80 -> 0 | P159: =Q159/Q162 -> #DIV/0! | Q159: =Q80 -> 0 | T159: =U159/U162 -> #DIV/0! | U159: =U80 -> 0
B160: C | C160: Materiais | G160: =H160/H162 -> #DIV/0! | H160: =H132 -> 0 | J160: =K160/K162 -> #DIV/0! | K160: =K132 -> 0 | M160: =N160/N162 -> #DIV/0! | N160: =N132 -> 0 | P160: =Q160/Q162 -> #DIV/0! | Q160: =Q132 -> 0 | T160: =U160/U162 -> #DIV/0! | U160: =U132 -> 0
B161: D | C161: Outros | G161: =H161/H162 -> #DIV/0! | H161: =H155 -> 0 | J161: =K161/K162 -> #DIV/0! | K161: =K155 -> 0 | M161: =N161/N162 -> #DIV/0! | N161: =N155 -> 0 | P161: =Q161/Q162 -> #DIV/0! | Q161: =Q155 -> 0 | T161: =U161/U162 -> #DIV/0! | U161: =U155 -> 0
C162: Subtotal: | E162: =SUM(E158:E161) -> 0 | G162: =SUM(G158:G161) -> #DIV/0! | H162: =SUM(H158:H161) -> 0 | J162: =SUM(J158:J161) -> #DIV/0! | K162: =SUM(K158:K161) -> 0 | M162: =SUM(M158:M161) -> #DIV/0! | N162: =SUM(N158:N161) -> 0 | P162: =SUM(P158:P161) -> #DIV/0! | Q162: =SUM(Q158:Q161) -> 0 | T162: =SUM(T158:T161) -> #DIV/0! | U162: =SUM(U158:U161) -> 0
B164: Item | C164: BDI | E164: Taxa | H164: $ | K164: $ | N164: $ | Q164: $ | U164: $
B165: 1 | C165: Administração Local | E165: ='BDI-TRIBUTOS'!D8 -> 0.09 | H165: =H162*$E$165 -> 0 | K165: =K162*$E$165 -> 0 | N165: =N162*$E$165 -> 0 | Q165: =Q162*$E$165 -> 0 | U165: =U162*$E$165 -> 0
B166: 2 | C166: Administração Central | E166: ='BDI-TRIBUTOS'!D6 -> 0.06 | H166: =H162*$E$166 -> 0 | K166: =K162*$E$166 -> 0 | N166: =N162*$E$166 -> 0 | Q166: =Q162*$E$166 -> 0 | U166: =U162*$E$166 -> 0
B167: 3 | C167: Custo financ. capital giro | E167: ='BDI-TRIBUTOS'!D10 -> 0.035 | H167: =H162*$E$167 -> 0 | K167: =K162*$E$167 -> 0 | N167: =N162*$E$167 -> 0 | Q167: =Q162*$E$167 -> 0 | U167: =U162*$E$167 -> 0
B168: 4 | C168: Risco do empreendimento | E168: ='BDI-TRIBUTOS'!D12 -> 0.02 | H168: =H162*$E$168 -> 0 | K168: =K162*$E$168 -> 0 | N168: =N162*$E$168 -> 0 | Q168: =Q162*$E$168 -> 0 | U168: =U162*$E$168 -> 0
B169: 5 | C169: Outros | E169: ='BDI-TRIBUTOS'!D14 -> 0.01 | H169: =H162*$E$169 -> 0 | K169: =K162*$E$169 -> 0 | N169: =N162*$E$169 -> 0 | Q169: =Q162*$E$169 -> 0 | U169: =U162*$E$169 -> 0
B170: 6 | C170: Lucro | E170: ='BDI-TRIBUTOS'!D4 -> 0.1 | H170: =H182*$E$170 -> 0 | K170: =K182*$E$170 -> 0 | N170: =N182*$E$170 -> 0 | Q170: =Q182*$E$170 -> 0 | U170: =U182*$E$170 -> 0
C171: Subtotal: | E171: =SUM(E165:E170) -> 0.315 | G171: =SUM(H165:H169)+H162 -> 0 | H171: =SUM(H165:H170) -> 0 | J171: =SUM(K165:K169)+K162 -> 0 | K171: =SUM(K165:K170) -> 0 | M171: =SUM(N165:N169)+N162 -> 0 | N171: =SUM(N165:N170) -> 0 | P171: =SUM(Q165:Q169)+Q162 -> 0 | Q171: =SUM(Q165:Q170) -> 0 | T171: =SUM(U165:U169)+U162 -> 0 | U171: =SUM(U165:U170) -> 0
F172: =H171/H162 -> #DIV/0! | I172: =K171/K162 -> #DIV/0! | L172: =N171/N162 -> #DIV/0! | O172: =Q171/Q162 -> #DIV/0! | S172: =U171/U162 -> #DIV/0!
B173: Item | C173: TRIBUTOS | E173: Taxa | H173: $ | K173: $ | N173: $ | Q173: $ | U173: $
B174: 1 | C174: ISS | E174: ='BDI-TRIBUTOS'!D20 -> 0.05 | H174: =H$182*$E174 -> 0 | K174: =K$182*$E174 -> 0 | N174: =N$182*$E174 -> 0 | Q174: =Q$182*$E174 -> 0 | U174: =$U$182*E174 -> 0
B175: 2 | C175: COFINS | E175: ='BDI-TRIBUTOS'!D21 -> 0.03 | H175: =H$182*$E175 -> 0 | K175: =K$182*$E175 -> 0 | N175: =N$182*$E175 -> 0 | Q175: =Q$182*$E175 -> 0 | U175: =$U$182*E175 -> 0
B176: 3 | C176: PIS | E176: ='BDI-TRIBUTOS'!D22 -> 0.0065 | H176: =H$182*$E176 -> 0 | K176: =K$182*$E176 -> 0 | N176: =N$182*$E176 -> 0 | Q176: =Q$182*$E176 -> 0 | U176: =$U$182*E176 -> 0
B177: 4 | C177: CSLL | E177: ='BDI-TRIBUTOS'!D23 -> 0.0288 | H177: =H$182*$E177 -> 0 | K177: =K$182*$E177 -> 0 | N177: =N$182*$E177 -> 0 | Q177: =Q$182*$E177 -> 0 | U177: =$U$182*E177 -> 0
B178: 5 | C178: IRPJ | E178: ='BDI-TRIBUTOS'!D24 -> 0.048 | H178: =H$182*$E178 -> 0 | K178: =K$182*$E178 -> 0 | N178: =N$182*$E178 -> 0 | Q178: =Q$182*$E178 -> 0 | U178: =$U$182*E178 -> 0
B179: 6 | C179: IRPJ Adicional 10% | E179: ='BDI-TRIBUTOS'!D25 -> 0.0318 | H179: =H$182*$E179 -> 0 | K179: =K$182*$E179 -> 0 | N179: =N$182*$E179 -> 0 | Q179: =Q$182*$E179 -> 0 | U179: =$U$182*E179 -> 0
B180: 7 | C180: Simples Nacional | E180: ='BDI-TRIBUTOS'!D26 -> 0
C181: Subtotal | E181: =SUM(E174:E180) -> 0.1951 | H181: =H182*$E$181 -> 0 | K181: =K182*$E$181 -> 0 | N181: =N182*$E$181 -> 0 | Q181: =Q182*$E$181 -> 0 | U181: =U182*$E$181 -> 0
C182: PREÇO | F182: =ROUND(H182,2) -> 0 | H182: =G171/(1-$E$181-$E$170) -> 0 | I182: =ROUND(K182,2) -> 0 | K182: =J171/(1-$E$181-$E$170) -> 0 | L182: =ROUND(N182,2) -> 0 | N182: =M171/(1-$E$181-$E$170) -> 0 | O182: =ROUND(Q182,2) -> 0 | Q182: =P171/(1-$E$181-$E$170) -> 0 | U182: =T171/(1-$E$181-$E$170) -> 0
H183: =H182/H162 -> #DIV/0! | K183: =K182/K162 -> #DIV/0! | N183: =N182/N162 -> #DIV/0! | Q183: =Q182/Q162 -> #DIV/0! | U183: =U182/U162 -> #DIV/0!

Sheet MO
B1: COMPOSIÇÃO DO CUSTO SALARIOS POR FUNÇÃO (MOD) | M1: QQP
B2: Cód. | C2: Função | D2: Escolaridade | E2: A1) Salário sem encargos | F2: A2) Adicional Periculosidade | G2: A3) Outros Adicionais | H2: Outros | I2: Encargos | J2: Por mês | K2: Em HH | M2: =QQP!G44 -> 0
B3: P01 | C3: Supervisor | D3: Superior | E3: 7500 | I3: =(H3+G3+F3+E3)*$E$22 -> 5712 | J3: =SUM(E3:I3) -> 13212 | K3: =J3/$K$22 -> 75.068182
B4: P02 | C4: Encarregado | D4: Médio/Técnico | E4: 4000 | I4: =(H4+G4+F4+E4)*$E$22 -> 3046.4 | J4: =SUM(E4:I4) -> 7046.4 | K4: =J4/$K$22 -> 40.036364
B5: P03 | C5: Técnico SSMA | D5: Técnico | E5: 4000 | I5: =(H5+G5+F5+E5)*$E$22 -> 3046.4 | J5: =SUM(E5:I5) -> 7046.4 | K5: =J5/$K$22 -> 40.036364
B6: P04 | C6: Pedreiro | D6: Médio/Técnico | E6: 1975 | I6: =(H6+G6+F6+E6)*$E$22 -> 1504.16 | J6: =SUM(E6:I6) -> 3479.16 | K6: =J6/$K$22 -> 19.767955
B7: P05 | C7: Carpinteiro | D7: Médio/Técnico | E7: 1975 | I7: =(H7+G7+F7+E7)*$E$22 -> 1504.16 | J7: =SUM(E7:I7) -> 3479.16 | K7: =J7/$K$22 -> 19.767955
B8: P06 | C8: Eletricista | D8: Médio/Técnico | E8: 2000 | F8: =E8*0.3 -> 600 | I8: =(H8+G8+F8+E8)*$E$22 -> 1980.16 | J8: =SUM(E8:I8) -> 4580.16 | K8: =J8/$K$22 -> 26.023636
B9: P07 | C9: Ajudante | D9: Médio/Técnico | E9: 1395 | I9: =(H9+G9+F9+E9)*$E$22 -> 1062.432 | J9: =SUM(E9:I9) -> 2457.432 | K9: =J9/$K$22 -> 13.962682
B10: P08 | C10: Armador | D10: Médio/Técnico | E10: 1975 | I10: =(H10+G10+F10+E10)*$E$22 -> 1504.16 | J10: =SUM(E10:I10) -> 3479.16 | K10: =J10/$K$22 -> 19.767955
B11: P09 | C11: Engenheiro | D11: Superior | E11: =1320*8.5 -> 11220 | I11: =(H11+G11+F11+E11)*$E$22 -> 8545.152 | J11: =SUM(E11:I11) -> 19765.152 | K11: =J11/$K$22 -> 112.302
B12: P10 | C12: Planejador | D12: Técnico | E12: 6000 | I12: =(H12+G12+F12+E12)*$E$22 -> 4569.6 | J12: =SUM(E12:I12) -> 10569.6 | K12: =J12/$K$22 -> 60.054545
B13: P11 | C13: Tópografo | D13: Técnico | E13: 3800 | I13: =(H13+G13+F13+E13)*$E$22 -> 2894.08 | J13: =SUM(E13:I13) -> 6694.08 | K13: =J13/$K$22 -> 38.034545
B14: P12 | C14: Auxiliar de Topografia | D14: Médio/Técnico | E14: 1700 | I14: =(H14+G14+F14+E14)*$E$22 -> 1294.72 | J14: =SUM(E14:I14) -> 2994.72 | K14: =J14/$K$22 -> 17.015455
B15: P13 | C15: Projetista | D15: Superior | E15: 7000 | I15: =(H15+G15+F15+E15)*$E$22 -> 5331.2 | J15: =SUM(E15:I15) -> 12331.2 | K15: =J15/$K$22 -> 70.063636
B16: P14 | C16: Operador/motorista | D16: Médio/Técnico | E16: 2500 | I16: =(H16+G16+F16+E16)*$E$22 -> 1904 | J16: =SUM(E16:I16) -> 4404 | K16: =J16/$K$22 -> 25.022727
B17: P15 | I17: =(H17+G17+F17+E17)*$E$22 -> 0 | J17: =SUM(E17:I17) -> 0 | K17: =J17/$K$22 -> 0
B18: P16 | I18: =(H18+G18+F18+E18)*$E$22 -> 0 | J18: =SUM(E18:I18) -> 0 | K18: =J18/$K$22 -> 0
B19: P17 | I19: =(H19+G19+F19+E19)*$E$22 -> 0 | J19: =SUM(E19:I19) -> 0 | K19: =J19/$K$22 -> 0
B20: P18 | I20: =(H20+G20+F20+E20)*$E$22 -> 0 | J20: =SUM(E20:I20) -> 0 | K20: =J20/$K$22 -> 0
C22: Encargos Sociais | E22: ='ENCARGOS SOCIAIS'!enc -> 0.7616 | G22: Total de horas trabalhadas mês | K22: 176

Sheet EPIs
B1: EPIs
B2: EPI | C2: Vida Útil (mês) | D2: Preço Compra | E2: OBRAS
E3: Qnt. | F3: Custo/Mês
B4: Capacete | C4: 6 | D4: 58 | E4: 1 | F4: =D4/C4*E4 -> 9.6666667
B5: Carneira e jugular | C5: 6 | D5: 33.6 | E5: 1 | F5: =D5/C5*E5 -> 5.6
B6: Óculos Amplavisão | C6: 4 | D6: 90 | E6: 1 | F6: =D6/C6*E6 -> 22.5
B7: Óculos impacto | C7: 2 | D7: 10 | E7: 1 | F7: =D7/C7*E7 -> 5
B8: Abafador ruido tipo concha - MSA | C8: 6 | D8: 208 | E8: 1 | F8: =D8/C8*E8 -> 34.666667
B9: Protetor facial - MSA | C9: 4 | D9: 120 | E9: 1 | F9: =D9/C9*E9 -> 30
B10: Luvas de Poliamida | C10: 0.25 | D10: 3 | E10: 1 | F10: =D10/C10*E10 -> 12
B11: Luvas de Vaqueta | C11: 1 | D11: 20 | E11: 1 | F11: =D11/C11*E11 -> 20
B12: Respirador | C12: 0.045454545 | D12: 3 | E12: 1 | F12: =D12/C12*E12 -> 66
B13: Bota de segurança manobreiro | C13: 6 | D13: 160 | E13: 1 | F13: =D13/C13*E13 -> 26.666667
B14: Camisa com Proteção Quimica Manga Longa de Brim | C14: 6 | D14: 90 | E14: 3 | F14: =D14/C14*E14 -> 45
B15: Calça de Brim | C15: 6 | D15: 90 | E15: 3 | F15: =D15/C15*E15 -> 45
B16: Perneira | C16: 6 | D16: 40 | E16: 1 | F16: =D16/C16*E16 -> 6.6666667
B17: Cinta de segurança com talabarte | C17: 12 | D17: =226+227 -> 453 | F17: =D17/C17*E17 -> 0
B18: Pretor solar 30fps 2 litros | C18: =1/10 -> 0.1 | D18: 231 | F18: =D18/C18*E18 -> 0
B19: Avental | C19: 12 | D19: 33 | F19: =D19/C19*E19 -> 0
B20: Mascara de solda carbografite | C20: 6 | D20: 77 | F20: =D20/C20*E20 -> 0
B22: TOTAL | E22: =SUM(E4:E21) -> 17 | F22: =SUM(F4:F21) -> 328.76667

Sheet TREINAMENTOS
B1: TREINAMENTOS
B2: TREINAMENTO | C2: EMPRESA | D2: MATRIZ | E2: CUSTO | F2: OBRAS
F3: Qnt. | G3: Total
B4: ÉTICA + VÍDEO INCLUSÃO/DIVERSIDADE (NEW) | C4: ALUMAR | D4: INTEGRAÇÃO PARA NOVOS FUNCIONÁRIOS | E4: 12 | F4: 1 | G4: =F4*E4 -> 12
B5: EHS INTRODUTÓRIO | C5: ALUMAR | D5: INTEGRAÇÃO PARA NOVOS FUNCIONÁRIOS | E5: 18 | F5: 1 | G5: =F5*E5 -> 18
B6: EMERGÊNCIA | C6: ALUMAR | D6: INTEGRAÇÃO PARA NOVOS FUNCIONÁRIOS | E6: 12 | F6: 1 | G6: =F6*E6 -> 12
B7: MEIO AMBIENTE | C7: ALUMAR | D7: INTEGRAÇÃO PARA NOVOS FUNCIONÁRIOS | E7: 18 | F7: 1 | G7: =F7*E7 -> 18
B8: PREVENÇÃO DE FSI - GERENCIAMENTO DE RISCOS CRÍTICOS (CRM) | C8: ALUMAR | D8: INTEGRAÇÃO PARA NOVOS FUNCIONÁRIOS | E8: 30 | F8: 1 | G8: =F8*E8 -> 30
B9: CRÍTICOS: EQUIPAMENTOS MÓVEIS/VEÍCULOS | C9: ALUMAR | D9: INTEGRAÇÃO PARA NOVOS FUNCIONÁRIOS | E9: 12 | F9: 1 | G9: =F9*E9 -> 12
B10: CRÍTICOS: LIBERAÇÃO DE ENERGIA INESPERADA | C10: ALUMAR | D10: INTEGRAÇÃO PARA NOVOS FUNCIONÁRIOS | E10: 12 | F10: 1 | G10: =F10*E10 -> 12
B11: CRÍTICOS: PREVENÇÃO DE QUEDAS/QUEDAS DE OBJETO | C11: ALUMAR | D11: INTEGRAÇÃO PARA NOVOS FUNCIONÁRIOS | E11: 12 | F11: 1 | G11: =F11*E11 -> 12
B12: CRÍTICOS: ESPAÇO CONFINADO | C12: ALUMAR | D12: INTEGRAÇÃO PARA NOVOS FUNCIONÁRIOS | E12: 12 | F12: 1 | G12: =F12*E12 -> 12
B13: CRÍTICOS: IÇAMENTO DE CARGA | C13: ALUMAR | D13: INTEGRAÇÃO PARA NOVOS FUNCIONÁRIOS | E13: 12 | F13: 1 | G13: =F13*E13 -> 12
B14: CRÍTICOS: CONTATO COM ELETRICIDADE | C14: ALUMAR | D14: INTEGRAÇÃO PARA NOVOS FUNCIONÁRIOS | E14: 12 | F14: 1 | G14: =F14*E14 -> 12
B15: CRÍTICOS: PROTEÇÃO DE MÁQUINAS | C15: ALUMAR | D15: INTEGRAÇÃO PARA NOVOS FUNCIONÁRIOS | E15: 12 | F15: 1 | G15: =F15*E15 -> 12
... B23: POLÍTICA GLOBAL DE BARRAGENS | C23: ALUMAR | D23: INTEGRAÇÃO PARA NOVOS FUNCIONÁRIOS | E23: 18 | F23: 1 | G23: =F23*E23 -> 18
B24: ÉTICA + VÍDEO INCLUSÃO/DIVERSIDADE (NEW) | C24: ALUMAR | D24: RECICLAGEM OBRIGATÓRIA ANUAL | E24: 12 | G24: =F24*E24 -> 0
B25: EHS INTRODUTÓRIO | C25: ALUMAR | D25: RECICLAGEM OBRIGATÓRIA ANUAL | E25: 18 | G25: =F25*E25 -> 0
B26: EMERGÊNCIA | C26: ALUMAR | D26: RECICLAGEM OBRIGATÓRIA ANUAL | E26: 12 | G26: =F26*E26 -> 0
B27: MEIO AMBIENTE | C27: ALUMAR | D27: RECICLAGEM OBRIGATÓRIA ANUAL | E27: 18 | G27: =F27*E27 -> 0
B28: PREVENÇÃO DE FSI - GERENCIAMENTO DE RISCOS CRÍTICOS (CRM) | C28: ALUMAR | D28: RECICLAGEM OBRIGATÓRIA ANUAL | E28: 30 | G28: =F28*E28 -> 0
B29: CRÍTICOS: EQUIPAMENTOS MÓVEIS/VEÍCULOS | C29: ALUMAR | D29: RECICLAGEM OBRIGATÓRIA ANUAL | E29: 12 | G29: =F29*E29 -> 0
B30: CRÍTICOS: LIBERAÇÃO DE ENERGIA INESPERADA | C30: ALUMAR | D30: RECICLAGEM OBRIGATÓRIA ANUAL | E30: 12 | G30: =F30*E30 -> 0
B31: CRÍTICOS: PREVENÇÃO DE QUEDAS/QUEDAS DE OBJETO | C31: ALUMAR | D31: RECICLAGEM OBRIGATÓRIA ANUAL | E31: 12 | G31: =F31*E31 -> 0
B32: CRÍTICOS: ESPAÇO CONFINADO | C32: ALUMAR | D32: RECICLAGEM OBRIGATÓRIA ANUAL | E32: 12 | G32: =F32*E32 -> 0
B33: CRÍTICOS: IÇAMENTO DE CARGA | C33: ALUMAR | D33: RECICLAGEM OBRIGATÓRIA ANUAL | E33: 12 | G33: =F33*E33 -> 0
B34: CRÍTICOS: CONTATO COM ELETRICIDADE | C34: ALUMAR | D34: RECICLAGEM OBRIGATÓRIA ANUAL | E34: 12 | G34: =F34*E34 -> 0
B35: CRÍTICOS: PROTEÇÃO DE MÁQUINAS | C35: ALUMAR | D35: RECICLAGEM OBRIGATÓRIA ANUAL | E35: 12 | G35: =F35*E35 -> 0
... B80: TREINAMENTO DE RAC E NR | C80: VALE | D80: RACs E NRs | E80: 100 | G80: =F80*E80 -> 0
G81: =F81*E81 -> 0
B82: TOTAL | G82: =SUM(G4:G81) -> 426

Sheet EXAMES
B1: EXAMES / DOCUMENTAÇÕES SESMT
B2: TABELA DE EXAMES | E2: DESCRIÇÃO EXAME | F2: QNT. | G2: CUSTO | H2: TOTAL
B3: EXAME | C3: VALOR | E3: ADMISSIONAL | F3: 1 | G3: 400 | H3: =G3*F3 -> 400
B4: ACUIDADE VISUAL | C4: 18 | E4: PERIÓDICO | F4: 0 | G4: 400 | H4: =G4*F4 -> 0
B5: ATESTADO DE APTIDAO FISICA | C5: 40 | E5: DEMISSIONAL | F5: 1 | G5: 200 | H5: =G5*F5 -> 200
B6: ATESTADO PNE | C6: 65 | E6: TOTAL GERAL | H6: =SUM(H3:H5) -> 600
B7: AUDIOMETRIA TONAL | C7: 25
B8: AUDIOMETRIA TONAL E VOCAL | C8: 27.5 | E8: DOCUMENTAÇÕES SESMT - (PCMSO - PGR - PCA - PPR)
B9: CAMPIMETRIA COMPUTADORIZADA | C9: 70 | E9: Contrato Quantidade de 0 a 10 Funcionários | H9: =SUM(H10:H13) -> 1580
B10: CLINICO ANAMNESE DIRIGIDA/EXAME FISICO E MENTAL | C10: 40 | E10: PCMSO | H10: 380
B11: COLESTEROL TOTAL E FRAÇÕES | C11: 54.5 | E11: PGR | H11: 600
B12: CONSULTA COM ENDOCRINOLOGISTA | C12: 190 | E12: PCA | H12: 300
B13: CONSULTA COM OFTALMOLOGISTA COM POTENCIAL ACUIDADE | C13: 85 | E13: PPR | H13: 300
B14: CONSULTA OFTALMOLOGICA -POTENCIAL ACUIDADE VISUAL | C14: 85 | E14: Contrato Quantidade de 11 a 30 Funcionários | H14: =SUM(H15:H18) -> 1950
B15: ELETROCARDIOGRAMA | C15: 28 | E15: PCMSO | H15: 450
B16: ELETROENCEFALOGRAMA | C16: 45 | E16: PGR | H16: 800
B17: ESPIROMETRIA | C17: 24.5 | E17: PCA | H17: 350
B18: EXAME CLINICO | C18: 38.5 | E18: PPR | H18: 350
B19: FATOR RH | C19: 7.5 | E19: Contrato Quantidade de 31 a 50 Funcionários | H19: =SUM(H20:H23) -> 2300
B20: FICHA RAC | C20: 22 | E20: PCMSO | H20: 500
B21: GAMA GT | C21: 12.5 | E21: PGR | H21: 1000
B22: GLICEMIA | C22: 10.5 | E22: PCA | H22: 400
B23: GLICEMIA EM JEJUM | C23: 10.5 | E23: PPR | H23: 400
B24: GRUPO SANGUINEO | C24: 7.5 | E24: Contrato Quantidade de 51 a 100 Funcionários | H24: =SUM(H25:H28) -> 2850
B25: HEMOGLOBINA GLICADA | C25: 26.5 | E25: PCMSO | H25: 700
B26: HEMOGLOBINA GLICOSADA | C26: 26.5 | E26: PGR | H26: 1250
B27: HEMOGRAMA COMPLETO | C27: 13.5 | E27: PCA | H27: 450
B28: LIPIDOGRAMA | C28: 48 | E28: PPR | H28: 450
B29: MANGANES URINARIO | C29: 78
B30: PSA LIVRE (ANTIGENO PROSTATICO ESPECIFICO) | C30: 85
B31: PSA TOTAL (ANTIGENO PROSTATICO ESPECIFICO) | C31: 85
B32: RX DA MAO DIREITA | C32: 40
B33: RX DO PE DIREITO | C33: 40
B34: RX DO TORAX | C34: 35
B35: RX DO TORAX OIT 2000 | C35: 45
B36: RX DO TORAX PADRÃO OIT | C36: 45
B37: TESTE ERGOMETRICO | C37: 120
B38: TGO | C38: 9.6
B39: TGP | C39: 9.6
B40: TOXICOLÓGICO | C40: 180
B41: URINA | C41: 11.2

Sheet BDI-TRIBUTOS
AB1: QQP | AD1: K
AB2: =QQP!G44 -> 0 | AD2: ='CPU 1'!H183 -> #DIV/0!
B3: BDI | D3: =D16 -> 0.315
B4: 1 | C4: LUCRO | D4: 0.1
B5: 2 | C5: DESPESAS INDIRETAS | D5: =SUM(D6:D14) -> 0.215
B6: 2.1 | C6: ADMINISTRAÇÃO CENTRAL | D6: 0.06
C7: Custos relacionados com a manutenção da sede da empresa para dar suporte técnico, administrativo e financeiro a todas aos contratos que estejam sendo executadas .Incluem-se entre os gastos com administração central: aluguel do escritório central, manutenção da edificação da sede da empresa, compra de material de expediente para o escritório central, despesas com aquisição de editais e elaboração de propostas comerciais, prolabore e representação da diretoria, despesas com atividades administrativo-financeiras (manutenção da secretaria da sede da empresa e de setores de contabilidade, de recursos humanos, de compras, de finanças e de cobranças), dentre outros. O valor da taxa de administração central decorre do rateio das despesas administrativas do escritório central por todas os contratos que a empresa esteja executando no período, e varia de acordo com a complexidade e com a estrutura da empresa. Pessupõe-se a estrutura necessária para execução de atividades específicas de direção geral da empresa como um todo, de forma que sejam alcançados os objetivos empresariais .
B8: 2.2 | C8: ADMINISTRAÇÃO LOCAL | D8: 0.09
C9: Custos relacionados ao contrato mas que não estão contemplados nas planilhas de custos diretos, como por exemplo, custos com reuniões de preposto ou diretoria em atendimento ao contrato, Custos complanejamento dos serviços do contrato, custo com Gestão de documentação do contrato, Controle tecnologico, Custos ligados `a melhoria e qualidade de processos, coordenação e distribuição de recursos do contrato, programas de melhorias continuas da qualidade do contrato, Gestão de Partes interessadas, Gestão da Comunicação, dentre outros. O valor da taxa de Administração Local decorre do rateio das despesas indiretas administrativas/operacionais por todas os contratos que a empresa esteja executando no período, e varia de acordo com a complexidade e com a estrutura da Empresa.
B10: 2.3 | C10: CUSTO FINANCEIRO CAPITAL DE GIRO | D10: 0.035
C11: Despesas financeiras são gastos relacionados à perda monetária decorrente da defasagem entre a data do efetivo desembolso e a data da receita correspondente, o contratado precisa lançar mão de recursos próprios para executar etapas que só serão pagas futuramente, o que gera despesas de investimento de capital. Para que esse capital de giro possa ser remunerado, é instituída a despesa financeira. Para estipulação do valor a ser cobrado como despesa financeira, pressupõe-se o custo de oportunidade do capital, ou seja, deve-se apurar qual seria o seu rendimento se o capital de giro tivesse sido aplicado no mercado financeiro
B12: 2.4 | C12: RISCO DO EMPREENDIMENTO | D12: 0.02
C13: Imprevistos contratuais. Há ainda a possibilidade de se causar, involuntariamente, danos corporais e materiais a terceiros. Apesar do seguro, no caso deste ser contemplado como custo direto, vale ressaltar que: Há imprevistos não cobertos pelo seguro. A cobertura restringe-se a danos que sejam classificados como acidentais, por serem súbitos e/ou imprevisíveis, obtem-se, em uma só apólice, extensa com uma gama de coberturas (incêndio, alagamento, desmoronamento, responsabilidade civil, roubo, etc). Cabe salientar, quanto aos custos que representam tais seguros, que suas taxas (percentuais a serem aplicados sobre a importância segurada da obra) variam de acordo com as características de cada obra. Consideram-se como imprevistos ou riscos os seguintes acontecimentos, dentre outros, cuja ocorrência prejudica o andamento dos serviços e independe da atuação prévia do executor da obra: fenômenos naturais; perdas de eficiência de mão-de-obra; perdas excessivas de material (por quebras ou retrabalhos) ; manutenções e/ou aferições de equipamentos não previstas; barganha do patrocinador em regras do contrato; regras de reajustes inferiores ao custo de oportunidade economico; greves.
B14: 2.5 | C14: OUTROS | D14: 0.01
C15: Outras despesas indiretas especificas do contrato, quando houver.
B16: 3 | C16: TOTAL BDI | D16: =D5+D4 -> 0.315
B18: TRIBUTOS | D18: =D27 -> 0.1951
F19: ENVIAR DIPJ - DECLARAÇÃO DE INFORMAÇÕES ECONÔMICO-FISCAIS DA PESSOA JURÍDICA
B20: 1 | C20: ISS | D20: 0.05 | T20: 0.03
B21: 2 | C21: COFINS | D21: 0.03 | T21: 0.04
B22: 3 | C22: PIS | D22: 0.0065 | T22: 0.05
B23: 4 | C23: CSLL | D23: 0.0288 | P23: 1
B24: 5 | C24: IRPJ | D24: 0.048
B25: 6 | C25: IRPJ ADICIONAL DE 10% | D25: 0.0318
B26: 7 | C26: SIMPLES NACIONAL
B27: 8 | C27: TOTAL TRIBUTOS | D27: =SUM(D20:D25) -> 0.1951

Sheet ENCARGOS SOCIAIS
B3: ENCARGOS SOCIAIS | D3: =D33 -> 0.7616
C4: - Empresa optante pelo Simples Nacional ? | D4: NÃO | W4: =IF(D4="SIM",TRUE,FALSE) -> FALSE | X4: FALSO
C5: Os percentuais abaixo são orientativos, caso sua empresa aplique outros favor justificar. Acompanhe a legislação (vide comentários).
B6: A | C6: ENCARGOS SOCIAIS BÁSICOS | D6: =SUM(D7:D15) -> 0.368
B7: A.1 | C7: INSS | D7: 0.2 | G7: Justifique % diferenciado: | W7: 0.2 | Y7: =IF($W$4,X7,W7) -> 0.2 | AA7: =IF(D7=Y7,"OK","JUSTIFICAR") -> OK | AB7: =IF(AA7="OK",1,0) -> 1
B8: A.2 | C8: FGTS | D8: 0.08 | G8: Justifique % diferenciado: | W8: 0.08 | X8: 0 | Y8: =IF($W$4,X8,W8) -> 0.08 | AA8: =IF(D8=Y8,"OK","JUSTIFICAR") -> OK | AB8: =IF(AA8="OK",1,0) -> 1
B9: A.3 | C9: SESI / SESC | D9: 0.015 | G9: Justifique % diferenciado: | W9: 0.015 | X9: 0 | Y9: =IF($W$4,X9,W9) -> 0.015 | AA9: =IF(D9=Y9,"OK","JUSTIFICAR") -> OK | AB9: =IF(AA9="OK",1,0) -> 1
B10: A.4 | C10: SENAI / SENAC | D10: 0.01 | G10: Justifique % diferenciado: | W10: 0.01 | X10: 0 | Y10: =IF($W$4,X10,W10) -> 0.01 | Z10: x | AA10: =IF(OR(D10=1%,D10=1.2%,D10=0%,D10=""),"OK","JUSTIFICAR") -> OK | AB10: =IF(AA10="OK",1,0) -> 1
B11: A.5 | C11: INCRA | D11: 0.002 | G11: Justifique % diferenciado: | W11: 0.002 | X11: 0 | Y11: =IF($W$4,X11,W11) -> 0.002 | AA11: =IF(D11=Y11,"OK","JUSTIFICAR") -> OK | AB11: =IF(AA11="OK",1,0) -> 1
B12: A.6 | C12: SALÁRIO EDUCAÇÃO | D12: 0.025 | G12: Justifique % diferenciado: | W12: 0.025 | X12: 0 | Y12: =IF($W$4,X12,W12) -> 0.025 | AA12: =IF(D12=Y12,"OK","JUSTIFICAR") -> OK | AB12: =IF(AA12="OK",1,0) -> 1
B13: A.7 | C13: SEGURO ACIDENTE/RAT | D13: 0.03 | G13: Justifique % diferenciado: | W13: 0.03 | X13: 0 | Y13: =IF($W$4,X13,W13) -> 0.03 | Z13: x | AA13: =IF(W4,IF(D13<>0%,"JUSTIFICAR","OK"),IF(AND(D13>0.99%,D13<3.01%),"OK","JUSTIFICAR")) -> OK | AB13: =IF(AA13="OK",1,0) -> 1
B14: A.8 | C14: SEBRAE | D14: 0.006 | G14: Justifique % diferenciado: | W14: 0.006 | X14: 0 | Y14: =IF($W$4,X14,W14) -> 0.006 | AA14: =IF(D14=Y14,"OK","JUSTIFICAR") -> OK | AB14: =IF(AA14="OK",1,0) -> 1
B15: A.9 | C15: SECONCI | D15: 0 | E15: 1 | G15: Justifique % diferenciado: | W15: 0 | X15: 0 | Y15: =IF($W$4,X15,W15) -> 0 | Z15: x | AA15: =IF(OR(D15=0%,D15=1%,D15=""),"OK","JUSTIFICAR") -> OK | AB15: =IF(AA15="OK",1,0) -> 1
B16: B | C16: ENCARGOS QUE RECEBEM INCIDÊNCIA DE "A" | D16: =IF(AB17=2,SUM(D18:D26),D18+D19+D20+D22+D24+D25+D26) -> 0.2861
C17: - Mão de Obra Tipo: | AB17: 1
B18: B.1 | C18: FÉRIAS + 1/3 FÉRIAS (separar férias e abono) | D18: 0.1111
B19: B.2 | C19: 13º SALÁRIO | D19: 0.0833
B20: B.3 | C20: ENCARGOS SOBRE 13º E FÉRIAS | D20: 0.0725 | F20: Conforme informação de nossa contabilidade
